Workbook

Sheet 0_Dashboard_Toggles
B1: Project Harmony – Spotify Technology S.A. Take-Private LBO | J1: Master check: | K1: =$D$49 -> OK
B2: € millions unless stated | Close 31-Dec-2026 | 7-year hold to FY2033E | Inputs blue, formulas black, cross-sheet links green, checks red
B3: GLOBAL CONTROLS
B4: Scenario selector | C4: Base | D4: Data validation: Base / Upside / Downside
B5: Scenario index (INDEX/MATCH) | C5: =MATCH(C4,$E$23:$G$23,0) -> 1 | D5: Drives column H of the scenario matrix
B7: Offer premium to unaffected price | C7: 0.3 | D7: IC case 30%
B8: Unaffected share price (USD) | C8: 490.3 | D8: SPOT Sep-2026 month-end close
B9: EUR per USD | C9: 0.8756 | D9: Spotify Q2'26 6-K guidance rate (30-Jun-2026)
B10: Interest circularity toggle (1 = avg balances, 0 = opening) | C10: 0 | D10: Shipped at 0 (opening-balance interest, fully balanced). Set 1 for average-balance interest – iterative calc is pre-enabled; or run macro SolveInterestCircularity. 0 is also the circuit breaker.
B11: Cash sweep toggle (1 = on) | C11: 1
B12: Cash sweep % of excess cash | C12: 1
B13: Minimum cash balance | C13: 1500 | D13: Buffer vs. €2.6bn accrued royalties (negative working capital)
B14: Entry gross leverage (x FY26E Adj. EBITDA) | C14: 6
B15: Advisory & legal fees (% of EV) | C15: 0.0035 | D15: Expensed at close
B16: Financing fees (% of funded debt) | C16: 0.0225 | D16: Capitalised, amortised over 7 years
B17: TLB OID (% of TLB) | C17: 0.005 | D17: Capitalised with financing fees
B18: Cash tax rate | C18: 0.2494 | D18: Luxembourg City combined CIT + MBT
B19: ATAD interest cap (% of tax-EBITDA) | C19: 0.3 | D19: Lux & Sweden implement ATAD Art. 4; €3m de minimis
B20: Management Incentive Plan (% of equity gain) | C20: 0.08
B21: Exit multiple override (blank = scenario value) | D21: Type a value to override
B22: Live exit EV / EBITDA multiple | C22: =IF(C21="",H35,C21) -> 22
B23: SCENARIO MATRIX | E23: Base | F23: Upside | G23: Downside | H23: Live
B24: Premium sub growth FY27E (fades linearly to FY33E) | E24: 0.075 | F24: 0.09 | G24: 0.05 | H24: =INDEX(E24:G24,1,$C$5) -> 0.075
B25: Premium sub growth FY33E | E25: 0.04 | F25: 0.05 | G25: 0.03 | H25: =INDEX(E25:G25,1,$C$5) -> 0.04
B26: Premium ARPU growth p.a. | E26: 0.04 | F26: 0.05 | G26: 0.025 | H26: =INDEX(E26:G26,1,$C$5) -> 0.04
B27: Monthly Premium churn (base level) | E27: 0.02 | F27: 0.018 | G27: 0.024 | H27: =INDEX(E27:G27,1,$C$5) -> 0.02
B28: Ad-Supported revenue growth p.a. | E28: 0.08 | F28: 0.12 | G28: 0.03 | H28: =INDEX(E28:G28,1,$C$5) -> 0.08
B29: Music royalty rate step-down p.a. (bps of Premium rev.) | E29: 70 | F29: 110 | G29: 15 | H29: =INDEX(E29:G29,1,$C$5) -> 70
B30: Ad-Supported gross margin FY33E | E30: 0.3 | F30: 0.34 | G30: 0.22 | H30: =INDEX(E30:G30,1,$C$5) -> 0.3
B31: R&D % revenue (reached FY29E) | E31: 0.07 | F31: 0.065 | G31: 0.078 | H31: =INDEX(E31:G31,1,$C$5) -> 0.07
B32: S&M % revenue (reached FY29E) | E32: 0.07 | F32: 0.066 | G32: 0.076 | H32: =INDEX(E32:G32,1,$C$5) -> 0.07
B33: G&A % revenue (reached FY29E) | E33: 0.025 | F33: 0.024 | G33: 0.026 | H33: =INDEX(E33:G33,1,$C$5) -> 0.025
B34: EURIBOR shift vs. forward curve (bps) | E34: 0 | F34: -25 | G34: 100 | H34: =INDEX(E34:G34,1,$C$5) -> 0
B35: Exit EV / EBITDA multiple | E35: 22 | F35: 25 | G35: 16 | H35: =INDEX(E35:G35,1,$C$5) -> 22
B36: % of SBC converted to cash compensation post-close | E36: 0.5 | F36: 0.4 | G36: 0.6 | H36: =INDEX(E36:G36,1,$C$5) -> 0.5
B37: Dividend recap switch (set in 4_Debt_Schedule!C73 – default OFF) | C37: ='4_Debt_Schedule'!C73 -> 0 | D37: Base case is unchanged when 0. See 6_IC_Analysis section C for recap results.
B39: AUTOMATED AUDIT CHECKS (must all be zero)
B40: Balance sheet balances (Σ|Assets − L&E|) | D40: =SUMPRODUCT(ABS('3_Financial_Statements'!E66:L66)) -> 0
B41: Cash flow closing cash = BS cash | D41: =SUMPRODUCT(ABS('3_Financial_Statements'!F44:L44-'3_Financial_Statements'!F47:L47)) -> 0
B42: Sources = Uses | D42: =ABS('1_Transaction_Summary'!C52) -> 0
B43: No negative debt balances (count) | D43: =COUNTIF('4_Debt_Schedule'!F31:L31,"<-0.001")+COUNTIF('4_Debt_Schedule'!F36:L36,"<-0.001")+COUNTIF('4_Debt_Schedule'!F47:L47,"<-0.001") -> 0
B44: RCF within €500m limit (count of breaches) | D44: =COUNTIF('4_Debt_Schedule'!F47:L47,">"&'4_Debt_Schedule'!C15+0.001) -> 0
B45: Minimum cash respected (count of breaches) | D45: =COUNTIF('3_Financial_Statements'!F44:L44,"<"&($C$13-0.5)) -> 0
B46: Net leverage covenant (TLA springing 7.0x) breaches | D46: =COUNTIF('4_Debt_Schedule'!F68:L68,"BREACH") -> 0
B47: Circularity converged (Σ residual, row 60 of Debt Schedule; was a hard-coded 0) | D47: =IF($C$10=1,ROUND(ABS('4_Debt_Schedule'!M60),2),0) -> 0
B49: MASTER CHECK | D49: =IF(ROUND(SUM(D40:D47),2)=0,"OK","ERROR") -> OK
B51: LIVE OUTPUTS (selected scenario)
B52: Offer price per share (USD / EUR) | C52: ='1_Transaction_Summary'!C6 -> 637.39 | E52: ='1_Transaction_Summary'!C8 -> 558.09868
B53: Equity purchase price / Enterprise value | C53: ='1_Transaction_Summary'!C19 -> 116840.95 | E53: ='1_Transaction_Summary'!C25 -> 106804.95
B54: EV / FY26E Adj. EBITDA | EV / LTM FCF | C54: ='1_Transaction_Summary'!C28 -> 32.536742 | E54: ='1_Transaction_Summary'!C30 -> 32.752207
B55: Total debt at close | gross leverage | C55: ='1_Transaction_Summary'!C47 -> 19700 | E55: ='1_Transaction_Summary'!E47 -> 6.0013495
B56: Total equity (sponsor + rollover) | % of capitalisation | C56: ='5_Returns_Sensitivities'!C14 -> 91000.964 | E56: ='5_Returns_Sensitivities'!C14/'1_Transaction_Summary'!C51 -> 0.77315394
B57: Exit EBITDA FY33E | exit multiple | C57: ='5_Returns_Sensitivities'!C5 -> 8418.4223 | E57: ='5_Returns_Sensitivities'!C6 -> 22
B58: Gross MoIC | Gross IRR | C58: ='5_Returns_Sensitivities'!C17 -> 2.0918942 | E58: ='5_Returns_Sensitivities'!C19 -> 0.11119784
B59: Net MoIC | Net IRR (LP, after fees & carry) | C59: ='5_Returns_Sensitivities'!C31 -> 1.7895154 | E59: ='5_Returns_Sensitivities'!C32 -> 0.084022948
B60: Net leverage FY27E | FY29E | C60: ='4_Debt_Schedule'!F65 -> 4.0351848 | E60: ='4_Debt_Schedule'!H65 -> 1.6179716
B62: SCENARIO SNAPSHOT – STATIC PASTED VALUES, NOT LIVE (regenerated by full model re-runs on v3, 06-Oct-2026; freshness test in C72)
E63: Base | F63: Upside | G63: Downside
B64: Exit Adj. EBITDA FY33E (€m) | E64: 8418.4223 | F64: 11135.878 | G64: 5278.2764
B65: FY33E gross margin | E65: 0.3926885 | F65: 0.42067834 | G65: 0.35204959
B66: Exit multiple | E66: 22 | F66: 25 | G66: 16
B67: Gross MoIC | E67: 2.0918942 | F67: 3.1211425 | G67: 0.9578158
B68: Gross IRR | E68: 0.11119784 | F68: 0.17656582 | G68: -0.0061381981
B69: Net MoIC | E69: 1.7895154 | F69: 2.612914 | G69: 0.8528158
B70: Net IRR | E70: 0.084022948 | F70: 0.14341737 | G70: -0.021424834
B71: Peak net leverage | E71: 4.0351848 | F71: 3.6989161 | G71: 4.6164591
B72: Snapshot freshness (selected scenario vs live Gross IRR) | C72: =IF(ABS(INDEX(E68:G68,1,C5)-'5_Returns_Sensitivities'!C19)<0.00005,"CURRENT","STALE") -> CURRENT | D72: STALE = an input has changed since the snapshot was pasted. Re-run harmony_rerun.py to refresh. Values above were NOT recomputed by Excel.

Sheet 1_Transaction_Summary
B1: 1 | Transaction Summary – Purchase Price Bridge & Sources and Uses | J1: Master check: | K1: ='0_Dashboard_Toggles'!$D$49 -> OK
B2: Share data: Spotify Q2 2026 Form 6-K (Ex. 99.1, filed 4-Aug-2026) EPS note; balance sheet at 30-Jun-2026
B4: PURCHASE PRICE BRIDGE
B5: Unaffected share price (USD) | C5: ='0_Dashboard_Toggles'!C8 -> 490.3
B6: Offer price per share (USD) | C6: =C5*(1+'0_Dashboard_Toggles'!C7) -> 637.39
B7: EUR per USD | C7: ='0_Dashboard_Toggles'!C9 -> 0.8756
B8: Offer price per share (EUR) | C8: =C6*C7 -> 558.09868
B10: Basic shares outstanding (m) | C10: 205.78824
B11: Option tranches (Treasury Stock Method) | C11: Options (m) | D11: Strike (USD) | E11: TSM shares (m) | F11: Cash-out (€m)
B12: Tranche 1 (legacy grants) | C12: 3 | D12: 150 | E12: =IF(D12<$C$6,C12-C12*D12/$C$6,0) -> 2.2939958 | F12: =IF(D12<$C$6,C12*($C$6-D12)*$C$7,0) -> 1280.2761
B13: Tranche 2 | C13: 1 | D13: 350 | E13: =IF(D13<$C$6,C13-C13*D13/$C$6,0) -> 0.45088564 | F13: =IF(D13<$C$6,C13*($C$6-D13)*$C$7,0) -> 251.63868
B14: Tranche 3 (recent grants) | C14: 0.6 | D14: 480 | E14: =IF(D14<$C$6,C14-C14*D14/$C$6,0) -> 0.14815733 | F14: =IF(D14<$C$6,C14*($C$6-D14)*$C$7,0) -> 82.68641
B15: Total options | C15: =SUM(C12:C14) -> 4.6 | E15: =SUM(E12:E14) -> 2.8930388 | F15: =SUM(F12:F14) -> 1614.6011
B16: Unvested RSUs (m) | C16: 0.674073
B17: Fully diluted shares outstanding (m) | C17: =C10+E15+C16 -> 209.35535
B19: Equity purchase price (incl. option cash-out) | C19: =C17*C8 -> 116840.95
B20: Less: cash and cash equivalents | C20: -5938 | G20: 6-K BS 30-Jun-26
B21: Less: short-term investments | C21: -3450 | G21: 6-K BS 30-Jun-26
B22: Less: long-term investments (non-operating) | C22: -1118 | G22: 6-K BS; incl. TME stake
B23: Plus: lease liabilities (IFRS 16) | C23: 470 | G23: €404m non-current + c.€66m current (E)
B24: Plus: financial debt | C24: 0 | G24: Exchangeable Notes repaid Q1'26 (€1,304m)
B25: Enterprise value | C25: =SUM(C19:C24) -> 106804.95
B27: FY26E Adj. EBITDA | C27: ='2_Operating_Build'!E79 -> 3282.595
B28: EV / FY26E Adj. EBITDA | C28: =C25/C27 -> 32.536742
B29: EV / LTM Adj. EBITDA (LTM Q2'26: €3,070m est.) | C29: =C25/D29 -> 34.789885 | D29: 3070
B30: EV / LTM FCF (LTM Q2'26: €3,261m, 6-K) | C30: =C25/D30 -> 32.752207 | D30: 3261
B31: Memo: unaffected EV / FY26E EBITDA | C31: =(C17*C5*C7+SUM(C20:C24))/C27 -> 24.322724
B32: Memo: EV / FY26E EBITDA on post-close SBC definition (only non-cash SBC added back) | C32: =C25/(C27-'2_Operating_Build'!E76*'0_Dashboard_Toggles'!H36) -> 34.207302
B33: SOURCES & USES | C33: €m | D33: % total | E33: x EBITDA
B34: Uses
B35: Equity purchase price | C35: =C19 -> 116840.95 | D35: =C35/$C$39 -> 0.9926932
B36: Advisory & legal fees | C36: ='0_Dashboard_Toggles'!C15*C25 -> 373.81731 | D36: =C36/$C$39 -> 0.0031759919
B37: Financing fees | C37: ='0_Dashboard_Toggles'!C16*C47 -> 443.25 | D37: =C37/$C$39 -> 0.0037658995
B38: TLB original issue discount | C38: ='0_Dashboard_Toggles'!C17*C43 -> 42.95 | D38: =C38/$C$39 -> 0.0003649078
B39: Total uses | C39: =SUM(C35:C38) -> 117700.96
B41: Sources | F41: Tranche split
B42: Senior Secured Term Loan A (E+325, 7-yr amortising) | C42: =ROUND(C47*F42,-1) -> 4040 | D42: =C42/$C$51 -> 0.034324273 | E42: =C42/$C$27 -> 1.2307336 | F42: 0.205
B43: Senior Term Loan B (E+400, 8-yr bullet) | C43: =ROUND(C47*F43,-1) -> 8590 | D43: =C43/$C$51 -> 0.07298156 | E43: =C43/$C$27 -> 2.6168321 | F43: 0.436
B44: Senior Unsecured Notes (7.50% fixed, 8-yr) | C44: =C47-C42-C43 -> 7070 | D44: =C44/$C$51 -> 0.060067477 | E44: =C44/$C$27 -> 2.1537838 | F44: =1-F42-F43 -> 0.359
B45: Revolving Credit Facility (€500m, undrawn at close) | C45: 0 | D45: =C45/$C$51 -> 0 | E45: =C45/$C$27 -> 0
B47: Total debt (leverage x FY26E EBITDA) | C47: =ROUND('0_Dashboard_Toggles'!C14*C27,-2) -> 19700 | D47: =C47/$C$51 -> 0.16737331 | E47: =C47/$C$27 -> 6.0013495
B48: Balance sheet cash used | C48: =-(C20+C21)-F48 -> 7000 | D48: =C48/$C$51 -> 0.05947275 | F48: 2388 | G48: F48 = cash retained on balance sheet at close
B49: Rollover equity (founders + Tencent) | C49: =F49*C19 -> 31547.056 | D49: =C49/$C$51 -> 0.26802716 | F49: 0.27
B50: Sponsor consortium equity (plug) | C50: =C39-C47-C48-C49 -> 59453.909 | D50: =C50/$C$51 -> 0.50512678
B51: Total sources | C51: =C47+C48+C49+C50 -> 117700.96
B52: Check: sources − uses | C52: =ROUND(C51-C39,3) -> 0
B54: Implied equity contribution (% of total capitalisation) | C54: =(C49+C50)/C51 -> 0.77315394
B55: Net leverage at close (x FY26E EBITDA) | C55: =(C47-F48)/C27 -> 5.2738763

Sheet 2_Operating_Build
B1: 2 | Operating Build – Segment Revenue, Royalties & OpEx | J1: Master check: | K1: ='0_Dashboard_Toggles'!$D$49 -> OK
B2: FY26E = Q1–Q2 actuals (6-K) + Q3 guidance + Q4E | Regional split estimated except Europe (36% of subs, disclosed) | E2: Close / LTM
B3: Fiscal year (Dec YE) | E3: 2026 | F3: 2027 | G3: 2028 | H3: 2029 | I3: 2030 | J3: 2031 | K3: 2032 | L3: 2033
B4: Period (t) | E4: 0 | F4: 1 | G4: 2 | H4: 3 | I4: 4 | J4: 5 | K4: 6 | L4: 7
B5: PREMIUM SUBSCRIBER DRIVERS
B6: Scenario base subscriber growth (linear fade) | C6: % | F6: ='0_Dashboard_Toggles'!$H$24+('0_Dashboard_Toggles'!$H$25-'0_Dashboard_Toggles'!$H$24)*(F$4-1)/6 -> 0.075 | G6: ='0_Dashboard_Toggles'!$H$24+('0_Dashboard_Toggles'!$H$25-'0_Dashboard_Toggles'!$H$24)*(G$4-1)/6 -> 0.069166667 | H6: ='0_Dashboard_Toggles'!$H$24+('0_Dashboard_Toggles'!$H$25-'0_Dashboard_Toggles'!$H$24)*(H$4-1)/6 -> 0.063333333 | I6: ='0_Dashboard_Toggles'!$H$24+('0_Dashboard_Toggles'!$H$25-'0_Dashboard_Toggles'!$H$24)*(I$4-1)/6 -> 0.0575 | J6: ='0_Dashboard_Toggles'!$H$24+('0_Dashboard_Toggles'!$H$25-'0_Dashboard_Toggles'!$H$24)*(J$4-1)/6 -> 0.051666667 | K6: ='0_Dashboard_Toggles'!$H$24+('0_Dashboard_Toggles'!$H$25-'0_Dashboard_Toggles'!$H$24)*(K$4-1)/6 -> 0.045833333 | L6: ='0_Dashboard_Toggles'!$H$24+('0_Dashboard_Toggles'!$H$25-'0_Dashboard_Toggles'!$H$24)*(L$4-1)/6 -> 0.04
B7: Premium ARPU growth | C7: % | F7: ='0_Dashboard_Toggles'!$H$26 -> 0.04 | G7: ='0_Dashboard_Toggles'!$H$26 -> 0.04 | H7: ='0_Dashboard_Toggles'!$H$26 -> 0.04 | I7: ='0_Dashboard_Toggles'!$H$26 -> 0.04 | J7: ='0_Dashboard_Toggles'!$H$26 -> 0.04 | K7: ='0_Dashboard_Toggles'!$H$26 -> 0.04 | L7: ='0_Dashboard_Toggles'!$H$26 -> 0.04
B8: Monthly churn incl. price elasticity | C8: % | E8: ='0_Dashboard_Toggles'!$H$27 -> 0.02 | F8: ='0_Dashboard_Toggles'!$H$27+$E$9*MAX(0,F7-$E$10) -> 0.0205 | G8: ='0_Dashboard_Toggles'!$H$27+$E$9*MAX(0,G7-$E$10) -> 0.0205 | H8: ='0_Dashboard_Toggles'!$H$27+$E$9*MAX(0,H7-$E$10) -> 0.0205 | I8: ='0_Dashboard_Toggles'!$H$27+$E$9*MAX(0,I7-$E$10) -> 0.0205 | J8: ='0_Dashboard_Toggles'!$H$27+$E$9*MAX(0,J7-$E$10) -> 0.0205 | K8: ='0_Dashboard_Toggles'!$H$27+$E$9*MAX(0,K7-$E$10) -> 0.0205 | L8: ='0_Dashboard_Toggles'!$H$27+$E$9*MAX(0,L7-$E$10) -> 0.0205
B9: Elasticity: Δ monthly churn per 1.0 of ARPU growth above neutral | C9: x | D9: Input | E9: 0.05
B10: Price-neutral ARPU growth | C10: % | D10: Input | E10: 0.03
B11: Incremental annual churn vs. base (drag on net adds) | C11: % | F11: =(1-(1-F8)^12)-(1-(1-'0_Dashboard_Toggles'!$H$27)^12) -> 0.0047909293 | G11: =(1-(1-G8)^12)-(1-(1-'0_Dashboard_Toggles'!$H$27)^12) -> 0.0047909293 | H11: =(1-(1-H8)^12)-(1-(1-'0_Dashboard_Toggles'!$H$27)^12) -> 0.0047909293 | I11: =(1-(1-I8)^12)-(1-(1-'0_Dashboard_Toggles'!$H$27)^12) -> 0.0047909293 | J11: =(1-(1-J8)^12)-(1-(1-'0_Dashboard_Toggles'!$H$27)^12) -> 0.0047909293 | K11: =(1-(1-K8)^12)-(1-(1-'0_Dashboard_Toggles'!$H$27)^12) -> 0.0047909293 | L11: =(1-(1-L8)^12)-(1-(1-'0_Dashboard_Toggles'!$H$27)^12) -> 0.0047909293
B13: North America | C13: Growth spread | D13: -0.025
B14: Closing Premium subs | C14: m | E14: 74 | F14: =E14*(1+F$6+$D$13-F$11) -> 77.345471 | G14: =F14*(1+G$6+$D$13-G$11) -> 80.391006 | H14: =G14*(1+H$6+$D$13-H$11) -> 83.087514 | I14: =H14*(1+I$6+$D$13-I$11) -> 85.389792 | J14: =I14*(1+J$6+$D$13-J$11) -> 87.257756 | K14: =J14*(1+K$6+$D$13-K$11) -> 88.65758 | L14: =K14*(1+L$6+$D$13-L$11) -> 89.562692
B15: Average subs | C15: m | F15: =AVERAGE(E14,F14) -> 75.672736 | G15: =AVERAGE(F14,G14) -> 78.868239 | H15: =AVERAGE(G14,H14) -> 81.73926 | I15: =AVERAGE(H14,I14) -> 84.238653 | J15: =AVERAGE(I14,J14) -> 86.323774 | K15: =AVERAGE(J14,K14) -> 87.957668 | L15: =AVERAGE(K14,L14) -> 89.110136
B16: Monthly ARPU | C16: € | E16: 8.95 | F16: =E16*(1+F$7) -> 9.308 | G16: =F16*(1+G$7) -> 9.68032 | H16: =G16*(1+H$7) -> 10.067533 | I16: =H16*(1+I$7) -> 10.470234 | J16: =I16*(1+J$7) -> 10.889043 | K16: =J16*(1+K$7) -> 11.324605 | L16: =K16*(1+L$7) -> 11.777589
B17: Premium revenue | C17: €m | F17: =F15*F16*12 -> 8452.3419 | G17: =G15*G16*12 -> 9161.6375 | H17: =H15*H16*12 -> 9874.9522 | I17: =I15*I16*12 -> 10583.981 | J17: =J15*J16*12 -> 11279.8 | K17: =K15*K16*12 -> 11953.03 | L17: =L15*L16*12 -> 12594.031
B18: Europe | C18: Growth spread | D18: -0.01
B19: Closing Premium subs | C19: m | E19: 111 | F19: =E19*(1+F$6+$D$18-F$11) -> 117.68321 | G19: =F19*(1+G$6+$D$18-G$11) -> 124.08232 | H19: =G19*(1+H$6+$D$18-H$11) -> 130.10557 | I19: =H19*(1+I$6+$D$18-I$11) -> 135.66226 | J19: =I19*(1+J$6+$D$18-J$11) -> 140.66491 | K19: =J19*(1+K$6+$D$18-K$11) -> 145.03148 | L19: =K19*(1+L$6+$D$18-L$11) -> 148.68759
B20: Average subs | C20: m | F20: =AVERAGE(E19,F19) -> 114.3416 | G20: =AVERAGE(F19,G19) -> 120.88276 | H20: =AVERAGE(G19,H19) -> 127.09395 | I20: =AVERAGE(H19,I19) -> 132.88392 | J20: =AVERAGE(I19,J19) -> 138.16358 | K20: =AVERAGE(J19,K19) -> 142.84819 | L20: =AVERAGE(K19,L19) -> 146.85954
B21: Monthly ARPU | C21: € | E21: 5.25 | F21: =E21*(1+F$7) -> 5.46 | G21: =F21*(1+G$7) -> 5.6784 | H21: =G21*(1+H$7) -> 5.905536 | I21: =H21*(1+I$7) -> 6.1417574 | J21: =I21*(1+J$7) -> 6.3874277 | K21: =J21*(1+K$7) -> 6.6429248 | L21: =K21*(1+L$7) -> 6.9086418
B22: Premium revenue | C22: €m | F22: =F20*F21*12 -> 7491.6619 | G22: =G20*G21*12 -> 8237.0481 | H22: =H20*H21*12 -> 9006.6944 | I22: =I20*I21*12 -> 9793.6894 | J22: =J20*J21*12 -> 10590.119 | K22: =K20*K21*12 -> 11387.158 | L22: =L20*L21*12 -> 12175.199
B23: Latin America | C23: Growth spread | D23: 0.01
B24: Closing Premium subs | C24: m | E24: 68 | F24: =E24*(1+F$6+$D$23-F$11) -> 73.454217 | G24: =F24*(1+G$6+$D$23-G$11) -> 78.917428 | H24: =G24*(1+H$6+$D$23-H$11) -> 84.326619 | I24: =H24*(1+I$6+$D$23-I$11) -> 89.614662 | J24: =I24*(1+J$6+$D$23-J$11) -> 94.711562 | K24: =J24*(1+K$6+$D$23-K$11) -> 99.545868 | L24: =K24*(1+L$6+$D$23-L$11) -> 104.04624
B25: Average subs | C25: m | F25: =AVERAGE(E24,F24) -> 70.727108 | G25: =AVERAGE(F24,G24) -> 76.185823 | H25: =AVERAGE(G24,H24) -> 81.622023 | I25: =AVERAGE(H24,I24) -> 86.970641 | J25: =AVERAGE(I24,J24) -> 92.163112 | K25: =AVERAGE(J24,K24) -> 97.128715 | L25: =AVERAGE(K24,L24) -> 101.79606
B26: Monthly ARPU | C26: € | E26: 2.3 | F26: =E26*(1+F$7) -> 2.392 | G26: =F26*(1+G$7) -> 2.48768 | H26: =G26*(1+H$7) -> 2.5871872 | I26: =H26*(1+I$7) -> 2.6906747 | J26: =I26*(1+J$7) -> 2.7983017 | K26: =J26*(1+K$7) -> 2.9102337 | L26: =K26*(1+L$7) -> 3.0266431
B27: Premium revenue | C27: €m | F27: =F25*F26*12 -> 2030.1509 | G27: =G25*G26*12 -> 2274.3114 | H27: =H25*H26*12 -> 2534.0575 | I27: =I25*I26*12 -> 2808.1164 | J27: =J25*J26*12 -> 3094.8023 | K27: =K25*K26*12 -> 3392.0072 | L27: =L25*L26*12 -> 3697.204
B28: Rest of World | C28: Growth spread | D28: 0.04
B29: Closing Premium subs | C29: m | E29: 56 | F29: =E29*(1+F$6+$D$28-F$11) -> 62.171708 | G29: =F29*(1+G$6+$D$28-G$11) -> 68.660926 | H29: =G29*(1+H$6+$D$28-H$11) -> 75.426939 | I29: =H29*(1+I$6+$D$28-I$11) -> 82.4197 | J29: =I29*(1+J$6+$D$28-J$11) -> 89.579972 | K29: =J29*(1+K$6+$D$28-K$11) -> 96.839748 | L29: =K29*(1+L$6+$D$28-L$11) -> 104.12298
B30: Average subs | C30: m | F30: =AVERAGE(E29,F29) -> 59.085854 | G30: =AVERAGE(F29,G29) -> 65.416317 | H30: =AVERAGE(G29,H29) -> 72.043932 | I30: =AVERAGE(H29,I29) -> 78.923319 | J30: =AVERAGE(I29,J29) -> 85.999836 | K30: =AVERAGE(J29,K29) -> 93.20986 | L30: =AVERAGE(K29,L29) -> 100.48136
B31: Monthly ARPU | C31: € | E31: 1.95 | F31: =E31*(1+F$7) -> 2.028 | G31: =F31*(1+G$7) -> 2.10912 | H31: =G31*(1+H$7) -> 2.1934848 | I31: =H31*(1+I$7) -> 2.2812242 | J31: =I31*(1+J$7) -> 2.3724732 | K31: =J31*(1+K$7) -> 2.4673721 | L31: =K31*(1+L$7) -> 2.566067
B32: Premium revenue | C32: €m | F32: =F30*F31*12 -> 1437.9133 | G32: =G30*G31*12 -> 1655.6503 | H32: =H30*H31*12 -> 1896.3272 | I32: =I30*I31*12 -> 2160.5014 | J32: =J30*J31*12 -> 2448.3876 | K32: =K30*K31*12 -> 2759.8009 | L32: =L30*L31*12 -> 3094.1029
B34: Total closing Premium subscribers | C34: m | E34: =E14+E19+E24+E29 -> 309 | F34: =F14+F19+F24+F29 -> 330.6546 | G34: =G14+G19+G24+G29 -> 352.05168 | H34: =H14+H19+H24+H29 -> 372.94664 | I34: =I14+I19+I24+I29 -> 393.08641 | J34: =J14+J19+J24+J29 -> 412.2142 | K34: =K14+K19+K24+K29 -> 430.07468 | L34: =L14+L19+L24+L29 -> 446.4195
B35: Average Premium subscribers | C35: m | F35: =AVERAGE(E34,F34) -> 319.8273 | G35: =AVERAGE(F34,G34) -> 341.35314 | H35: =AVERAGE(G34,H34) -> 362.49916 | I35: =AVERAGE(H34,I34) -> 383.01653 | J35: =AVERAGE(I34,J34) -> 402.65031 | K35: =AVERAGE(J34,K34) -> 421.14444 | L35: =AVERAGE(K34,L34) -> 438.24709
B36: Churned subscribers (memo) | C36: m | F36: =E34*(1-(1-F8)^12) -> 68.00293 | G36: =F34*(1-(1-G8)^12) -> 72.768549 | H36: =G34*(1-(1-H8)^12) -> 77.477493 | I36: =H34*(1-(1-I8)^12) -> 82.075936 | J36: =I34*(1-(1-J8)^12) -> 86.50818 | K36: =J34*(1-(1-K8)^12) -> 90.717712 | L36: =K34*(1-(1-L8)^12) -> 94.648344
B37: Implied gross adds (memo) | C37: m | F37: =F34-E34+F36 -> 89.657532 | G37: =G34-F34+G36 -> 94.165625 | H37: =H34-G34+H36 -> 98.372458 | I37: =I34-H34+I36 -> 102.21571 | J37: =J34-I34+J36 -> 105.63596 | K37: =K34-J34+K36 -> 108.5782 | L37: =L34-K34+L36 -> 110.99317
B38: Blended monthly ARPU | C38: € | F38: =F39/F35/12 -> 5.0579557 | G38: =G39/G35/12 -> 5.2068871 | H38: =H39/H35/12 -> 5.3591001 | I38: =I39/I35/12 -> 5.5146202 | J38: =J39/J35/12 -> 5.6734732 | K38: =K39/K35/12 -> 5.8356852 | L38: =L39/L35/12 -> 6.0012829
B39: Premium revenue | C39: €m | E39: 17700 | F39: =F17+F22+F27+F32 -> 19412.068 | G39: =G17+G22+G27+G32 -> 21328.647 | H39: =H17+H22+H27+H32 -> 23312.031 | I39: =I17+I22+I27+I32 -> 25346.288 | J39: =J17+J22+J27+J32 -> 27413.109 | K39: =K17+K22+K27+K32 -> 29491.996 | L39: =L17+L22+L27+L32 -> 31560.537
B40: Premium revenue growth | C40: % | F40: =F39/E39-1 -> 0.096727005 | G40: =G39/F39-1 -> 0.098731331 | H40: =H39/G39-1 -> 0.09299155 | I40: =I39/H39-1 -> 0.087262104 | J40: =J39/I39-1 -> 0.081543321 | K40: =K39/J39-1 -> 0.075835531 | L40: =L39/K39-1 -> 0.070139063
B41: AD-SUPPORTED
B42: Ad-supported MAU growth p.a. | C42: % | D42: Input | E42: 0.06
B43: Ad-supported MAUs (closing) | C43: m | E43: 505 | F43: =E43*(1+$E$42) -> 535.3 | G43: =F43*(1+$E$42) -> 567.418 | H43: =G43*(1+$E$42) -> 601.46308 | I43: =H43*(1+$E$42) -> 637.55086 | J43: =I43*(1+$E$42) -> 675.80392 | K43: =J43*(1+$E$42) -> 716.35215 | L43: =K43*(1+$E$42) -> 759.33328
B44: Ad-Supported revenue | C44: €m | E44: 1850 | F44: =E44*(1+'0_Dashboard_Toggles'!$H$28) -> 1998 | G44: =F44*(1+'0_Dashboard_Toggles'!$H$28) -> 2157.84 | H44: =G44*(1+'0_Dashboard_Toggles'!$H$28) -> 2330.4672 | I44: =H44*(1+'0_Dashboard_Toggles'!$H$28) -> 2516.9046 | J44: =I44*(1+'0_Dashboard_Toggles'!$H$28) -> 2718.2569 | K44: =J44*(1+'0_Dashboard_Toggles'!$H$28) -> 2935.7175 | L44: =K44*(1+'0_Dashboard_Toggles'!$H$28) -> 3170.5749
B45: Ad revenue per average ad MAU | C45: €/yr | F45: =F44/AVERAGE(E43,F43) -> 3.8411997 | G45: =G44/AVERAGE(F43,G43) -> 3.9136751 | H45: =H44/AVERAGE(G43,H43) -> 3.987518 | I45: =I44/AVERAGE(H43,I43) -> 4.0627542 | J45: =J44/AVERAGE(I43,J43) -> 4.13941 | K45: =K44/AVERAGE(J43,K43) -> 4.2175121 | L45: =L44/AVERAGE(K43,L43) -> 4.2970877
B47: TOTAL REVENUE | C47: €m | E47: =E39+E44 -> 19550 | F47: =F39+F44 -> 21410.068 | G47: =G39+G44 -> 23486.487 | H47: =H39+H44 -> 25642.498 | I47: =I39+I44 -> 27863.193 | J47: =J39+J44 -> 30131.366 | K47: =K39+K44 -> 32427.714 | L47: =L39+L44 -> 34731.112
B48: Revenue growth | C48: % | F48: =F47/E47-1 -> 0.095144143 | G48: =G47/F47-1 -> 0.096983313 | H48: =H47/G47-1 -> 0.091797941 | I48: =I47/H47-1 -> 0.086602102 | J48: =J47/I47-1 -> 0.081403912 | K48: =K47/J47-1 -> 0.076211222 | L48: =L47/K47-1 -> 0.071031784
B49: COST OF REVENUE (royalties scale down from current filing levels)
B50: Music royalty rate (% Premium revenue) | C50: % | E50: 0.578 | F50: =E50-'0_Dashboard_Toggles'!$H$29/10000 -> 0.571 | G50: =F50-'0_Dashboard_Toggles'!$H$29/10000 -> 0.564 | H50: =G50-'0_Dashboard_Toggles'!$H$29/10000 -> 0.557 | I50: =H50-'0_Dashboard_Toggles'!$H$29/10000 -> 0.55 | J50: =I50-'0_Dashboard_Toggles'!$H$29/10000 -> 0.543 | K50: =J50-'0_Dashboard_Toggles'!$H$29/10000 -> 0.536 | L50: =K50-'0_Dashboard_Toggles'!$H$29/10000 -> 0.529
B51: Music label & publisher royalties | C51: €m | E51: =E39*E50 -> 10230.6 | F51: =F39*F50 -> 11084.291 | G51: =G39*G50 -> 12029.357 | H51: =H39*H50 -> 12984.801 | I51: =I39*I50 -> 13940.458 | J51: =J39*J50 -> 14885.318 | K51: =K39*K50 -> 15807.71 | L51: =L39*L50 -> 16695.524
B52: Non-music content % (podcasts, audiobooks) | C52: % | E52: 0.04 | F52: =E52 -> 0.04 | G52: =F52 -> 0.04 | H52: =G52 -> 0.04 | I52: =H52 -> 0.04 | J52: =I52 -> 0.04 | K52: =J52 -> 0.04 | L52: =K52 -> 0.04
B53: Non-music content cost | C53: €m | E53: =E39*E52 -> 708 | F53: =F39*F52 -> 776.48272 | G53: =G39*G52 -> 853.14589 | H53: =H39*H52 -> 932.48125 | I53: =I39*I52 -> 1013.8515 | J53: =J39*J52 -> 1096.5243 | K53: =K39*K52 -> 1179.6799 | L53: =L39*L52 -> 1262.4215
B54: Other Premium COGS % (payments, delivery, cloud) | C54: % | D54: 0.001 | E54: 0.036 | F54: =E54-$D$54 -> 0.035 | G54: =F54-$D$54 -> 0.034 | H54: =G54-$D$54 -> 0.033 | I54: =H54-$D$54 -> 0.032 | J54: =I54-$D$54 -> 0.031 | K54: =J54-$D$54 -> 0.03 | L54: =K54-$D$54 -> 0.029
B55: Other Premium COGS | C55: €m | E55: =E39*E54 -> 637.2 | F55: =F39*F54 -> 679.42238 | G55: =G39*G54 -> 725.17401 | H55: =H39*H54 -> 769.29703 | I55: =I39*I54 -> 811.08122 | J55: =J39*J54 -> 849.80637 | K55: =K39*K54 -> 884.75989 | L55: =L39*L54 -> 915.25558
B56: Premium gross margin | C56: % | E56: =1-E50-E52-E54 -> 0.346 | F56: =1-F50-F52-F54 -> 0.354 | G56: =1-G50-G52-G54 -> 0.362 | H56: =1-H50-H52-H54 -> 0.37 | I56: =1-I50-I52-I54 -> 0.378 | J56: =1-J50-J52-J54 -> 0.386 | K56: =1-K50-K52-K54 -> 0.394 | L56: =1-L50-L52-L54 -> 0.402
B57: Ad-Supported gross margin | C57: % | E57: 0.177 | F57: =E57+('0_Dashboard_Toggles'!$H$30-$E$57)/7 -> 0.19457143 | G57: =F57+('0_Dashboard_Toggles'!$H$30-$E$57)/7 -> 0.21214286 | H57: =G57+('0_Dashboard_Toggles'!$H$30-$E$57)/7 -> 0.22971429 | I57: =H57+('0_Dashboard_Toggles'!$H$30-$E$57)/7 -> 0.24728571 | J57: =I57+('0_Dashboard_Toggles'!$H$30-$E$57)/7 -> 0.26485714 | K57: =J57+('0_Dashboard_Toggles'!$H$30-$E$57)/7 -> 0.28242857 | L57: =K57+('0_Dashboard_Toggles'!$H$30-$E$57)/7 -> 0.3
B58: Ad-Supported cost of revenue | C58: €m | E58: =E44*(1-E57) -> 1522.55 | F58: =F44*(1-F57) -> 1609.2463 | G58: =G44*(1-G57) -> 1700.0697 | H58: =H44*(1-H57) -> 1795.1256 | I58: =I44*(1-I57) -> 1894.51 | J58: =J44*(1-J57) -> 1998.3072 | K58: =K44*(1-K57) -> 2106.587 | L58: =L44*(1-L57) -> 2219.4024
B59: Total cost of revenue | C59: €m | E59: =E51+E53+E55+E58 -> 13098.35 | F59: =F51+F53+F55+F58 -> 14149.442 | G59: =G51+G53+G55+G58 -> 15307.747 | H59: =H51+H53+H55+H58 -> 16481.705 | I59: =I51+I53+I55+I58 -> 17659.901 | J59: =J51+J53+J55+J58 -> 18829.956 | K59: =K51+K53+K55+K58 -> 19978.737 | L59: =L51+L53+L55+L58 -> 21092.604
B60: Gross profit | C60: €m | E60: =E47-E59 -> 6451.65 | F60: =F47-F59 -> 7260.6258 | G60: =G47-G59 -> 8178.7407 | H60: =H47-H59 -> 9160.7932 | I60: =I47-I59 -> 10203.291 | J60: =J47-J59 -> 11301.41 | K60: =K47-K59 -> 12448.977 | L60: =L47-L59 -> 13638.508
B61: Gross margin | C61: % | E61: =E60/E47 -> 0.33000767 | F61: =F60/F47 -> 0.33912203 | G61: =G60/G47 -> 0.34823175 | H61: =H60/H47 -> 0.35725041 | I61: =I60/I47 -> 0.36619247 | J61: =J60/J47 -> 0.37507127 | K61: =K60/K47 -> 0.38389931 | L61: =L60/L47 -> 0.3926885
B62: OPERATING EXPENSES (glide to scenario targets by FY29E)
B63: R&D % revenue | C63: % | E63: 0.079 | F63: =$E$63+('0_Dashboard_Toggles'!$H$31-$E$63)*MIN(1,F$4/3) -> 0.076 | G63: =$E$63+('0_Dashboard_Toggles'!$H$31-$E$63)*MIN(1,G$4/3) -> 0.073 | H63: =$E$63+('0_Dashboard_Toggles'!$H$31-$E$63)*MIN(1,H$4/3) -> 0.07 | I63: =$E$63+('0_Dashboard_Toggles'!$H$31-$E$63)*MIN(1,I$4/3) -> 0.07 | J63: =$E$63+('0_Dashboard_Toggles'!$H$31-$E$63)*MIN(1,J$4/3) -> 0.07 | K63: =$E$63+('0_Dashboard_Toggles'!$H$31-$E$63)*MIN(1,K$4/3) -> 0.07 | L63: =$E$63+('0_Dashboard_Toggles'!$H$31-$E$63)*MIN(1,L$4/3) -> 0.07
B64: S&M % revenue | C64: % | E64: 0.079 | F64: =$E$64+('0_Dashboard_Toggles'!$H$32-$E$64)*MIN(1,F$4/3) -> 0.076 | G64: =$E$64+('0_Dashboard_Toggles'!$H$32-$E$64)*MIN(1,G$4/3) -> 0.073 | H64: =$E$64+('0_Dashboard_Toggles'!$H$32-$E$64)*MIN(1,H$4/3) -> 0.07 | I64: =$E$64+('0_Dashboard_Toggles'!$H$32-$E$64)*MIN(1,I$4/3) -> 0.07 | J64: =$E$64+('0_Dashboard_Toggles'!$H$32-$E$64)*MIN(1,J$4/3) -> 0.07 | K64: =$E$64+('0_Dashboard_Toggles'!$H$32-$E$64)*MIN(1,K$4/3) -> 0.07 | L64: =$E$64+('0_Dashboard_Toggles'!$H$32-$E$64)*MIN(1,L$4/3) -> 0.07
B65: G&A % revenue | C65: % | E65: 0.027 | F65: =$E$65+('0_Dashboard_Toggles'!$H$33-$E$65)*MIN(1,F$4/3) -> 0.026333333 | G65: =$E$65+('0_Dashboard_Toggles'!$H$33-$E$65)*MIN(1,G$4/3) -> 0.025666667 | H65: =$E$65+('0_Dashboard_Toggles'!$H$33-$E$65)*MIN(1,H$4/3) -> 0.025 | I65: =$E$65+('0_Dashboard_Toggles'!$H$33-$E$65)*MIN(1,I$4/3) -> 0.025 | J65: =$E$65+('0_Dashboard_Toggles'!$H$33-$E$65)*MIN(1,J$4/3) -> 0.025 | K65: =$E$65+('0_Dashboard_Toggles'!$H$33-$E$65)*MIN(1,K$4/3) -> 0.025 | L65: =$E$65+('0_Dashboard_Toggles'!$H$33-$E$65)*MIN(1,L$4/3) -> 0.025
B66: Research & development | C66: €m | E66: =E47*E63 -> 1544.45 | F66: =F47*F63 -> 1627.1652 | G66: =G47*G63 -> 1714.5136 | H66: =H47*H63 -> 1794.9749 | I66: =I47*I63 -> 1950.4235 | J66: =J47*J63 -> 2109.1956 | K66: =K47*K63 -> 2269.94 | L66: =L47*L63 -> 2431.1779
B67: Sales & marketing | C67: €m | E67: =E47*E64 -> 1544.45 | F67: =F47*F64 -> 1627.1652 | G67: =G47*G64 -> 1714.5136 | H67: =H47*H64 -> 1794.9749 | I67: =I47*I64 -> 1950.4235 | J67: =J47*J64 -> 2109.1956 | K67: =K47*K64 -> 2269.94 | L67: =L47*L64 -> 2431.1779
B68: General & administrative | C68: €m | E68: =E47*E65 -> 527.85 | F68: =F47*F65 -> 563.79846 | G68: =G47*G65 -> 602.81984 | H68: =H47*H65 -> 641.06246 | I68: =I47*I65 -> 696.57982 | J68: =J47*J65 -> 753.28414 | K68: =K47*K65 -> 810.69285 | L68: =L47*L65 -> 868.27781
B69: Total operating expenses | C69: €m | E69: =SUM(E66:E68) -> 3616.75 | F69: =SUM(F66:F68) -> 3818.1288 | G69: =SUM(G66:G68) -> 4031.847 | H69: =SUM(H66:H68) -> 4231.0122 | I69: =SUM(I66:I68) -> 4597.4268 | J69: =SUM(J66:J68) -> 4971.6753 | K69: =SUM(K66:K68) -> 5350.5728 | L69: =SUM(L66:L68) -> 5730.6335
B70: EBIT | C70: €m | E70: =E60-E69 -> 2834.9 | F70: =F60-F69 -> 3442.497 | G70: =G60-G69 -> 4146.8937 | H70: =H60-H69 -> 4929.7809 | I70: =I60-I69 -> 5605.8647 | J70: =J60-J69 -> 6329.7344 | K70: =K60-K69 -> 7098.4043 | L70: =L60-L69 -> 7907.875
B71: EBIT margin | C71: % | E71: =E70/E47 -> 0.14500767 | F71: =F70/F47 -> 0.1607887 | G71: =G70/G47 -> 0.17656509 | H71: =H70/H47 -> 0.19225041 | I71: =I70/I47 -> 0.20119247 | J71: =J70/J47 -> 0.21007127 | K71: =K70/K47 -> 0.21889931 | L71: =L70/L47 -> 0.2276885
B72: EBITDA, CAPEX & WORKING CAPITAL
B73: D&A % revenue | C73: % | E73: 0.0065
B74: Depreciation & amortisation (in OpEx/COGS) | C74: €m | E74: =E47*$E$73 -> 127.075 | F74: =F47*$E$73 -> 139.16544 | G74: =G47*$E$73 -> 152.66217 | H74: =H47*$E$73 -> 166.67624 | I74: =I47*$E$73 -> 181.11075 | J74: =J47*$E$73 -> 195.85388 | K74: =K47*$E$73 -> 210.78014 | L74: =L47*$E$73 -> 225.75223
B75: SBC / MIP % revenue | C75: % | E75: 0.0164
B76: Share-based compensation / MIP expense | C76: €m | E76: =E47*$E$75 -> 320.62 | F76: =F47*$E$75 -> 351.12512 | G76: =G47*$E$75 -> 385.17839 | H76: =H47*$E$75 -> 420.53698 | I76: =I47*$E$75 -> 456.95636 | J76: =J47*$E$75 -> 494.1544 | K76: =K47*$E$75 -> 531.81451 | L76: =L47*$E$75 -> 569.59024
B77: % converted to cash compensation | C77: % | E77: 0 | F77: ='0_Dashboard_Toggles'!$H$36 -> 0.5 | G77: ='0_Dashboard_Toggles'!$H$36 -> 0.5 | H77: ='0_Dashboard_Toggles'!$H$36 -> 0.5 | I77: ='0_Dashboard_Toggles'!$H$36 -> 0.5 | J77: ='0_Dashboard_Toggles'!$H$36 -> 0.5 | K77: ='0_Dashboard_Toggles'!$H$36 -> 0.5 | L77: ='0_Dashboard_Toggles'!$H$36 -> 0.5
B78: Non-cash SBC / MIP | C78: €m | E78: =E76*(1-E77) -> 320.62 | F78: =F76*(1-F77) -> 175.56256 | G78: =G76*(1-G77) -> 192.5892 | H78: =H76*(1-H77) -> 210.26849 | I78: =I76*(1-I77) -> 228.47818 | J78: =J76*(1-J77) -> 247.0772 | K78: =K76*(1-K77) -> 265.90725 | L78: =L76*(1-L77) -> 284.79512
B79: Adj. EBITDA (EBIT + D&A + non-cash SBC) | C79: €m | E79: =E70+E74+E78 -> 3282.595 | F79: =F70+F74+F78 -> 3757.225 | G79: =G70+G74+G78 -> 4492.145 | H79: =H70+H74+H78 -> 5306.7257 | I79: =I70+I74+I78 -> 6015.4536 | J79: =J70+J74+J78 -> 6772.6655 | K79: =K70+K74+K78 -> 7575.0917 | L79: =L70+L74+L78 -> 8418.4223
B80: Adj. EBITDA margin | C80: % | E80: =E79/E47 -> 0.16790767 | F80: =F79/F47 -> 0.1754887 | G80: =G79/G47 -> 0.19126509 | H80: =H79/H47 -> 0.20695041 | I80: =I79/I47 -> 0.21589247 | J80: =J79/J47 -> 0.22477127 | K80: =K79/K47 -> 0.23359931 | L80: =L79/L47 -> 0.2423885
B82: Capex % revenue | C82: % | E82: 0.0045
B83: Capital expenditure | C83: €m | E83: =E47*$E$82 -> 87.975 | F83: =F47*$E$82 -> 96.345306 | G83: =G47*$E$82 -> 105.68919 | H83: =H47*$E$82 -> 115.39124 | I83: =I47*$E$82 -> 125.38437 | J83: =J47*$E$82 -> 135.59115 | K83: =K47*$E$82 -> 145.92471 | L83: =L47*$E$82 -> 156.29
B84: Net operating working capital % revenue | C84: % | E84: =E85/E47 -> -0.1973913 | F84: =$E$84 -> -0.1973913 | G84: =$E$84 -> -0.1973913 | H84: =$E$84 -> -0.1973913 | I84: =$E$84 -> -0.1973913 | J84: =$E$84 -> -0.1973913 | K84: =$E$84 -> -0.1973913 | L84: =$E$84 -> -0.1973913
B85: Net operating working capital (negative) | C85: €m | E85: -3859 | F85: =F47*F84 -> -4226.1612 | G85: =G47*G84 -> -4636.0284 | H85: =H47*H84 -> -5061.6062 | I85: =I47*I84 -> -5499.952 | J85: =J47*J84 -> -5947.6696 | K85: =K47*K84 -> -6400.9487 | L85: =L47*L84 -> -6855.6195
B86: New leases % revenue | C86: % | E86: 0.0025
B87: New lease additions | C87: €m | F87: =F47*$E$86 -> 53.52517 | G87: =G47*$E$86 -> 58.716218 | H87: =H47*$E$86 -> 64.106246 | I87: =I47*$E$86 -> 69.657982 | J87: =J47*$E$86 -> 75.328414 | K87: =K47*$E$86 -> 81.069285 | L87: =L47*$E$86 -> 86.827781

Sheet 3_Financial_Statements
B1: 3 | Integrated Financial Statements (IFRS basis, simplified) | J1: Master check: | K1: ='0_Dashboard_Toggles'!$D$49 -> OK
B2: Income statement → cash flow → balance sheet; debt and interest from Tab 4 | E2: Close / LTM
B3: Fiscal year (Dec YE) | E3: 2026 | F3: 2027 | G3: 2028 | H3: 2029 | I3: 2030 | J3: 2031 | K3: 2032 | L3: 2033
B4: Period (t) | E4: 0 | F4: 1 | G4: 2 | H4: 3 | I4: 4 | J4: 5 | K4: 6 | L4: 7
B5: Revenue | C5: €m | E5: ='2_Operating_Build'!E47 -> 19550 | F5: ='2_Operating_Build'!F47 -> 21410.068 | G5: ='2_Operating_Build'!G47 -> 23486.487 | H5: ='2_Operating_Build'!H47 -> 25642.498 | I5: ='2_Operating_Build'!I47 -> 27863.193 | J5: ='2_Operating_Build'!J47 -> 30131.366 | K5: ='2_Operating_Build'!K47 -> 32427.714 | L5: ='2_Operating_Build'!L47 -> 34731.112
B6: Cost of revenue | C6: €m | E6: =-'2_Operating_Build'!E59 -> -13098.35 | F6: =-'2_Operating_Build'!F59 -> -14149.442 | G6: =-'2_Operating_Build'!G59 -> -15307.747 | H6: =-'2_Operating_Build'!H59 -> -16481.705 | I6: =-'2_Operating_Build'!I59 -> -17659.901 | J6: =-'2_Operating_Build'!J59 -> -18829.956 | K6: =-'2_Operating_Build'!K59 -> -19978.737 | L6: =-'2_Operating_Build'!L59 -> -21092.604
B7: Gross profit | C7: €m | E7: =E5+E6 -> 6451.65 | F7: =F5+F6 -> 7260.6258 | G7: =G5+G6 -> 8178.7407 | H7: =H5+H6 -> 9160.7932 | I7: =I5+I6 -> 10203.291 | J7: =J5+J6 -> 11301.41 | K7: =K5+K6 -> 12448.977 | L7: =L5+L6 -> 13638.508
B8: Research & development | C8: €m | E8: =-'2_Operating_Build'!E66 -> -1544.45 | F8: =-'2_Operating_Build'!F66 -> -1627.1652 | G8: =-'2_Operating_Build'!G66 -> -1714.5136 | H8: =-'2_Operating_Build'!H66 -> -1794.9749 | I8: =-'2_Operating_Build'!I66 -> -1950.4235 | J8: =-'2_Operating_Build'!J66 -> -2109.1956 | K8: =-'2_Operating_Build'!K66 -> -2269.94 | L8: =-'2_Operating_Build'!L66 -> -2431.1779
B9: Sales & marketing | C9: €m | E9: =-'2_Operating_Build'!E67 -> -1544.45 | F9: =-'2_Operating_Build'!F67 -> -1627.1652 | G9: =-'2_Operating_Build'!G67 -> -1714.5136 | H9: =-'2_Operating_Build'!H67 -> -1794.9749 | I9: =-'2_Operating_Build'!I67 -> -1950.4235 | J9: =-'2_Operating_Build'!J67 -> -2109.1956 | K9: =-'2_Operating_Build'!K67 -> -2269.94 | L9: =-'2_Operating_Build'!L67 -> -2431.1779
B10: General & administrative | C10: €m | E10: =-'2_Operating_Build'!E68 -> -527.85 | F10: =-'2_Operating_Build'!F68 -> -563.79846 | G10: =-'2_Operating_Build'!G68 -> -602.81984 | H10: =-'2_Operating_Build'!H68 -> -641.06246 | I10: =-'2_Operating_Build'!I68 -> -696.57982 | J10: =-'2_Operating_Build'!J68 -> -753.28414 | K10: =-'2_Operating_Build'!K68 -> -810.69285 | L10: =-'2_Operating_Build'!L68 -> -868.27781
B11: EBIT | C11: €m | E11: =SUM(E7:E10) -> 2834.9 | F11: =SUM(F7:F10) -> 3442.497 | G11: =SUM(G7:G10) -> 4146.8937 | H11: =SUM(H7:H10) -> 4929.7809 | I11: =SUM(I7:I10) -> 5605.8647 | J11: =SUM(J7:J10) -> 6329.7344 | K11: =SUM(K7:K10) -> 7098.4043 | L11: =SUM(L7:L10) -> 7907.875
B12: Interest expense (cash) | C12: €m | F12: =-'4_Debt_Schedule'!F56 -> -1272.255 | G12: =-'4_Debt_Schedule'!G56 -> -1119.2648 | H12: =-'4_Debt_Schedule'!H56 -> -951.66878 | I12: =-'4_Debt_Schedule'!I56 -> -725.15742 | J12: =-'4_Debt_Schedule'!J56 -> -532.125 | K12: =-'4_Debt_Schedule'!K56 -> -532.125 | L12: =-'4_Debt_Schedule'!L56 -> -532.125
B13: Interest income on cash | C13: €m | F13: ='4_Debt_Schedule'!F57 -> 47.76 | G13: ='4_Debt_Schedule'!G57 -> 30 | H13: ='4_Debt_Schedule'!H57 -> 30 | I13: ='4_Debt_Schedule'!I57 -> 30 | J13: ='4_Debt_Schedule'!J57 -> 56.819112 | K13: ='4_Debt_Schedule'!K57 -> 158.77528 | L13: ='4_Debt_Schedule'!L57 -> 274.36042
B14: Amortisation of financing fees & OID | C14: €m | F14: =-'4_Debt_Schedule'!F58 -> -69.457143 | G14: =-'4_Debt_Schedule'!G58 -> -69.457143 | H14: =-'4_Debt_Schedule'!H58 -> -69.457143 | I14: =-'4_Debt_Schedule'!I58 -> -69.457143 | J14: =-'4_Debt_Schedule'!J58 -> -69.457143 | K14: =-'4_Debt_Schedule'!K58 -> -69.457143 | L14: =-'4_Debt_Schedule'!L58 -> -69.457143
B15: Profit before tax | C15: €m | F15: =F11+F12+F13+F14 -> 2148.5448 | G15: =G11+G12+G13+G14 -> 2988.1717 | H15: =H11+H12+H13+H14 -> 3938.655 | I15: =I11+I12+I13+I14 -> 4841.2501 | J15: =J11+J12+J13+J14 -> 5784.9714 | K15: =K11+K12+K13+K14 -> 6655.5974 | L15: =L11+L12+L13+L14 -> 7580.6532
B17: Net interest expense (tax basis) | C17: €m | F17: =-(F12+F13+F14) -> 1293.9521 | G17: =-(G12+G13+G14) -> 1158.7219 | H17: =-(H12+H13+H14) -> 991.12592 | I17: =-(I12+I13+I14) -> 764.61457 | J17: =-(J12+J13+J14) -> 544.76303 | K17: =-(K12+K13+K14) -> 442.80686 | L17: =-(L12+L13+L14) -> 327.22173
B18: ATAD cap: max(€3m, 30% × tax-EBITDA) | C18: €m | F18: =MAX(3,'0_Dashboard_Toggles'!$C$19*'2_Operating_Build'!F79) -> 1127.1675 | G18: =MAX(3,'0_Dashboard_Toggles'!$C$19*'2_Operating_Build'!G79) -> 1347.6435 | H18: =MAX(3,'0_Dashboard_Toggles'!$C$19*'2_Operating_Build'!H79) -> 1592.0177 | I18: =MAX(3,'0_Dashboard_Toggles'!$C$19*'2_Operating_Build'!I79) -> 1804.6361 | J18: =MAX(3,'0_Dashboard_Toggles'!$C$19*'2_Operating_Build'!J79) -> 2031.7996 | K18: =MAX(3,'0_Dashboard_Toggles'!$C$19*'2_Operating_Build'!K79) -> 2272.5275 | L18: =MAX(3,'0_Dashboard_Toggles'!$C$19*'2_Operating_Build'!L79) -> 2525.5267
B19: Disallowed interest carried forward – opening | C19: €m | F19: =E21 -> 0 | G19: =F21 -> 166.78465 | H19: =G21 -> 0 | I19: =H21 -> 0 | J19: =I21 -> 0 | K19: =J21 -> 0 | L19: =K21 -> 0
B20: Deductible interest | C20: €m | F20: =MIN(F17+F19,F18) -> 1127.1675 | G20: =MIN(G17+G19,G18) -> 1325.5066 | H20: =MIN(H17+H19,H18) -> 991.12592 | I20: =MIN(I17+I19,I18) -> 764.61457 | J20: =MIN(J17+J19,J18) -> 544.76303 | K20: =MIN(K17+K19,K18) -> 442.80686 | L20: =MIN(L17+L19,L18) -> 327.22173
B21: Disallowed interest carried forward – closing | C21: €m | E21: 0 | F21: =F19+F17-F20 -> 166.78465 | G21: =G19+G17-G20 -> 0 | H21: =H19+H17-H20 -> 0 | I21: =I19+I17-I20 -> 0 | J21: =J19+J17-J20 -> 0 | K21: =K19+K17-K20 -> 0 | L21: =L19+L17-L20 -> 0
B22: Taxable income | C22: €m | F22: =F11-F20 -> 2315.3295 | G22: =G11-G20 -> 2821.3871 | H22: =H11-H20 -> 3938.655 | I22: =I11-I20 -> 4841.2501 | J22: =J11-J20 -> 5784.9714 | K22: =K11-K20 -> 6655.5974 | L22: =L11-L20 -> 7580.6532
B23: Corporate income tax | C23: €m | F23: =-MAX(0,F22)*'0_Dashboard_Toggles'!$C$18 -> -577.44318 | G23: =-MAX(0,G22)*'0_Dashboard_Toggles'!$C$18 -> -703.65394 | H23: =-MAX(0,H22)*'0_Dashboard_Toggles'!$C$18 -> -982.30056 | I23: =-MAX(0,I22)*'0_Dashboard_Toggles'!$C$18 -> -1207.4078 | J23: =-MAX(0,J22)*'0_Dashboard_Toggles'!$C$18 -> -1442.7719 | K23: =-MAX(0,K22)*'0_Dashboard_Toggles'!$C$18 -> -1659.906 | L23: =-MAX(0,L22)*'0_Dashboard_Toggles'!$C$18 -> -1890.6149
B24: Pillar Two top-up tax (15% GloBE floor) | C24: €m | F24: =-MAX(0,0.15*F22+F23) -> 0 | G24: =-MAX(0,0.15*G22+G23) -> 0 | H24: =-MAX(0,0.15*H22+H23) -> 0 | I24: =-MAX(0,0.15*I22+I23) -> 0 | J24: =-MAX(0,0.15*J22+J23) -> 0 | K24: =-MAX(0,0.15*K22+K23) -> 0 | L24: =-MAX(0,0.15*L22+L23) -> 0
B25: Net income | C25: €m | F25: =F15+F23+F24 -> 1571.1017 | G25: =G15+G23+G24 -> 2284.5178 | H25: =H15+H23+H24 -> 2956.3545 | I25: =I15+I23+I24 -> 3633.8423 | J25: =J15+J23+J24 -> 4342.1995 | K25: =K15+K23+K24 -> 4995.6914 | L25: =L15+L23+L24 -> 5690.0383
B27: CASH FLOW STATEMENT
B28: Net income | C28: €m | F28: =F25 -> 1571.1017 | G28: =G25 -> 2284.5178 | H28: =H25 -> 2956.3545 | I28: =I25 -> 3633.8423 | J28: =J25 -> 4342.1995 | K28: =K25 -> 4995.6914 | L28: =L25 -> 5690.0383
B29: D&A | C29: €m | F29: ='2_Operating_Build'!F74 -> 139.16544 | G29: ='2_Operating_Build'!G74 -> 152.66217 | H29: ='2_Operating_Build'!H74 -> 166.67624 | I29: ='2_Operating_Build'!I74 -> 181.11075 | J29: ='2_Operating_Build'!J74 -> 195.85388 | K29: ='2_Operating_Build'!K74 -> 210.78014 | L29: ='2_Operating_Build'!L74 -> 225.75223
B30: Non-cash SBC / MIP | C30: €m | F30: ='2_Operating_Build'!F78 -> 175.56256 | G30: ='2_Operating_Build'!G78 -> 192.5892 | H30: ='2_Operating_Build'!H78 -> 210.26849 | I30: ='2_Operating_Build'!I78 -> 228.47818 | J30: ='2_Operating_Build'!J78 -> 247.0772 | K30: ='2_Operating_Build'!K78 -> 265.90725 | L30: ='2_Operating_Build'!L78 -> 284.79512
B31: Amortisation of financing fees | C31: €m | F31: =-F14 -> 69.457143 | G31: =-G14 -> 69.457143 | H31: =-H14 -> 69.457143 | I31: =-I14 -> 69.457143 | J31: =-J14 -> 69.457143 | K31: =-K14 -> 69.457143 | L31: =-L14 -> 69.457143
B32: (Increase)/decrease in net working capital | C32: €m | F32: =-('2_Operating_Build'!F85-'2_Operating_Build'!E85) -> 367.16125 | G32: =-('2_Operating_Build'!G85-'2_Operating_Build'!F85) -> 409.86712 | H32: =-('2_Operating_Build'!H85-'2_Operating_Build'!G85) -> 425.57786 | I32: =-('2_Operating_Build'!I85-'2_Operating_Build'!H85) -> 438.34574 | J32: =-('2_Operating_Build'!J85-'2_Operating_Build'!I85) -> 447.7176 | K32: =-('2_Operating_Build'!K85-'2_Operating_Build'!J85) -> 453.27917 | L32: =-('2_Operating_Build'!L85-'2_Operating_Build'!K85) -> 454.67081
B33: Cash flow from operations | C33: €m | F33: =SUM(F28:F32) -> 2322.4481 | G33: =SUM(G28:G32) -> 3109.0934 | H33: =SUM(H28:H32) -> 3828.3342 | I33: =SUM(I28:I32) -> 4551.2341 | J33: =SUM(J28:J32) -> 5302.3053 | K33: =SUM(K28:K32) -> 5995.1151 | L33: =SUM(L28:L32) -> 6724.7136
B34: Capital expenditure | C34: €m | F34: =-'2_Operating_Build'!F83 -> -96.345306 | G34: =-'2_Operating_Build'!G83 -> -105.68919 | H34: =-'2_Operating_Build'!H83 -> -115.39124 | I34: =-'2_Operating_Build'!I83 -> -125.38437 | J34: =-'2_Operating_Build'!J83 -> -135.59115 | K34: =-'2_Operating_Build'!K83 -> -145.92471 | L34: =-'2_Operating_Build'!L83 -> -156.29
B35: Lease principal payments | C35: €m | F35: =-'4_Debt_Schedule'!F52 -> -75.2 | G35: =-'4_Debt_Schedule'!G52 -> -71.732027 | H35: =-'4_Debt_Schedule'!H52 -> -69.649498 | I35: =-'4_Debt_Schedule'!I52 -> -68.762578 | J35: =-'4_Debt_Schedule'!J52 -> -68.905842 | K35: =-'4_Debt_Schedule'!K52 -> -69.933454 | L35: =-'4_Debt_Schedule'!L52 -> -71.715187
B36: Free cash flow before debt service | C36: €m | F36: =F33+F34+F35 -> 2150.9028 | G36: =G33+G34+G35 -> 2931.6722 | H36: =H33+H34+H35 -> 3643.2934 | I36: =I33+I34+I35 -> 4357.0872 | J36: =J33+J34+J35 -> 5097.8083 | K36: =K33+K34+K35 -> 5779.257 | L36: =L33+L34+L35 -> 6496.7084
B37: Recap: net debt proceeds less dividends paid (net cash effect) | F37: ='4_Debt_Schedule'!F84-'4_Debt_Schedule'!F87-'4_Debt_Schedule'!F89 -> 0 | G37: ='4_Debt_Schedule'!G84-'4_Debt_Schedule'!G87-'4_Debt_Schedule'!G89 -> 0 | H37: ='4_Debt_Schedule'!H84-'4_Debt_Schedule'!H87-'4_Debt_Schedule'!H89 -> 0 | I37: ='4_Debt_Schedule'!I84-'4_Debt_Schedule'!I87-'4_Debt_Schedule'!I89 -> 0 | J37: ='4_Debt_Schedule'!J84-'4_Debt_Schedule'!J87-'4_Debt_Schedule'!J89 -> 0 | K37: ='4_Debt_Schedule'!K84-'4_Debt_Schedule'!K87-'4_Debt_Schedule'!K89 -> 0 | L37: ='4_Debt_Schedule'!L84-'4_Debt_Schedule'!L87-'4_Debt_Schedule'!L89 -> 0
B38: TLA mandatory amortisation | C38: €m | F38: =-'4_Debt_Schedule'!F28 -> -404 | G38: =-'4_Debt_Schedule'!G28 -> -404 | H38: =-'4_Debt_Schedule'!H28 -> 0 | I38: =-'4_Debt_Schedule'!I28 -> 0 | J38: =-'4_Debt_Schedule'!J28 -> 0 | K38: =-'4_Debt_Schedule'!K28 -> 0 | L38: =-'4_Debt_Schedule'!L28 -> 0
B39: TLA optional prepayment (sweep) | C39: €m | F39: =-'4_Debt_Schedule'!F29 -> -2634.9028 | G39: =-'4_Debt_Schedule'!G29 -> -597.09724 | H39: =-'4_Debt_Schedule'!H29 -> 0 | I39: =-'4_Debt_Schedule'!I29 -> 0 | J39: =-'4_Debt_Schedule'!J29 -> 0 | K39: =-'4_Debt_Schedule'!K29 -> 0 | L39: =-'4_Debt_Schedule'!L29 -> 0
B40: TLB optional prepayment (sweep) | C40: €m | F40: =-'4_Debt_Schedule'!F35 -> 0 | G40: =-'4_Debt_Schedule'!G35 -> -1930.575 | H40: =-'4_Debt_Schedule'!H35 -> -3643.2934 | I40: =-'4_Debt_Schedule'!I35 -> -3016.1316 | J40: =-'4_Debt_Schedule'!J35 -> 0 | K40: =-'4_Debt_Schedule'!K35 -> 0 | L40: =-'4_Debt_Schedule'!L35 -> 0
B41: RCF drawdown / (repayment) | C41: €m | F41: ='4_Debt_Schedule'!F22 -> 0 | G41: ='4_Debt_Schedule'!G22 -> 0 | H41: ='4_Debt_Schedule'!H22 -> 0 | I41: ='4_Debt_Schedule'!I22 -> 0 | J41: ='4_Debt_Schedule'!J22 -> 0 | K41: ='4_Debt_Schedule'!K22 -> 0 | L41: ='4_Debt_Schedule'!L22 -> 0
B42: Net change in cash | C42: €m | F42: =F36+SUM(F38:F41)+F37 -> -888 | G42: =G36+SUM(G38:G41)+G37 -> 0 | H42: =H36+SUM(H38:H41)+H37 -> 0 | I42: =I36+SUM(I38:I41)+I37 -> 1340.9556 | J42: =J36+SUM(J38:J41)+J37 -> 5097.8083 | K42: =K36+SUM(K38:K41)+K37 -> 5779.257 | L42: =L36+SUM(L38:L41)+L37 -> 6496.7084
B43: Opening cash | C43: €m | F43: =E44 -> 2388 | G43: =F44 -> 1500 | H43: =G44 -> 1500 | I43: =H44 -> 1500 | J43: =I44 -> 2840.9556 | K43: =J44 -> 7938.7639 | L43: =K44 -> 13718.021
B44: Closing cash | C44: €m | E44: ='1_Transaction_Summary'!F48 -> 2388 | F44: =F43+F42 -> 1500 | G44: =G43+G42 -> 1500 | H44: =H43+H42 -> 1500 | I44: =I43+I42 -> 2840.9556 | J44: =J43+J42 -> 7938.7639 | K44: =K43+K42 -> 13718.021 | L44: =L43+L42 -> 20214.729
B46: BALANCE SHEET (pro forma at close in FY26E column)
B47: Cash and equivalents | C47: €m | E47: =E44 -> 2388 | F47: =F44 -> 1500 | G47: =G44 -> 1500 | H47: =H44 -> 1500 | I47: =I44 -> 2840.9556 | J47: =J44 -> 7938.7639 | K47: =K44 -> 13718.021 | L47: =L44 -> 20214.729
B48: Net operating working capital | C48: €m | E48: ='2_Operating_Build'!E85 -> -3859 | F48: ='2_Operating_Build'!F85 -> -4226.1612 | G48: ='2_Operating_Build'!G85 -> -4636.0284 | H48: ='2_Operating_Build'!H85 -> -5061.6062 | I48: ='2_Operating_Build'!I85 -> -5499.952 | J48: ='2_Operating_Build'!J85 -> -5947.6696 | K48: ='2_Operating_Build'!K85 -> -6400.9487 | L48: ='2_Operating_Build'!L85 -> -6855.6195
B49: PP&E and right-of-use assets | C49: €m | E49: 418 | F49: =E49+'2_Operating_Build'!F83+'2_Operating_Build'!F87-'2_Operating_Build'!F74 -> 428.70503 | G49: =F49+'2_Operating_Build'!G83+'2_Operating_Build'!G87-'2_Operating_Build'!G74 -> 440.44828 | H49: =G49+'2_Operating_Build'!H83+'2_Operating_Build'!H87-'2_Operating_Build'!H74 -> 453.26953 | I49: =H49+'2_Operating_Build'!I83+'2_Operating_Build'!I87-'2_Operating_Build'!I74 -> 467.20112 | J49: =I49+'2_Operating_Build'!J83+'2_Operating_Build'!J87-'2_Operating_Build'!J74 -> 482.26681 | K49: =J49+'2_Operating_Build'!K83+'2_Operating_Build'!K87-'2_Operating_Build'!K74 -> 498.48066 | L49: =K49+'2_Operating_Build'!L83+'2_Operating_Build'!L87-'2_Operating_Build'!L74 -> 515.84622
B50: Long-term investments | C50: €m | E50: 1118 | F50: =E50 -> 1118 | G50: =F50 -> 1118 | H50: =G50 -> 1118 | I50: =H50 -> 1118 | J50: =I50 -> 1118 | K50: =J50 -> 1118 | L50: =K50 -> 1118
B51: Other non-current assets (DTA, finance lease rec., restricted) | C51: €m | E51: 690 | F51: =E51 -> 690 | G51: =F51 -> 690 | H51: =G51 -> 690 | I51: =H51 -> 690 | J51: =I51 -> 690 | K51: =J51 -> 690 | L51: =K51 -> 690
B52: Goodwill & intangibles (incl. transaction goodwill) | C52: €m | E52: =E64-SUM(E47:E51)-E53 -> 109667.95 | F52: =E52 -> 109667.95 | G52: =F52 -> 109667.95 | H52: =G52 -> 109667.95 | I52: =H52 -> 109667.95 | J52: =I52 -> 109667.95 | K52: =J52 -> 109667.95 | L52: =K52 -> 109667.95
B53: Capitalised financing fees & OID | C53: €m | E53: ='1_Transaction_Summary'!C37+'1_Transaction_Summary'!C38 -> 486.2 | F53: =E53+F14 -> 416.74286 | G53: =F53+G14 -> 347.28571 | H53: =G53+H14 -> 277.82857 | I53: =H53+I14 -> 208.37143 | J53: =I53+J14 -> 138.91429 | K53: =J53+K14 -> 69.457143 | L53: =K53+L14 -> 0
B54: Total assets | C54: €m | E54: =SUM(E47:E53) -> 110909.15 | F54: =SUM(F47:F53) -> 109595.23 | G54: =SUM(G47:G53) -> 109127.65 | H54: =SUM(H47:H53) -> 108645.44 | I54: =SUM(I47:I53) -> 109492.52 | J54: =SUM(J47:J53) -> 114088.22 | K54: =SUM(K47:K53) -> 119360.96 | L54: =SUM(L47:L53) -> 125350.9
B55: Recap notes (dividend recap module) | E55: ='4_Debt_Schedule'!E85 -> 0 | F55: ='4_Debt_Schedule'!F85 -> 0 | G55: ='4_Debt_Schedule'!G85 -> 0 | H55: ='4_Debt_Schedule'!H85 -> 0 | I55: ='4_Debt_Schedule'!I85 -> 0 | J55: ='4_Debt_Schedule'!J85 -> 0 | K55: ='4_Debt_Schedule'!K85 -> 0 | L55: ='4_Debt_Schedule'!L85 -> 0
B56: Term Loan A | C56: €m | E56: ='4_Debt_Schedule'!E31 -> 4040 | F56: ='4_Debt_Schedule'!F31 -> 1001.0972 | G56: ='4_Debt_Schedule'!G31 -> 0 | H56: ='4_Debt_Schedule'!H31 -> 0 | I56: ='4_Debt_Schedule'!I31 -> 0 | J56: ='4_Debt_Schedule'!J31 -> 0 | K56: ='4_Debt_Schedule'!K31 -> 0 | L56: ='4_Debt_Schedule'!L31 -> 0
B57: Term Loan B | C57: €m | E57: ='4_Debt_Schedule'!E36 -> 8590 | F57: ='4_Debt_Schedule'!F36 -> 8590 | G57: ='4_Debt_Schedule'!G36 -> 6659.425 | H57: ='4_Debt_Schedule'!H36 -> 3016.1316 | I57: ='4_Debt_Schedule'!I36 -> 0 | J57: ='4_Debt_Schedule'!J36 -> 0 | K57: ='4_Debt_Schedule'!K36 -> 0 | L57: ='4_Debt_Schedule'!L36 -> 0
B58: Senior Unsecured Notes | C58: €m | E58: ='4_Debt_Schedule'!E41 -> 7070 | F58: ='4_Debt_Schedule'!F41 -> 7070 | G58: ='4_Debt_Schedule'!G41 -> 7070 | H58: ='4_Debt_Schedule'!H41 -> 7070 | I58: ='4_Debt_Schedule'!I41 -> 7070 | J58: ='4_Debt_Schedule'!J41 -> 7070 | K58: ='4_Debt_Schedule'!K41 -> 7070 | L58: ='4_Debt_Schedule'!L41 -> 7070
B59: Revolving Credit Facility | C59: €m | E59: ='4_Debt_Schedule'!E47 -> 0 | F59: ='4_Debt_Schedule'!F47 -> 0 | G59: ='4_Debt_Schedule'!G47 -> 0 | H59: ='4_Debt_Schedule'!H47 -> 0 | I59: ='4_Debt_Schedule'!I47 -> 0 | J59: ='4_Debt_Schedule'!J47 -> 0 | K59: ='4_Debt_Schedule'!K47 -> 0 | L59: ='4_Debt_Schedule'!L47 -> 0
B60: Lease liabilities | C60: €m | E60: ='4_Debt_Schedule'!E53 -> 470 | F60: ='4_Debt_Schedule'!F53 -> 448.32517 | G60: ='4_Debt_Schedule'!G53 -> 435.30936 | H60: ='4_Debt_Schedule'!H53 -> 429.76611 | I60: ='4_Debt_Schedule'!I53 -> 430.66151 | J60: ='4_Debt_Schedule'!J53 -> 437.08409 | K60: ='4_Debt_Schedule'!K53 -> 448.21992 | L60: ='4_Debt_Schedule'!L53 -> 463.33251
B61: Other liabilities (provisions, derivatives, DTL) | C61: €m | E61: 112 | F61: =E61 -> 112 | G61: =F61 -> 112 | H61: =G61 -> 112 | I61: =H61 -> 112 | J61: =I61 -> 112 | K61: =J61 -> 112 | L61: =K61 -> 112
B62: Total liabilities | C62: €m | E62: =SUM(E55:E61) -> 20282 | F62: =SUM(F55:F61) -> 17221.422 | G62: =SUM(G55:G61) -> 14276.734 | H62: =SUM(H55:H61) -> 10627.898 | I62: =SUM(I55:I61) -> 7612.6615 | J62: =SUM(J55:J61) -> 7619.0841 | K62: =SUM(K55:K61) -> 7630.2199 | L62: =SUM(L55:L61) -> 7645.3325
B63: Shareholders' equity | C63: €m | E63: ='1_Transaction_Summary'!C49+'1_Transaction_Summary'!C50-'1_Transaction_Summary'!C36 -> 90627.147 | F63: =E63+F25+F30-'4_Debt_Schedule'!F89-'4_Debt_Schedule'!F87 -> 92373.811 | G63: =F63+G25+G30-'4_Debt_Schedule'!G89-'4_Debt_Schedule'!G87 -> 94850.918 | H63: =G63+H25+H30-'4_Debt_Schedule'!H89-'4_Debt_Schedule'!H87 -> 98017.541 | I63: =H63+I25+I30-'4_Debt_Schedule'!I89-'4_Debt_Schedule'!I87 -> 101879.86 | J63: =I63+J25+J30-'4_Debt_Schedule'!J89-'4_Debt_Schedule'!J87 -> 106469.14 | K63: =J63+K25+K30-'4_Debt_Schedule'!K89-'4_Debt_Schedule'!K87 -> 111730.74 | L63: =K63+L25+L30-'4_Debt_Schedule'!L89-'4_Debt_Schedule'!L87 -> 117705.57
B64: Total liabilities & equity | C64: €m | E64: =E62+E63 -> 110909.15 | F64: =F62+F63 -> 109595.23 | G64: =G62+G63 -> 109127.65 | H64: =H62+H63 -> 108645.44 | I64: =I62+I63 -> 109492.52 | J64: =J62+J63 -> 114088.22 | K64: =K62+K63 -> 119360.96 | L64: =L62+L63 -> 125350.9
B66: CHECK: assets − (liabilities + equity) | C66: €m | E66: =ROUND(E54-E64,3) -> 0 | F66: =ROUND(F54-F64,3) -> 0 | G66: =ROUND(G54-G64,3) -> 0 | H66: =ROUND(H54-H64,3) -> 0 | I66: =ROUND(I54-I64,3) -> 0 | J66: =ROUND(J54-J64,3) -> 0 | K66: =ROUND(K54-K64,3) -> 0 | L66: =ROUND(L54-L64,3) -> 0

Sheet 4_Debt_Schedule
B1: 4 | Debt Schedule – Multi-Tranche European Capital Structure & Cash Sweep | J1: Master check: | K1: ='0_Dashboard_Toggles'!$D$49 -> OK
B2: Circularity: CircOn=1 uses average balances (enable iterative calc: 100 iterations, 0.001) or run macro SolveInterestCircularity | E2: Close / LTM
B3: Fiscal year (Dec YE) | E3: 2026 | F3: 2027 | G3: 2028 | H3: 2029 | I3: 2030 | J3: 2031 | K3: 2032 | L3: 2033
B4: Period (t) | E4: 0 | F4: 1 | G4: 2 | H4: 3 | I4: 4 | J4: 5 | K4: 6 | L4: 7
B5: RATES
B6: 3M EURIBOR forward curve | C6: % | D6: Input – refresh from Bloomberg EUR 3M forwards | F6: 0.021 | G6: 0.022 | H6: 0.023 | I6: 0.024 | J6: 0.025 | K6: 0.025 | L6: 0.025
B7: EURIBOR incl. scenario shift | C7: % | F7: =MAX(0,F6+'0_Dashboard_Toggles'!$H$34/10000) -> 0.021 | G7: =MAX(0,G6+'0_Dashboard_Toggles'!$H$34/10000) -> 0.022 | H7: =MAX(0,H6+'0_Dashboard_Toggles'!$H$34/10000) -> 0.023 | I7: =MAX(0,I6+'0_Dashboard_Toggles'!$H$34/10000) -> 0.024 | J7: =MAX(0,J6+'0_Dashboard_Toggles'!$H$34/10000) -> 0.025 | K7: =MAX(0,K6+'0_Dashboard_Toggles'!$H$34/10000) -> 0.025 | L7: =MAX(0,L6+'0_Dashboard_Toggles'!$H$34/10000) -> 0.025
B8: Yield on cash deposits | C8: % | D8: Input | E8: 0.02
B10: TRANCHE TERMS | C10: Size €m | D10: Margin / coupon | E10: Maturity (FY) | F10: Amort. % p.a.
B11: Term Loan A (senior secured, amortising) | C11: ='1_Transaction_Summary'!C42 -> 4040 | D11: 0.0325 | E11: 2033 | F11: 0.1
B12: Term Loan B (senior secured, bullet, 0% floor) | C12: ='1_Transaction_Summary'!C43 -> 8590 | D12: 0.04 | E12: 2034 | F12: 0
B13: Senior Unsecured Notes (fixed, NC3) | C13: ='1_Transaction_Summary'!C44 -> 7070 | D13: 0.075 | E13: 2034 | F13: 0
B14: RCF margin (drawn) | D14: 0.03 | E14: 2032
B15: RCF commitment (limit) | undrawn fee | C15: 500 | D15: 0.00375
B17: CASH AVAILABLE FOR DEBT SWEEP
B18: Opening cash | C18: €m | F18: ='3_Financial_Statements'!E44 -> 2388 | G18: ='3_Financial_Statements'!F44 -> 1500 | H18: ='3_Financial_Statements'!G44 -> 1500 | I18: ='3_Financial_Statements'!H44 -> 1500 | J18: ='3_Financial_Statements'!I44 -> 2840.9556 | K18: ='3_Financial_Statements'!J44 -> 7938.7639 | L18: ='3_Financial_Statements'!K44 -> 13718.021
B19: Free cash flow before debt service | C19: €m | F19: ='3_Financial_Statements'!F36 -> 2150.9028 | G19: ='3_Financial_Statements'!G36 -> 2931.6722 | H19: ='3_Financial_Statements'!H36 -> 3643.2934 | I19: ='3_Financial_Statements'!I36 -> 4357.0872 | J19: ='3_Financial_Statements'!J36 -> 5097.8083 | K19: ='3_Financial_Statements'!K36 -> 5779.257 | L19: ='3_Financial_Statements'!L36 -> 6496.7084
B20: Less: TLA mandatory amortisation | C20: €m | F20: =-F28 -> -404 | G20: =-G28 -> -404 | H20: =-H28 -> 0 | I20: =-I28 -> 0 | J20: =-J28 -> 0 | K20: =-K28 -> 0 | L20: =-L28 -> 0
B21: Cash available after mandatory debt service and minimum cash | C21: €m | F21: =F18+F19+F20-'0_Dashboard_Toggles'!$C$13 -> 2634.9028 | G21: =G18+G19+G20-'0_Dashboard_Toggles'!$C$13 -> 2527.6722 | H21: =H18+H19+H20-'0_Dashboard_Toggles'!$C$13 -> 3643.2934 | I21: =I18+I19+I20-'0_Dashboard_Toggles'!$C$13 -> 4357.0872 | J21: =J18+J19+J20-'0_Dashboard_Toggles'!$C$13 -> 6438.7639 | K21: =K18+K19+K20-'0_Dashboard_Toggles'!$C$13 -> 12218.021 | L21: =L18+L19+L20-'0_Dashboard_Toggles'!$C$13 -> 18714.729
B22: RCF drawdown / (repayment) | C22: €m | F22: =IF(F21<0,MIN(-F21,$C$15-E47),-MIN(E47,F21)) -> 0 | G22: =IF(G21<0,MIN(-G21,$C$15-F47),-MIN(F47,G21)) -> 0 | H22: =IF(H21<0,MIN(-H21,$C$15-G47),-MIN(G47,H21)) -> 0 | I22: =IF(I21<0,MIN(-I21,$C$15-H47),-MIN(H47,I21)) -> 0 | J22: =IF(J21<0,MIN(-J21,$C$15-I47),-MIN(I47,J21)) -> 0 | K22: =IF(K21<0,MIN(-K21,$C$15-J47),-MIN(J47,K21)) -> 0 | L22: =IF(L21<0,MIN(-L21,$C$15-K47),-MIN(K47,L21)) -> 0
B23: Cash available for optional sweep | C23: €m | F23: =MAX(0,F21+MIN(0,F22)) -> 2634.9028 | G23: =MAX(0,G21+MIN(0,G22)) -> 2527.6722 | H23: =MAX(0,H21+MIN(0,H22)) -> 3643.2934 | I23: =MAX(0,I21+MIN(0,I22)) -> 4357.0872 | J23: =MAX(0,J21+MIN(0,J22)) -> 6438.7639 | K23: =MAX(0,K21+MIN(0,K22)) -> 12218.021 | L23: =MAX(0,L21+MIN(0,L22)) -> 18714.729
B24: Cash applied to sweep | C24: €m | F24: =F23*'0_Dashboard_Toggles'!$C$11*'0_Dashboard_Toggles'!$C$12 -> 2634.9028 | G24: =G23*'0_Dashboard_Toggles'!$C$11*'0_Dashboard_Toggles'!$C$12 -> 2527.6722 | H24: =H23*'0_Dashboard_Toggles'!$C$11*'0_Dashboard_Toggles'!$C$12 -> 3643.2934 | I24: =I23*'0_Dashboard_Toggles'!$C$11*'0_Dashboard_Toggles'!$C$12 -> 4357.0872 | J24: =J23*'0_Dashboard_Toggles'!$C$11*'0_Dashboard_Toggles'!$C$12 -> 6438.7639 | K24: =K23*'0_Dashboard_Toggles'!$C$11*'0_Dashboard_Toggles'!$C$12 -> 12218.021 | L24: =L23*'0_Dashboard_Toggles'!$C$11*'0_Dashboard_Toggles'!$C$12 -> 18714.729
B26: TERM LOAN A (E + 325 bps, 7-yr, 10% p.a. amortisation, balloon FY33)
B27: Opening balance | C27: €m | F27: =E31 -> 4040 | G27: =F31 -> 1001.0972 | H27: =G31 -> 0 | I27: =H31 -> 0 | J27: =I31 -> 0 | K27: =J31 -> 0 | L27: =K31 -> 0
B28: Mandatory amortisation | C28: €m | F28: =IF(F$3>=$E$11,F27,MIN(F27,$C$11*$F$11)) -> 404 | G28: =IF(G$3>=$E$11,G27,MIN(G27,$C$11*$F$11)) -> 404 | H28: =IF(H$3>=$E$11,H27,MIN(H27,$C$11*$F$11)) -> 0 | I28: =IF(I$3>=$E$11,I27,MIN(I27,$C$11*$F$11)) -> 0 | J28: =IF(J$3>=$E$11,J27,MIN(J27,$C$11*$F$11)) -> 0 | K28: =IF(K$3>=$E$11,K27,MIN(K27,$C$11*$F$11)) -> 0 | L28: =IF(L$3>=$E$11,L27,MIN(L27,$C$11*$F$11)) -> 0
B29: Optional prepayment (sweep) | C29: €m | F29: =MIN(F27-F28,F24) -> 2634.9028 | G29: =MIN(G27-G28,G24) -> 597.09724 | H29: =MIN(H27-H28,H24) -> 0 | I29: =MIN(I27-I28,I24) -> 0 | J29: =MIN(J27-J28,J24) -> 0 | K29: =MIN(K27-K28,K24) -> 0 | L29: =MIN(L27-L28,L24) -> 0
B30: Interest expense | C30: €m | F30: =IF('0_Dashboard_Toggles'!$C$10=1,AVERAGE(F27,F31),F27)*(F$7+$D$11) -> 216.14 | G30: =IF('0_Dashboard_Toggles'!$C$10=1,AVERAGE(G27,G31),G27)*(G$7+$D$11) -> 54.5598 | H30: =IF('0_Dashboard_Toggles'!$C$10=1,AVERAGE(H27,H31),H27)*(H$7+$D$11) -> 0 | I30: =IF('0_Dashboard_Toggles'!$C$10=1,AVERAGE(I27,I31),I27)*(I$7+$D$11) -> 0 | J30: =IF('0_Dashboard_Toggles'!$C$10=1,AVERAGE(J27,J31),J27)*(J$7+$D$11) -> 0 | K30: =IF('0_Dashboard_Toggles'!$C$10=1,AVERAGE(K27,K31),K27)*(K$7+$D$11) -> 0 | L30: =IF('0_Dashboard_Toggles'!$C$10=1,AVERAGE(L27,L31),L27)*(L$7+$D$11) -> 0
B31: Closing balance | C31: €m | E31: =C11 -> 4040 | F31: =F27-F28-F29 -> 1001.0972 | G31: =G27-G28-G29 -> 0 | H31: =H27-H28-H29 -> 0 | I31: =I27-I28-I29 -> 0 | J31: =J27-J28-J29 -> 0 | K31: =K27-K28-K29 -> 0 | L31: =L27-L28-L29 -> 0
B33: TERM LOAN B (E + 400 bps, 8-yr bullet, swept after TLA)
B34: Opening balance | C34: €m | F34: =E36 -> 8590 | G34: =F36 -> 8590 | H34: =G36 -> 6659.425 | I34: =H36 -> 3016.1316 | J34: =I36 -> 0 | K34: =J36 -> 0 | L34: =K36 -> 0
B35: Optional prepayment (sweep) | C35: €m | F35: =MIN(F34,F24-F29) -> 0 | G35: =MIN(G34,G24-G29) -> 1930.575 | H35: =MIN(H34,H24-H29) -> 3643.2934 | I35: =MIN(I34,I24-I29) -> 3016.1316 | J35: =MIN(J34,J24-J29) -> 0 | K35: =MIN(K34,K24-K29) -> 0 | L35: =MIN(L34,L24-L29) -> 0
B36: Closing balance | C36: €m | E36: =C12 -> 8590 | F36: =F34-F35 -> 8590 | G36: =G34-G35 -> 6659.425 | H36: =H34-H35 -> 3016.1316 | I36: =I34-I35 -> 0 | J36: =J34-J35 -> 0 | K36: =K34-K35 -> 0 | L36: =L34-L35 -> 0
B37: Interest expense | C37: €m | F37: =IF('0_Dashboard_Toggles'!$C$10=1,AVERAGE(F34,F36),F34)*(F$7+$D$12) -> 523.99 | G37: =IF('0_Dashboard_Toggles'!$C$10=1,AVERAGE(G34,G36),G34)*(G$7+$D$12) -> 532.58 | H37: =IF('0_Dashboard_Toggles'!$C$10=1,AVERAGE(H34,H36),H34)*(H$7+$D$12) -> 419.54378 | I37: =IF('0_Dashboard_Toggles'!$C$10=1,AVERAGE(I34,I36),I34)*(I$7+$D$12) -> 193.03242 | J37: =IF('0_Dashboard_Toggles'!$C$10=1,AVERAGE(J34,J36),J34)*(J$7+$D$12) -> 0 | K37: =IF('0_Dashboard_Toggles'!$C$10=1,AVERAGE(K34,K36),K34)*(K$7+$D$12) -> 0 | L37: =IF('0_Dashboard_Toggles'!$C$10=1,AVERAGE(L34,L36),L34)*(L$7+$D$12) -> 0
B39: SENIOR UNSECURED NOTES (7.50% fixed, 8-yr, non-call 3)
B40: Opening balance | C40: €m | F40: =E41 -> 7070 | G40: =F41 -> 7070 | H40: =G41 -> 7070 | I40: =H41 -> 7070 | J40: =I41 -> 7070 | K40: =J41 -> 7070 | L40: =K41 -> 7070
B41: Closing balance | C41: €m | E41: =C13 -> 7070 | F41: =F40 -> 7070 | G41: =G40 -> 7070 | H41: =H40 -> 7070 | I41: =I40 -> 7070 | J41: =J40 -> 7070 | K41: =K40 -> 7070 | L41: =L40 -> 7070
B42: Interest expense (fixed – no circularity) | C42: €m | F42: =F40*$D$13 -> 530.25 | G42: =G40*$D$13 -> 530.25 | H42: =H40*$D$13 -> 530.25 | I42: =I40*$D$13 -> 530.25 | J42: =J40*$D$13 -> 530.25 | K42: =K40*$D$13 -> 530.25 | L42: =L40*$D$13 -> 530.25
B44: REVOLVING CREDIT FACILITY (€500m, E + 300 bps, 37.5 bps undrawn)
B45: Opening balance | C45: €m | F45: =E47 -> 0 | G45: =F47 -> 0 | H45: =G47 -> 0 | I45: =H47 -> 0 | J45: =I47 -> 0 | K45: =J47 -> 0 | L45: =K47 -> 0
B46: Drawdown / (repayment) | C46: €m | F46: =F22 -> 0 | G46: =G22 -> 0 | H46: =H22 -> 0 | I46: =I22 -> 0 | J46: =J22 -> 0 | K46: =K22 -> 0 | L46: =L22 -> 0
B47: Closing balance | C47: €m | E47: ='1_Transaction_Summary'!C45 -> 0 | F47: =F45+F46 -> 0 | G47: =G45+G46 -> 0 | H47: =H45+H46 -> 0 | I47: =I45+I46 -> 0 | J47: =J45+J46 -> 0 | K47: =K45+K46 -> 0 | L47: =L45+L46 -> 0
B48: Interest + commitment fee | C48: €m | F48: =IF('0_Dashboard_Toggles'!$C$10=1,AVERAGE(F45,F47),F45)*(F$7+$D$14)+($C$15-IF('0_Dashboard_Toggles'!$C$10=1,AVERAGE(F45,F47),F45))*$D$15 -> 1.875 | G48: =IF('0_Dashboard_Toggles'!$C$10=1,AVERAGE(G45,G47),G45)*(G$7+$D$14)+($C$15-IF('0_Dashboard_Toggles'!$C$10=1,AVERAGE(G45,G47),G45))*$D$15 -> 1.875 | H48: =IF('0_Dashboard_Toggles'!$C$10=1,AVERAGE(H45,H47),H45)*(H$7+$D$14)+($C$15-IF('0_Dashboard_Toggles'!$C$10=1,AVERAGE(H45,H47),H45))*$D$15 -> 1.875 | I48: =IF('0_Dashboard_Toggles'!$C$10=1,AVERAGE(I45,I47),I45)*(I$7+$D$14)+($C$15-IF('0_Dashboard_Toggles'!$C$10=1,AVERAGE(I45,I47),I45))*$D$15 -> 1.875 | J48: =IF('0_Dashboard_Toggles'!$C$10=1,AVERAGE(J45,J47),J45)*(J$7+$D$14)+($C$15-IF('0_Dashboard_Toggles'!$C$10=1,AVERAGE(J45,J47),J45))*$D$15 -> 1.875 | K48: =IF('0_Dashboard_Toggles'!$C$10=1,AVERAGE(K45,K47),K45)*(K$7+$D$14)+($C$15-IF('0_Dashboard_Toggles'!$C$10=1,AVERAGE(K45,K47),K45))*$D$15 -> 1.875 | L48: =IF('0_Dashboard_Toggles'!$C$10=1,AVERAGE(L45,L47),L45)*(L$7+$D$14)+($C$15-IF('0_Dashboard_Toggles'!$C$10=1,AVERAGE(L45,L47),L45))*$D$15 -> 1.875
B50: LEASE LIABILITIES (IFRS 16)
B51: Opening balance | C51: €m | F51: =E53 -> 470 | G51: =F53 -> 448.32517 | H51: =G53 -> 435.30936 | I51: =H53 -> 429.76611 | J51: =I53 -> 430.66151 | K51: =J53 -> 437.08409 | L51: =K53 -> 448.21992
B52: Principal repayment | C52: €m | D52: 0.16 | F52: =F51*$D$52 -> 75.2 | G52: =G51*$D$52 -> 71.732027 | H52: =H51*$D$52 -> 69.649498 | I52: =I51*$D$52 -> 68.762578 | J52: =J51*$D$52 -> 68.905842 | K52: =K51*$D$52 -> 69.933454 | L52: =L51*$D$52 -> 71.715187
B53: Closing balance (incl. new leases) | C53: €m | E53: ='1_Transaction_Summary'!C23 -> 470 | F53: =F51-F52+'2_Operating_Build'!F87 -> 448.32517 | G53: =G51-G52+'2_Operating_Build'!G87 -> 435.30936 | H53: =H51-H52+'2_Operating_Build'!H87 -> 429.76611 | I53: =I51-I52+'2_Operating_Build'!I87 -> 430.66151 | J53: =J51-J52+'2_Operating_Build'!J87 -> 437.08409 | K53: =K51-K52+'2_Operating_Build'!K87 -> 448.21992 | L53: =L51-L52+'2_Operating_Build'!L87 -> 463.33251
B55: TOTALS & CREDIT STATISTICS
B56: Total cash interest expense | C56: €m | F56: =F30+F37+F42+F48+F86 -> 1272.255 | G56: =G30+G37+G42+G48+G86 -> 1119.2648 | H56: =H30+H37+H42+H48+H86 -> 951.66878 | I56: =I30+I37+I42+I48+I86 -> 725.15742 | J56: =J30+J37+J42+J48+J86 -> 532.125 | K56: =K30+K37+K42+K48+K86 -> 532.125 | L56: =L30+L37+L42+L48+L86 -> 532.125
B57: Interest income on cash | C57: €m | F57: =IF('0_Dashboard_Toggles'!$C$10=1,AVERAGE('3_Financial_Statements'!E44,'3_Financial_Statements'!F44),'3_Financial_Statements'!E44)*$E$8 -> 47.76 | G57: =IF('0_Dashboard_Toggles'!$C$10=1,AVERAGE('3_Financial_Statements'!F44,'3_Financial_Statements'!G44),'3_Financial_Statements'!F44)*$E$8 -> 30 | H57: =IF('0_Dashboard_Toggles'!$C$10=1,AVERAGE('3_Financial_Statements'!G44,'3_Financial_Statements'!H44),'3_Financial_Statements'!G44)*$E$8 -> 30 | I57: =IF('0_Dashboard_Toggles'!$C$10=1,AVERAGE('3_Financial_Statements'!H44,'3_Financial_Statements'!I44),'3_Financial_Statements'!H44)*$E$8 -> 30 | J57: =IF('0_Dashboard_Toggles'!$C$10=1,AVERAGE('3_Financial_Statements'!I44,'3_Financial_Statements'!J44),'3_Financial_Statements'!I44)*$E$8 -> 56.819112 | K57: =IF('0_Dashboard_Toggles'!$C$10=1,AVERAGE('3_Financial_Statements'!J44,'3_Financial_Statements'!K44),'3_Financial_Statements'!J44)*$E$8 -> 158.77528 | L57: =IF('0_Dashboard_Toggles'!$C$10=1,AVERAGE('3_Financial_Statements'!K44,'3_Financial_Statements'!L44),'3_Financial_Statements'!K44)*$E$8 -> 274.36042
B58: Amortisation of financing fees & OID (7 years) | C58: €m | F58: =MIN('3_Financial_Statements'!E53,'3_Financial_Statements'!$E$53/7) -> 69.457143 | G58: =MIN('3_Financial_Statements'!F53,'3_Financial_Statements'!$E$53/7) -> 69.457143 | H58: =MIN('3_Financial_Statements'!G53,'3_Financial_Statements'!$E$53/7) -> 69.457143 | I58: =MIN('3_Financial_Statements'!H53,'3_Financial_Statements'!$E$53/7) -> 69.457143 | J58: =MIN('3_Financial_Statements'!I53,'3_Financial_Statements'!$E$53/7) -> 69.457143 | K58: =MIN('3_Financial_Statements'!J53,'3_Financial_Statements'!$E$53/7) -> 69.457143 | L58: =MIN('3_Financial_Statements'!K53,'3_Financial_Statements'!$E$53/7) -> 69.457143
B59: Memo: interest at opening balances (for convergence test) | C59: €m | F59: =F27*(F$7+$D$11)+F34*(F$7+$D$12)+F42+F45*(F$7+$D$14)+($C$15-F45)*$D$15+F86 -> 1272.255 | G59: =G27*(G$7+$D$11)+G34*(G$7+$D$12)+G42+G45*(G$7+$D$14)+($C$15-G45)*$D$15+G86 -> 1119.2648 | H59: =H27*(H$7+$D$11)+H34*(H$7+$D$12)+H42+H45*(H$7+$D$14)+($C$15-H45)*$D$15+H86 -> 951.66878 | I59: =I27*(I$7+$D$11)+I34*(I$7+$D$12)+I42+I45*(I$7+$D$14)+($C$15-I45)*$D$15+I86 -> 725.15742 | J59: =J27*(J$7+$D$11)+J34*(J$7+$D$12)+J42+J45*(J$7+$D$14)+($C$15-J45)*$D$15+J86 -> 532.125 | K59: =K27*(K$7+$D$11)+K34*(K$7+$D$12)+K42+K45*(K$7+$D$14)+($C$15-K45)*$D$15+K86 -> 532.125 | L59: =L27*(L$7+$D$11)+L34*(L$7+$D$12)+L42+L45*(L$7+$D$14)+($C$15-L45)*$D$15+L86 -> 532.125 | M59: Residual →
B60: Check: |reported interest − interest recomputed on current avg balances| (CircOn=1 only) | F60: =IF('0_Dashboard_Toggles'!$C$10=1,ABS(F56-(AVERAGE(F27,F31)*(F$7+$D$11)+AVERAGE(F34,F36)*(F$7+$D$12)+F42+AVERAGE(F45,F47)*(F$7+$D$14)+($C$15-AVERAGE(F45,F47))*$D$15+F86))+ABS(F57-AVERAGE('3_Financial_Statements'!E44,'3_Financial_Statements'!F44)*$E$8),0) -> 0 | G60: =IF('0_Dashboard_Toggles'!$C$10=1,ABS(G56-(AVERAGE(G27,G31)*(G$7+$D$11)+AVERAGE(G34,G36)*(G$7+$D$12)+G42+AVERAGE(G45,G47)*(G$7+$D$14)+($C$15-AVERAGE(G45,G47))*$D$15+G86))+ABS(G57-AVERAGE('3_Financial_Statements'!F44,'3_Financial_Statements'!G44)*$E$8),0) -> 0 | H60: =IF('0_Dashboard_Toggles'!$C$10=1,ABS(H56-(AVERAGE(H27,H31)*(H$7+$D$11)+AVERAGE(H34,H36)*(H$7+$D$12)+H42+AVERAGE(H45,H47)*(H$7+$D$14)+($C$15-AVERAGE(H45,H47))*$D$15+H86))+ABS(H57-AVERAGE('3_Financial_Statements'!G44,'3_Financial_Statements'!H44)*$E$8),0) -> 0 | I60: =IF('0_Dashboard_Toggles'!$C$10=1,ABS(I56-(AVERAGE(I27,I31)*(I$7+$D$11)+AVERAGE(I34,I36)*(I$7+$D$12)+I42+AVERAGE(I45,I47)*(I$7+$D$14)+($C$15-AVERAGE(I45,I47))*$D$15+I86))+ABS(I57-AVERAGE('3_Financial_Statements'!H44,'3_Financial_Statements'!I44)*$E$8),0) -> 0 | J60: =IF('0_Dashboard_Toggles'!$C$10=1,ABS(J56-(AVERAGE(J27,J31)*(J$7+$D$11)+AVERAGE(J34,J36)*(J$7+$D$12)+J42+AVERAGE(J45,J47)*(J$7+$D$14)+($C$15-AVERAGE(J45,J47))*$D$15+J86))+ABS(J57-AVERAGE('3_Financial_Statements'!I44,'3_Financial_Statements'!J44)*$E$8),0) -> 0 | K60: =IF('0_Dashboard_Toggles'!$C$10=1,ABS(K56-(AVERAGE(K27,K31)*(K$7+$D$11)+AVERAGE(K34,K36)*(K$7+$D$12)+K42+AVERAGE(K45,K47)*(K$7+$D$14)+($C$15-AVERAGE(K45,K47))*$D$15+K86))+ABS(K57-AVERAGE('3_Financial_Statements'!J44,'3_Financial_Statements'!K44)*$E$8),0) -> 0 | L60: =IF('0_Dashboard_Toggles'!$C$10=1,ABS(L56-(AVERAGE(L27,L31)*(L$7+$D$11)+AVERAGE(L34,L36)*(L$7+$D$12)+L42+AVERAGE(L45,L47)*(L$7+$D$14)+($C$15-AVERAGE(L45,L47))*$D$15+L86))+ABS(L57-AVERAGE('3_Financial_Statements'!K44,'3_Financial_Statements'!L44)*$E$8),0) -> 0 | M60: =SUM(F60:L60) -> 0
B61: Total debt | C61: €m | E61: =E31+E36+E41+E47+E85 -> 19700 | F61: =F31+F36+F41+F47+F85 -> 16661.097 | G61: =G31+G36+G41+G47+G85 -> 13729.425 | H61: =H31+H36+H41+H47+H85 -> 10086.132 | I61: =I31+I36+I41+I47+I85 -> 7070 | J61: =J31+J36+J41+J47+J85 -> 7070 | K61: =K31+K36+K41+K47+K85 -> 7070 | L61: =L31+L36+L41+L47+L85 -> 7070
B62: Net debt (excl. leases) | C62: €m | E62: =E61-'3_Financial_Statements'!E44 -> 17312 | F62: =F61-'3_Financial_Statements'!F44 -> 15161.097 | G62: =G61-'3_Financial_Statements'!G44 -> 12229.425 | H62: =H61-'3_Financial_Statements'!H44 -> 8586.1316 | I62: =I61-'3_Financial_Statements'!I44 -> 4229.0444 | J62: =J61-'3_Financial_Statements'!J44 -> -868.76394 | K62: =K61-'3_Financial_Statements'!K44 -> -6648.0209 | L62: =L61-'3_Financial_Statements'!L44 -> -13144.729
B63: Adj. EBITDA | C63: €m | E63: ='2_Operating_Build'!E79 -> 3282.595 | F63: ='2_Operating_Build'!F79 -> 3757.225 | G63: ='2_Operating_Build'!G79 -> 4492.145 | H63: ='2_Operating_Build'!H79 -> 5306.7257 | I63: ='2_Operating_Build'!I79 -> 6015.4536 | J63: ='2_Operating_Build'!J79 -> 6772.6655 | K63: ='2_Operating_Build'!K79 -> 7575.0917 | L63: ='2_Operating_Build'!L79 -> 8418.4223
B64: Gross leverage (total debt / EBITDA) | C64: x | E64: =E61/E63 -> 6.0013495 | F64: =F61/F63 -> 4.4344156 | G64: =G61/G63 -> 3.0563183 | H64: =H61/H63 -> 1.9006318 | I64: =I61/I63 -> 1.1753062 | J64: =J61/J63 -> 1.0439021 | K64: =K61/K63 -> 0.93332204 | L64: =L61/L63 -> 0.83982482
B65: Net leverage (net debt / EBITDA) | C65: x | E65: =E62/E63 -> 5.2738763 | F65: =F62/F63 -> 4.0351848 | G65: =G62/G63 -> 2.7224021 | H65: =H62/H63 -> 1.6179716 | I65: =I62/I63 -> 0.70303001 | J65: =J62/J63 -> -0.12827504 | K65: =K62/K63 -> -0.8776159 | L65: =L62/L63 -> -1.5614243
B66: Interest cover (EBITDA / cash interest) | C66: x | F66: =F63/F56 -> 2.9532012 | G66: =G63/G56 -> 4.0134784 | H66: =H63/H56 -> 5.5762318 | I66: =I63/I56 -> 8.2953762 | J66: =J63/J56 -> 12.727584 | K66: =K63/K56 -> 14.235549 | L66: =L63/L56 -> 15.820385
B67: Cumulative debt paydown (% of opening) | C67: % | F67: =1-F61/$E$61 -> 0.15425902 | G67: =1-G61/$E$61 -> 0.30307487 | H67: =1-H61/$E$61 -> 0.48801362 | I67: =1-I61/$E$61 -> 0.64111675 | J67: =1-J61/$E$61 -> 0.64111675 | K67: =1-K61/$E$61 -> 0.64111675 | L67: =1-L61/$E$61 -> 0.64111675
B68: TLA springing covenant test (net leverage ≤ 7.0x) | C68: test | D68: Input threshold in D69 | F68: =IF(F65>$D$69,"BREACH","OK") -> OK | G68: =IF(G65>$D$69,"BREACH","OK") -> OK | H68: =IF(H65>$D$69,"BREACH","OK") -> OK | I68: =IF(I65>$D$69,"BREACH","OK") -> OK | J68: =IF(J65>$D$69,"BREACH","OK") -> OK | K68: =IF(K65>$D$69,"BREACH","OK") -> OK | L68: =IF(L65>$D$69,"BREACH","OK") -> OK
B69: Covenant threshold | D69: 7
B72: DIVIDEND RECAP / EXCESS-CASH PAYOUT MODULE (switch C73 – shipped OFF, so base case is unchanged)
B73: Recap switch (1 = on, 0 = off) | C73: 0 | D73: Master switch. When 0 every line below is zero.
B74: Recap year (FY, executed at year-end) | C74: 2031 | D74: ASSUMPTION: first year all term loans are repaid is FY2030E, so FY2031E is the earliest "clean" recap.
B75: Target gross leverage after recap (x that year's Adj. EBITDA) | C75: 4 | D75: ASSUMPTION: new notes sized so total debt = this multiple; zero issuance if already above.
B76: Payout of excess cash above minimum cash (%) | C76: 1 | D76: ASSUMPTION: share of post-sweep cash above Dashboard C13 distributed to equity.
B77: Coupon on recap notes (fixed) | C77: 0.075 | D77: ASSUMPTION: set equal to the 7.50% entry notes; no market evidence in the file for FY31 pricing.
B78: Recap financing fee (% of new debt, cash, charged to equity) | C78: 0.0225 | D78: ASSUMPTION: same 2.25% as entry financing fee; not tax-deducted (conservative simplification).
B79: Repeat excess-cash payout every year from recap year (1) or recap year only (0) | C79: 1 | D79: ASSUMPTION: 1 = cash above minimum is paid out each year after the recap year too.
B81: Fiscal year (Dec YE) | E81: =E3 -> 2026 | F81: =F3 -> 2027 | G81: =G3 -> 2028 | H81: =H3 -> 2029 | I81: =I3 -> 2030 | J81: =J3 -> 2031 | K81: =K3 -> 2032 | L81: =L3 -> 2033
B82: Recap flag (1 in recap year) | F82: =IF(AND($C$73=1,F$3=$C$74),1,0) -> 0 | G82: =IF(AND($C$73=1,G$3=$C$74),1,0) -> 0 | H82: =IF(AND($C$73=1,H$3=$C$74),1,0) -> 0 | I82: =IF(AND($C$73=1,I$3=$C$74),1,0) -> 0 | J82: =IF(AND($C$73=1,J$3=$C$74),1,0) -> 0 | K82: =IF(AND($C$73=1,K$3=$C$74),1,0) -> 0 | L82: =IF(AND($C$73=1,L$3=$C$74),1,0) -> 0
B83: Recap notes – opening balance | F83: =E85 -> 0 | G83: =F85 -> 0 | H83: =G85 -> 0 | I83: =H85 -> 0 | J83: =I85 -> 0 | K83: =J85 -> 0 | L83: =K85 -> 0
B84: New recap notes issued | F84: =F82*MAX(0,$C$75*F63-(F31+F36+F41+F47+F83)) -> 0 | G84: =G82*MAX(0,$C$75*G63-(G31+G36+G41+G47+G83)) -> 0 | H84: =H82*MAX(0,$C$75*H63-(H31+H36+H41+H47+H83)) -> 0 | I84: =I82*MAX(0,$C$75*I63-(I31+I36+I41+I47+I83)) -> 0 | J84: =J82*MAX(0,$C$75*J63-(J31+J36+J41+J47+J83)) -> 0 | K84: =K82*MAX(0,$C$75*K63-(K31+K36+K41+K47+K83)) -> 0 | L84: =L82*MAX(0,$C$75*L63-(L31+L36+L41+L47+L83)) -> 0
B85: Recap notes – closing balance | E85: 0 | F85: =F83+F84 -> 0 | G85: =G83+G84 -> 0 | H85: =H83+H84 -> 0 | I85: =I83+I84 -> 0 | J85: =J83+J84 -> 0 | K85: =K83+K84 -> 0 | L85: =L83+L84 -> 0
B86: Interest on recap notes (on opening balance) | F86: =F83*$C$77 -> 0 | G86: =G83*$C$77 -> 0 | H86: =H83*$C$77 -> 0 | I86: =I83*$C$77 -> 0 | J86: =J83*$C$77 -> 0 | K86: =K83*$C$77 -> 0 | L86: =L83*$C$77 -> 0
B87: Financing fees on new notes (cash) | F87: =F84*$C$78 -> 0 | G87: =G84*$C$78 -> 0 | H87: =H84*$C$78 -> 0 | I87: =I84*$C$78 -> 0 | J87: =J84*$C$78 -> 0 | K87: =K84*$C$78 -> 0 | L87: =L84*$C$78 -> 0
B88: Cash before dividend (opening + FCF + debt flows) | F88: ='3_Financial_Statements'!F43+'3_Financial_Statements'!F36+SUM('3_Financial_Statements'!F38:F41) -> 1500 | G88: ='3_Financial_Statements'!G43+'3_Financial_Statements'!G36+SUM('3_Financial_Statements'!G38:G41) -> 1500 | H88: ='3_Financial_Statements'!H43+'3_Financial_Statements'!H36+SUM('3_Financial_Statements'!H38:H41) -> 1500 | I88: ='3_Financial_Statements'!I43+'3_Financial_Statements'!I36+SUM('3_Financial_Statements'!I38:I41) -> 2840.9556 | J88: ='3_Financial_Statements'!J43+'3_Financial_Statements'!J36+SUM('3_Financial_Statements'!J38:J41) -> 7938.7639 | K88: ='3_Financial_Statements'!K43+'3_Financial_Statements'!K36+SUM('3_Financial_Statements'!K38:K41) -> 13718.021 | L88: ='3_Financial_Statements'!L43+'3_Financial_Statements'!L36+SUM('3_Financial_Statements'!L38:L41) -> 20214.729
B89: Total dividend to equity (recap proceeds net of fees + excess cash) | F89: =F90+F91 -> 0 | G89: =G90+G91 -> 0 | H89: =H90+H91 -> 0 | I89: =I90+I91 -> 0 | J89: =J90+J91 -> 0 | K89: =K90+K91 -> 0 | L89: =L90+L91 -> 0
B90: Memo: excess-cash payout component | F90: =IF($C$73=1,IF($C$79=1,IF(F$3>=$C$74,1,0),F82)*$C$76*MAX(0,F88-'0_Dashboard_Toggles'!$C$13),0) -> 0 | G90: =IF($C$73=1,IF($C$79=1,IF(G$3>=$C$74,1,0),G82)*$C$76*MAX(0,G88-'0_Dashboard_Toggles'!$C$13),0) -> 0 | H90: =IF($C$73=1,IF($C$79=1,IF(H$3>=$C$74,1,0),H82)*$C$76*MAX(0,H88-'0_Dashboard_Toggles'!$C$13),0) -> 0 | I90: =IF($C$73=1,IF($C$79=1,IF(I$3>=$C$74,1,0),I82)*$C$76*MAX(0,I88-'0_Dashboard_Toggles'!$C$13),0) -> 0 | J90: =IF($C$73=1,IF($C$79=1,IF(J$3>=$C$74,1,0),J82)*$C$76*MAX(0,J88-'0_Dashboard_Toggles'!$C$13),0) -> 0 | K90: =IF($C$73=1,IF($C$79=1,IF(K$3>=$C$74,1,0),K82)*$C$76*MAX(0,K88-'0_Dashboard_Toggles'!$C$13),0) -> 0 | L90: =IF($C$73=1,IF($C$79=1,IF(L$3>=$C$74,1,0),L82)*$C$76*MAX(0,L88-'0_Dashboard_Toggles'!$C$13),0) -> 0
B91: Memo: recap proceeds distributed (net of fees) | F91: =F84-F87 -> 0 | G91: =G84-G87 -> 0 | H91: =H84-H87 -> 0 | I91: =I84-I87 -> 0 | J91: =J84-J87 -> 0 | K91: =K84-K87 -> 0 | L91: =L84-L87 -> 0
B93: Mechanics: new notes are issued at year-end, fees are paid in cash, proceeds are paid straight out as a dividend; interest starts the following year (opening-balance basis, so no extra circularity). Sweep runs first, so excess cash is only paid out once term loans are gone.
B95: VBA REMOVED (05-Oct-2026): rows 72–130 previously held macro source as plain text. A .xlsx cannot contain or run VBA, the code was untested here, and the check it fed (old M60) was a hard-coded 0.
B96: Replacements: (1) CircOn toggle (Dashboard C10) + workbook iterative calc (on, 1000 iterations); (2) real convergence residual in row 60 / M60 feeding Dashboard D47; (3) external Python/LibreOffice harness harmony_rerun.py for scenario snapshots and sensitivity grids.

Sheet 5_Returns_Sensitivities
B1: 5 | Returns Analysis & Sensitivities | J1: Master check: | K1: ='0_Dashboard_Toggles'!$D$49 -> OK
B2: Exit at FY2033E (7-year hold). Gross = all equity after MIP; Net = LP view on sponsor cash only after 1.5% annual fee on invested capital and 20% carry over 8% pref (full catch-up). Fees are paid annually (rows 33); carry is crystallised at exit. Interim recap dividends (if switched on) flow through rows 20/33.
B4: EXIT VALUATION BRIDGE
B5: Exit Adj. EBITDA (FY33E) | C5: ='2_Operating_Build'!L79 -> 8418.4223
B6: Exit EV / EBITDA multiple | C6: ='0_Dashboard_Toggles'!C22 -> 22
B7: Exit enterprise value | C7: =C5*C6 -> 185205.29
B8: FY33E free cash flow before debt service | C8: ='3_Financial_Statements'!L36 -> 6496.7084
B9: Implied exit EV / FCF (cross-check) | C9: =C7/C8 -> 28.507558
B10: Less: total debt | C10: =-'4_Debt_Schedule'!L61 -> -7070
B11: Plus: cash and long-term investments (non-operating, netted out of EV at entry) | C11: ='3_Financial_Statements'!L44+'3_Financial_Statements'!L50 -> 21332.729
B12: Less: lease liabilities | C12: =-'4_Debt_Schedule'!L53 -> -463.33251
B13: Exit equity value (pre-MIP) | C13: =SUM(C7,C10:C12) -> 199004.69
B14: Total equity invested (sponsor + rollover) | C14: ='1_Transaction_Summary'!C49+'1_Transaction_Summary'!C50 -> 91000.964
B15: Less: Management Incentive Plan | C15: =-'0_Dashboard_Toggles'!C20*MAX(0,C13+C21-C14) -> -8640.2979
B16: Equity proceeds to sponsor & rollover | C16: =C13+C15 -> 190364.39
B17: Gross MoIC | C17: =(C16+C21)/C14 -> 2.0918942
B18: Sponsor-only proceeds / invested (pro rata) | C18: =(C16+C21)*'1_Transaction_Summary'!C50/C14 -> 124371.29 | D18: ='1_Transaction_Summary'!C50 -> 59453.909
B19: Gross IRR | C19: =IRR(E20:L20) -> 0.11119784 | E19: 2026 | F19: 2027 | G19: 2028 | H19: 2029 | I19: 2030 | J19: 2031 | K19: 2032 | L19: 2033
D20: Equity CF | E20: =-$C$14 -> -91000.964 | F20: ='4_Debt_Schedule'!F89 -> 0 | G20: ='4_Debt_Schedule'!G89 -> 0 | H20: ='4_Debt_Schedule'!H89 -> 0 | I20: ='4_Debt_Schedule'!I89 -> 0 | J20: ='4_Debt_Schedule'!J89 -> 0 | K20: ='4_Debt_Schedule'!K89 -> 0 | L20: =$C$16+'4_Debt_Schedule'!L89 -> 190364.39
B21: Memo: cumulative interim dividends to equity (recap module) | C21: =SUM('4_Debt_Schedule'!F89:L89) -> 0
B22: NET RETURNS (LP VIEW – sponsor cash only; rollover equity pays no fee or carry; fee paid annually)
B23: Management fee (p.a. on invested) | C23: 0.015
B24: Carried interest | C24: 0.2
B25: Preferred return (hurdle) | C25: 0.08
B26: Hold period (years) | C26: ='2_Operating_Build'!L3-'2_Operating_Build'!E3 -> 7
B27: Management fees over hold (1.5% p.a. × sponsor cash) | C27: =-C23*D18*C26 -> -6242.6604
B28: Sponsor profit after fees | C28: =C18+C27-D18 -> 58674.718
B29: Preferred return amount (on sponsor cash) | C29: =D18*((1+C25)^C26-1) -> 42439.643
B30: Carry (full catch-up) | C30: =-MAX(0,MIN(C24*C28,C28-C29)) -> -11734.944
B31: Net MoIC | C31: =(C18+C27+C30)/D18 -> 1.7895154
B32: Net IRR | C32: =IF(C31>0,IRR(E33:L33),-1) -> 0.084022948
D33: Net LP cash flows | E33: =-$D$18 -> -59453.909 | F33: =F20*$D$18/$C$14-$C$23*$D$18 -> -891.80863 | G33: =G20*$D$18/$C$14-$C$23*$D$18 -> -891.80863 | H33: =H20*$D$18/$C$14-$C$23*$D$18 -> -891.80863 | I33: =I20*$D$18/$C$14-$C$23*$D$18 -> -891.80863 | J33: =J20*$D$18/$C$14-$C$23*$D$18 -> -891.80863 | K33: =K20*$D$18/$C$14-$C$23*$D$18 -> -891.80863 | L33: =L20*$D$18/$C$14-$C$23*$D$18+$C$30 -> 111744.53
B34: VALUE CREATION ATTRIBUTION
B35: Entry Adj. EBITDA (FY26E) | C35: ='2_Operating_Build'!E79 -> 3282.595
B36: Entry EV / EBITDA | C36: ='1_Transaction_Summary'!C28 -> 32.536742
B37: EBITDA growth × entry multiple | C37: =(C5-C35)*C36 -> 167103.09
B38: Multiple expansion / (compression) | C38: =(C6-C36)*C5 -> -88702.745
B39: Deleveraging & cash build (net debt incl. LT investments) | C39: =('1_Transaction_Summary'!C47-'1_Transaction_Summary'!F48-'3_Financial_Statements'!E50+'1_Transaction_Summary'!C23)-(-C10-C11-C12) -> 30463.397
B40: Fees & other leakage (plug = advisory + financing fees + OID) | C40: =C41-C37-C38-C39 -> -860.01731
B41: Total value created (exit equity − invested) | C41: =C13+C21-C14 -> 108003.72
B43: SENSITIVITIES – FULL MODEL RE-RUNS (STATIC VALUES, NOT LIVE FORMULAS)
B44: Replaces the former closed-form engine (rows 43–92). Every cell below is the output of a complete recalculation of this workbook (LibreOffice engine, 06-Oct-2026, v3) with the stated Dashboard input(s) changed; all eight audit checks were read on every run.
B45: Exit multiple: Dashboard C21 override. Premium: Dashboard C7. Gross-margin axis: moved through Dashboard E29 (royalty step-down, bps p.a.), solved so FY33E gross margin hits the row value; the bps used is shown in column K.
B46: Entry-multiple axis (Tables 4–5): Dashboard C7 solved (negative premium) so Tab 1 C28 hits the row value; debt stays at 6.0x FY26E EBITDA = €19.7bn. Hypothetical – not achievable with any control premium.
B47: To refresh: run harmony_rerun.py (delivered alongside this file). Green fill = gross MoIC ≥ 3.58x (the 7-year equivalent of a 20% gross IRR) or net IRR ≥ 20%.
B52: TABLE 1 – GROSS MoIC: Exit EV/EBITDA × FY33E gross margin (full re-run) | D52: Exit EV / EBITDA →
C53: FY33E GM ↓ | D53: 12 | E53: 13.5 | F53: 15 | G53: 16.5 | H53: 18 | I53: 22 | J53: 25 | K53: Royalty bps p.a.
C54: 0.36 | D54: 1.0720007 | E54: 1.1824468 | F54: 1.2928928 | G54: 1.4033389 | H54: 1.5137849 | I54: 1.8083078 | J54: 2.0291999 | K54: 18.610866
C55: 0.38 | D55: 1.1752861 | E55: 1.2962658 | F55: 1.4172456 | G55: 1.5382254 | H55: 1.6592052 | I55: 1.9818179 | J55: 2.2237775 | K55: 50.052583
C56: 0.4 | D56: 1.2785656 | E56: 1.4100791 | F56: 1.5415926 | G56: 1.6731061 | H56: 1.8046196 | I56: 2.1553222 | J56: 2.4183492 | K56: 81.494301
C57: 0.42 | D57: 1.3818429 | E57: 1.5238901 | F57: 1.6659373 | G57: 1.8079846 | H57: 1.9500318 | I57: 2.3288243 | J57: 2.6129188 | K57: 112.93602
C58: 0.44 | D58: 1.4851202 | E58: 1.6377012 | F58: 1.7902821 | G58: 1.942863 | H58: 2.095444 | I58: 2.5023265 | J58: 2.8074884 | K58: 144.37774
B60: TABLE 2 – NET IRR (LP): Exit EV/EBITDA × FY33E gross margin (full re-run) | D60: Exit EV / EBITDA →
C61: FY33E GM ↓ | D61: 12 | E61: 13.5 | F61: 15 | G61: 16.5 | H61: 18 | I61: 22 | J61: 25 | K61: Royalty bps p.a.
C62: 0.36 | D62: -0.004572234 | E62: 0.010271614 | F62: 0.023932395 | G62: 0.036596612 | H62: 0.048409108 | I62: 0.076550433 | J62: 0.079712705 | K62: 18.610866
C63: 0.38 | D63: 0.009347376 | E63: 0.024333084 | F63: 0.038128218 | G63: 0.05091995 | H63: 0.062853744 | I63: 0.077478555 | J63: 0.092772497 | K63: 50.052583
C64: 0.4 | D64: 0.022220037 | E64: 0.037340603 | F64: 0.051263111 | G64: 0.064175473 | H64: 0.076223813 | I64: 0.088282904 | J64: 0.1049693 | K64: 81.494301
C65: 0.42 | D65: 0.034202582 | E65: 0.049451546 | F65: 0.063495066 | G65: 0.076521834 | H65: 0.077478555 | I65: 0.099456662 | J65: 0.11641781 | K65: 112.93602
C66: 0.44 | D66: 0.04541834 | E66: 0.060789774 | F66: 0.074948516 | G66: 0.077478555 | H66: 0.084263987 | I66: 0.10999645 | J66: 0.12721081 | K66: 144.37774
B67: Cells at exactly 8.0% sit in the GP catch-up zone: LPs get the 8% preferred return and the GP takes 100% of profit until carry equals 20% of total profit.
B68: TABLE 3 – NET IRR (LP): Offer premium × Exit EV/EBITDA (full re-run) | D68: Exit EV / EBITDA →
C69: Premium ↓ | D69: 12 | E69: 13.5 | F69: 15 | G69: 16.5 | H69: 18 | I69: 22 | J69: 25 | K69: Entry EV/EBITDA
C70: 0.15 | D70: 0.041195734 | E70: 0.056682246 | F70: 0.070934376 | G70: 0.077478555 | H70: 0.080887693 | I70: 0.10667546 | J70: 0.12391737 | K70: 28.396247
C71: 0.2 | D71: 0.03283262 | E71: 0.048173374 | F71: 0.062293402 | G71: 0.075384945 | H71: 0.077478555 | I71: 0.098605589 | J71: 0.11561626 | K71: 29.776412
C72: 0.25 | D72: 0.024994821 | E72: 0.040197703 | F72: 0.054192852 | G72: 0.067170156 | H72: 0.077478555 | I72: 0.091074661 | J72: 0.107865 | K72: 31.156577
C73: 0.3 | D73: 0.01762483 | E73: 0.032696868 | F73: 0.046573578 | G73: 0.059442593 | H73: 0.071449793 | I73: 0.084022948 | J73: 0.10060277 | K73: 32.536742
C74: 0.35 | D74: 0.010673916 | E74: 0.02562142 | F74: 0.039385468 | G74: 0.052151528 | H74: 0.064063861 | I74: 0.077478555 | J74: 0.09377807 | K74: 33.916907
B76: TABLE 4 – GROSS MoIC: Entry EV/EBITDA (hypothetical) × Exit EV/EBITDA (full re-run) | D76: Exit EV / EBITDA →
C77: Entry multiple ↓ | D77: 12 | E77: 13.5 | F77: 15 | G77: 16.5 | H77: 18 | I77: 22 | J77: 25 | K77: Implied offer $/sh
C78: 12 | D78: 4.6037412 | E78: 5.1012497 | F78: 5.5987581 | G78: 6.0962665 | H78: 6.5937749 | I78: 7.920464 | J78: 8.9154808 | K78: 271.64529
C79: 13.5 | D79: 3.8136907 | E79: 4.2243115 | F79: 4.6349324 | G79: 5.0455532 | H79: 5.4561741 | I79: 6.551163 | J79: 7.3724047 | K79: 298.49236
C80: 15 | D80: 3.2585683 | E80: 3.6081384 | F80: 3.9577084 | G80: 4.3072785 | H80: 4.6568485 | I80: 5.5890353 | J80: 6.2881754 | K80: 325.33944
C81: 16.5 | D81: 2.8471505 | E81: 3.1514739 | F81: 3.4557974 | G81: 3.7601209 | H81: 4.0644443 | I81: 4.8759736 | J81: 5.4846205 | K81: 352.17612
C82: 18 | D82: 2.5300308 | E82: 2.7994784 | F82: 3.0689259 | G82: 3.3383734 | H82: 3.607821 | I82: 4.3263477 | J82: 4.8652428 | K82: 378.89563
B84: TABLE 5 – NET IRR (LP): Entry EV/EBITDA (hypothetical) × Exit EV/EBITDA (full re-run) | D84: Exit EV / EBITDA →
C85: Entry multiple ↓ | D85: 12 | E85: 13.5 | F85: 15 | G85: 16.5 | H85: 18 | I85: 22 | J85: 25 | K85: Implied offer $/sh
C86: 12 | D86: 0.20582556 | E86: 0.22306311 | F86: 0.23896813 | G86: 0.25374521 | H86: 0.26755429 | I86: 0.30054204 | J86: 0.32237177 | K86: 271.64529
C87: 13.5 | D87: 0.17502321 | E87: 0.19162074 | F87: 0.2069501 | G87: 0.22120389 | H87: 0.23453313 | I87: 0.26640607 | J87: 0.28751924 | K87: 298.49236
C88: 15 | D88: 0.15010969 | E88: 0.16616262 | F88: 0.18100313 | G88: 0.19481337 | H88: 0.20773655 | I88: 0.23866869 | J88: 0.25917901 | K88: 325.33944
C89: 16.5 | D89: 0.1293376 | E89: 0.14491448 | F89: 0.15932834 | G89: 0.17275205 | H89: 0.18532188 | I89: 0.21543721 | J89: 0.23542552 | K89: 352.17612
C90: 18 | D90: 0.11162577 | E90: 0.1267784 | F90: 0.1408125 | G90: 0.15389257 | H90: 0.16614863 | I90: 0.19554006 | J90: 0.21506679 | K90: 378.89563
B92: Entry multiples of 12–18x sit 23–45% below the unaffected share price (offer $272–$379 vs $490.30); Table 3 is the only executable entry sensitivity. Tables 4–5 are hypothetical.
B94: TABLE 6 (NEW) – GROSS IRR: Entry leverage × Exit EV/EBITDA (full re-run; red = an audit check fails, i.e. covenant breach) | D94: Exit EV / EBITDA →
C95: Leverage ↓ | D95: 16 | E95: 18 | F95: 22 | G95: 25
C96: 4 | D96: 0.065865106 | E96: 0.080718018 | F96: 0.1071987 | G96: 0.12407911
C97: 5 | D97: 0.066762926 | E97: 0.082028544 | F97: 0.10916785 | G97: 0.12642357
C98: 6 | D98: 0.06764876 | E98: 0.083356713 | F98: 0.11119784 | G98: 0.12885137
C99: 7 | D99: 0.068535273 | E99: 0.084717213 | F99: 0.11330578 | G99: 0.13138066
C100: 8 | D100: 0.069423283 | E100: 0.086114266 | F100: 0.11550031 | G100: 0.13402214
C101: 9 | D101: 0.070244522 | E101: 0.087470156 | F101: 0.11768788 | G101: 0.13667288
C102: 10 | D102: 0.071100532 | E102: 0.088919969 | F102: 0.12005458 | G102: 0.13954691
B104: Each extra turn of leverage adds only ~0.2pp of gross IRR (equity falls from €91.0bn at 6x to €78.2bn at 10x) while interest cover falls from 3.0x to 1.8x. See 6_IC_Analysis section B.

Sheet 6_IC_Analysis
B1: 6 | IC Analysis – what must be true, leverage, dividend recap, size, ownership, minority alternative
B2: Sections A–C and E–G are STATIC outputs of full workbook re-runs or sourced facts (grey fill). Section D is LIVE. € millions unless stated. Run date 06-Oct-2026 (v3).
B4: A. WHAT HAS TO BE TRUE FOR A 20% GROSS IRR (one lever at a time, everything else = Base; 7-year hold)
B5: Lever | C5: Base value | D5: Needed for 20% | E5: Gross IRR | F5: Gross MoIC | G5: Net IRR | H5: Total equity €bn | I5: Sponsor equity €bn | J5: Realistic?
B6: Offer premium to unaffected ($490.30) | C6: 0.3 | D6: -0.12633792 | E6: 0.2 | F6: 3.5831808 | G6: 0.16505916 | H6: 52.262308 | I6: 31.138209 | J6: No – offer would be $428, 13% below market
B7: Exit EV / EBITDA (entry 32.5x) | C7: 22 | D7: 39.522198 | E7: 0.2 | F7: 3.5831808 | G7: 0.16505916 | H7: 91.000964 | I7: 59.453909 | J7: No – 21% ABOVE entry multiple
B8: FY33E gross margin (royalty step-down bps p.a.) | C8: 0.3926885 | D8: 0.56459263 | E8: 0.2 | F8: 3.5831808 | G8: 0.16505916 | H8: 91.000964 | I8: 59.453909 | J8: No – 340 bps p.a. vs 70; GM today 33.4%
B9: Entry leverage (x FY26E EBITDA) | C9: 6 | D9: none (15x shown) | E9: 0.13206689 | F9: 2.3828935 | G9: 0.10280552 | H9: 62.229014 | I9: 30.681959 | J9: No – 15x gives only 13.2% and covenant fails from 10x
B10: Hold period at 22x exit | C10: 7 | D10: none | E10: 0.11119784 | F10: 2.0918942 | J10: No – best case 11.1% (FY33); shorter holds are worse
B11: Hold period if exit multiple = entry 32.5x (no de-rating) | C11: 7 | D11: FY2029 (3 yrs) | E11: 0.20364032 | F11: 1.7437739 | J11: No – needs zero de-rating and a 3-year flip
B12: Structure: dividend recap / excess-cash payout (best tested) | C12: none | D12: recap FY30 to 6.0x | E12: 0.11716658 | F12: 2.0291365 | G12: 0.088636084 | H12: 91.000964 | I12: 59.453909 | J12: No – adds ≤0.6pp; debt at exit €36bn
B13: Operating case: Upside (GM 42.1%, ARPU 5%, 25x exit) | C13: Base | D13: Upside @25x | E13: 0.17656582 | F13: 3.1211425 | G13: 0.14341737 | H13: 91.000964 | I13: 59.453909 | J13: No – 17.7% even if everything goes right
B14: Upside operating case: exit multiple needed | C14: 22.0x | D14: 29.104041 | E14: 0.2 | F14: 3.5831808 | G14: 0.16505916 | H14: 91.000964 | I14: 59.453909 | J14: No – 29.1x vs 25x upside assumption
B15: Memo's own 'what you have to believe' bundle (GM 44%, 25x, ARPU 5%, zero churn penalty) | C15: 20% claimed | D15: reaches 17.4% | E15: 0.17384099 | F15: 3.0708945 | G15: 0.14091135 | H15: 91.000964 | I15: 59.453909 | J15: No – memo text (§8) overstates: bundle does NOT reach 20%
B16: Everything at once: Upside + 25x + 8x leverage + recap FY30 to 6x | C16: — | D16: — | E16: 0.1951113 | F16: 3.1839624 | G16: 0.16049811 | H16: 84.563864 | I16: 53.016809 | J16: No – 19.5%; same structure on Downside loses money (see D below)
B17: Same structure, Downside operating case at 8x leverage (no recap) | E17: -0.012958179 | F17: 0.91274378 | G17: -0.02857503 | J17: Peak net leverage 6.7x vs 7.0x covenant
B18: For reference: buy at zero premium (offer = $490.30) | C18: 0 | D18: — | E18: 0.16730265 | F18: 2.9531418 | G18: 0.13490751 | H18: 63.722685 | I18: 39.515077 | J18: Not a control deal – no seller accepts
B19: Conclusion: no single lever, and no realistic combination, reaches 20% at a 30% premium. Only the entry price does it, and that price is below the market.
B21: B. IDLE-CASH / LEVERAGE TEST – entry leverage 4x–15x (full re-runs, Base operating case, 22x exit)
B22: Entry leverage (x FY26E EBITDA) | C22: Total debt €bn | D22: Total equity €bn | E22: Sponsor equity €bn | F22: Gross IRR | G22: Gross MoIC | H22: Net IRR | I22: FY27E interest cover | J22: FY27E net leverage | K22: FY27E ATAD disallowed €m | L22: 7.0x covenant breaches | M22: Master check
B23: 4 | C23: 13.1 | D23: 97.438064 | E23: 65.891009 | F23: 0.1071987 | G23: 2.0292034 | H23: 0.082284533 | I23: 4.4380168 | J23: 2.1840077 | K23: 0 | L23: 0 | M23: OK
B24: 5 | C24: 16.4 | D24: 94.219514 | E24: 62.672459 | F24: 0.10916785 | G24: 2.0543727 | H24: 0.084065558 | I24: 3.5461075 | J24: 3.1040823 | K24: 0 | L24: 0 | M24: OK
B25: 6 | C25: 19.7 | D25: 91.000964 | E25: 59.453909 | F25: 0.11119784 | G25: 2.0805915 | H25: 0.085902358 | I25: 2.9532012 | J25: 4.0351848 | K25: 166.78465 | L25: 0 | M25: OK
B26: 7 | C26: 23 | D26: 87.782414 | E26: 56.235359 | F26: 0.11330578 | G26: 2.1081138 | H26: 0.087810642 | I26: 2.5301604 | J26: 4.9701089 | K26: 391.14036 | L26: 0 | M26: OK
B27: 8 | C27: 26.3 | D27: 84.563864 | E27: 53.016809 | F27: 0.11550031 | G27: 2.1370915 | H27: 0.089798358 | I27: 2.2128529 | J27: 5.9050901 | K27: 615.71107 | L27: 0 | M27: OK
B28: 9 | C28: 29.5 | D28: 81.442814 | E28: 49.895759 | F28: 0.11768788 | G28: 2.1663034 | H28: 0.091780358 | I28: 1.973063 | J28: 6.8117034 | K28: 833.33965 | L28: 0 | M28: OK
B29: 10 | C29: 32.8 | D29: 78.224264 | E29: 46.677209 | F29: 0.12005458 | G29: 2.1982868 | H29: 0.093925936 | I29: 1.774624 | J29: 7.7466847 | K29: 1057.9104 | L29: 1 | M29: ERROR
B30: 12 | C30: 39.4 | D30: 71.787164 | E30: 40.240109 | F30: 0.12438555 | G30: 2.257664 | H30: 0.097843494 | I30: 1.4776895 | J30: 9.6165328 | K30: 1506.6218 | L30: 2 | M30: ERROR
B31: 15 | C31: 49.2 | D31: 62.229014 | E31: 30.681959 | F31: 0.13206689 | G31: 2.3663649 | H31: 0.10480514 | I31: 1.1835121 | J31: 12.393051 | K31: 2173.1768 | L31: 3 | M31: ERROR
B32: Read-across: leverage is a weak lever. +1 turn ≈ +0.2pp gross IRR but −0.4x interest cover. FY27E ATAD cap (30% of tax-EBITDA = €1,127m) already bites at 6x (€167m disallowed, carried forward) and bites harder above it. Covenant (TLA springing 7.0x net) breaks at 10x. RCF is untouched up to 12x because the cash sweep absorbs FCF.
B34: C. DIVIDEND RECAP / EXCESS-CASH PAYOUT TEST (module in 4_Debt_Schedule rows 72–93; 6.0x entry leverage; Base case; 22x exit)
B35: Case | C35: Gross IRR | D35: Gross MoIC | E35: Net IRR | F35: Dividends paid €bn | G35: Debt at exit €bn | H35: Min interest cover after recap | I35: Peak net leverage after recap | J35: Max net interest ÷ ATAD cap | K35: Max ATAD carry-fwd €m | L35: Δ gross IRR vs none (pp) | M35: Master check
B36: No recap (base) | C36: 0.11119784 | D36: 2.0918942 | E36: 0.084022948 | F36: 0 | G36: 7.07 | H36: 2.9532012 | I36: 4.0351848 | J36: 1.1479679 | K36: 166.78465 | L36: 0 | M36: OK
B37: Pay out excess cash from FY30 (no new debt) | C37: 0.11292809 | D37: 2.0888592 | E37: 0.085458024 | F37: 18.414523 | G37: 7.07 | H37: 8.2953762 | I37: 0.92594846 | J37: 0.4236946 | K37: 0 | L37: 0.1722454 | M37: OK
B38: Pay out excess cash from FY31 (no new debt) | C38: 0.11279007 | D38: 2.0890627 | E38: 0.085347996 | F38: 18.434654 | G38: 7.07 | H38: 12.727584 | I38: 0.82242361 | J38: 0.26811848 | K38: 0 | L38: 0.15852066 | M38: OK
B39: Recap FY29 to 5.0x + excess cash | C39: 0.11664638 | D39: 2.0476748 | E39: 0.088220708 | F39: 30.788304 | G39: 23.517497 | H39: 3.0711151 | I39: 4.7173398 | J39: 1.1072464 | K39: 193.54074 | L39: 0.53955495 | M39: OK
B40: Recap FY30 to 3.0x + excess cash | C40: 0.11458131 | D40: 2.0676215 | E40: 0.086708878 | F40: 27.290173 | G40: 18.046361 | H40: 4.9969788 | I40: 2.7506422 | J40: 0.68648954 | K40: 0 | L40: 0.33552597 | M40: OK
B41: Recap FY30 to 4.0x + excess cash | C41: 0.11552723 | D41: 2.0559824 | E41: 0.087428289 | F41: 32.154359 | G41: 24.061814 | H41: 3.7490307 | I41: 3.7506422 | J41: 0.90853851 | K41: 0 | L41: 0.42897327 | M41: OK
B42: Recap FY30 to 5.0x + excess cash | C42: 0.11647537 | D42: 2.0441882 | E42: 0.088149148 | F42: 37.0032 | G42: 30.077268 | H42: 2.9998473 | I42: 4.7506422 | J42: 1.1305875 | K42: 289.92735 | L42: 0.52262322 | M42: OK
B43: Recap FY30 to 6.0x + excess cash | C43: 0.11716658 | D43: 2.0291365 | E43: 0.088636084 | F43: 41.529829 | G43: 36.092722 | H43: 2.5002188 | I43: 5.7506422 | J43: 1.3526365 | K43: 1415.005 | L43: 0.59042484 | M43: OK
B44: Recap FY31 to 4.0x + excess cash | C44: 0.11456674 | D44: 2.0617199 | E44: 0.086714047 | F44: 35.750724 | G44: 27.090662 | H44: 3.7248297 | I44: 3.7785215 | J44: 0.91225817 | K44: 0 | L44: 0.33386484 | M44: OK
B45: Recap FY31 to 5.0x + excess cash | C45: 0.11511298 | D45: 2.0515522 | E45: 0.087126474 | F45: 41.517662 | G45: 33.863327 | H45: 2.9804133 | I45: 4.7785215 | J45: 1.1357758 | K45: 364.10919 | L45: 0.38765138 | M45: OK
B46: Recap FY31 to 6.0x + excess cash | C46: 0.11553463 | D46: 2.0397411 | E46: 0.087425728 | F46: 47.122042 | G46: 40.635993 | H46: 2.4839832 | I46: 5.7785215 | J46: 1.3592934 | K46: 1380.009 | L46: 0.42890264 | M46: OK
B47: 7.0x entry leverage + recap FY30 to 5.0x | C47: 0.11771207 | D47: 2.0770324 | E47: 0.089364641 | F47: 31.787361 | G47: 28.599138 | H47: 3.0196171 | I47: 4.7506422 | J47: 1.1290393 | K47: 262.18202 | L47: 0.6448207 | M47: OK
B49: Read-across: the ~€20bn of exit cash is a real inefficiency, but fixing it is worth at most +0.6pp of gross IRR (11.1% → 11.7%) because the cash only earns 2.0% (4_Debt_Schedule E8) and the recap debt costs 7.5%. Gross MoIC FALLS (2.09x → 2.03x). The ATAD cap (net interest ≤ 30% of tax-EBITDA) starts to bind once recap leverage reaches ≥5x; interest cover drops to 2.5x–3.0x at 5–6x. A recap is a cash-timing tool, not a returns engine.
B51: D. HOLD PERIOD × EXIT MULTIPLE – LIVE FORMULAS (valid with recap switch OFF; exit at year-end of the stated FY)
B52: GROSS IRR (after 8% MIP) | C52: 16 | D52: 18 | E52: 22 | F52: 25 | G52: ='1_Transaction_Summary'!C28 -> 32.536742 | H52: ← last column = entry multiple (no de-rating)
B53: 2028 | C53: =IF('4_Debt_Schedule'!$C$73=1,"n/a",(((C$52*'4_Debt_Schedule'!G63-'4_Debt_Schedule'!G61+'3_Financial_Statements'!G44+'3_Financial_Statements'!G50-'4_Debt_Schedule'!G53)-'0_Dashboard_Toggles'!$C$20*MAX(0,(C$52*'4_Debt_Schedule'!G63-'4_Debt_Schedule'!G61+'3_Financial_Statements'!G44+'3_Financial_Statements'!G50-'4_Debt_Schedule'!G53)-'5_Returns_Sensitivities'!$C$14))/'5_Returns_Sensitivities'!$C$14)^(1/($B53-2026))-1) -> -0.18579273 | D53: =IF('4_Debt_Schedule'!$C$73=1,"n/a",(((D$52*'4_Debt_Schedule'!G63-'4_Debt_Schedule'!G61+'3_Financial_Statements'!G44+'3_Financial_Statements'!G50-'4_Debt_Schedule'!G53)-'0_Dashboard_Toggles'!$C$20*MAX(0,(D$52*'4_Debt_Schedule'!G63-'4_Debt_Schedule'!G61+'3_Financial_Statements'!G44+'3_Financial_Statements'!G50-'4_Debt_Schedule'!G53)-'5_Returns_Sensitivities'!$C$14))/'5_Returns_Sensitivities'!$C$14)^(1/($B53-2026))-1) -> -0.12726814 | E53: =IF('4_Debt_Schedule'!$C$73=1,"n/a",(((E$52*'4_Debt_Schedule'!G63-'4_Debt_Schedule'!G61+'3_Financial_Statements'!G44+'3_Financial_Statements'!G50-'4_Debt_Schedule'!G53)-'0_Dashboard_Toggles'!$C$20*MAX(0,(E$52*'4_Debt_Schedule'!G63-'4_Debt_Schedule'!G61+'3_Financial_Statements'!G44+'3_Financial_Statements'!G50-'4_Debt_Schedule'!G53)-'5_Returns_Sensitivities'!$C$14))/'5_Returns_Sensitivities'!$C$14)^(1/($B53-2026))-1) -> -0.020655457 | F53: =IF('4_Debt_Schedule'!$C$73=1,"n/a",(((F$52*'4_Debt_Schedule'!G63-'4_Debt_Schedule'!G61+'3_Financial_Statements'!G44+'3_Financial_Statements'!G50-'4_Debt_Schedule'!G53)-'0_Dashboard_Toggles'!$C$20*MAX(0,(F$52*'4_Debt_Schedule'!G63-'4_Debt_Schedule'!G61+'3_Financial_Statements'!G44+'3_Financial_Statements'!G50-'4_Debt_Schedule'!G53)-'5_Returns_Sensitivities'!$C$14))/'5_Returns_Sensitivities'!$C$14)^(1/($B53-2026))-1) -> 0.048155671 | G53: =IF('4_Debt_Schedule'!$C$73=1,"n/a",(((G$52*'4_Debt_Schedule'!G63-'4_Debt_Schedule'!G61+'3_Financial_Statements'!G44+'3_Financial_Statements'!G50-'4_Debt_Schedule'!G53)-'0_Dashboard_Toggles'!$C$20*MAX(0,(G$52*'4_Debt_Schedule'!G63-'4_Debt_Schedule'!G61+'3_Financial_Statements'!G44+'3_Financial_Statements'!G50-'4_Debt_Schedule'!G53)-'5_Returns_Sensitivities'!$C$14))/'5_Returns_Sensitivities'!$C$14)^(1/($B53-2026))-1) -> 0.20037849
B54: 2029 | C54: =IF('4_Debt_Schedule'!$C$73=1,"n/a",(((C$52*'4_Debt_Schedule'!H63-'4_Debt_Schedule'!H61+'3_Financial_Statements'!H44+'3_Financial_Statements'!H50-'4_Debt_Schedule'!H53)-'0_Dashboard_Toggles'!$C$20*MAX(0,(C$52*'4_Debt_Schedule'!H63-'4_Debt_Schedule'!H61+'3_Financial_Statements'!H44+'3_Financial_Statements'!H50-'4_Debt_Schedule'!H53)-'5_Returns_Sensitivities'!$C$14))/'5_Returns_Sensitivities'!$C$14)^(1/($B54-2026))-1) -> -0.054126257 | D54: =IF('4_Debt_Schedule'!$C$73=1,"n/a",(((D$52*'4_Debt_Schedule'!H63-'4_Debt_Schedule'!H61+'3_Financial_Statements'!H44+'3_Financial_Statements'!H50-'4_Debt_Schedule'!H53)-'0_Dashboard_Toggles'!$C$20*MAX(0,(D$52*'4_Debt_Schedule'!H63-'4_Debt_Schedule'!H61+'3_Financial_Statements'!H44+'3_Financial_Statements'!H50-'4_Debt_Schedule'!H53)-'5_Returns_Sensitivities'!$C$14))/'5_Returns_Sensitivities'!$C$14)^(1/($B54-2026))-1) -> -0.012529085 | E54: =IF('4_Debt_Schedule'!$C$73=1,"n/a",(((E$52*'4_Debt_Schedule'!H63-'4_Debt_Schedule'!H61+'3_Financial_Statements'!H44+'3_Financial_Statements'!H50-'4_Debt_Schedule'!H53)-'0_Dashboard_Toggles'!$C$20*MAX(0,(E$52*'4_Debt_Schedule'!H63-'4_Debt_Schedule'!H61+'3_Financial_Statements'!H44+'3_Financial_Statements'!H50-'4_Debt_Schedule'!H53)-'5_Returns_Sensitivities'!$C$14))/'5_Returns_Sensitivities'!$C$14)^(1/($B54-2026))-1) -> 0.056856283 | F54: =IF('4_Debt_Schedule'!$C$73=1,"n/a",(((F$52*'4_Debt_Schedule'!H63-'4_Debt_Schedule'!H61+'3_Financial_Statements'!H44+'3_Financial_Statements'!H50-'4_Debt_Schedule'!H53)-'0_Dashboard_Toggles'!$C$20*MAX(0,(F$52*'4_Debt_Schedule'!H63-'4_Debt_Schedule'!H61+'3_Financial_Statements'!H44+'3_Financial_Statements'!H50-'4_Debt_Schedule'!H53)-'5_Returns_Sensitivities'!$C$14))/'5_Returns_Sensitivities'!$C$14)^(1/($B54-2026))-1) -> 0.10285761 | G54: =IF('4_Debt_Schedule'!$C$73=1,"n/a",(((G$52*'4_Debt_Schedule'!H63-'4_Debt_Schedule'!H61+'3_Financial_Statements'!H44+'3_Financial_Statements'!H50-'4_Debt_Schedule'!H53)-'0_Dashboard_Toggles'!$C$20*MAX(0,(G$52*'4_Debt_Schedule'!H63-'4_Debt_Schedule'!H61+'3_Financial_Statements'!H44+'3_Financial_Statements'!H50-'4_Debt_Schedule'!H53)-'5_Returns_Sensitivities'!$C$14))/'5_Returns_Sensitivities'!$C$14)^(1/($B54-2026))-1) -> 0.20409369
B55: 2030 | C55: =IF('4_Debt_Schedule'!$C$73=1,"n/a",(((C$52*'4_Debt_Schedule'!I63-'4_Debt_Schedule'!I61+'3_Financial_Statements'!I44+'3_Financial_Statements'!I50-'4_Debt_Schedule'!I53)-'0_Dashboard_Toggles'!$C$20*MAX(0,(C$52*'4_Debt_Schedule'!I63-'4_Debt_Schedule'!I61+'3_Financial_Statements'!I44+'3_Financial_Statements'!I50-'4_Debt_Schedule'!I53)-'5_Returns_Sensitivities'!$C$14))/'5_Returns_Sensitivities'!$C$14)^(1/($B55-2026))-1) -> 0.0042806877 | D55: =IF('4_Debt_Schedule'!$C$73=1,"n/a",(((D$52*'4_Debt_Schedule'!I63-'4_Debt_Schedule'!I61+'3_Financial_Statements'!I44+'3_Financial_Statements'!I50-'4_Debt_Schedule'!I53)-'0_Dashboard_Toggles'!$C$20*MAX(0,(D$52*'4_Debt_Schedule'!I63-'4_Debt_Schedule'!I61+'3_Financial_Statements'!I44+'3_Financial_Statements'!I50-'4_Debt_Schedule'!I53)-'5_Returns_Sensitivities'!$C$14))/'5_Returns_Sensitivities'!$C$14)^(1/($B55-2026))-1) -> 0.033041714 | E55: =IF('4_Debt_Schedule'!$C$73=1,"n/a",(((E$52*'4_Debt_Schedule'!I63-'4_Debt_Schedule'!I61+'3_Financial_Statements'!I44+'3_Financial_Statements'!I50-'4_Debt_Schedule'!I53)-'0_Dashboard_Toggles'!$C$20*MAX(0,(E$52*'4_Debt_Schedule'!I63-'4_Debt_Schedule'!I61+'3_Financial_Statements'!I44+'3_Financial_Statements'!I50-'4_Debt_Schedule'!I53)-'5_Returns_Sensitivities'!$C$14))/'5_Returns_Sensitivities'!$C$14)^(1/($B55-2026))-1) -> 0.084268002 | F55: =IF('4_Debt_Schedule'!$C$73=1,"n/a",(((F$52*'4_Debt_Schedule'!I63-'4_Debt_Schedule'!I61+'3_Financial_Statements'!I44+'3_Financial_Statements'!I50-'4_Debt_Schedule'!I53)-'0_Dashboard_Toggles'!$C$20*MAX(0,(F$52*'4_Debt_Schedule'!I63-'4_Debt_Schedule'!I61+'3_Financial_Statements'!I44+'3_Financial_Statements'!I50-'4_Debt_Schedule'!I53)-'5_Returns_Sensitivities'!$C$14))/'5_Returns_Sensitivities'!$C$14)^(1/($B55-2026))-1) -> 0.11840363 | G55: =IF('4_Debt_Schedule'!$C$73=1,"n/a",(((G$52*'4_Debt_Schedule'!I63-'4_Debt_Schedule'!I61+'3_Financial_Statements'!I44+'3_Financial_Statements'!I50-'4_Debt_Schedule'!I53)-'0_Dashboard_Toggles'!$C$20*MAX(0,(G$52*'4_Debt_Schedule'!I63-'4_Debt_Schedule'!I61+'3_Financial_Statements'!I44+'3_Financial_Statements'!I50-'4_Debt_Schedule'!I53)-'5_Returns_Sensitivities'!$C$14))/'5_Returns_Sensitivities'!$C$14)^(1/($B55-2026))-1) -> 0.19259874
B56: 2031 | C56: =IF('4_Debt_Schedule'!$C$73=1,"n/a",(((C$52*'4_Debt_Schedule'!J63-'4_Debt_Schedule'!J61+'3_Financial_Statements'!J44+'3_Financial_Statements'!J50-'4_Debt_Schedule'!J53)-'0_Dashboard_Toggles'!$C$20*MAX(0,(C$52*'4_Debt_Schedule'!J63-'4_Debt_Schedule'!J61+'3_Financial_Statements'!J44+'3_Financial_Statements'!J50-'4_Debt_Schedule'!J53)-'5_Returns_Sensitivities'!$C$14))/'5_Returns_Sensitivities'!$C$14)^(1/($B56-2026))-1) -> 0.035609895 | D56: =IF('4_Debt_Schedule'!$C$73=1,"n/a",(((D$52*'4_Debt_Schedule'!J63-'4_Debt_Schedule'!J61+'3_Financial_Statements'!J44+'3_Financial_Statements'!J50-'4_Debt_Schedule'!J53)-'0_Dashboard_Toggles'!$C$20*MAX(0,(D$52*'4_Debt_Schedule'!J63-'4_Debt_Schedule'!J61+'3_Financial_Statements'!J44+'3_Financial_Statements'!J50-'4_Debt_Schedule'!J53)-'5_Returns_Sensitivities'!$C$14))/'5_Returns_Sensitivities'!$C$14)^(1/($B56-2026))-1) -> 0.058395845 | E56: =IF('4_Debt_Schedule'!$C$73=1,"n/a",(((E$52*'4_Debt_Schedule'!J63-'4_Debt_Schedule'!J61+'3_Financial_Statements'!J44+'3_Financial_Statements'!J50-'4_Debt_Schedule'!J53)-'0_Dashboard_Toggles'!$C$20*MAX(0,(E$52*'4_Debt_Schedule'!J63-'4_Debt_Schedule'!J61+'3_Financial_Statements'!J44+'3_Financial_Statements'!J50-'4_Debt_Schedule'!J53)-'5_Returns_Sensitivities'!$C$14))/'5_Returns_Sensitivities'!$C$14)^(1/($B56-2026))-1) -> 0.098836534 | F56: =IF('4_Debt_Schedule'!$C$73=1,"n/a",(((F$52*'4_Debt_Schedule'!J63-'4_Debt_Schedule'!J61+'3_Financial_Statements'!J44+'3_Financial_Statements'!J50-'4_Debt_Schedule'!J53)-'0_Dashboard_Toggles'!$C$20*MAX(0,(F$52*'4_Debt_Schedule'!J63-'4_Debt_Schedule'!J61+'3_Financial_Statements'!J44+'3_Financial_Statements'!J50-'4_Debt_Schedule'!J53)-'5_Returns_Sensitivities'!$C$14))/'5_Returns_Sensitivities'!$C$14)^(1/($B56-2026))-1) -> 0.12567205 | G56: =IF('4_Debt_Schedule'!$C$73=1,"n/a",(((G$52*'4_Debt_Schedule'!J63-'4_Debt_Schedule'!J61+'3_Financial_Statements'!J44+'3_Financial_Statements'!J50-'4_Debt_Schedule'!J53)-'0_Dashboard_Toggles'!$C$20*MAX(0,(G$52*'4_Debt_Schedule'!J63-'4_Debt_Schedule'!J61+'3_Financial_Statements'!J44+'3_Financial_Statements'!J50-'4_Debt_Schedule'!J53)-'5_Returns_Sensitivities'!$C$14))/'5_Returns_Sensitivities'!$C$14)^(1/($B56-2026))-1) -> 0.18366054
B57: 2032 | C57: =IF('4_Debt_Schedule'!$C$73=1,"n/a",(((C$52*'4_Debt_Schedule'!K63-'4_Debt_Schedule'!K61+'3_Financial_Statements'!K44+'3_Financial_Statements'!K50-'4_Debt_Schedule'!K53)-'0_Dashboard_Toggles'!$C$20*MAX(0,(C$52*'4_Debt_Schedule'!K63-'4_Debt_Schedule'!K61+'3_Financial_Statements'!K44+'3_Financial_Statements'!K50-'4_Debt_Schedule'!K53)-'5_Returns_Sensitivities'!$C$14))/'5_Returns_Sensitivities'!$C$14)^(1/($B57-2026))-1) -> 0.055058537 | D57: =IF('4_Debt_Schedule'!$C$73=1,"n/a",(((D$52*'4_Debt_Schedule'!K63-'4_Debt_Schedule'!K61+'3_Financial_Statements'!K44+'3_Financial_Statements'!K50-'4_Debt_Schedule'!K53)-'0_Dashboard_Toggles'!$C$20*MAX(0,(D$52*'4_Debt_Schedule'!K63-'4_Debt_Schedule'!K61+'3_Financial_Statements'!K44+'3_Financial_Statements'!K50-'4_Debt_Schedule'!K53)-'5_Returns_Sensitivities'!$C$14))/'5_Returns_Sensitivities'!$C$14)^(1/($B57-2026))-1) -> 0.073738488 | E57: =IF('4_Debt_Schedule'!$C$73=1,"n/a",(((E$52*'4_Debt_Schedule'!K63-'4_Debt_Schedule'!K61+'3_Financial_Statements'!K44+'3_Financial_Statements'!K50-'4_Debt_Schedule'!K53)-'0_Dashboard_Toggles'!$C$20*MAX(0,(E$52*'4_Debt_Schedule'!K63-'4_Debt_Schedule'!K61+'3_Financial_Statements'!K44+'3_Financial_Statements'!K50-'4_Debt_Schedule'!K53)-'5_Returns_Sensitivities'!$C$14))/'5_Returns_Sensitivities'!$C$14)^(1/($B57-2026))-1) -> 0.10685051 | F57: =IF('4_Debt_Schedule'!$C$73=1,"n/a",(((F$52*'4_Debt_Schedule'!K63-'4_Debt_Schedule'!K61+'3_Financial_Statements'!K44+'3_Financial_Statements'!K50-'4_Debt_Schedule'!K53)-'0_Dashboard_Toggles'!$C$20*MAX(0,(F$52*'4_Debt_Schedule'!K63-'4_Debt_Schedule'!K61+'3_Financial_Statements'!K44+'3_Financial_Statements'!K50-'4_Debt_Schedule'!K53)-'5_Returns_Sensitivities'!$C$14))/'5_Returns_Sensitivities'!$C$14)^(1/($B57-2026))-1) -> 0.12878393 | G57: =IF('4_Debt_Schedule'!$C$73=1,"n/a",(((G$52*'4_Debt_Schedule'!K63-'4_Debt_Schedule'!K61+'3_Financial_Statements'!K44+'3_Financial_Statements'!K50-'4_Debt_Schedule'!K53)-'0_Dashboard_Toggles'!$C$20*MAX(0,(G$52*'4_Debt_Schedule'!K63-'4_Debt_Schedule'!K61+'3_Financial_Statements'!K44+'3_Financial_Statements'!K50-'4_Debt_Schedule'!K53)-'5_Returns_Sensitivities'!$C$14))/'5_Returns_Sensitivities'!$C$14)^(1/($B57-2026))-1) -> 0.17604566
B58: 2033 | C58: =IF('4_Debt_Schedule'!$C$73=1,"n/a",(((C$52*'4_Debt_Schedule'!L63-'4_Debt_Schedule'!L61+'3_Financial_Statements'!L44+'3_Financial_Statements'!L50-'4_Debt_Schedule'!L53)-'0_Dashboard_Toggles'!$C$20*MAX(0,(C$52*'4_Debt_Schedule'!L63-'4_Debt_Schedule'!L61+'3_Financial_Statements'!L44+'3_Financial_Statements'!L50-'4_Debt_Schedule'!L53)-'5_Returns_Sensitivities'!$C$14))/'5_Returns_Sensitivities'!$C$14)^(1/($B58-2026))-1) -> 0.06764876 | D58: =IF('4_Debt_Schedule'!$C$73=1,"n/a",(((D$52*'4_Debt_Schedule'!L63-'4_Debt_Schedule'!L61+'3_Financial_Statements'!L44+'3_Financial_Statements'!L50-'4_Debt_Schedule'!L53)-'0_Dashboard_Toggles'!$C$20*MAX(0,(D$52*'4_Debt_Schedule'!L63-'4_Debt_Schedule'!L61+'3_Financial_Statements'!L44+'3_Financial_Statements'!L50-'4_Debt_Schedule'!L53)-'5_Returns_Sensitivities'!$C$14))/'5_Returns_Sensitivities'!$C$14)^(1/($B58-2026))-1) -> 0.083356713 | E58: =IF('4_Debt_Schedule'!$C$73=1,"n/a",(((E$52*'4_Debt_Schedule'!L63-'4_Debt_Schedule'!L61+'3_Financial_Statements'!L44+'3_Financial_Statements'!L50-'4_Debt_Schedule'!L53)-'0_Dashboard_Toggles'!$C$20*MAX(0,(E$52*'4_Debt_Schedule'!L63-'4_Debt_Schedule'!L61+'3_Financial_Statements'!L44+'3_Financial_Statements'!L50-'4_Debt_Schedule'!L53)-'5_Returns_Sensitivities'!$C$14))/'5_Returns_Sensitivities'!$C$14)^(1/($B58-2026))-1) -> 0.11119784 | F58: =IF('4_Debt_Schedule'!$C$73=1,"n/a",(((F$52*'4_Debt_Schedule'!L63-'4_Debt_Schedule'!L61+'3_Financial_Statements'!L44+'3_Financial_Statements'!L50-'4_Debt_Schedule'!L53)-'0_Dashboard_Toggles'!$C$20*MAX(0,(F$52*'4_Debt_Schedule'!L63-'4_Debt_Schedule'!L61+'3_Financial_Statements'!L44+'3_Financial_Statements'!L50-'4_Debt_Schedule'!L53)-'5_Returns_Sensitivities'!$C$14))/'5_Returns_Sensitivities'!$C$14)^(1/($B58-2026))-1) -> 0.12963007 | G58: =IF('4_Debt_Schedule'!$C$73=1,"n/a",(((G$52*'4_Debt_Schedule'!L63-'4_Debt_Schedule'!L61+'3_Financial_Statements'!L44+'3_Financial_Statements'!L50-'4_Debt_Schedule'!L53)-'0_Dashboard_Toggles'!$C$20*MAX(0,(G$52*'4_Debt_Schedule'!L63-'4_Debt_Schedule'!L61+'3_Financial_Statements'!L44+'3_Financial_Statements'!L50-'4_Debt_Schedule'!L53)-'5_Returns_Sensitivities'!$C$14))/'5_Returns_Sensitivities'!$C$14)^(1/($B58-2026))-1) -> 0.16929801
B59: GROSS MoIC
B60: 2028 | C60: =IF('4_Debt_Schedule'!$C$73=1,"n/a",((C$52*'4_Debt_Schedule'!G63-'4_Debt_Schedule'!G61+'3_Financial_Statements'!G44+'3_Financial_Statements'!G50-'4_Debt_Schedule'!G53)-'0_Dashboard_Toggles'!$C$20*MAX(0,(C$52*'4_Debt_Schedule'!G63-'4_Debt_Schedule'!G61+'3_Financial_Statements'!G44+'3_Financial_Statements'!G50-'4_Debt_Schedule'!G53)-'5_Returns_Sensitivities'!$C$14))/'5_Returns_Sensitivities'!$C$14) -> 0.66293348 | D60: =IF('4_Debt_Schedule'!$C$73=1,"n/a",((D$52*'4_Debt_Schedule'!G63-'4_Debt_Schedule'!G61+'3_Financial_Statements'!G44+'3_Financial_Statements'!G50-'4_Debt_Schedule'!G53)-'0_Dashboard_Toggles'!$C$20*MAX(0,(D$52*'4_Debt_Schedule'!G63-'4_Debt_Schedule'!G61+'3_Financial_Statements'!G44+'3_Financial_Statements'!G50-'4_Debt_Schedule'!G53)-'5_Returns_Sensitivities'!$C$14))/'5_Returns_Sensitivities'!$C$14) -> 0.7616609 | E60: =IF('4_Debt_Schedule'!$C$73=1,"n/a",((E$52*'4_Debt_Schedule'!G63-'4_Debt_Schedule'!G61+'3_Financial_Statements'!G44+'3_Financial_Statements'!G50-'4_Debt_Schedule'!G53)-'0_Dashboard_Toggles'!$C$20*MAX(0,(E$52*'4_Debt_Schedule'!G63-'4_Debt_Schedule'!G61+'3_Financial_Statements'!G44+'3_Financial_Statements'!G50-'4_Debt_Schedule'!G53)-'5_Returns_Sensitivities'!$C$14))/'5_Returns_Sensitivities'!$C$14) -> 0.95911573 | F60: =IF('4_Debt_Schedule'!$C$73=1,"n/a",((F$52*'4_Debt_Schedule'!G63-'4_Debt_Schedule'!G61+'3_Financial_Statements'!G44+'3_Financial_Statements'!G50-'4_Debt_Schedule'!G53)-'0_Dashboard_Toggles'!$C$20*MAX(0,(F$52*'4_Debt_Schedule'!G63-'4_Debt_Schedule'!G61+'3_Financial_Statements'!G44+'3_Financial_Statements'!G50-'4_Debt_Schedule'!G53)-'5_Returns_Sensitivities'!$C$14))/'5_Returns_Sensitivities'!$C$14) -> 1.0986303 | G60: =IF('4_Debt_Schedule'!$C$73=1,"n/a",((G$52*'4_Debt_Schedule'!G63-'4_Debt_Schedule'!G61+'3_Financial_Statements'!G44+'3_Financial_Statements'!G50-'4_Debt_Schedule'!G53)-'0_Dashboard_Toggles'!$C$20*MAX(0,(G$52*'4_Debt_Schedule'!G63-'4_Debt_Schedule'!G61+'3_Financial_Statements'!G44+'3_Financial_Statements'!G50-'4_Debt_Schedule'!G53)-'5_Returns_Sensitivities'!$C$14))/'5_Returns_Sensitivities'!$C$14) -> 1.4409085
B61: 2029 | C61: =IF('4_Debt_Schedule'!$C$73=1,"n/a",((C$52*'4_Debt_Schedule'!H63-'4_Debt_Schedule'!H61+'3_Financial_Statements'!H44+'3_Financial_Statements'!H50-'4_Debt_Schedule'!H53)-'0_Dashboard_Toggles'!$C$20*MAX(0,(C$52*'4_Debt_Schedule'!H63-'4_Debt_Schedule'!H61+'3_Financial_Statements'!H44+'3_Financial_Statements'!H50-'4_Debt_Schedule'!H53)-'5_Returns_Sensitivities'!$C$14))/'5_Returns_Sensitivities'!$C$14) -> 0.84625161 | D61: =IF('4_Debt_Schedule'!$C$73=1,"n/a",((D$52*'4_Debt_Schedule'!H63-'4_Debt_Schedule'!H61+'3_Financial_Statements'!H44+'3_Financial_Statements'!H50-'4_Debt_Schedule'!H53)-'0_Dashboard_Toggles'!$C$20*MAX(0,(D$52*'4_Debt_Schedule'!H63-'4_Debt_Schedule'!H61+'3_Financial_Statements'!H44+'3_Financial_Statements'!H50-'4_Debt_Schedule'!H53)-'5_Returns_Sensitivities'!$C$14))/'5_Returns_Sensitivities'!$C$14) -> 0.96288171 | E61: =IF('4_Debt_Schedule'!$C$73=1,"n/a",((E$52*'4_Debt_Schedule'!H63-'4_Debt_Schedule'!H61+'3_Financial_Statements'!H44+'3_Financial_Statements'!H50-'4_Debt_Schedule'!H53)-'0_Dashboard_Toggles'!$C$20*MAX(0,(E$52*'4_Debt_Schedule'!H63-'4_Debt_Schedule'!H61+'3_Financial_Statements'!H44+'3_Financial_Statements'!H50-'4_Debt_Schedule'!H53)-'5_Returns_Sensitivities'!$C$14))/'5_Returns_Sensitivities'!$C$14) -> 1.1804506 | F61: =IF('4_Debt_Schedule'!$C$73=1,"n/a",((F$52*'4_Debt_Schedule'!H63-'4_Debt_Schedule'!H61+'3_Financial_Statements'!H44+'3_Financial_Statements'!H50-'4_Debt_Schedule'!H53)-'0_Dashboard_Toggles'!$C$20*MAX(0,(F$52*'4_Debt_Schedule'!H63-'4_Debt_Schedule'!H61+'3_Financial_Statements'!H44+'3_Financial_Statements'!H50-'4_Debt_Schedule'!H53)-'5_Returns_Sensitivities'!$C$14))/'5_Returns_Sensitivities'!$C$14) -> 1.3414001 | G61: =IF('4_Debt_Schedule'!$C$73=1,"n/a",((G$52*'4_Debt_Schedule'!H63-'4_Debt_Schedule'!H61+'3_Financial_Statements'!H44+'3_Financial_Statements'!H50-'4_Debt_Schedule'!H53)-'0_Dashboard_Toggles'!$C$20*MAX(0,(G$52*'4_Debt_Schedule'!H63-'4_Debt_Schedule'!H61+'3_Financial_Statements'!H44+'3_Financial_Statements'!H50-'4_Debt_Schedule'!H53)-'5_Returns_Sensitivities'!$C$14))/'5_Returns_Sensitivities'!$C$14) -> 1.7457451
B62: 2030 | C62: =IF('4_Debt_Schedule'!$C$73=1,"n/a",((C$52*'4_Debt_Schedule'!I63-'4_Debt_Schedule'!I61+'3_Financial_Statements'!I44+'3_Financial_Statements'!I50-'4_Debt_Schedule'!I53)-'0_Dashboard_Toggles'!$C$20*MAX(0,(C$52*'4_Debt_Schedule'!I63-'4_Debt_Schedule'!I61+'3_Financial_Statements'!I44+'3_Financial_Statements'!I50-'4_Debt_Schedule'!I53)-'5_Returns_Sensitivities'!$C$14))/'5_Returns_Sensitivities'!$C$14) -> 1.017233 | D62: =IF('4_Debt_Schedule'!$C$73=1,"n/a",((D$52*'4_Debt_Schedule'!I63-'4_Debt_Schedule'!I61+'3_Financial_Statements'!I44+'3_Financial_Statements'!I50-'4_Debt_Schedule'!I53)-'0_Dashboard_Toggles'!$C$20*MAX(0,(D$52*'4_Debt_Schedule'!I63-'4_Debt_Schedule'!I61+'3_Financial_Statements'!I44+'3_Financial_Statements'!I50-'4_Debt_Schedule'!I53)-'5_Returns_Sensitivities'!$C$14))/'5_Returns_Sensitivities'!$C$14) -> 1.1388629 | E62: =IF('4_Debt_Schedule'!$C$73=1,"n/a",((E$52*'4_Debt_Schedule'!I63-'4_Debt_Schedule'!I61+'3_Financial_Statements'!I44+'3_Financial_Statements'!I50-'4_Debt_Schedule'!I53)-'0_Dashboard_Toggles'!$C$20*MAX(0,(E$52*'4_Debt_Schedule'!I63-'4_Debt_Schedule'!I61+'3_Financial_Statements'!I44+'3_Financial_Statements'!I50-'4_Debt_Schedule'!I53)-'5_Returns_Sensitivities'!$C$14))/'5_Returns_Sensitivities'!$C$14) -> 1.3821226 | F62: =IF('4_Debt_Schedule'!$C$73=1,"n/a",((F$52*'4_Debt_Schedule'!I63-'4_Debt_Schedule'!I61+'3_Financial_Statements'!I44+'3_Financial_Statements'!I50-'4_Debt_Schedule'!I53)-'0_Dashboard_Toggles'!$C$20*MAX(0,(F$52*'4_Debt_Schedule'!I63-'4_Debt_Schedule'!I61+'3_Financial_Statements'!I44+'3_Financial_Statements'!I50-'4_Debt_Schedule'!I53)-'5_Returns_Sensitivities'!$C$14))/'5_Returns_Sensitivities'!$C$14) -> 1.5645674 | G62: =IF('4_Debt_Schedule'!$C$73=1,"n/a",((G$52*'4_Debt_Schedule'!I63-'4_Debt_Schedule'!I61+'3_Financial_Statements'!I44+'3_Financial_Statements'!I50-'4_Debt_Schedule'!I53)-'0_Dashboard_Toggles'!$C$20*MAX(0,(G$52*'4_Debt_Schedule'!I63-'4_Debt_Schedule'!I61+'3_Financial_Statements'!I44+'3_Financial_Statements'!I50-'4_Debt_Schedule'!I53)-'5_Returns_Sensitivities'!$C$14))/'5_Returns_Sensitivities'!$C$14) -> 2.0229138
B63: 2031 | C63: =IF('4_Debt_Schedule'!$C$73=1,"n/a",((C$52*'4_Debt_Schedule'!J63-'4_Debt_Schedule'!J61+'3_Financial_Statements'!J44+'3_Financial_Statements'!J50-'4_Debt_Schedule'!J53)-'0_Dashboard_Toggles'!$C$20*MAX(0,(C$52*'4_Debt_Schedule'!J63-'4_Debt_Schedule'!J61+'3_Financial_Statements'!J44+'3_Financial_Statements'!J50-'4_Debt_Schedule'!J53)-'5_Returns_Sensitivities'!$C$14))/'5_Returns_Sensitivities'!$C$14) -> 1.1911898 | D63: =IF('4_Debt_Schedule'!$C$73=1,"n/a",((D$52*'4_Debt_Schedule'!J63-'4_Debt_Schedule'!J61+'3_Financial_Statements'!J44+'3_Financial_Statements'!J50-'4_Debt_Schedule'!J53)-'0_Dashboard_Toggles'!$C$20*MAX(0,(D$52*'4_Debt_Schedule'!J63-'4_Debt_Schedule'!J61+'3_Financial_Statements'!J44+'3_Financial_Statements'!J50-'4_Debt_Schedule'!J53)-'5_Returns_Sensitivities'!$C$14))/'5_Returns_Sensitivities'!$C$14) -> 1.3281301 | E63: =IF('4_Debt_Schedule'!$C$73=1,"n/a",((E$52*'4_Debt_Schedule'!J63-'4_Debt_Schedule'!J61+'3_Financial_Statements'!J44+'3_Financial_Statements'!J50-'4_Debt_Schedule'!J53)-'0_Dashboard_Toggles'!$C$20*MAX(0,(E$52*'4_Debt_Schedule'!J63-'4_Debt_Schedule'!J61+'3_Financial_Statements'!J44+'3_Financial_Statements'!J50-'4_Debt_Schedule'!J53)-'5_Returns_Sensitivities'!$C$14))/'5_Returns_Sensitivities'!$C$14) -> 1.6020108 | F63: =IF('4_Debt_Schedule'!$C$73=1,"n/a",((F$52*'4_Debt_Schedule'!J63-'4_Debt_Schedule'!J61+'3_Financial_Statements'!J44+'3_Financial_Statements'!J50-'4_Debt_Schedule'!J53)-'0_Dashboard_Toggles'!$C$20*MAX(0,(F$52*'4_Debt_Schedule'!J63-'4_Debt_Schedule'!J61+'3_Financial_Statements'!J44+'3_Financial_Statements'!J50-'4_Debt_Schedule'!J53)-'5_Returns_Sensitivities'!$C$14))/'5_Returns_Sensitivities'!$C$14) -> 1.8074214 | G63: =IF('4_Debt_Schedule'!$C$73=1,"n/a",((G$52*'4_Debt_Schedule'!J63-'4_Debt_Schedule'!J61+'3_Financial_Statements'!J44+'3_Financial_Statements'!J50-'4_Debt_Schedule'!J53)-'0_Dashboard_Toggles'!$C$20*MAX(0,(G$52*'4_Debt_Schedule'!J63-'4_Debt_Schedule'!J61+'3_Financial_Statements'!J44+'3_Financial_Statements'!J50-'4_Debt_Schedule'!J53)-'5_Returns_Sensitivities'!$C$14))/'5_Returns_Sensitivities'!$C$14) -> 2.3234635
B64: 2032 | C64: =IF('4_Debt_Schedule'!$C$73=1,"n/a",((C$52*'4_Debt_Schedule'!K63-'4_Debt_Schedule'!K61+'3_Financial_Statements'!K44+'3_Financial_Statements'!K50-'4_Debt_Schedule'!K53)-'0_Dashboard_Toggles'!$C$20*MAX(0,(C$52*'4_Debt_Schedule'!K63-'4_Debt_Schedule'!K61+'3_Financial_Statements'!K44+'3_Financial_Statements'!K50-'4_Debt_Schedule'!K53)-'5_Returns_Sensitivities'!$C$14))/'5_Returns_Sensitivities'!$C$14) -> 1.3793019 | D64: =IF('4_Debt_Schedule'!$C$73=1,"n/a",((D$52*'4_Debt_Schedule'!K63-'4_Debt_Schedule'!K61+'3_Financial_Statements'!K44+'3_Financial_Statements'!K50-'4_Debt_Schedule'!K53)-'0_Dashboard_Toggles'!$C$20*MAX(0,(D$52*'4_Debt_Schedule'!K63-'4_Debt_Schedule'!K61+'3_Financial_Statements'!K44+'3_Financial_Statements'!K50-'4_Debt_Schedule'!K53)-'5_Returns_Sensitivities'!$C$14))/'5_Returns_Sensitivities'!$C$14) -> 1.532467 | E64: =IF('4_Debt_Schedule'!$C$73=1,"n/a",((E$52*'4_Debt_Schedule'!K63-'4_Debt_Schedule'!K61+'3_Financial_Statements'!K44+'3_Financial_Statements'!K50-'4_Debt_Schedule'!K53)-'0_Dashboard_Toggles'!$C$20*MAX(0,(E$52*'4_Debt_Schedule'!K63-'4_Debt_Schedule'!K61+'3_Financial_Statements'!K44+'3_Financial_Statements'!K50-'4_Debt_Schedule'!K53)-'5_Returns_Sensitivities'!$C$14))/'5_Returns_Sensitivities'!$C$14) -> 1.8387971 | F64: =IF('4_Debt_Schedule'!$C$73=1,"n/a",((F$52*'4_Debt_Schedule'!K63-'4_Debt_Schedule'!K61+'3_Financial_Statements'!K44+'3_Financial_Statements'!K50-'4_Debt_Schedule'!K53)-'0_Dashboard_Toggles'!$C$20*MAX(0,(F$52*'4_Debt_Schedule'!K63-'4_Debt_Schedule'!K61+'3_Financial_Statements'!K44+'3_Financial_Statements'!K50-'4_Debt_Schedule'!K53)-'5_Returns_Sensitivities'!$C$14))/'5_Returns_Sensitivities'!$C$14) -> 2.0685447 | G64: =IF('4_Debt_Schedule'!$C$73=1,"n/a",((G$52*'4_Debt_Schedule'!K63-'4_Debt_Schedule'!K61+'3_Financial_Statements'!K44+'3_Financial_Statements'!K50-'4_Debt_Schedule'!K53)-'0_Dashboard_Toggles'!$C$20*MAX(0,(G$52*'4_Debt_Schedule'!K63-'4_Debt_Schedule'!K61+'3_Financial_Statements'!K44+'3_Financial_Statements'!K50-'4_Debt_Schedule'!K53)-'5_Returns_Sensitivities'!$C$14))/'5_Returns_Sensitivities'!$C$14) -> 2.6457275
B65: 2033 | C65: =IF('4_Debt_Schedule'!$C$73=1,"n/a",((C$52*'4_Debt_Schedule'!L63-'4_Debt_Schedule'!L61+'3_Financial_Statements'!L44+'3_Financial_Statements'!L50-'4_Debt_Schedule'!L53)-'0_Dashboard_Toggles'!$C$20*MAX(0,(C$52*'4_Debt_Schedule'!L63-'4_Debt_Schedule'!L61+'3_Financial_Statements'!L44+'3_Financial_Statements'!L50-'4_Debt_Schedule'!L53)-'5_Returns_Sensitivities'!$C$14))/'5_Returns_Sensitivities'!$C$14) -> 1.5812437 | D65: =IF('4_Debt_Schedule'!$C$73=1,"n/a",((D$52*'4_Debt_Schedule'!L63-'4_Debt_Schedule'!L61+'3_Financial_Statements'!L44+'3_Financial_Statements'!L50-'4_Debt_Schedule'!L53)-'0_Dashboard_Toggles'!$C$20*MAX(0,(D$52*'4_Debt_Schedule'!L63-'4_Debt_Schedule'!L61+'3_Financial_Statements'!L44+'3_Financial_Statements'!L50-'4_Debt_Schedule'!L53)-'5_Returns_Sensitivities'!$C$14))/'5_Returns_Sensitivities'!$C$14) -> 1.7514605 | E65: =IF('4_Debt_Schedule'!$C$73=1,"n/a",((E$52*'4_Debt_Schedule'!L63-'4_Debt_Schedule'!L61+'3_Financial_Statements'!L44+'3_Financial_Statements'!L50-'4_Debt_Schedule'!L53)-'0_Dashboard_Toggles'!$C$20*MAX(0,(E$52*'4_Debt_Schedule'!L63-'4_Debt_Schedule'!L61+'3_Financial_Statements'!L44+'3_Financial_Statements'!L50-'4_Debt_Schedule'!L53)-'5_Returns_Sensitivities'!$C$14))/'5_Returns_Sensitivities'!$C$14) -> 2.0918942 | F65: =IF('4_Debt_Schedule'!$C$73=1,"n/a",((F$52*'4_Debt_Schedule'!L63-'4_Debt_Schedule'!L61+'3_Financial_Statements'!L44+'3_Financial_Statements'!L50-'4_Debt_Schedule'!L53)-'0_Dashboard_Toggles'!$C$20*MAX(0,(F$52*'4_Debt_Schedule'!L63-'4_Debt_Schedule'!L61+'3_Financial_Statements'!L44+'3_Financial_Statements'!L50-'4_Debt_Schedule'!L53)-'5_Returns_Sensitivities'!$C$14))/'5_Returns_Sensitivities'!$C$14) -> 2.3472195 | G65: =IF('4_Debt_Schedule'!$C$73=1,"n/a",((G$52*'4_Debt_Schedule'!L63-'4_Debt_Schedule'!L61+'3_Financial_Statements'!L44+'3_Financial_Statements'!L50-'4_Debt_Schedule'!L53)-'0_Dashboard_Toggles'!$C$20*MAX(0,(G$52*'4_Debt_Schedule'!L63-'4_Debt_Schedule'!L61+'3_Financial_Statements'!L44+'3_Financial_Statements'!L50-'4_Debt_Schedule'!L53)-'5_Returns_Sensitivities'!$C$14))/'5_Returns_Sensitivities'!$C$14) -> 2.9886597
B66: Check: FY33E / 22x cell equals 5_Returns_Sensitivities C19 → | C66: =IF(ABS(E58-'5_Returns_Sensitivities'!C19)<0.00001,"OK","CHECK") -> OK
B67: Read-across: at 22x no holding period reaches 20%; shorter holds are worse because the multiple compression is front-loaded. Only an exit at the 32.5x entry multiple within ~3 years reaches 20% – i.e. a bet that the premium itself is recouped.
B69: E. REALISM OF SIZE vs LARGEST PRECEDENT BUYOUTS (sourced, static; USD bn)
B70: Deal | C70: Year | D70: Enterprise value $bn | E70: Total equity $bn | F70: Debt $bn | G70: Harmony EV ÷ deal | H70: Harmony total equity ÷ deal | I70: Source / status
B71: Project Harmony (this model; € converted at Dashboard C9) | C71: 2026E | D71: ='1_Transaction_Summary'!C25/'0_Dashboard_Toggles'!C9/1000 -> 121.97915 | E71: ='5_Returns_Sensitivities'!C14/'0_Dashboard_Toggles'!C9/1000 -> 103.92984 | F71: ='1_Transaction_Summary'!C47/'0_Dashboard_Toggles'!C9/1000 -> 22.498858
B72: of which new sponsor cash (excl. rollover) | E72: ='1_Transaction_Summary'!C50/'0_Dashboard_Toggles'!C9/1000 -> 67.900764
B73: Electronic Arts (Silver Lake / PIF / Affinity) | C73: 2025–26 | D73: 55 | E73: 36 | F73: 20 | G73: =$D$71/D73 -> 2.2178028 | H73: =$E$71/E73 -> 2.8869399 | I73: Press: ~$36bn equity incl. PIF 9.9% rollover; $20bn JPM debt ($18bn funded at close); reported closed after approvals 30-Jul. thewrap.com; paperjam.lu
B74: TXU / Energy Future Holdings (KKR / TPG / GS) | C74: 2007 | D74: 45 | E74: 8 | G74: =$D$71/D74 -> 2.7106479 | H74: =$E$71/E74 -> 12.991229 | I74: EV ~$45bn; equity ~$8bn per case-study site (secondary source – verify); Chapter 11 in 2014. ibinterviewquestions.com; dealroom.net
B75: HCA (Bain / KKR / Merrill) | C75: 2006 | D75: 33 | G75: =$D$71/D75 -> 3.696338 | I75: EV only (dealroom.net). Equity not verified here.
B76: Hilton (Blackstone) | C76: 2007 | D76: 26 | G76: =$D$71/D76 -> 4.6915059 | I76: EV only (dealroom.net). Equity not verified here.
B77: Dell (Silver Lake / Michael Dell) | C77: 2013 | D77: 24.9 | G77: =$D$71/D77 -> 4.8987612 | I77: EV only (dealroom.net). Equity not verified here.
B79: Read-across: Harmony would be ~2.2x the EV of EA (the largest LBO on record) and needs ~2.9x its total equity, or ~1.9x if only the new sponsor cash is compared with EA's $36bn (which itself includes a rollover). The memo's "larger than any LBO in history" is correct. Single-sponsor feasibility: none – needs a club of sovereign/pension co-underwriters.
B81: F. FOUNDER / TENCENT ROLLOVER AND GOVERNANCE FEASIBILITY (sourced from FY2025 Form 20-F ownership table via SEC filing; static)
B82: Holder | C82: % ordinary shares | D82: % total voting power | E82: Note
B83: Martin Lorentzon | C83: 0.093 | D83: 0.405 | E83: 20-F ownership table (SEC): 9.3% of shares, 61.3% of beneficiary certificates
B84: Daniel Ek | C84: 0.139 | D84: 0.288 | E84: Secondary sources quoting the 20-F table (techbloat.com, aifundingtracker.com) – verify against the filing
B85: Tencent entities | C85: 0.081 | E85: Secondary sources: ~8.1% of shares; voting under irrevocable proxy held by Ek's D.G.E. (musicbusinessworldwide.com)
B86: Combined economic stake (Lorentzon + Ek + Tencent) | C86: =SUM(C83:C85) -> 0.313 | D86: =D83+D84 -> 0.693 | E86: Founders alone ≈ 69% of votes: no deal without both. Cannot be overridden by a premium.
B87: Value of that stake at offer (€m) = % × basic shares × offer price € | C87: =C86*'1_Transaction_Summary'!C10*'1_Transaction_Summary'!C8 -> 35948.096
B88: Model rollover assumption (€m) – 1_Transaction_Summary C49 | C88: ='1_Transaction_Summary'!C49 -> 31547.056
B89: Rollover as % of their stake | C89: =C88/C87 -> 0.87757237
B90: Rollover as % of total new equity (91.0bn) | C90: =C88/'5_Returns_Sensitivities'!C14 -> 0.34666727
B91: Cash taken out by founders/Tencent at offer (€m) | C91: =C87-C88 -> 4401.0402
B92: Read-across: the model's 27% rollover (27% of the €116.8bn equity price) ≈ 88% of the three holders' combined economic stake, i.e. they are assumed to roll almost everything at the OFFER price, take a ~€4bn cash-out, and accept a consortium that puts in €59.5bn of new cash. They keep dual-class voting power today; in a TopCo they would demand governance rights (board seats, veto over exit/recap/leverage), which the memo treats as an assumption, not a fact.
B94: G. MINORITY / CONVERTIBLE ALTERNATIVE – model-derived illustration (NOT part of the original model; static inputs + live formulas)
B95: Run basis: premium 0%, entry leverage 0x, MIP 0%, advisory fees 0 → all-equity, buy at unaffected price; Base operating case; exit FY33E. Cash is retained (no buybacks).
B96: Exit EV / EBITDA | C96: 16 | D96: 18 | E96: 22 | F96: 24.3 | G96: 25
B97: Exit equity value – unlevered run (€m, static) | C97: 173423.31 | D97: 190260.16 | E97: 223933.85 | F97: 243296.22 | G97: 249189.11
B98: Fully diluted shares in that run (m, static) | C98: 208.84326 | D98: 208.84326 | E98: 208.84326 | F98: 208.84326 | G98: 208.84326
B99: Exit value per share (€) | C99: =C97/C98 -> 830.39936 | D99: =D97/D98 -> 911.01888 | E99: =E97/E98 -> 1072.2579 | F99: =F97/F98 -> 1164.9704 | G99: =G97/G98 -> 1193.1872
B100: Unlevered buy-and-hold gross IRR – model run (static; uses €7.0bn of company cash at close) | C100: 0.11166722 | D100: 0.12647984 | E100: 0.15301164 | F100: 0.16675261 | G100: 0.17074846
B101: Convertible preferred: payoff per €100 par at exit (€) | C101: =100*MAX((1+$C$103)^7,(1+$C$103)^7*C99/$C$105) -> 242.37017 | D101: =100*MAX((1+$C$103)^7,(1+$C$103)^7*D99/$C$105) -> 265.90074 | E101: =100*MAX((1+$C$103)^7,(1+$C$103)^7*E99/$C$105) -> 312.96187 | F101: =100*MAX((1+$C$103)^7,(1+$C$103)^7*F99/$C$105) -> 340.02202 | G101: =100*MAX((1+$C$103)^7,(1+$C$103)^7*G99/$C$105) -> 348.25772
B102: Convertible preferred: IRR | C102: =(C101/100)^(1/7)-1 -> 0.13481638 | D102: =(D101/100)^(1/7)-1 -> 0.14993746 | E102: =(E101/100)^(1/7)-1 -> 0.17702176 | F102: =(F101/100)^(1/7)-1 -> 0.19104886 | G102: =(G101/100)^(1/7)-1 -> 0.19512792
B103: inputs → PIK coupon | C103: 0.06 | D103: Memo §1 Alternative A
B104: inputs → conversion premium to unaffected | C104: 0.2 | D104: Memo §1 Alternative A
B105: conversion price (€/share) | C105: ='0_Dashboard_Toggles'!C8*(1+C104)*'0_Dashboard_Toggles'!C9 -> 515.16802
B106: unaffected price (€/share) | C106: ='0_Dashboard_Toggles'!C8*'0_Dashboard_Toggles'!C9 -> 429.30668
B107: Exit price needed for a 12% / 14% IRR (€/share) | C107: =$C$105*(1.12/(1+$C$103))^7 -> 757.41516 | D107: =$C$105*(1.14/(1+$C$103))^7 -> 857.31771
B108: as share-price CAGR from unaffected (12% / 14% cases) | C108: =(C107/$C$106)^(1/7)-1 -> 0.084485536 | D108: =(D107/$C$106)^(1/7)-1 -> 0.10385135
B109: Read-across: the convertible's CONTRACTED floor is the 6% PIK, not 12–14%. 12–14% only arrives if the share price compounds at roughly the rates in row 108, which needs the deal team's operating case to be delivered AND an exit multiple of roughly 14x (for 12%) to 17x (for 14%) on row 99 prices. The memo's "12–14% contracted floor" is mislabelled. Row 100 also shows that the unlevered public-equity route earns 11–17% on the same operating case – the control premium and leverage are what destroy the return.

Sheet 7_Assumptions_Register
B1: 7 | Assumptions Register – what the model assumes, where, on what basis, and how much it matters
B2: Basis tags: FILE = figure in the 6-K / 20-F as quoted in the memo; ESTIMATE = deal-team estimate pending 20-F notes; ASSUMPTION = judgement with no evidence in the file. Sensitivities = gross IRR from full model re-runs (06-Oct-2026), one input changed, rest Base (11.1%).
B4: # | C4: Assumption | D4: Model value | E4: Cell(s) | F4: Basis | G4: Evidence in the file / what it implies | H4: Sensitivity (gross IRR, full re-run) | I4: What would change my view / diligence
B5: 1 | C5: Music royalty step-down | D5: 70 bps p.a. (Base) / 110 (Up) / 15 (Down): 57.8% → 52.9% of Premium revenue FY26E→FY33E | E5: Dashboard E29:G29 → 2_Operating_Build row 50 | F5: ASSUMPTION | G5: The memo says it does NOT underwrite a lower headline rate; the step-down is meant to stand in for marketplace netting, superfan add-ons, bundling. None of these is modelled separately and no contract term in the file supports 490 bps cumulative. Q2'26 Premium GM 34.9% (+174 bps Y/Y) is the only observed datapoint. | H5: 0 bps: 7.9% | 15: 8.7% | 40: 9.8% | 70: 11.1% | 110: 12.7%. ≈0.46pp of IRR per 10 bps p.a.; 20% needs 340 bps p.a. (GM 56.5%). | I5: Label contract terms and renewal calendar; MFN clauses; split of GM gain between mix, marketplace and rate (data room, Phase 2).
B6: 2 | C6: Premium ARPU growth | D6: 4.0% p.a. (Base) / 5.0% / 2.5%; blended ARPU €5.06 → €6.00 (≈2.9% CAGR FY27–33 after regional mix) | E6: Dashboard E26:G26; regional spreads 2_Operating_Build D13/D18/D23/D28 | F6: ASSUMPTION | G6: Haircut to the observed +7% Y/Y (Q2'26, per memo). Price-neutral level assumed at 3% (2_Operating_Build E10). Regional mix (Rest of World subs growing 4pp faster) pulls blended growth below the 4% price assumption. | H6: 3%: 10.5% | 4%: 11.1% | 5%: 11.7%. ≈0.6pp per 1pp of ARPU growth (matches memo). | I6: Price-increase vintage cohorts: retention after each hike by region.
B7: 3 | C7: Churn elasticity | D7: 0.05pp extra monthly churn per 1pp of ARPU growth above 3% neutral; base monthly churn 2.0% (1.8% Up / 2.4% Down) | E7: 2_Operating_Build E9, E10, rows 8 and 11; Dashboard E27:G27 | F7: ASSUMPTION | G7: Spotify does not disclose churn; nothing in the file evidences 2.0%. DEFECT FOUND: only the ELASTICITY term drives returns (extra annual churn = (1−(1−c_elastic)^12) − (1−(1−c_base)^12), 0.5pp/yr in Base). The BASE churn level has almost no effect (1%: 11.07%, 2%: 11.12%, 3%: 11.17% – higher churn slightly HELPS), so the Downside's 2.4% churn does not hurt the downside case. | H7: Elasticity 0: 11.6% | 0.05: 11.1% | 0.10: 10.7%. Base churn 1%/2%/3%: 11.1% / 11.1% / 11.2%. | I7: Replace with a cohort-based churn build; until then do not cite the churn assumption as a downside driver.
B8: 4 | C8: SBC → cash compensation | D8: 50% of SBC becomes cash pay post-close (40% Up / 60% Down); not added back to Adj. EBITDA | E8: Dashboard E36:G36 → 2_Operating_Build rows 76–79 | F8: ASSUMPTION | G8: FY26E SBC €321m (1.6% of revenue). FY26E Adj. EBITDA (€3,283m) adds back 100% of SBC (E77 = 0%) while FY27E+ adds back only the non-cash half. Entry multiple is therefore flattered: on the post-close definition FY26E EBITDA ≈ €3,122m and EV/EBITDA ≈ 34.2x, not 32.5x. | H8: 0%: 11.7% | 50%: 11.1% | 100%: 10.5%. ≈0.6pp per 50pts. | I8: MIP terms and retention economics; which SBC is genuinely cash-substituted.
B9: 5 | C9: Negative working capital | D9: −19.7% of revenue held constant (−€3,859m at close → −€6,856m FY33E); releases €367m (FY27E) rising to €455m (FY33E) of cash p.a. | E9: 2_Operating_Build E84 (=E85/E47), F84:L84; 3_Financial_Statements row 32 | F9: FILE level (6-K balances per memo) + ASSUMPTION (constant ratio) | G9: Level is built from receivables less payables, accrued royalties and deferred revenue. Holding the ratio flat means growth keeps releasing cash. It is a liquidity risk as much as a return driver: if the ratio normalised, FY27E would swing by ≈ −€1.0bn (at −15%) or −€2.1bn (at −10%) against €1.5bn minimum cash. | H9: −15%: 11.0% | −10%: 10.8% (small on IRR; large on liquidity). | I9: Monthly liquidity model; royalty payment timing; deferred-revenue seasonality (Phase 2).
B10: 6 | C10: FX (EUR per USD) | D10: 0.8756 EUR per USD (6-K guidance rate, 30-Jun-26) | E10: Dashboard C9 → 1_Transaction_Summary C7:C8 | F10: FILE (rate) / MODEL LIMITATION (use) | G10: DEFECT/LIMITATION: FX enters ONLY by converting the $637.39 offer into euros. All revenue and costs are built in EUR; there is no USD revenue translation, no USD debt tranche and no hedge P&L, so the memo's §7 hedging programme (35% USD TLB, swaps, caps, layered cash-flow hedges) is narrative only and is not in the numbers. North America ≈ 44% of FY27E Premium revenue (€8.5bn of €19.4bn). | H10: 0.80: 12.9% | 0.8756: 11.1% | 0.95: 9.5% (entry-price effect only). | I10: Currency split of revenue, costs and LP base; build USD cash flows before relying on any hedging claim.
B11: 7 | C11: Exit multiple: 22x vs 32.5x entry | D11: 22.0x Base / 25.0x Up / 16.0x Down FY33E Adj. EBITDA; Dashboard C21 overrides | E11: Dashboard E35:G35, C21; 5_Returns_Sensitivities C6 | F11: ASSUMPTION (not derived from comps or DCF in the file) | G11: Of the 10.5-turn gap, 8.2 turns is the 30% premium itself (32.5x entry vs 24.3x unaffected, 1_Transaction_Summary C28 vs C31) and only 2.3 turns is an assumed de-rating from today's market multiple. Cross-check: implied exit EV/FCF 28.5x (5_Returns C9) vs entry EV/LTM FCF 32.8x. Nothing in the file shows why a business growing revenue 7% and EBITDA 11% in FY33E should trade at 22x rather than 18x or 25x. | H11: 16x: 6.8% | 18x: 8.3% | 22x: 11.1% | 25x: 13.0% | 32.5x: 16.9%. 20% needs 39.5x. | I11: Public comps for scaled platforms with 7–8% growth and 24% EBITDA margins; exit-route evidence (re-IPO float, continuation vehicle).
B12: 8 | C12: Ad-Supported revenue growth and margin | D12: 8% p.a. (12% Up / 3% Down); Ad GM 17.7% → 30% FY33E | E12: Dashboard E28:G28, E30:G30; 2_Operating_Build E42 (dead input) | F12: ASSUMPTION | G12: Q2'26 Ad-Supported revenue grew 1% Y/Y (memo). DEFECT FOUND: 2_Operating_Build E42 (ad MAU growth) does not drive revenue – ad revenue is the Dashboard growth rate applied to the prior year; the input only feeds a memo MAU line. | H12: 1%: 10.8% | 3%: 10.9% | 8%: 11.1% | 12%: 11.4%. | I12: Ad-tier pricing and load data.
B13: 9 | C13: Premium subscriber growth | D13: 7.5% FY27E fading linearly to 4.0% FY33E (9.0%→5.0% Up; 5.0%→3.0% Down) | E13: Dashboard E24:G25 → 2_Operating_Build row 6 | F13: ASSUMPTION | G13: Q2'26 Premium subscribers +9% Y/Y (memo). Subscribers 309m (FY26E) → 446m (FY33E). | H13: FY33E fade to 3%: 10.7% | FY27E 5%: 9.8%. | I13: Regional net-add history and saturation in NA/Europe.
B14: 10 | C14: Rollover equity | D14: 27% of the equity purchase price (€31.5bn = 34.7% of new equity) at the offer price | E14: 1_Transaction_Summary F49, C49 | F14: ASSUMPTION | G14: The memo's S&U labels it '27%', which is 27% of the equity PURCHASE PRICE, not of the equity cheque. It is ≈88% of the three large holders' combined economic stake (6_IC_Analysis F). It does not change gross IRR (pooled equity) but decides the €59.5bn sponsor cheque. | H14: n/a for IRR; sponsor cheque falls €1.17bn per 1pt of extra rollover. | I14: Founder/Tencent term sheet; tax on rollover; governance asks.
B15: 11 | C15: Option tranches | D15: 4.6m options in 3 tranches (strikes $150 / $350 / $480); €1.6bn cash-out | E15: 1_Transaction_Summary C12:D14 | F15: ESTIMATE | G15: Calibrated so TSM at the Q2 average price reproduces the 2.40m dilutive options in the 6-K EPS note. Real strike schedule is in the 20-F share-based payment note. | H15: Each €100m of extra cash-out ≈ 0.1% of equity cheque. | I15: 20-F SBC note.
B16: 12 | C16: Minimum cash and sweep | D16: €1.5bn minimum; 100% sweep of excess cash to TLA then TLB; notes not swept | E16: Dashboard C11:C13; 4_Debt_Schedule rows 21–24 | F16: ASSUMPTION | G16: Buffer vs €2.6bn accrued royalties. Annual periodicity ignores intra-year royalty seasonality. | H16: Cash is not a return driver once debt is repaid (see 6_IC_Analysis C). | I16: Monthly liquidity sub-model.
... B21: 17 | C21: Dividend-recap module (new) | D21: Switch OFF; recap year FY31; target 4.0x; 100% excess-cash payout; 7.5% coupon; 2.25% fee | E21: 4_Debt_Schedule C73:C79 | F21: ASSUMPTION | G21: All six inputs are my assumptions, labelled in-cell; coupon and fee copy the entry notes/financing fee. Notes are unswept, interest on opening balance, fees charged to equity (not tax-deducted). | H21: See 6_IC_Analysis C. | I21: Market soundings on a post-FY30 recap.

Sheet 8_Change_Log
B1: 8 | Change Log – before / after
B2: Original: Project_Harmony_Spotify_LBO_Model.xlsx (cached values). Updated: this file, recalculated in full on 05-Oct-2026. Base/Upside/Downside outputs are unchanged to the last digit because every edit is switched off or presentational by default.
B4: 1. OUTPUTS – BEFORE vs AFTER
B5: Output | C5: Original file | D5: Updated file | E5: Δ | F5: Comment
B6: Base – gross IRR | C6: 0.11033814 | D6: 0.11033814 | E6: =D6-C6 -> 0 | F6: Differences are zero to 1e-12: edits are default-off or presentational.
B7: Base – gross MoIC | C7: 2.0805915 | D7: 2.0805915 | E7: =D7-C7 -> 0
B8: Base – net IRR | C8: 0.085902358 | D8: 0.085902358 | E8: =D8-C8 -> 0
B9: Base – net MoIC | C9: 1.7804732 | D9: 1.7804732 | E9: =D9-C9 -> 0
B10: Upside – gross IRR | C10: 0.1759562 | D10: 0.1759562 | E10: =D10-C10 -> 0
B11: Upside – net IRR | C11: 0.14650045 | D11: 0.14650045 | E11: =D11-C11 -> -3.3001379e-14
B12: Downside – gross IRR | C12: -0.0079694228 | D12: -0.0079694228 | E12: =D12-C12 -> 0
B13: Downside – net IRR | C13: -0.024512061 | D13: -0.024512061 | E13: =D13-C13 -> 9.7144515e-17
B14: Base – exit EBITDA FY33E (€m) | C14: 8418.4223 | D14: 8418.4223 | E14: =D14-C14 -> 0
B15: Base – total equity (€m) | C15: 91000.964 | D15: 91000.964 | E15: =D15-C15 -> 0
B16: Base – sponsor equity (€m) | C16: 59453.909 | D16: 59453.909 | E16: =D16-C16 -> 0
B17: Entry EV / FY26E EBITDA | C17: 32.536742 | D17: 32.536742 | E17: =D17-C17 -> 0
B18: Base – FY27E interest cover | C18: 2.9532012 | D18: 2.9532012 | E18: =D18-C18 -> 0
B19: Master audit check | C19: OK | D19: OK
B20: Circularity ON (CircOn=1) gross IRR | C20: n/a – not tested | D20: 0.11069053 | F20: New: converges in ~6 passes, residual now tested (row 60). +0.04pp vs opening-balance basis.
B22: 2. SENSITIVITY TABLES (5_Returns_Sensitivities rows 43–92): closed-form (before) vs full re-run (after)
B23: Table | C23: Cells compared | D23: Max |Δ| | E23: Mean Δ | F23: What changed
B24: Table 1 – gross MoIC (exit × GM) | C24: 35 | D24: 0.0016197923 | E24: 0.0002478447 | F24: Old: GM flexed at exit only (ΔGM × FY33E revenue added to EBITDA and a ramp-weighted amount to cash). New: royalty step-down changed in the model so GM, tax, ATAD, sweep and interest all re-compute. Result: closed form was accurate to ≤0.002x.
B25: Table 2 – net IRR (exit × GM) | C25: 35 | D25: 0.00017689439 | E25: 7.9079905e-06 | F25: As above; max gap 0.02pp.
B26: Table 3 – net IRR (premium × exit) | C26: 35 | D26: 0.00022154589 | E26: 6.0466477e-05 | F26: Old: equity cheque flexed algebraically, debt held. New: premium changed in Dashboard C7 so TSM dilution, fees and S&U re-compute. Max gap 0.02pp.
B27: Table 4 – gross MoIC (entry × exit, hypothetical) | C27: 35 | D27: 7.1054274e-15 | E27: -1.8144216e-15 | F27: Old: algebraic. New: negative premium solved to hit each entry multiple (−23% to −45%, offer $272–$379). Identical to 4dp.
B28: Table 5 – net IRR (entry × exit, hypothetical) | C28: 35 | D28: 2.8338443e-14 | E28: -1.3275095e-15 | F28: As Table 4.
B29: Net effect: no table value moved by more than 0.002x MoIC or 0.02pp IRR. The closed-form engine was sound; what changed is that the grids are now produced by the model itself, show the lever used (royalty bps, premium, offer price) and are labelled static. New Table 6 (leverage × exit) was added.
B31: 3. EDITS MADE TO THE WORKBOOK
B32: Location | C32: Before | D32: After | F32: Why
B33: Dashboard rows 62–71, new C72 | C33: Pasted values presented as a live "scenario snapshot"; label said refresh by macro | D33: Labelled STATIC; grey fill; freshness test in C72 (CURRENT / STALE) | F33: Values were pasted by a macro that cannot run in .xlsx. Verified equal to a full re-run today.
B34: Dashboard B37:C37 | C34: Blank | D34: Shows recap switch state | F34: Visibility of the new module.
B35: 4_Debt_Schedule rows 72–130 | C35: VBA source as plain text (SolveInterestCircularity, RunScenarioSnapshot) | D35: REMOVED; replaced by recap module rows 72–93 and notes rows 95–96 | F35: Inert text; cannot run in .xlsx; untested; fed a hard-coded check.
B36: 4_Debt_Schedule row 60, M60; Dashboard B47 | C36: M60 = hard-coded 0, so D47 always passed | D36: Row 60 residual (reported vs recomputed average-balance interest and interest income); M60 = Σ residual | F36: A check that cannot fail is not a check; now fails until CircOn=1 converges.
B37: 4_Debt_Schedule F56:L56, F59:L59, E61:L61 | C37: Tranche sums | D37: + recap interest / recap notes | F37: Recap module wiring (zero when switch = 0).
B38: 3_Financial_Statements rows 37, 42, 55, 62, 63 | C38: Row 37 and 55 blank | D38: Row 37 = net recap cash effect; row 42 adds it; row 55 = recap notes; row 62 sums 55:61; equity less dividends and recap fees | F38: Keeps balance sheet balanced with recap on (checked on 12 recap cases).
B39: 5_Returns_Sensitivities C15, C17, C18, C20:L20, C21, C28, C31, C32, row 33, C41 | C39: Exit-only proceeds; net IRR = MoIC^(1/7)−1 | D39: Dividend-aware proceeds; interim dividends in row 20; net IRR = IRR of row 33 flows | F39: Identical to the old result when no dividends (checked).
B40: 5_Returns_Sensitivities rows 43–92 | C40: Closed-form formulas (long single-cell expressions) | D40: Static grids from full re-runs, lever shown, hit-colouring | F40: Requested. See section 2.
B41: 5_Returns_Sensitivities rows 94–104 | C41: — | D41: New Table 6 leverage × exit (gross IRR) | F41: Requested leverage test.
B42: New sheets 6, 7, 8 | C42: — | D42: 6_IC_Analysis; 7_Assumptions_Register; 8_Change_Log | F42: Requested deliverables.
B44: 4. FLAGS – issues found in the original model and memo (not silently fixed)
B45: Item | C45: Where | D45: Finding
B46: Memo "what you have to believe" | C46: Memo §8 | D46: Claims GM 44%+, 25x exit and ARPU 5% with no churn penalty reach 20% gross IRR. Full re-run of exactly that bundle gives 17.3% (3.06x). GM 44% + 25x alone: 15.8%.
B47: Convertible "12–14% contracted floor" | C47: Memo §1 Alt. A | D47: Contracted floor is the 6% PIK. 12–14% needs ~8–10% p.a. share-price compounding; see 6_IC_Analysis G.
B48: "Table 1 never reaches 2.0x within 12–18x" | C48: Memo Q11 | D48: False at the 44% GM corner: 18x / 44% = 2.08x (Table 1 H58). True for GM ≤ 42%.
B49: Vacuous convergence check | C49: Dashboard D47 / 4_Debt_Schedule M60 | D49: M60 was a hard-coded 0; the memo's "all eight checks = OK" therefore covered only seven live checks. Fixed.
B50: Base churn level is not a driver | C50: 2_Operating_Build rows 8, 11 | D50: Raising base churn from 2% to 3% slightly raises IRR. Downside "2.4% churn" has no bite; only the elasticity term does.
B51: Dead input | C51: 2_Operating_Build E42 | D51: Ad MAU growth does not feed ad revenue.
B52: FX only at entry | C52: Dashboard C9 | D52: No USD revenue translation or hedge P&L in the model; memo §7 hedging is narrative.
B53: EBITDA definition shift | C53: 2_Operating_Build E77 vs F77 | D53: FY26E EBITDA adds back 100% of SBC, FY27E+ only 50%: like-for-like entry multiple ≈34.2x, not 32.5x.
B54: Net IRR timing | C54: 5_Returns C27, C32 | D54: Fees charged at exit; annual fees lower net IRR by 0.26–0.36pp. RESOLVED in v3 (section 5).
B55: Memo risk-table cases not reproducible | C55: Memo §8 | D55: "+200 bps royalty from FY28E: 9.7%" and "ARPU frozen from FY28E: 7.9%" are not Dashboard inputs; cannot be reproduced from this file. Verified: 18x exit 8.2%, 15x exit 5.8%, EURIBOR +100bps −0.02pp, ARPU 3%/5% 10.5%/11.6%.
B56: Rollover label | C56: Memo §3 S&U | D56: "27%" is of the equity purchase price (€116.8bn), i.e. 34.7% of the equity cheque.
B57: External facts not verified here | C57: Memo Q2, Q6, §7 | D57: Loud & Clear ~$10bn, April share-price move, EC fine on Apple and licensing terms were not checked against sources.
B59: Engine note: re-runs used LibreOffice Calc (not Excel). It reproduced the original Base/Upside/Downside outputs to 1e-12. Excel may differ in the last digits; iterative-calc behaviour with CircOn=1 was verified in LibreOffice only.
B61: 5. v3 CHANGES (06-Oct-2026) – what was fixed, and what moved
B62: Model logic changed in three places (exit bridge, net-return convention, entry-multiple memo). Operating build, purchase price, S&U, debt schedule and tax are untouched. Because the exit bridge changed, every static grid / snapshot / IC value was regenerated by full re-runs of this workbook and re-validated (the harness reproduced every v2 static grid, snapshot, IC and unlevered-run value to within 1e-10 before it was used).
B64: Output | C64: v2 (before) | D64: v3 (after) | E64: Δ | F64: Comment
B65: Base – gross IRR | C65: 0.11033814 | D65: 0.11119784 | E65: =D65-C65 -> 0.00085969645 | F65: Long-term investments (€1.1bn) now added back at exit
B66: Base – gross MoIC | C66: 2.0805915 | D66: 2.0918942 | E66: =D66-C66 -> 0.011302737
B67: Base – net IRR | C67: 0.085902358 | D67: 0.084022948 | E67: =D67-C67 -> -0.0018794109 | F67: Annual fees (−0.26pp) partly offset by exit-bridge fix
B68: Base – net MoIC | C68: 1.7804732 | D68: 1.7895154 | E68: =D68-C68 -> 0.0090421899 | F68: Fees/carry pro-rata, so MoIC moves only with the exit-bridge fix
B69: Upside – gross IRR | C69: 0.1759562 | D69: 0.17656582 | E69: =D69-C69 -> 0.00060962567
B70: Upside – net IRR | C70: 0.14650045 | D70: 0.14341737 | E70: =D70-C70 -> -0.0030830779
B71: Downside – gross IRR | C71: -0.0079694228 | D71: -0.0061381981 | E71: =D71-C71 -> 0.0018312247
B72: Downside – net IRR | C72: -0.024512061 | D72: -0.021424834 | E72: =D72-C72 -> 0.0030872272
B73: Entry EV / FY26E EBITDA | C73: 32.536742 | D73: 32.536742 | E73: =D73-C73 -> 0 | F73: Unchanged; like-for-like memo (34.2x) added in 1_Transaction_Summary C32
B74: Master audit check | C74: OK | D74: OK | F74: All 8 checks = 0
B76: Location | C76: Before | D76: After | F76: Why
B77: 5_Returns_Sensitivities C11, B11 | C77: Exit bridge added cash only | D77: Adds cash AND long-term investments (3_Financial_Statements L50) | F77: Entry EV nets out the €1,118m investments; exit must add them back. Plug in value-creation table (C40) now equals fees exactly (−€860m).
B78: 5_Returns_Sensitivities C39 | C78: Entry net debt ignored LT investments | D78: Entry net debt deducts them (consistent with exit) | F78: Keeps deleveraging bar like-for-like.
B79: 5_Returns_Sensitivities rows 27–33 | C79: Net returns on total equity; fees charged once at exit | D79: Net returns on sponsor cash (D18); fee 1.5% p.a. paid annually in row 33; carry at exit | F79: LP view should exclude founders/Tencent rollover and pay fees as they fall due.
B80: 6_IC_Analysis C53:F65 | C80: Hold-period grid excluded LT investments | D80: Includes them (live formulas) | F80: Consistency with 5_Returns C13; check cell C66 still reads OK.
B81: 1_Transaction_Summary B32:C32 | C81: — | D81: Memo: EV / EBITDA with only non-cash SBC added back (34.2x) | F81: Like-for-like with FY27E+ EBITDA definition.
B82: Dashboard rows 62–71; 5_Returns Tables 1–6; 6_IC A–C, G; 7_Assumptions_Register col H | C82: Static values from v2 model | D82: Static values regenerated from v3 by full re-runs | F82: Static outputs must follow the model. C72 freshness test reads CURRENT.
B83: 9_Interview_Brief | C83: — | D83: New tab | F83: Q&A, key numbers (live links) and known limitations.
B85: Not changed on purpose: interest on opening balances (conservative; +0.04pp on average balances), unswept 7.5% notes and ≈€21bn of exit cash (tested via the recap module), single blended tax rate, FX at entry only, royalty step-down and exit-multiple assumptions. These are disclosed in 7_Assumptions_Register and 9_Interview_Brief.

Sheet 9_Interview_Brief
B1: Project Harmony – Interview brief (Base case, v3)
B2: Numbers in the key-numbers block are live links to the model (green). Answer text quotes the Base case as of 06-Oct-2026; if you change an input, re-read the live numbers.
B4: 1. THE 30-SECOND PITCH
B5: Project Harmony is a take-private LBO of Spotify at a 30% premium ($637 a share), a €106.8bn enterprise value or 32.5x FY26E Adj. EBITDA. It is funded with €19.7bn of debt (6.0x), €31.5bn of founder/Tencent rollover and €59.5bn of sponsor equity. I built a segment-level operating model, a three-tranche debt schedule with a cash sweep, an integrated three-statement model and a returns engine. Base case returns are 11.1% gross / 8.4% net IRR (2.09x / 1.79x), Upside 17.7%, Downside -0.6%. My conclusion is that it does not clear a 20% hurdle at this price, and no realistic lever fixes that. The entry price is the problem, not the operations.
B7: 2. KEY NUMBERS (live)
B8: Offer price (USD / share) | C8: ='1_Transaction_Summary'!C6 -> 637.39
B9: Equity purchase price (€m) | C9: ='1_Transaction_Summary'!C19 -> 116840.95
B10: Enterprise value (€m) | C10: ='1_Transaction_Summary'!C25 -> 106804.95
B11: EV / FY26E Adj. EBITDA | C11: ='1_Transaction_Summary'!C28 -> 32.536742
B12: … like-for-like (post-close SBC definition) | C12: ='1_Transaction_Summary'!C32 -> 34.207302
B13: Total debt at close (€m) | C13: ='1_Transaction_Summary'!C47 -> 19700
B14: Gross leverage at close | C14: ='1_Transaction_Summary'!E47 -> 6.0013495
B15: Sponsor equity (€m) | C15: ='1_Transaction_Summary'!C50 -> 59453.909
B16: Rollover equity (€m) | C16: ='1_Transaction_Summary'!C49 -> 31547.056
B17: Equity as % of capitalisation | C17: ='1_Transaction_Summary'!C54 -> 0.77315394
B18: FY33E Adj. EBITDA (€m) | C18: ='5_Returns_Sensitivities'!C5 -> 8418.4223
B19: Exit multiple | C19: ='5_Returns_Sensitivities'!C6 -> 22
B20: Exit enterprise value (€m) | C20: ='5_Returns_Sensitivities'!C7 -> 185205.29
B21: Gross MoIC | C21: ='5_Returns_Sensitivities'!C17 -> 2.0918942
B22: Gross IRR | C22: ='5_Returns_Sensitivities'!C19 -> 0.11119784
B23: Net MoIC (LP) | C23: ='5_Returns_Sensitivities'!C31 -> 1.7895154
B24: Net IRR (LP) | C24: ='5_Returns_Sensitivities'!C32 -> 0.084022948
B25: Interest cover FY27E (EBITDA / cash interest) | C25: ='4_Debt_Schedule'!F66 -> 2.9532012
B26: Net leverage FY27E | C26: ='4_Debt_Schedule'!F65 -> 4.0351848
B27: Net leverage FY29E | C27: ='4_Debt_Schedule'!H65 -> 1.6179716
B28: Master audit check | C28: ='0_Dashboard_Toggles'!D49 -> OK
B30: 3. QUESTIONS YOU SHOULD EXPECT (and a grounded answer)
B31: Topic | C31: Question | D31: Answer
B32: Why this deal | C32: Why did you pick Spotify and how did you value it? | D32: I used a 30% control premium to the unaffected price ($490.30 → $637.39), converted at 0.8756 EUR/USD, on 209.4m fully diluted shares (205.8m basic + 2.9m from options by treasury-stock method + 0.7m RSUs). That is an equity price of €116.8bn. I then netted €10.5bn of cash and investments and added €470m of leases for an EV of €106.8bn. Unaffected, the stock trades at 24.3x FY26E EBITDA; at the offer it is 32.5x.
B33: Sources & uses | C33: Walk me through sources and uses. | D33: Uses are €116.8bn equity price plus about €0.86bn of advisory fees, financing fees and OID, so €117.7bn. Sources are €19.7bn of debt (TLA €4.0bn, TLB €8.6bn, 7.5% unsecured notes €7.1bn), €7.0bn of Spotify's own balance-sheet cash, €31.5bn of rollover (27% of the equity price) and a €59.5bn sponsor equity plug. Sources equal uses is audit check #3 on the Dashboard.
B34: Leverage | C34: Why only 6x debt and 77% equity? | D34: Scale. At 32.5x entry, 6x EBITDA funds under 20% of the price. More debt is a weak lever: each extra turn adds only about 0.2pp of gross IRR while cutting FY27E interest cover by about 0.4x (3.0x at 6x). The ATAD interest cap (30% of tax-EBITDA, €1,127m) already bites in FY27E, and the TLA springing covenant breaks at 10x (IC tab, section B).
B35: Operating model | C35: How do you forecast revenue and EBITDA? | D35: Premium revenue is built by region (North America, Europe, LatAm, Rest of World) as average subscribers × monthly ARPU × 12. Subscriber growth fades from 7.5% to 4.0%, ARPU grows 4% a year, and a price-elasticity term adds churn when ARPU growth exceeds a 3% neutral level. Ad-supported revenue grows 8%. Total revenue goes from €19.6bn to €34.7bn; Adj. EBITDA from €3.3bn to €8.4bn, a margin of 16.8% → 24.2%, driven mainly by a 70 bps a year royalty-rate step-down (gross margin 33.0% → 39.3%) and operating leverage on R&D, S&M and G&A.
B36: Biggest assumption | C36: Which single assumption matters most, and is it supportable? | D36: The music royalty step-down: 57.8% to 52.9% of Premium revenue, 490 bps cumulative. Each 10 bps a year is worth about 0.45pp of IRR. It is an assumption standing in for marketplace netting, bundling and superfan tiers; no contract term in the file supports it. Q2'26 Premium gross margin of 34.9% is the only observed data point. I would say that up front and point to the sensitivity table showing returns at gross margins from 36% to 44%.
B37: Debt & sweep | C37: How does the cash sweep work? | D37: Each year cash available = opening cash + free cash flow before debt service − TLA mandatory amortisation − €1.5bn minimum cash. A shortfall draws the €500m RCF; a surplus repays the TLA first, then the TLB. The 7.5% notes are not swept. Term loans are fully repaid by FY30, after which cash accumulates (about €20bn at exit). Net leverage falls from 4.0x in FY27E to 1.6x in FY29E.
B38: Circularity | C38: How did you handle the interest circularity? | D38: A toggle on the Dashboard (C10). At 0, interest is computed on opening balances, which is conservative because it ignores the paydown during the year. At 1, it uses average balances with iterative calc on, and gross IRR rises by only 0.04pp. I also replaced a hard-coded convergence check with a real residual (4_Debt_Schedule row 60), so that check can now fail.
B39: Tax | C39: How is tax modelled? | D39: A single 24.94% blended Luxembourg rate. Net interest deductibility is capped at 30% of tax-EBITDA (ATAD), with disallowed interest carried forward: €167m disallowed in FY27E, fully used in FY28E. A Pillar Two 15% top-up is modelled but is zero every year because the cash rate is above 15%.
B40: Returns | C40: Why is the exit multiple 22x when you paid 32.5x? | D40: Of the 10.5-turn gap, 8.2 turns is the control premium itself (24.3x unaffected vs 32.5x) and only 2.3 turns is assumed de-rating. The value bridge shows it clearly: EBITDA growth adds €167bn, multiple compression removes €89bn, deleveraging adds €30bn and fees take €0.9bn, for €108bn of value created on €91bn of equity. Honest caveat: 22x is an assumption, not derived from comps. At 18x the gross IRR is about 8%, at 25x about 13%.
B41: Returns | C41: How do you get from gross to net returns? | D41: Gross is all equity after an 8% management incentive plan on the gain: 11.1% / 2.09x. Net is the LP view on sponsor cash only: a 1.5% annual fee, an 8% preferred return and 20% carry with full catch-up, giving 8.4% / 1.79x. Rollover equity pays no fee or carry. In v3 I fixed fees to be paid annually instead of at exit, which lowers net IRR by about 0.26pp.
B42: Conclusion | C42: What is your recommendation? | D42: Do not proceed at a 30% premium. Gross IRR is 11.1%, the Upside only reaches 17.7%, and the Downside loses money (-0.6%). To reach 20% you would need one of: a 12.6% discount to market ($428 offer), a 39.5x exit, or a 56% gross margin. A dividend recap adds at most about 0.6pp. Alternatives worth exploring are a minority stake or a convertible preferred (6% PIK, 20% conversion premium; IC tab, section G).
... B45: What changed in v3 | C45: What did you improve after review? | D45: I added the long-term investments back at exit (they were netted from EV at entry but dropped at exit), moved net returns to an annual fee on sponsor cash only, added a like-for-like entry multiple (34.2x), and regenerated every static table. Gross IRR moved from 11.03% to 11.12% and net IRR from 8.59% to 8.40%. I also removed untested VBA text and replaced the hard-coded convergence check.
B47: 4. WEAKNESSES – say these before they are asked
B48: • Royalty step-down (490 bps) and 22x exit multiple are assumptions, not derived from contracts or comps. Both are the main swing factors; sensitivity tables show the range.
B49: • Negative working capital (−19.7% of revenue) releases €0.4–0.5bn a year. If the ratio normalised, FY27E would swing by about −€1.0bn against €1.5bn minimum cash. It is a liquidity risk, not only a return driver.
B50: • Churn: base churn level barely moves returns (only the elasticity term does), so the Downside's 2.4% churn has little bite. Known defect, documented in the register.
B51: • FX enters only at entry. Revenue and costs are all in EUR; the hedging programme in the memo is narrative, not in the numbers.
B52: • Interest runs on opening balances by default (conservative). About €20bn of cash sits idle at exit while 7.5% notes stay outstanding; the recap module shows fixing it is worth at most about 0.6pp.
B53: • Sensitivity grids and the scenario snapshot are static outputs of full re-runs. If an input changes they go stale (Dashboard C72 flags this for Base). Use the re-run script to refresh.
B54: • Single blended tax rate; no separate Swedish or US tax groups. Annual periodicity ignores intra-year royalty seasonality.
