Workbook

Sheet 0_Control_Panel
A1: VODAFONE IDEA LIMITED (NSE: IDEA) — RESTRUCTURING MODEL v3: CONTROL PANEL
A2: ₹ crore unless stated | Blue = hardcoded input | Black = formula | Red (#C00000) = deficit / breach warning | Steel grey (#2F4F4F) = section header | Model date: 06-Oct-2026 (v3)
A3: v3 (6-Oct-2026 review of v2): anchors refreshed to quarter ended 30-Jun-2026 (results announced 10-Aug-2026) · TWCF cost base reconciled to 3_Proj · "DoT cash deferral" + NPV + cliff test (2_Cap rows 90-115) · liquidation SBI switch default 0 (4_Liq B8) · conversion-price sensitivity (rows 132-152) · new checks 6_Reconciliations R8-R11 · v2→v3 change log: 6_Reconciliations R7 (row 125+). v2 (4-Oct-2026): bridge switch B23 · Plan D · asset-sale row 89 · Plan C s.14 fix · week-10 sensitivity.
A4: 1. RESTRUCTURING SCENARIO SWITCHER
A5: Active scenario (1 = Plan A, 2 = Plan B, 3 = Plan C, 4 = Plan D) | B5: 1
A6: Active scenario name | B6: =CHOOSE(B5,"Plan A: Govt AGR/Spectrum Equity Swap + Deferral","Plan B: Consensual Out-of-Court Bank Haircut (RBI Prudential Framework ICA)","Plan C: Formal CIRP / Liquidation under IBC s.53","Plan D: Strategic Investor / Asset Sale + 12-month DoT Standstill (no Govt conversion)") -> Plan A: Govt AGR/Spectrum Equity Swap + Deferral
A8: 2. MACRO SWITCHES
A9: 5G CapEx switch (1 = On, 0 = Off) | B9: 1
A10: 5G CapEx intensity multiplier (x) | B10: 1
A11: ARPU expansion case (1 = Low, 2 = Base, 3 = High) | B11: 2
A12: ARPU growth p.a. — Low (tariff repair stalls) | B12: 0.04
A13: ARPU growth p.a. — Base (one industry hike per ~18 months) | B13: 0.07
A14: ARPU growth p.a. — High (management plan) | B14: 0.11
A15: Active ARPU growth p.a. | B15: =CHOOSE($B$11,$B$12,$B$13,$B$14) -> 0.07
A16: 5G ARPU premium uplift p.a. (applies if 5G switch = 1) | B16: 0.005
A17: Subscriber churn-reduction switch (1 = On) | B17: 1
A18: Operating-cost rationalisation switch (1 = On) | B18: 1
A19: Default penalty manual override (1 = force +bps on) | B19: 0
A20: Default penalty interest step-up (bps) | B20: 200
A21: Interest mode — bank & SBI facility (1 = Cash-pay, 2 = PIK) | B21: 1
A22: Interest mode — NCDs (1 = Cash-pay, 2 = PIK) | B22: 1
A23: Valuation bridge treatment (1 = Strict, 2 = Middle, 3 = Conservative) | B23: 2
A24: 3. PUBLIC-DISCLOSURE ANCHORS (balance sheet, debt stack, operating run-rate) | C24: Class | D24: In claims (₹ cr) | E24: v3 check | F24: Source / basis
A25: Deferred spectrum payment obligation (DPO) incl. accrued interest | B25: 130299 | C25: Sourced | D25: =B25 -> 130299 | E25: Updated v3 | F25: VIL Q1 FY27 results (quarter ended 30-Jun-2026; announced 10-Aug-2026): deferred payment obligations towards spectrum ₹1,30,299 cr (Free Press Journal, 10-Aug-2026). v2 used the 31-Mar-2026 figure ₹1,27,360 cr. [v3: verified vs public report; primary filing not opened]
A26: AGR dues — nominal, as finalised by DoT committee | B26: 64046 | C26: Sourced | D26: =B26 -> 64046 | E26: Verified | F26: VIL BSE/NSE filing 30-Apr-2026: AGR finalised at ₹64,046 cr as of 31-Dec-2025 (down ₹23,649 cr from ₹87,695 cr).
A27: AGR DPO — carrying value (discounted, Ind AS) | B27: 25759 | C27: Sourced | E27: Updated v3 | F27: VIL Q1 FY27 results (quarter ended 30-Jun-2026): ₹25,759 cr deferred payment obligation towards AGR (Free Press Journal, 10-Aug-2026); used as the Ind AS carrying value of the back-ended schedule. v2: ₹25,254 cr at 31-Mar-2026. [v3: verified vs public report]
A28: Senior secured bank loans (SBI-led consortium) — outstanding | B28: 211 | C28: Sourced | D28: =B28 -> 211 | E28: Verified | F28: Quarter ended 30-Jun-2026; results announced 10-Aug-2026: bank debt ₹211 cr (₹1,926 cr a year earlier). [v3: verified — public reports show bank debt ₹211 cr vs ₹1,926 cr a year earlier]
A29: Non-convertible debentures (secured) | B29: 3300 | C29: Sourced | D29: =B29 -> 3300 | E29: Partly verified | F29: Quarter ended 30-Jun-2026; results announced 10-Aug-2026 — earnings call: ₹3,300 cr NCDs; net debt ₹3,489 cr. [v3: PARTLY verified — ₹3,300 cr + ₹211 cr ties to reported ₹3,708 cr bank & other debt incl. accrued interest; the ₹3,489 cr net-debt figure was not re-verified]
A30: Cash & bank balances | B30: 6558 | C30: Sourced | E30: Verified | F30: Quarter ended 30-Jun-2026; results announced 10-Aug-2026 — Q1 FY27 results: ₹6,558 cr at 30-Jun-2026 (incl. part warrant proceeds). [v3: verified]
A31: Revenue from operations — Q1 FY27 | B31: 11689 | C31: Sourced | E31: Verified | F31: Quarter ended 30-Jun-2026; results announced 10-Aug-2026 — Q1 FY27 results: ₹11,689 cr (+6.0% YoY). [v3: verified]
A32: EBITDA (Ind AS 116) — Q1 FY27 | B32: 5034 | C32: Sourced | E32: Verified | F32: Quarter ended 30-Jun-2026; results announced 10-Aug-2026 — Q1 FY27 results: ₹5,034 cr, 43.1% margin. [v3: verified]
A33: Cash EBITDA (post lease rentals) — Q1 FY27 | B33: 2475 | C33: Sourced | E33: Verified | F33: Quarter ended 30-Jun-2026; results announced 10-Aug-2026 — earnings call: ₹2,475 cr (+13.5% YoY). [v3: verified]
A34: Capex — Q1 FY27 | B34: 1930 | C34: Sourced | E34: Verified | F34: Quarter ended 30-Jun-2026; results announced 10-Aug-2026 — earnings call: ₹1,930 cr (supply-chain constrained). [v3: verified]
A35: Subscribers (mn) — 30-Jun-2026 | B35: 193.1 | C35: Sourced | E35: Verified | F35: Quarter ended 30-Jun-2026; results announced 10-Aug-2026: 193.1 mn (first positive net add quarter since merger). [v3: verified]
A36: Customer ARPU (₹/month, ex-M2M) | B36: 195 | C36: Sourced | E36: Verified | F36: Quarter ended 30-Jun-2026; results announced 10-Aug-2026: ₹195 (+10.2% YoY). [v3: verified]
A37: Government of India shareholding | B37: 0.4899 | C37: Sourced | E37: Partly verified | F37: Post April-2025 conversion of ₹36,950 cr spectrum dues: 48.99%.
A38: Reference share price (₹) | B38: 12.64 | C38: Sourced | E38: Updated v3 (dated) | F38: NSE close 1-Oct-2026 ₹12.64 (ICICI Direct). 5-Oct-2026 intraday ₹12.63–12.74 (Anand Rathi / HDFC Sky) — close not confirmed. 10-Aug-2026 close ₹12.92 (per v3 brief; NOT independently verified). Not a live feed: UPDATE TO LIVE PRICE before circulation.
A39: Market capitalisation at reference price | B39: 136945.6 | C39: Sourced | E39: Updated v3 (3rd party) | F39: Third-party market cap at ₹12.64 as of 1-Oct-2026: ₹1,36,945.6 cr (ICICI Direct / Tickertape). UNVERIFIED vs exchange data.
A40: Shares outstanding (crore) — derived | B40: =$B$39/$B$38 -> 10834.304 | C40: Sourced | E40: Derived; ties to 3rd party | F40: Calc: market cap / price = ~10,834 cr; ties to third-party share count 10,834.3 cr (Tickertape / Yahoo 108.34bn). v2 derived 10,311 cr from a stale price × market cap pair. Replace with the BSE shareholding-pattern count.
A41: Face value / par (₹) — legal floor on issue price | B41: 10 | C41: Sourced | E41: Verified (face value) | F41: Companies Act 2013 s.53 prohibits issue at a discount to par; 2023 and 2025 Govt conversions were at ₹10.
A42: Spectrum DPO instalment — FY27 | B42: 7076 | C42: Sourced | E42: UNVERIFIED (exact) | F42: FY27 (to Mar-2027) spectrum instalment ₹7,076 cr — exact figure NOT located in public reports (they say ~₹7,000 cr; Business Standard 1-May-2026) → UNVERIFIED. RECONCILIATION: ₹9,259 cr (spectrum + AGR) is disclosed as due by Jun-2027 [per v3 brief; UNVERIFIED — not located]. = FY27 spectrum 7,076 + FY27 AGR 124 + ₹2,059 cr residual falling Apr–Jun 2027 (FY28). Model keeps fiscal-year columns; the residual sits inside FY28 (B43). See 6_Reconciliations R11.
A43: Spectrum DPO instalment — FY28 | B43: 15000 | C43: Sourced | E43: Corroborated (rounded) | F43: Chairman's AGM address (FY26 AGM): ~₹15,000 cr in FY28. [v3: ~₹15,000 cr FY28 corroborated by Business Standard 1-May-2026; rounded — UNVERIFIED as exact]
A44: Spectrum DPO instalment — FY29 | B44: 27000 | C44: Sourced | E44: Corroborated (rounded) | F44: Chairman's AGM address: ~₹27,000 cr in FY29 (₹49,000 cr over FY27–29). [v3: ~₹27,000 cr FY29 corroborated by Business Standard 1-May-2026; rounded — UNVERIFIED as exact]
A45: Spectrum DPO instalment — FY30 (model estimate) | B45: 18000 | C45: Model estimate | E45: UNVERIFIED | F45: MODEL ESTIMATE — UNVERIFIED: not disclosed; DPO runs to FY44. Reconcile to DoT demand schedule.
A46: Spectrum DPO instalment — FY31 (model estimate) | B46: 18000 | C46: Model estimate | E46: UNVERIFIED | F46: MODEL ESTIMATE — UNVERIFIED: not disclosed (as B45).
A47: AGR annual instalment FY27–FY31 | B47: 124 | C47: Sourced | E47: Corroborated to FY31 | F47: Relief package: ₹124 cr p.a. Mar-26 to Mar-31; ₹100 cr p.a. FY32–35; balance six equal instalments FY36–41. [v3: ₹124 cr p.a. to Mar-2031 corroborated (Business Standard 1-May-2026); FY32+ schedule not re-verified]
A48: Management 3-year capex plan | B48: 45000 | C48: Sourced | E48: Verified | F48: Company guidance: ₹45,000 cr over three years.
A49: Minimum operating liquidity threshold (₹40 bn) | B49: 4000 | C49: Model estimate | E49: UNVERIFIED | F49: Treated as MODEL ESTIMATE / UNVERIFIED in v3: v2 called this "board-mandated" but no source was found. ≈ US$500 mn at ₹80/$ reference.
A50: USD/INR (model) | B50: 88 | C50: Model estimate | E50: UNVERIFIED | F50: Model assumption; update to RBI reference rate.
A51: Threshold in US$ mn at model FX | B51: =$B$49*10/$B$50 -> 454.54545 | C51: Calc | E51: Calc | F51: Calc: ₹ cr × 10 / FX
A52: Lease liabilities (Ind AS 116; Indus Towers & other towercos) | B52: 19500 | C52: Model estimate | D52: =B52 -> 19500 | E52: UNVERIFIED | F52: MODEL ESTIMATE — calibrate to Jun-26 limited-review balance sheet.
A53: Trade payables — Indus Towers (current MSA dues) | B53: 2800 | C53: Model estimate | D53: =B53 -> 2800 | E53: UNVERIFIED | F53: MODEL ESTIMATE — legacy >₹10,000 cr overdues largely cleared by 2025 (Indus disclosures).
A54: Trade payables — network vendors (Ericsson, Nokia, Samsung) | B54: 5500 | C54: Model estimate | D54: =B54 -> 5500 | E54: UNVERIFIED | F54: MODEL ESTIMATE — capex creditors on 4G/5G rollout contracts.
A55: Trade payables — other operational creditors | B55: 3200 | C55: Model estimate | D55: =B55 -> 3200 | E55: UNVERIFIED | F55: MODEL ESTIMATE.
A56: Trade payables — total | B56: =$B$53+$B$54+$B$55 -> 11500 | C56: Calc | E56: Calc (sum of 53-55) | F56: Sum.
A57: Other liabilities & provisions (deferred revenue, statutory, employee) | B57: 22000 | C57: Plug | D57: =B57 -> 22000 | E57: UNVERIFIED (plug) | F57: MODEL ESTIMATE — plug so book total liabilities reconcile to ~₹2.1 trn.
A58: Proposed SBI-led consortium capex facility (pro forma limit) | B58: 25000 | C58: Model estimate | E58: UNVERIFIED (press) | F58: Pro forma — under negotiation per press; funded limit assumption.
A59: Trade receivables | B59: 2400 | C59: Model estimate | E59: UNVERIFIED | F59: MODEL ESTIMATE.
A60: Other current assets (GST input credits, deposits, prepaid) | B60: 14500 | C60: Model estimate | E60: UNVERIFIED | F60: MODEL ESTIMATE.
A61: Net PP&E (RAN, transmission, fibre, core) | B61: 38000 | C61: Model estimate | E61: UNVERIFIED | F61: MODEL ESTIMATE.
A62: Spectrum & other intangibles (net) | B62: 95000 | C62: Model estimate | E62: UNVERIFIED | F62: MODEL ESTIMATE.
A63: Right-of-use assets (tower & site leases) | B63: 15000 | C63: Model estimate | E63: UNVERIFIED | F63: MODEL ESTIMATE.
A64: TOTAL LIABILITIES — book (AGR at carrying value) | B64: =$B$25+$B$27+$B$28+$B$29+$B$52+$B$56+$B$57 -> 212569 | C64: Calc | E64: Calc | F64: Reconciles to the ~₹2.1 trn total-liabilities anchor.
A65: TOTAL CLAIMS — nominal (AGR at face, for IBC claims) | B65: =$B$25+$B$26+$B$28+$B$29+$B$52+$B$56+$B$57 -> 250856 | C65: Calc | D65: =SUM(D25:D63) -> 250856 | E65: =IF(ROUND(D65-B65,2)=0,"D65 ties to B65","CHECK: D65 <> B65") -> D65 ties to B65 | F65: Claims basis used in the s.53 waterfall.
A66: =" Claims by class (B65): Sourced "&TEXT('6_Reconciliations'!$C$213,"0.0%")&" · Model estimate "&TEXT('6_Reconciliations'!$C$214,"0.0%")&" · Plug "&TEXT('6_Reconciliations'!$C$215,"0.0%")&" — see 6_Reconciliations R8" -> Claims by class (B65): Sourced 78.9% · Model estimate 12.4% · Plug 8.8% — see 6_Reconciliations R8
A67: 4. SCENARIO PARAMETER MATRIX
A68: Parameter | B68: Plan A | C68: Plan B | D68: Plan C | E68: ACTIVE | F68: Plan D | G68: Mechanics
A69: AGR nominal converted to Govt equity (%) | B69: 0.25 | C69: 0 | D69: 0 | E69: =CHOOSE($B$5,B69,C69,D69,F69) -> 0.25 | F69: 0 | G69: Plan A: 25% of finalised AGR face swapped into equity at ≥ par. | Plan D: no Government conversion — the State is asked only for a standstill.
A70: Spectrum DPO converted to Govt equity (%) | B70: 0.2 | C70: 0 | D70: 0 | E70: =CHOOSE($B$5,B70,C70,D70,F70) -> 0.2 | F70: 0 | G70: Plan A: 20% of spectrum DPO (≈ accrued-interest component) swapped into equity. | Plan D: none.
A71: Conversion price (₹/share) — floored at par | B71: 10 | C71: 10 | D71: 10 | E71: =MAX(CHOOSE($B$5,B71,C71,D71,F71),$B$41) -> 10 | F71: 10 | G71: Floor = ₹10 par (Companies Act s.53). Active cell applies MAX(input, par). | n/a in Plan D (no conversion). | v3: Govt stake at par vs market price → rows 132-145; why ₹10 vs new-money ₹12 and the legal/SEBI flag → rows 147-151.
A72: Spectrum DPO moratorium (years from FY27) | B72: 4 | C72: 0 | D72: 2 | E72: =CHOOSE($B$5,B72,C72,D72,F72) -> 4 | F72: 1 | G72: Plan A: 4-yr moratorium on spectrum instalments (FY27–FY30), mirrors 2021 relief architecture. | Plan D: 12-month DoT standstill/deferral on spectrum instalments (ASSUMPTION — a short standstill is the ask that a strategic would need to see; the length is untested). | v2 FIX Plan C: s.14 moratorium freezes pre-CIRP dues for the 24-month CIRP (row 86); interest accrues (was 0 yrs, cash-paid, which forced ₹49k of DPO instalments into the Plan C liquidity need).
A73: Spectrum DPO interest rate (post-deal) | B73: 0.075 | C73: 0.09 | D73: 0.09 | E73: =CHOOSE($B$5,B73,C73,D73,F73) -> 0.075 | F73: 0.09 | G73: Base ~9.0% blended (MCLR-linked auction terms, MODEL ESTIMATE); Plan A resets to 7.5%. | Plan D: contract-rate ~9% (MODEL ESTIMATE), no reset.
A74: Spectrum interest during moratorium (1 = Cash, 2 = PIK) | B74: 2 | C74: 1 | D74: 2 | E74: =CHOOSE($B$5,B74,C74,D74,F74) -> 2 | F74: 2 | G74: Plan A capitalises interest (PIK) during moratorium. | Plan D: interest accrues (PIK) during the standstill. | v2 FIX Plan C: interest accrues (PIK) under the s.14 stay.
A75: Senior secured bank haircut (%) | B75: 0 | C75: 0.4 | D75: 0 | E75: =CHOOSE($B$5,B75,C75,D75,F75) -> 0 | F75: 0 | G75: Plan B: 40% (range 35–50%) under RBI Prudential Framework (7-Jun-2019) ICA. | Plan D: no haircuts — a strategic investor changes the credit, so lenders and vendors are not asked to take losses.
A76: NCD haircut (%) | B76: 0 | C76: 0.25 | D76: 0 | E76: =CHOOSE($B$5,B76,C76,D76,F76) -> 0 | F76: 0 | G76: Plan B: 25% haircut via debenture-trustee consent (SEBI NCS regulations).
A77: Network vendor & other payables haircut (%) | B77: 0 | C77: 0.15 | D77: 0 | E77: =CHOOSE($B$5,B77,C77,D77,F77) -> 0 | F77: 0 | G77: Plan B: 15% on Ericsson/Nokia/Samsung & other trade; Indus Towers excluded (critical supplier).
A78: 13-week vendor payment deferral (% of capex disbursements) | B78: 0.1 | C78: 0.3 | D78: 0.5 | E78: =CHOOSE($B$5,B78,C78,D78,F78) -> 0.1 | F78: 0.1 | G78: Standstill / s.14 moratorium effect on capex creditors within TWCF window. | Plan D: 10% capex-vendor deferral during the standstill (as Plan A).
A79: 13-week receipts stress (collection haircut) | B79: 0 | C79: 0.03 | D79: 0.15 | E79: =CHOOSE($B$5,B79,C79,D79,F79) -> 0 | F79: 0.03 | G79: Plan C: CIRP announcement triggers MNP port-outs and prepaid recharge decline. | Plan D: 3% collection stress from a visible sale process (ASSUMPTION; same as Plan B).
A80: Funded debt maturity extension (years) | B80: 5 | C80: 5 | D80: 0 | E80: =CHOOSE($B$5,B80,C80,D80,F80) -> 5 | F80: 5 | G80: 5-year extension on bank and NCD maturities. | Plan D: 5-yr extension on bank/NCD (as Plan A/B).
A81: New-money equity (₹ cr) — promoters / QIP | B81: 15000 | C81: 7500 | D81: 0 | E81: =CHOOSE($B$5,B81,C81,D81,F81) -> 15000 | F81: 30000 | G81: Plan A conditional on ABG/Vodafone + QIP; Plan B smaller rights issue. | Plan D: ₹30,000 cr strategic equity — ILLUSTRATIVE (2× Plan A new money, ~22% of reference market cap (B39)). No buyer is identified; the break-even cheque is solved on 6_Reconciliations.
A82: New-money issue price (₹/share) | B82: 12 | C82: 10 | D82: 10 | E82: =MAX(CHOOSE($B$5,B82,C82,D82,F82),$B$41) -> 12 | F82: =$B$38 -> 12.64 | G82: Floored at par. | Plan D: strategic buys at the reference price (B38), i.e. no control premium — ASSUMPTION. | v3: Plan A new money priced at ₹12 is a MODEL ASSUMPTION; see rows 147-151 for why Govt converts at ₹10.
A83: SBI-led facility drawn (% of pro forma limit) | B83: 0.6 | C83: 0.3 | D83: 0 | E83: =CHOOSE($B$5,B83,C83,D83,F83) -> 0.6 | F83: 0.3 | G83: Banks lend only behind Govt relief; Plan C = nil. | Plan D: 30% of the SBI limit drawn (as Plan B).
A84: Contractual default penalty triggered (1/0) | B84: 0 | C84: 1 | D84: 1 | E84: =CHOOSE($B$5,B84,C84,D84,F84) -> 0 | F84: 0 | G84: Standstill / CIRP constitutes an event of default → +200 bps. | Plan D: consensual standstill documented with lender/DoT waiver, so +200 bps not triggered (ASSUMPTION).
A85: Restructuring / CIRP process costs (₹ cr) | B85: 150 | C85: 300 | D85: 2500 | E85: =CHOOSE($B$5,B85,C85,D85,F85) -> 150 | F85: 300 | G85: Advisers, IRP/RP fees, ICA costs; Plan C incl. liquidation costs. | Plan D: advisers + sale process (ASSUMPTION = Plan B level).
A86: Indicative timeline to implementation (months) | B86: 6 | C86: 9 | D86: 24 | E86: =CHOOSE($B$5,B86,C86,D86,F86) -> 6 | F86: 9 | G86: IBC 330-day outer limit routinely exceeded in large CIRPs. | Plan D: sale process + DoT/Cabinet consent ~9 months (ASSUMPTION).
A87: Going concern preserved (1/0) | B87: 1 | C87: 1 | D87: 0 | E87: =CHOOSE($B$5,B87,C87,D87,F87) -> 1 | F87: 1
A88: Govt voting-stake cap (excess via non-voting OCRPS) | B88: 0.49 | C88: 0.49 | D88: 0.49 | E88: =CHOOSE($B$5,B88,C88,D88,F88) -> 0.49 | F88: 0.49 | G88: Govt has signalled it does not want operational control; excess structured as OCRPS.
A89: Asset-sale proceeds (₹ cr; non-dilutive; sold at book, assumed zero EBITDA) | B89: 0 | C89: 0 | D89: 0 | E89: =CHOOSE($B$5,B89,C89,D89,F89) -> 0 | F89: 0 | G89: v2 NEW. No saleable non-spectrum asset is identified in the source files; spectrum cannot be sold without DoT clearance. Kept at 0 — use as a sensitivity (liquidity need falls ₹-for-₹, before any lost EBITDA).
A90: 5. SCENARIO DASHBOARD — LIVE OUTPUTS
A91: Active scenario | B91: =B6 -> Plan A: Govt AGR/Spectrum Equity Swap + Deferral
A92: 13-week minimum closing cash (₹ cr) | B92: ='1_TWCF_13_Week_Liquidity'!$B$75 -> 3000.0279
A93: Weeks below ₹40 bn threshold | B93: ='1_TWCF_13_Week_Liquidity'!$B$77 -> 5
A94: First breach week (0 = none) | B94: ='1_TWCF_13_Week_Liquidity'!$B$78 -> 5
A95: Liquidity status | B95: ='1_TWCF_13_Week_Liquidity'!$B$80 -> BREACH of ₹40 bn floor — liquidity action required | G95: =IF(AND('1_TWCF_13_Week_Liquidity'!$B$24=0,'1_TWCF_13_Week_Liquidity'!$B$29=0),"WHY THIS CAN CONTRADICT THE 5-YEAR VIEW: the 13-week window excludes restructuring relief (1_TWCF B24 = 0, so the week-10 DoT instalment is still paid) and new money (B29 = 0, no SBI draw). Plan A can therefore show a breach here while the 5-year model (rows 101-103) — which assumes the moratorium and ₹30,000 cr new money from FY27 — shows ample cash. They answer different questions: (1) can VIL bridge to the deal unaided; (2) is the post-deal structure fundable.","Window now includes relief and/or new money (1_TWCF B24 / B29 changed): the status-quo explanation in v3 no longer applies — compare like with like.") -> WHY THIS CAN CONTRADICT THE 5-YEAR VIEW: the 13-week window excludes restructuring relief (1_TWCF B24 = 0, so the week-10 DoT instalment is still paid) and new money (B29 = 0, no SBI draw). Plan A can therefore show a breach here while the 5-year model (rows 101-103) — which assumes the moratorium and ₹30,000 cr new money from FY27 — shows ample cash. They answer different questions: (1) can VIL bridge to the deal unaided; (2) is the post-deal structure fundable.
A96: Default penalty active (+200 bps) | B96: ='2_Capital_Structure_Waterfall'!$B$8 -> 0
A97: Statutory dues converted to equity (₹ cr) | B97: ='2_Capital_Structure_Waterfall'!$N$25 -> 42071.3
A98: DoT cash deferral FY27–FY31 vs contract (₹ cr) | B98: =SUM('2_Capital_Structure_Waterfall'!D90:H90) -> 70831 | G98: v3: renamed from "cash relief". This is a DEFERRAL, not forgiveness: the carried balance still accrues interest and falls due FY32+ — see NPV, carry-forward and cliff test below (rows 119-123; 2_Cap rows 91-115).
A99: Government economic stake — post deal | B99: ='2_Capital_Structure_Waterfall'!$B$39 -> 0.5840404
A100: Excess Govt shares to non-voting OCRPS (crore) | B100: ='2_Capital_Structure_Waterfall'!$B$41 -> 1532.0529
A101: FY29 cash EBITDA (₹ cr) | B101: ='3_Restructuring_Projections'!F39 -> 16612.812
...

Sheet 1_TWCF_13_Week_Liquidity
A1: 1. THIRTEEN-WEEK DIRECT CASH FLOW (TWCF) — LIQUIDITY RUNWAY & ₹40 BN ALERT [v3]
A2: ₹ crore | Direct method (receipts vs disbursements) | Weeks commence Monday 05-Oct-2026 (Q3 FY27) | Breach = closing cash < threshold → red flag
A3: ILLUSTRATIVE ASSUMPTIONS (not disclosed figures): B5 opening cash · B23 spectrum instalment amount · C23 instalment week. Everything in rows 75-82 and 85-121 is conditional on them.
A4: DRIVERS | B4: Value | C4: Week # | D4: Basis
A5: Opening cash — week beginning 05-Oct-2026 | B5: 5800 | D5: ILLUSTRATIVE — MODEL ESTIMATE: Jun-26 ₹6,558 cr less ~₹750 cr Q2 net burn. Replace with treasury position.
A6: First week beginning (Monday) | B6: 46300
A7: QoQ revenue growth (Q1 → Q3 FY27) | B7: 0.025 | D7: Q1 FY27 QoQ was +3.2%.
A8: Q3 FY27E revenue (₹ cr) | B8: ='0_Control_Panel'!$B$31*(1+$B$7)^2 -> 12280.756 | D8: Calc: Q1 × (1+QoQ)^2
A9: Q2 FY27E revenue (base for LF/SUC payable) | B9: ='0_Control_Panel'!$B$31*(1+$B$7) -> 11981.225 | D9: Calc: Q1 × (1+QoQ)
A10: Prepaid share of collections | B10: 0.88 | D10: Prepaid collected upfront at recharge.
A11: Collection efficiency (post-scenario stress) | B11: =$B$12*(1-'0_Control_Panel'!$E$79) -> 0.985 | D11: Calc: 98.5% × (1 − scenario receipts stress)
A12: Base collection efficiency | B12: 0.985
A13: Quarterly tower & site rentals (₹ cr) | B13: =('0_Control_Panel'!$B$32-'0_Control_Panel'!$B$33)*(1+$B$7)^2 -> 2688.5494 | D13: Calc: (EBITDA − cash EBITDA) Q1 × (1+QoQ)^2; paid monthly in advance
A14: Indus Towers share of rentals | B14: 0.7 | D14: MODEL ESTIMATE — balance to other towercos (e.g., Data Infrastructure Trust).
A15: Network power & fuel (% revenue) | B15: 0.11 | D15: Diesel/grid electricity pass-through at sites.
A16: Other network O&M (% revenue) | B16: ='3_Restructuring_Projections'!$C$22-$B$15 -> 0.105 | D16: v3: = 3_Proj C22 (21.5% network opex ex-lease, calibrated to the reported 43.1% EBITDA margin) − B15. v2 input was 6.0% (network 17.0%; total cost 52.4% vs 56.9% in 3_Proj). Check rows 124-137.
A17: Licence fee & SUC (% revenue) — paid quarterly | B17: 0.09 | C17: 2 | D17: LF 8% of AGR + SUC; Q2 dues paid within 15 days of quarter end.
A18: Employee costs (% revenue) — paid monthly | B18: 0.046
A19: SG&A, dealer commissions (% revenue) | B19: 0.118
A20: Interconnect, roaming & other (% revenue) | B20: 0.1
A21: Capex cash disbursements in window (₹ cr) | B21: 3800 | D21: Ericsson / Nokia / Samsung milestone payments.
A22: Vendor deferral (% of capex) — active scenario | B22: ='0_Control_Panel'!$E$78 -> 0.1 | D22: From scenario matrix.
A23: Spectrum DPO instalment falling in window (₹ cr) | B23: 2500 | C23: 10 | D23: ILLUSTRATIVE (amount and week) — MODEL TIMING ESTIMATE — NOT a disclosed date; part of FY27 ₹7,076 cr. Amount × week sensitivity in rows 85-117; reconcile to DoT demand notices.
A24: Restructuring relief effective within window? (1 = Yes) | B24: 0 | D24: If 1 and active scenario has a spectrum moratorium, the instalment is deferred.
A25: NCD coupon in window (₹ cr) | B25: ='0_Control_Panel'!$B$29*'2_Capital_Structure_Waterfall'!$E$18/4 -> 88.6875 | C25: 7 | D25: Calc: NCD × coupon / 4
A26: Bank loan amortisation in window (₹ cr) | B26: ='0_Control_Panel'!$B$28*(1-'0_Control_Panel'!$E$75)*IF(OR('0_Control_Panel'!$E$80>0,'0_Control_Panel'!$B$5=3),0,1) -> 0 | C26: 13 | D26: Calc: existing bank debt (bullet in window)
A27: Restructuring professional fees in window (% of process cost) | B27: 0.25
A28: Warrant / equity proceeds (₹ cr) | B28: 1500 | C28: 8 | D28: MODEL ESTIMATE — balance of promoter warrant subscription (₹1,182 cr received Jun-26).
A29: Committed bank facility drawdown (₹ cr) | B29: 0 | C29: 11 | D29: Set > 0 once SBI-led facility documented.
A30: Minimum liquidity threshold (₹ cr) | B30: ='0_Control_Panel'!$B$49 -> 4000 | D30: From Control Panel (₹40 bn).
A31: v3 checks: cost-base reconciliation vs 3_Proj and 13-week cash margin vs reported cash EBITDA margin → rows 123-140.
A33: WEEKLY GRID
A34: Week # | C34: =1 -> 1 | D34: =C34+1 -> 2 | E34: =D34+1 -> 3 | F34: =E34+1 -> 4 | G34: =F34+1 -> 5 | H34: =G34+1 -> 6 | I34: =H34+1 -> 7 | J34: =I34+1 -> 8 | K34: =J34+1 -> 9 | ... O34: =N34+1 -> 13 | P34: 13-wk Total
A35: Week beginning | C35: =$B$6+7*(C34-1) -> 46300 | D35: =$B$6+7*(D34-1) -> 46307 | E35: =$B$6+7*(E34-1) -> 46314 | F35: =$B$6+7*(F34-1) -> 46321 | G35: =$B$6+7*(G34-1) -> 46328 | H35: =$B$6+7*(H34-1) -> 46335 | I35: =$B$6+7*(I34-1) -> 46342 | J35: =$B$6+7*(J34-1) -> 46349 | ... O35: =$B$6+7*(O34-1) -> 46384
A36: First week of month flag (rent / payroll) | C36: =IF(DAY(C35)<=7,1,0) -> 1 | D36: =IF(DAY(D35)<=7,1,0) -> 0 | E36: =IF(DAY(E35)<=7,1,0) -> 0 | F36: =IF(DAY(F35)<=7,1,0) -> 0 | G36: =IF(DAY(G35)<=7,1,0) -> 1 | H36: =IF(DAY(H35)<=7,1,0) -> 0 | I36: =IF(DAY(I35)<=7,1,0) -> 0 | J36: =IF(DAY(J35)<=7,1,0) -> 0 | ... O36: =IF(DAY(O35)<=7,1,0) -> 0
A37: Collections seasonality factor | C37: 1 | D37: 1.02 | E37: 1.04 | F37: 1.03 | G37: 1.01 | H37: 1 | I37: 0.99 | J37: 0.99 | K37: 1 | L37: 1 | M37: 0.98 | N37: 0.97 | O37: 0.97
A39: OPERATING RECEIPTS
A40: Prepaid recharge collections | C40: =$B$8*$B$10*$B$11/13*C$37 -> 818.843 | D40: =$B$8*$B$10*$B$11/13*D$37 -> 835.21986 | E40: =$B$8*$B$10*$B$11/13*E$37 -> 851.59672 | F40: =$B$8*$B$10*$B$11/13*F$37 -> 843.40829 | G40: =$B$8*$B$10*$B$11/13*G$37 -> 827.03143 | H40: =$B$8*$B$10*$B$11/13*H$37 -> 818.843 | I40: =$B$8*$B$10*$B$11/13*I$37 -> 810.65457 | J40: =$B$8*$B$10*$B$11/13*J$37 -> 810.65457 | ... O40: =$B$8*$B$10*$B$11/13*O$37 -> 794.27771 | P40: =SUM(C40:O40) -> 10644.959
A41: Postpaid, enterprise & wholesale collections | C41: =$B$8*(1-$B$10)*$B$11/13 -> 111.66041 | D41: =$B$8*(1-$B$10)*$B$11/13 -> 111.66041 | E41: =$B$8*(1-$B$10)*$B$11/13 -> 111.66041 | F41: =$B$8*(1-$B$10)*$B$11/13 -> 111.66041 | G41: =$B$8*(1-$B$10)*$B$11/13 -> 111.66041 | H41: =$B$8*(1-$B$10)*$B$11/13 -> 111.66041 | I41: =$B$8*(1-$B$10)*$B$11/13 -> 111.66041 | J41: =$B$8*(1-$B$10)*$B$11/13 -> 111.66041 | ... O41: =$B$8*(1-$B$10)*$B$11/13 -> 111.66041 | P41: =SUM(C41:O41) -> 1451.5853
A42: Total operating receipts | C42: =SUM(C40:C41) -> 930.50341 | D42: =SUM(D40:D41) -> 946.88027 | E42: =SUM(E40:E41) -> 963.25713 | F42: =SUM(F40:F41) -> 955.0687 | G42: =SUM(G40:G41) -> 938.69184 | H42: =SUM(H40:H41) -> 930.50341 | I42: =SUM(I40:I41) -> 922.31498 | J42: =SUM(J40:J41) -> 922.31498 | ... O42: =SUM(O40:O41) -> 905.93812 | P42: =SUM(C42:O42) -> 12096.544
A44: OPERATING DISBURSEMENTS
A45: Tower rent — Indus Towers (monthly in advance) | C45: =-IF(C$36=1,$B$13*$B$14/3,0) -> -627.32819 | D45: =-IF(D$36=1,$B$13*$B$14/3,0) -> 0 | E45: =-IF(E$36=1,$B$13*$B$14/3,0) -> 0 | F45: =-IF(F$36=1,$B$13*$B$14/3,0) -> 0 | G45: =-IF(G$36=1,$B$13*$B$14/3,0) -> -627.32819 | H45: =-IF(H$36=1,$B$13*$B$14/3,0) -> 0 | I45: =-IF(I$36=1,$B$13*$B$14/3,0) -> 0 | J45: =-IF(J$36=1,$B$13*$B$14/3,0) -> 0 | ... O45: =-IF(O$36=1,$B$13*$B$14/3,0) -> 0 | P45: =SUM(C45:O45) -> -1881.9846
A46: Tower rent — other towercos | C46: =-IF(C$36=1,$B$13*(1-$B$14)/3,0) -> -268.85494 | D46: =-IF(D$36=1,$B$13*(1-$B$14)/3,0) -> 0 | E46: =-IF(E$36=1,$B$13*(1-$B$14)/3,0) -> 0 | F46: =-IF(F$36=1,$B$13*(1-$B$14)/3,0) -> 0 | G46: =-IF(G$36=1,$B$13*(1-$B$14)/3,0) -> -268.85494 | H46: =-IF(H$36=1,$B$13*(1-$B$14)/3,0) -> 0 | I46: =-IF(I$36=1,$B$13*(1-$B$14)/3,0) -> 0 | J46: =-IF(J$36=1,$B$13*(1-$B$14)/3,0) -> 0 | ... O46: =-IF(O$36=1,$B$13*(1-$B$14)/3,0) -> 0 | P46: =SUM(C46:O46) -> -806.56481
A47: Network power & fuel | C47: =-$B$8*$B$15/13 -> -103.91409 | D47: =-$B$8*$B$15/13 -> -103.91409 | E47: =-$B$8*$B$15/13 -> -103.91409 | F47: =-$B$8*$B$15/13 -> -103.91409 | G47: =-$B$8*$B$15/13 -> -103.91409 | H47: =-$B$8*$B$15/13 -> -103.91409 | I47: =-$B$8*$B$15/13 -> -103.91409 | J47: =-$B$8*$B$15/13 -> -103.91409 | ... O47: =-$B$8*$B$15/13 -> -103.91409 | P47: =SUM(C47:O47) -> -1350.8831
A48: Network O&M & other | C48: =-$B$8*$B$16/13 -> -99.190719 | D48: =-$B$8*$B$16/13 -> -99.190719 | E48: =-$B$8*$B$16/13 -> -99.190719 | F48: =-$B$8*$B$16/13 -> -99.190719 | G48: =-$B$8*$B$16/13 -> -99.190719 | H48: =-$B$8*$B$16/13 -> -99.190719 | I48: =-$B$8*$B$16/13 -> -99.190719 | J48: =-$B$8*$B$16/13 -> -99.190719 | ... O48: =-$B$8*$B$16/13 -> -99.190719 | P48: =SUM(C48:O48) -> -1289.4793
A49: Licence fee & spectrum usage charges (quarterly) | C49: =-IF(C$34=$C$17,$B$9*$B$17,0) -> 0 | D49: =-IF(D$34=$C$17,$B$9*$B$17,0) -> -1078.3102 | E49: =-IF(E$34=$C$17,$B$9*$B$17,0) -> 0 | F49: =-IF(F$34=$C$17,$B$9*$B$17,0) -> 0 | G49: =-IF(G$34=$C$17,$B$9*$B$17,0) -> 0 | H49: =-IF(H$34=$C$17,$B$9*$B$17,0) -> 0 | I49: =-IF(I$34=$C$17,$B$9*$B$17,0) -> 0 | J49: =-IF(J$34=$C$17,$B$9*$B$17,0) -> 0 | ... O49: =-IF(O$34=$C$17,$B$9*$B$17,0) -> 0 | P49: =SUM(C49:O49) -> -1078.3102
A50: Employee costs | C50: =-IF(C$36=1,$B$8*$B$18/3,0) -> -188.30492 | D50: =-IF(D$36=1,$B$8*$B$18/3,0) -> 0 | E50: =-IF(E$36=1,$B$8*$B$18/3,0) -> 0 | F50: =-IF(F$36=1,$B$8*$B$18/3,0) -> 0 | G50: =-IF(G$36=1,$B$8*$B$18/3,0) -> -188.30492 | H50: =-IF(H$36=1,$B$8*$B$18/3,0) -> 0 | I50: =-IF(I$36=1,$B$8*$B$18/3,0) -> 0 | J50: =-IF(J$36=1,$B$8*$B$18/3,0) -> 0 | ... O50: =-IF(O$36=1,$B$8*$B$18/3,0) -> 0 | P50: =SUM(C50:O50) -> -564.91476
A51: SG&A & dealer commissions | C51: =-$B$8*$B$19/13 -> -111.47147 | D51: =-$B$8*$B$19/13 -> -111.47147 | E51: =-$B$8*$B$19/13 -> -111.47147 | F51: =-$B$8*$B$19/13 -> -111.47147 | G51: =-$B$8*$B$19/13 -> -111.47147 | H51: =-$B$8*$B$19/13 -> -111.47147 | I51: =-$B$8*$B$19/13 -> -111.47147 | J51: =-$B$8*$B$19/13 -> -111.47147 | ... O51: =-$B$8*$B$19/13 -> -111.47147 | P51: =SUM(C51:O51) -> -1449.1292
A52: Interconnect, roaming & other | C52: =-$B$8*$B$20/13 -> -94.467351 | D52: =-$B$8*$B$20/13 -> -94.467351 | E52: =-$B$8*$B$20/13 -> -94.467351 | F52: =-$B$8*$B$20/13 -> -94.467351 | G52: =-$B$8*$B$20/13 -> -94.467351 | H52: =-$B$8*$B$20/13 -> -94.467351 | I52: =-$B$8*$B$20/13 -> -94.467351 | J52: =-$B$8*$B$20/13 -> -94.467351 | ... O52: =-$B$8*$B$20/13 -> -94.467351 | P52: =SUM(C52:O52) -> -1228.0756
A53: Total operating disbursements | C53: =SUM(C45:C52) -> -1493.5317 | D53: =SUM(D45:D52) -> -1487.3539 | E53: =SUM(E45:E52) -> -409.04363 | F53: =SUM(F45:F52) -> -409.04363 | G53: =SUM(G45:G52) -> -1493.5317 | H53: =SUM(H45:H52) -> -409.04363 | I53: =SUM(I45:I52) -> -409.04363 | J53: =SUM(J45:J52) -> -409.04363 | ... O53: =SUM(O45:O52) -> -409.04363 | P53: =SUM(C53:O53) -> -9649.3416
A54: NET OPERATING CASH FLOW | C54: =C42+C53 -> -563.02827 | D54: =D42+D53 -> -540.47361 | E54: =E42+E53 -> 554.2135 | F54: =F42+F53 -> 546.02507 | G54: =G42+G53 -> -554.83984 | H54: =H42+H53 -> 521.45978 | I54: =I42+I53 -> 513.27135 | J54: =J42+J53 -> 513.27135 | ... O54: =O42+O53 -> 496.89449 | P54: =SUM(C54:O54) -> 2447.2027
A56: CAPEX, STATUTORY & FINANCING FLOWS
A57: Capex — network vendors (Ericsson / Nokia / Samsung), net of deferral | C57: =-$B$21/13*(1-$B$22) -> -263.07692 | D57: =-$B$21/13*(1-$B$22) -> -263.07692 | E57: =-$B$21/13*(1-$B$22) -> -263.07692 | F57: =-$B$21/13*(1-$B$22) -> -263.07692 | G57: =-$B$21/13*(1-$B$22) -> -263.07692 | H57: =-$B$21/13*(1-$B$22) -> -263.07692 | I57: =-$B$21/13*(1-$B$22) -> -263.07692 | J57: =-$B$21/13*(1-$B$22) -> -263.07692 | ... O57: =-$B$21/13*(1-$B$22) -> -263.07692 | P57: =SUM(C57:O57) -> -3420
A58: Spectrum DPO instalment (principal + interest) — DoT | C58: =-IF(C$34=$C$23,$B$23*(1-$B$24*IF('0_Control_Panel'!$E$72>0,1,0)),0) -> 0 | D58: =-IF(D$34=$C$23,$B$23*(1-$B$24*IF('0_Control_Panel'!$E$72>0,1,0)),0) -> 0 | E58: =-IF(E$34=$C$23,$B$23*(1-$B$24*IF('0_Control_Panel'!$E$72>0,1,0)),0) -> 0 | F58: =-IF(F$34=$C$23,$B$23*(1-$B$24*IF('0_Control_Panel'!$E$72>0,1,0)),0) -> 0 | G58: =-IF(G$34=$C$23,$B$23*(1-$B$24*IF('0_Control_Panel'!$E$72>0,1,0)),0) -> 0 | H58: =-IF(H$34=$C$23,$B$23*(1-$B$24*IF('0_Control_Panel'!$E$72>0,1,0)),0) -> 0 | I58: =-IF(I$34=$C$23,$B$23*(1-$B$24*IF('0_Control_Panel'!$E$72>0,1,0)),0) -> 0 | J58: =-IF(J$34=$C$23,$B$23*(1-$B$24*IF('0_Control_Panel'!$E$72>0,1,0)),0) -> 0 | ... O58: =-IF(O$34=$C$23,$B$23*(1-$B$24*IF('0_Control_Panel'!$E$72>0,1,0)),0) -> 0 | P58: =SUM(C58:O58) -> -2500
A59: NCD coupon | C59: =-IF(C$34=$C$25,$B$25,0) -> 0 | D59: =-IF(D$34=$C$25,$B$25,0) -> 0 | E59: =-IF(E$34=$C$25,$B$25,0) -> 0 | F59: =-IF(F$34=$C$25,$B$25,0) -> 0 | G59: =-IF(G$34=$C$25,$B$25,0) -> 0 | H59: =-IF(H$34=$C$25,$B$25,0) -> 0 | I59: =-IF(I$34=$C$25,$B$25,0) -> -88.6875 | J59: =-IF(J$34=$C$25,$B$25,0) -> 0 | ... O59: =-IF(O$34=$C$25,$B$25,0) -> 0 | P59: =SUM(C59:O59) -> -88.6875
A60: Bank loan amortisation (SBI consortium) | C60: =-IF(C$34=$C$26,$B$26,0) -> 0 | D60: =-IF(D$34=$C$26,$B$26,0) -> 0 | E60: =-IF(E$34=$C$26,$B$26,0) -> 0 | F60: =-IF(F$34=$C$26,$B$26,0) -> 0 | G60: =-IF(G$34=$C$26,$B$26,0) -> 0 | H60: =-IF(H$34=$C$26,$B$26,0) -> 0 | I60: =-IF(I$34=$C$26,$B$26,0) -> 0 | J60: =-IF(J$34=$C$26,$B$26,0) -> 0 | ... O60: =-IF(O$34=$C$26,$B$26,0) -> 0 | P60: =SUM(C60:O60) -> 0
A61: Restructuring / CIRP professional fees | C61: =-'0_Control_Panel'!$E$85*$B$27/13 -> -2.8846154 | D61: =-'0_Control_Panel'!$E$85*$B$27/13 -> -2.8846154 | E61: =-'0_Control_Panel'!$E$85*$B$27/13 -> -2.8846154 | F61: =-'0_Control_Panel'!$E$85*$B$27/13 -> -2.8846154 | G61: =-'0_Control_Panel'!$E$85*$B$27/13 -> -2.8846154 | H61: =-'0_Control_Panel'!$E$85*$B$27/13 -> -2.8846154 | I61: =-'0_Control_Panel'!$E$85*$B$27/13 -> -2.8846154 | J61: =-'0_Control_Panel'!$E$85*$B$27/13 -> -2.8846154 | ... O61: =-'0_Control_Panel'!$E$85*$B$27/13 -> -2.8846154 | P61: =SUM(C61:O61) -> -37.5
A62: Equity / warrant proceeds | C62: =IF(C$34=$C$28,$B$28,0) -> 0 | D62: =IF(D$34=$C$28,$B$28,0) -> 0 | E62: =IF(E$34=$C$28,$B$28,0) -> 0 | F62: =IF(F$34=$C$28,$B$28,0) -> 0 | G62: =IF(G$34=$C$28,$B$28,0) -> 0 | H62: =IF(H$34=$C$28,$B$28,0) -> 0 | I62: =IF(I$34=$C$28,$B$28,0) -> 0 | J62: =IF(J$34=$C$28,$B$28,0) -> 1500 | ... O62: =IF(O$34=$C$28,$B$28,0) -> 0 | P62: =SUM(C62:O62) -> 1500
A63: Committed facility drawdown | C63: =IF(C$34=$C$29,$B$29,0) -> 0 | D63: =IF(D$34=$C$29,$B$29,0) -> 0 | E63: =IF(E$34=$C$29,$B$29,0) -> 0 | F63: =IF(F$34=$C$29,$B$29,0) -> 0 | G63: =IF(G$34=$C$29,$B$29,0) -> 0 | H63: =IF(H$34=$C$29,$B$29,0) -> 0 | I63: =IF(I$34=$C$29,$B$29,0) -> 0 | J63: =IF(J$34=$C$29,$B$29,0) -> 0 | ... O63: =IF(O$34=$C$29,$B$29,0) -> 0 | P63: =SUM(C63:O63) -> 0
A64: NET CASH FLOW | C64: =C54+SUM(C57:C63) -> -828.98981 | D64: =D54+SUM(D57:D63) -> -806.43515 | E64: =E54+SUM(E57:E63) -> 288.25196 | F64: =F54+SUM(F57:F63) -> 280.06353 | G64: =G54+SUM(G57:G63) -> -820.80138 | H64: =H54+SUM(H57:H63) -> 255.49824 | I64: =I54+SUM(I57:I63) -> 158.62231 | J64: =J54+SUM(J57:J63) -> 1747.3098 | ... O64: =O54+SUM(O57:O63) -> 230.93295 | P64: =SUM(C64:O64) -> -2098.9848
A66: LIQUIDITY POSITION & ALERT
A67: Opening cash | C67: =$B$5 -> 5800 | D67: =C68 -> 4971.0102 | E67: =D68 -> 4164.575 | F67: =E68 -> 4452.827 | G67: =F68 -> 4732.8905 | H67: =G68 -> 3912.0892 | I67: =H68 -> 4167.5874 | J67: =I68 -> 4326.2097 | K67: =J68 -> 6073.5195 | ... O67: =N68 -> 3470.0823
A68: Closing cash | C68: =C67+C64 -> 4971.0102 | D68: =D67+D64 -> 4164.575 | E68: =E67+E64 -> 4452.827 | F68: =F67+F64 -> 4732.8905 | G68: =G67+G64 -> 3912.0892 | H68: =H67+H64 -> 4167.5874 | I68: =I67+I64 -> 4326.2097 | J68: =J67+J64 -> 6073.5195 | ... O68: =O67+O64 -> 3701.0152
A69: Minimum liquidity threshold (₹40 bn) | C69: =$B$30 -> 4000 | D69: =$B$30 -> 4000 | E69: =$B$30 -> 4000 | F69: =$B$30 -> 4000 | G69: =$B$30 -> 4000 | H69: =$B$30 -> 4000 | I69: =$B$30 -> 4000 | J69: =$B$30 -> 4000 | ... O69: =$B$30 -> 4000
A70: Headroom / (deficit) vs threshold | C70: =C68-C69 -> 971.01019 | D70: =D68-D69 -> 164.57504 | E70: =E68-E69 -> 452.827 | F70: =F68-F69 -> 732.89053 | G70: =G68-G69 -> -87.910845 | H70: =H68-H69 -> 167.58739 | I70: =I68-I69 -> 326.2097 | J70: =J68-J69 -> 2073.5195 | ... O70: =O68-O69 -> -298.98478
A71: ALERT FLAG | C71: =IF(C68<0,"DEFAULT",IF(C68<C69,"BREACH","OK")) -> OK | D71: =IF(D68<0,"DEFAULT",IF(D68<D69,"BREACH","OK")) -> OK | E71: =IF(E68<0,"DEFAULT",IF(E68<E69,"BREACH","OK")) -> OK | F71: =IF(F68<0,"DEFAULT",IF(F68<F69,"BREACH","OK")) -> OK | G71: =IF(G68<0,"DEFAULT",IF(G68<G69,"BREACH","OK")) -> BREACH | H71: =IF(H68<0,"DEFAULT",IF(H68<H69,"BREACH","OK")) -> OK | I71: =IF(I68<0,"DEFAULT",IF(I68<I69,"BREACH","OK")) -> OK | J71: =IF(J68<0,"DEFAULT",IF(J68<J69,"BREACH","OK")) -> OK | ... O71: =IF(O68<0,"DEFAULT",IF(O68<O69,"BREACH","OK")) -> BREACH
A72: Breach indicator (1/0) | C72: =IF(C71="OK",0,1) -> 0 | D72: =IF(D71="OK",0,1) -> 0 | E72: =IF(E71="OK",0,1) -> 0 | F72: =IF(F71="OK",0,1) -> 0 | G72: =IF(G71="OK",0,1) -> 1 | H72: =IF(H71="OK",0,1) -> 0 | I72: =IF(I71="OK",0,1) -> 0 | J72: =IF(J71="OK",0,1) -> 0 | ... O72: =IF(O71="OK",0,1) -> 1
A74: SUMMARY
A75: Minimum closing cash (13 weeks) | B75: =MIN(C68:O68) -> 3000.0279
A76: Week of minimum | B76: =INDEX(C34:O34,MATCH(B75,C68:O68,0)) -> 10
A77: Number of breach weeks (< threshold) | B77: =COUNTIF(C71:O71,"<>OK") -> 5
A78: First breach week (0 = none) | B78: =IFERROR(MATCH(1,C72:O72,0),0) -> 5
A79: Payment default flag (closing cash < 0) | B79: =IF(MIN(C68:O68)<0,1,0) -> 0
A80: LIQUIDITY STATUS | B80: =IF($B$79=1,"PAYMENT DEFAULT — immediate standstill required",IF($B$77>0,"BREACH of ₹40 bn floor — liquidity action required","WITHIN THRESHOLD")) -> BREACH of ₹40 bn floor — liquidity action required
A81: Cumulative net operating cash flow | B81: =P54 -> 2447.2027
A82: Cumulative net cash flow | B82: =P64 -> -2098.9848
A85: WEEK-10 SPECTRUM INSTALMENT — AMOUNT × TIMING SENSITIVITY (B23:C23 are MODEL ASSUMPTIONS, not a finding)
A86: Closing cash EXCLUDING the modelled instalment (₹ cr) | C86: =C68-SUM($C58:C58) -> 4971.0102 | D86: =D68-SUM($C58:D58) -> 4164.575 | E86: =E68-SUM($C58:E58) -> 4452.827 | F86: =F68-SUM($C58:F58) -> 4732.8905 | G86: =G68-SUM($C58:G58) -> 3912.0892 | H86: =H68-SUM($C58:H58) -> 4167.5874 | I86: =I68-SUM($C58:I58) -> 4326.2097 | J86: =J68-SUM($C58:J58) -> 6073.5195 | ... O86: =O68-SUM($C58:O58) -> 6201.0152
A87: Running minimum, weeks 1..w | C87: =C86 -> 4971.0102 | D87: =MIN(C87,D86) -> 4164.575 | E87: =MIN(D87,E86) -> 4164.575 | F87: =MIN(E87,F86) -> 4164.575 | G87: =MIN(F87,G86) -> 3912.0892 | H87: =MIN(G87,H86) -> 3912.0892 | I87: =MIN(H87,I86) -> 3912.0892 | J87: =MIN(I87,J86) -> 3912.0892 | K87: =MIN(J87,K86) -> 3912.0892 | ... O87: =MIN(N87,O86) -> 3912.0892
A88: Running minimum, weeks w..13 | C88: =MIN(D88,C86) -> 3912.0892 | D88: =MIN(E88,D86) -> 3912.0892 | E88: =MIN(F88,E86) -> 3912.0892 | F88: =MIN(G88,F86) -> 3912.0892 | G88: =MIN(H88,G86) -> 3912.0892 | H88: =MIN(I88,H86) -> 4167.5874 | I88: =MIN(J88,I86) -> 4326.2097 | J88: =MIN(K88,J86) -> 5500.0279 | ... N88: =MIN(O88,N86) -> 5970.0823 | O88: =O86 -> 6201.0152
A90: A. Minimum closing cash (₹ cr) — instalment amount (rows) × week paid (columns). Red = below ₹40 bn floor
A91: Amount ↓ / week paid → | C91: =C34 -> 1 | D91: =D34 -> 2 | E91: =E34 -> 3 | F91: =F34 -> 4 | G91: =G34 -> 5 | H91: =H34 -> 6 | I91: =I34 -> 7 | J91: =J34 -> 8 | ... O91: =O34 -> 13
B92: 0 | C92: =MIN(IF(C$91=1,1E+099,INDEX($C$87:$O$87,MAX(1,C$91-1))),INDEX($C$88:$O$88,C$91)-$B92) -> 3912.0892 | D92: =MIN(IF(D$91=1,1E+099,INDEX($C$87:$O$87,MAX(1,D$91-1))),INDEX($C$88:$O$88,D$91)-$B92) -> 3912.0892 | E92: =MIN(IF(E$91=1,1E+099,INDEX($C$87:$O$87,MAX(1,E$91-1))),INDEX($C$88:$O$88,E$91)-$B92) -> 3912.0892 | F92: =MIN(IF(F$91=1,1E+099,INDEX($C$87:$O$87,MAX(1,F$91-1))),INDEX($C$88:$O$88,F$91)-$B92) -> 3912.0892 | G92: =MIN(IF(G$91=1,1E+099,INDEX($C$87:$O$87,MAX(1,G$91-1))),INDEX($C$88:$O$88,G$91)-$B92) -> 3912.0892 | H92: =MIN(IF(H$91=1,1E+099,INDEX($C$87:$O$87,MAX(1,H$91-1))),INDEX($C$88:$O$88,H$91)-$B92) -> 3912.0892 | I92: =MIN(IF(I$91=1,1E+099,INDEX($C$87:$O$87,MAX(1,I$91-1))),INDEX($C$88:$O$88,I$91)-$B92) -> 3912.0892 | J92: =MIN(IF(J$91=1,1E+099,INDEX($C$87:$O$87,MAX(1,J$91-1))),INDEX($C$88:$O$88,J$91)-$B92) -> 3912.0892 | ... O92: =MIN(IF(O$91=1,1E+099,INDEX($C$87:$O$87,MAX(1,O$91-1))),INDEX($C$88:$O$88,O$91)-$B92) -> 3912.0892
B93: 1000 | C93: =MIN(IF(C$91=1,1E+099,INDEX($C$87:$O$87,MAX(1,C$91-1))),INDEX($C$88:$O$88,C$91)-$B93) -> 2912.0892 | D93: =MIN(IF(D$91=1,1E+099,INDEX($C$87:$O$87,MAX(1,D$91-1))),INDEX($C$88:$O$88,D$91)-$B93) -> 2912.0892 | E93: =MIN(IF(E$91=1,1E+099,INDEX($C$87:$O$87,MAX(1,E$91-1))),INDEX($C$88:$O$88,E$91)-$B93) -> 2912.0892 | F93: =MIN(IF(F$91=1,1E+099,INDEX($C$87:$O$87,MAX(1,F$91-1))),INDEX($C$88:$O$88,F$91)-$B93) -> 2912.0892 | G93: =MIN(IF(G$91=1,1E+099,INDEX($C$87:$O$87,MAX(1,G$91-1))),INDEX($C$88:$O$88,G$91)-$B93) -> 2912.0892 | H93: =MIN(IF(H$91=1,1E+099,INDEX($C$87:$O$87,MAX(1,H$91-1))),INDEX($C$88:$O$88,H$91)-$B93) -> 3167.5874 | I93: =MIN(IF(I$91=1,1E+099,INDEX($C$87:$O$87,MAX(1,I$91-1))),INDEX($C$88:$O$88,I$91)-$B93) -> 3326.2097 | J93: =MIN(IF(J$91=1,1E+099,INDEX($C$87:$O$87,MAX(1,J$91-1))),INDEX($C$88:$O$88,J$91)-$B93) -> 3912.0892 | ... O93: =MIN(IF(O$91=1,1E+099,INDEX($C$87:$O$87,MAX(1,O$91-1))),INDEX($C$88:$O$88,O$91)-$B93) -> 3912.0892
B94: 1500 | C94: =MIN(IF(C$91=1,1E+099,INDEX($C$87:$O$87,MAX(1,C$91-1))),INDEX($C$88:$O$88,C$91)-$B94) -> 2412.0892 | D94: =MIN(IF(D$91=1,1E+099,INDEX($C$87:$O$87,MAX(1,D$91-1))),INDEX($C$88:$O$88,D$91)-$B94) -> 2412.0892 | E94: =MIN(IF(E$91=1,1E+099,INDEX($C$87:$O$87,MAX(1,E$91-1))),INDEX($C$88:$O$88,E$91)-$B94) -> 2412.0892 | F94: =MIN(IF(F$91=1,1E+099,INDEX($C$87:$O$87,MAX(1,F$91-1))),INDEX($C$88:$O$88,F$91)-$B94) -> 2412.0892 | G94: =MIN(IF(G$91=1,1E+099,INDEX($C$87:$O$87,MAX(1,G$91-1))),INDEX($C$88:$O$88,G$91)-$B94) -> 2412.0892 | H94: =MIN(IF(H$91=1,1E+099,INDEX($C$87:$O$87,MAX(1,H$91-1))),INDEX($C$88:$O$88,H$91)-$B94) -> 2667.5874 | I94: =MIN(IF(I$91=1,1E+099,INDEX($C$87:$O$87,MAX(1,I$91-1))),INDEX($C$88:$O$88,I$91)-$B94) -> 2826.2097 | J94: =MIN(IF(J$91=1,1E+099,INDEX($C$87:$O$87,MAX(1,J$91-1))),INDEX($C$88:$O$88,J$91)-$B94) -> 3912.0892 | ... O94: =MIN(IF(O$91=1,1E+099,INDEX($C$87:$O$87,MAX(1,O$91-1))),INDEX($C$88:$O$88,O$91)-$B94) -> 3912.0892
B95: 2000 | C95: =MIN(IF(C$91=1,1E+099,INDEX($C$87:$O$87,MAX(1,C$91-1))),INDEX($C$88:$O$88,C$91)-$B95) -> 1912.0892 | D95: =MIN(IF(D$91=1,1E+099,INDEX($C$87:$O$87,MAX(1,D$91-1))),INDEX($C$88:$O$88,D$91)-$B95) -> 1912.0892 | E95: =MIN(IF(E$91=1,1E+099,INDEX($C$87:$O$87,MAX(1,E$91-1))),INDEX($C$88:$O$88,E$91)-$B95) -> 1912.0892 | F95: =MIN(IF(F$91=1,1E+099,INDEX($C$87:$O$87,MAX(1,F$91-1))),INDEX($C$88:$O$88,F$91)-$B95) -> 1912.0892 | G95: =MIN(IF(G$91=1,1E+099,INDEX($C$87:$O$87,MAX(1,G$91-1))),INDEX($C$88:$O$88,G$91)-$B95) -> 1912.0892 | H95: =MIN(IF(H$91=1,1E+099,INDEX($C$87:$O$87,MAX(1,H$91-1))),INDEX($C$88:$O$88,H$91)-$B95) -> 2167.5874 | I95: =MIN(IF(I$91=1,1E+099,INDEX($C$87:$O$87,MAX(1,I$91-1))),INDEX($C$88:$O$88,I$91)-$B95) -> 2326.2097 | J95: =MIN(IF(J$91=1,1E+099,INDEX($C$87:$O$87,MAX(1,J$91-1))),INDEX($C$88:$O$88,J$91)-$B95) -> 3500.0279 | ... O95: =MIN(IF(O$91=1,1E+099,INDEX($C$87:$O$87,MAX(1,O$91-1))),INDEX($C$88:$O$88,O$91)-$B95) -> 3912.0892
B96: 2500 | C96: =MIN(IF(C$91=1,1E+099,INDEX($C$87:$O$87,MAX(1,C$91-1))),INDEX($C$88:$O$88,C$91)-$B96) -> 1412.0892 | D96: =MIN(IF(D$91=1,1E+099,INDEX($C$87:$O$87,MAX(1,D$91-1))),INDEX($C$88:$O$88,D$91)-$B96) -> 1412.0892 | E96: =MIN(IF(E$91=1,1E+099,INDEX($C$87:$O$87,MAX(1,E$91-1))),INDEX($C$88:$O$88,E$91)-$B96) -> 1412.0892 | F96: =MIN(IF(F$91=1,1E+099,INDEX($C$87:$O$87,MAX(1,F$91-1))),INDEX($C$88:$O$88,F$91)-$B96) -> 1412.0892 | G96: =MIN(IF(G$91=1,1E+099,INDEX($C$87:$O$87,MAX(1,G$91-1))),INDEX($C$88:$O$88,G$91)-$B96) -> 1412.0892 | H96: =MIN(IF(H$91=1,1E+099,INDEX($C$87:$O$87,MAX(1,H$91-1))),INDEX($C$88:$O$88,H$91)-$B96) -> 1667.5874 | I96: =MIN(IF(I$91=1,1E+099,INDEX($C$87:$O$87,MAX(1,I$91-1))),INDEX($C$88:$O$88,I$91)-$B96) -> 1826.2097 | J96: =MIN(IF(J$91=1,1E+099,INDEX($C$87:$O$87,MAX(1,J$91-1))),INDEX($C$88:$O$88,J$91)-$B96) -> 3000.0279 | ... O96: =MIN(IF(O$91=1,1E+099,INDEX($C$87:$O$87,MAX(1,O$91-1))),INDEX($C$88:$O$88,O$91)-$B96) -> 3701.0152
B97: 3000 | C97: =MIN(IF(C$91=1,1E+099,INDEX($C$87:$O$87,MAX(1,C$91-1))),INDEX($C$88:$O$88,C$91)-$B97) -> 912.08915 | D97: =MIN(IF(D$91=1,1E+099,INDEX($C$87:$O$87,MAX(1,D$91-1))),INDEX($C$88:$O$88,D$91)-$B97) -> 912.08915 | E97: =MIN(IF(E$91=1,1E+099,INDEX($C$87:$O$87,MAX(1,E$91-1))),INDEX($C$88:$O$88,E$91)-$B97) -> 912.08915 | F97: =MIN(IF(F$91=1,1E+099,INDEX($C$87:$O$87,MAX(1,F$91-1))),INDEX($C$88:$O$88,F$91)-$B97) -> 912.08915 | G97: =MIN(IF(G$91=1,1E+099,INDEX($C$87:$O$87,MAX(1,G$91-1))),INDEX($C$88:$O$88,G$91)-$B97) -> 912.08915 | H97: =MIN(IF(H$91=1,1E+099,INDEX($C$87:$O$87,MAX(1,H$91-1))),INDEX($C$88:$O$88,H$91)-$B97) -> 1167.5874 | I97: =MIN(IF(I$91=1,1E+099,INDEX($C$87:$O$87,MAX(1,I$91-1))),INDEX($C$88:$O$88,I$91)-$B97) -> 1326.2097 | J97: =MIN(IF(J$91=1,1E+099,INDEX($C$87:$O$87,MAX(1,J$91-1))),INDEX($C$88:$O$88,J$91)-$B97) -> 2500.0279 | ... O97: =MIN(IF(O$91=1,1E+099,INDEX($C$87:$O$87,MAX(1,O$91-1))),INDEX($C$88:$O$88,O$91)-$B97) -> 3201.0152
B98: 3500 | C98: =MIN(IF(C$91=1,1E+099,INDEX($C$87:$O$87,MAX(1,C$91-1))),INDEX($C$88:$O$88,C$91)-$B98) -> 412.08915 | D98: =MIN(IF(D$91=1,1E+099,INDEX($C$87:$O$87,MAX(1,D$91-1))),INDEX($C$88:$O$88,D$91)-$B98) -> 412.08915 | E98: =MIN(IF(E$91=1,1E+099,INDEX($C$87:$O$87,MAX(1,E$91-1))),INDEX($C$88:$O$88,E$91)-$B98) -> 412.08915 | F98: =MIN(IF(F$91=1,1E+099,INDEX($C$87:$O$87,MAX(1,F$91-1))),INDEX($C$88:$O$88,F$91)-$B98) -> 412.08915 | G98: =MIN(IF(G$91=1,1E+099,INDEX($C$87:$O$87,MAX(1,G$91-1))),INDEX($C$88:$O$88,G$91)-$B98) -> 412.08915 | H98: =MIN(IF(H$91=1,1E+099,INDEX($C$87:$O$87,MAX(1,H$91-1))),INDEX($C$88:$O$88,H$91)-$B98) -> 667.58739 | I98: =MIN(IF(I$91=1,1E+099,INDEX($C$87:$O$87,MAX(1,I$91-1))),INDEX($C$88:$O$88,I$91)-$B98) -> 826.2097 | J98: =MIN(IF(J$91=1,1E+099,INDEX($C$87:$O$87,MAX(1,J$91-1))),INDEX($C$88:$O$88,J$91)-$B98) -> 2000.0279 | ... O98: =MIN(IF(O$91=1,1E+099,INDEX($C$87:$O$87,MAX(1,O$91-1))),INDEX($C$88:$O$88,O$91)-$B98) -> 2701.0152
A99: (full FY27 instalment, ₹7,076 cr, paid in one go) | B99: ='0_Control_Panel'!$B$42 -> 7076 | C99: =MIN(IF(C$91=1,1E+099,INDEX($C$87:$O$87,MAX(1,C$91-1))),INDEX($C$88:$O$88,C$91)-$B99) -> -3163.9108 | D99: =MIN(IF(D$91=1,1E+099,INDEX($C$87:$O$87,MAX(1,D$91-1))),INDEX($C$88:$O$88,D$91)-$B99) -> -3163.9108 | E99: =MIN(IF(E$91=1,1E+099,INDEX($C$87:$O$87,MAX(1,E$91-1))),INDEX($C$88:$O$88,E$91)-$B99) -> -3163.9108 | F99: =MIN(IF(F$91=1,1E+099,INDEX($C$87:$O$87,MAX(1,F$91-1))),INDEX($C$88:$O$88,F$91)-$B99) -> -3163.9108 | G99: =MIN(IF(G$91=1,1E+099,INDEX($C$87:$O$87,MAX(1,G$91-1))),INDEX($C$88:$O$88,G$91)-$B99) -> -3163.9108 | H99: =MIN(IF(H$91=1,1E+099,INDEX($C$87:$O$87,MAX(1,H$91-1))),INDEX($C$88:$O$88,H$91)-$B99) -> -2908.4126 | I99: =MIN(IF(I$91=1,1E+099,INDEX($C$87:$O$87,MAX(1,I$91-1))),INDEX($C$88:$O$88,I$91)-$B99) -> -2749.7903 | J99: =MIN(IF(J$91=1,1E+099,INDEX($C$87:$O$87,MAX(1,J$91-1))),INDEX($C$88:$O$88,J$91)-$B99) -> -1575.9721 | ... O99: =MIN(IF(O$91=1,1E+099,INDEX($C$87:$O$87,MAX(1,O$91-1))),INDEX($C$88:$O$88,O$91)-$B99) -> -874.98478
A101: B. Number of weeks below the floor (of 13)
A102: Amount ↓ / week paid → | C102: =C34 -> 1 | D102: =D34 -> 2 | E102: =E34 -> 3 | F102: =F34 -> 4 | G102: =G34 -> 5 | H102: =H34 -> 6 | I102: =I34 -> 7 | J102: =J34 -> 8 | ... O102: =O34 -> 13
B103: =B92 -> 0 | C103: =SUMPRODUCT(--(($C$86:$O$86-$B103*($C$34:$O$34>=C$102))<$B$30)) -> 1 | D103: =SUMPRODUCT(--(($C$86:$O$86-$B103*($C$34:$O$34>=D$102))<$B$30)) -> 1 | E103: =SUMPRODUCT(--(($C$86:$O$86-$B103*($C$34:$O$34>=E$102))<$B$30)) -> 1 | F103: =SUMPRODUCT(--(($C$86:$O$86-$B103*($C$34:$O$34>=F$102))<$B$30)) -> 1 | G103: =SUMPRODUCT(--(($C$86:$O$86-$B103*($C$34:$O$34>=G$102))<$B$30)) -> 1 | H103: =SUMPRODUCT(--(($C$86:$O$86-$B103*($C$34:$O$34>=H$102))<$B$30)) -> 1 | I103: =SUMPRODUCT(--(($C$86:$O$86-$B103*($C$34:$O$34>=I$102))<$B$30)) -> 1 | J103: =SUMPRODUCT(--(($C$86:$O$86-$B103*($C$34:$O$34>=J$102))<$B$30)) -> 1 | ... O103: =SUMPRODUCT(--(($C$86:$O$86-$B103*($C$34:$O$34>=O$102))<$B$30)) -> 1
B104: =B93 -> 1000 | C104: =SUMPRODUCT(--(($C$86:$O$86-$B104*($C$34:$O$34>=C$102))<$B$30)) -> 7 | D104: =SUMPRODUCT(--(($C$86:$O$86-$B104*($C$34:$O$34>=D$102))<$B$30)) -> 6 | E104: =SUMPRODUCT(--(($C$86:$O$86-$B104*($C$34:$O$34>=E$102))<$B$30)) -> 5 | F104: =SUMPRODUCT(--(($C$86:$O$86-$B104*($C$34:$O$34>=F$102))<$B$30)) -> 4 | G104: =SUMPRODUCT(--(($C$86:$O$86-$B104*($C$34:$O$34>=G$102))<$B$30)) -> 3 | H104: =SUMPRODUCT(--(($C$86:$O$86-$B104*($C$34:$O$34>=H$102))<$B$30)) -> 3 | I104: =SUMPRODUCT(--(($C$86:$O$86-$B104*($C$34:$O$34>=I$102))<$B$30)) -> 2 | J104: =SUMPRODUCT(--(($C$86:$O$86-$B104*($C$34:$O$34>=J$102))<$B$30)) -> 1 | ... O104: =SUMPRODUCT(--(($C$86:$O$86-$B104*($C$34:$O$34>=O$102))<$B$30)) -> 1
B105: =B94 -> 1500 | C105: =SUMPRODUCT(--(($C$86:$O$86-$B105*($C$34:$O$34>=C$102))<$B$30)) -> 7 | D105: =SUMPRODUCT(--(($C$86:$O$86-$B105*($C$34:$O$34>=D$102))<$B$30)) -> 6 | E105: =SUMPRODUCT(--(($C$86:$O$86-$B105*($C$34:$O$34>=E$102))<$B$30)) -> 5 | F105: =SUMPRODUCT(--(($C$86:$O$86-$B105*($C$34:$O$34>=F$102))<$B$30)) -> 4 | G105: =SUMPRODUCT(--(($C$86:$O$86-$B105*($C$34:$O$34>=G$102))<$B$30)) -> 3 | H105: =SUMPRODUCT(--(($C$86:$O$86-$B105*($C$34:$O$34>=H$102))<$B$30)) -> 3 | I105: =SUMPRODUCT(--(($C$86:$O$86-$B105*($C$34:$O$34>=I$102))<$B$30)) -> 2 | J105: =SUMPRODUCT(--(($C$86:$O$86-$B105*($C$34:$O$34>=J$102))<$B$30)) -> 1 | ... O105: =SUMPRODUCT(--(($C$86:$O$86-$B105*($C$34:$O$34>=O$102))<$B$30)) -> 1
B106: =B95 -> 2000 | C106: =SUMPRODUCT(--(($C$86:$O$86-$B106*($C$34:$O$34>=C$102))<$B$30)) -> 10 | D106: =SUMPRODUCT(--(($C$86:$O$86-$B106*($C$34:$O$34>=D$102))<$B$30)) -> 9 | E106: =SUMPRODUCT(--(($C$86:$O$86-$B106*($C$34:$O$34>=E$102))<$B$30)) -> 8 | F106: =SUMPRODUCT(--(($C$86:$O$86-$B106*($C$34:$O$34>=F$102))<$B$30)) -> 7 | G106: =SUMPRODUCT(--(($C$86:$O$86-$B106*($C$34:$O$34>=G$102))<$B$30)) -> 6 | H106: =SUMPRODUCT(--(($C$86:$O$86-$B106*($C$34:$O$34>=H$102))<$B$30)) -> 6 | I106: =SUMPRODUCT(--(($C$86:$O$86-$B106*($C$34:$O$34>=I$102))<$B$30)) -> 5 | J106: =SUMPRODUCT(--(($C$86:$O$86-$B106*($C$34:$O$34>=J$102))<$B$30)) -> 4 | ... O106: =SUMPRODUCT(--(($C$86:$O$86-$B106*($C$34:$O$34>=O$102))<$B$30)) -> 1
B107: =B96 -> 2500 | C107: =SUMPRODUCT(--(($C$86:$O$86-$B107*($C$34:$O$34>=C$102))<$B$30)) -> 13 | D107: =SUMPRODUCT(--(($C$86:$O$86-$B107*($C$34:$O$34>=D$102))<$B$30)) -> 12 | E107: =SUMPRODUCT(--(($C$86:$O$86-$B107*($C$34:$O$34>=E$102))<$B$30)) -> 11 | F107: =SUMPRODUCT(--(($C$86:$O$86-$B107*($C$34:$O$34>=F$102))<$B$30)) -> 10 | G107: =SUMPRODUCT(--(($C$86:$O$86-$B107*($C$34:$O$34>=G$102))<$B$30)) -> 9 | H107: =SUMPRODUCT(--(($C$86:$O$86-$B107*($C$34:$O$34>=H$102))<$B$30)) -> 9 | I107: =SUMPRODUCT(--(($C$86:$O$86-$B107*($C$34:$O$34>=I$102))<$B$30)) -> 8 | J107: =SUMPRODUCT(--(($C$86:$O$86-$B107*($C$34:$O$34>=J$102))<$B$30)) -> 7 | ... O107: =SUMPRODUCT(--(($C$86:$O$86-$B107*($C$34:$O$34>=O$102))<$B$30)) -> 2
B108: =B97 -> 3000 | C108: =SUMPRODUCT(--(($C$86:$O$86-$B108*($C$34:$O$34>=C$102))<$B$30)) -> 13 | D108: =SUMPRODUCT(--(($C$86:$O$86-$B108*($C$34:$O$34>=D$102))<$B$30)) -> 12 | E108: =SUMPRODUCT(--(($C$86:$O$86-$B108*($C$34:$O$34>=E$102))<$B$30)) -> 11 | F108: =SUMPRODUCT(--(($C$86:$O$86-$B108*($C$34:$O$34>=F$102))<$B$30)) -> 10 | G108: =SUMPRODUCT(--(($C$86:$O$86-$B108*($C$34:$O$34>=G$102))<$B$30)) -> 9 | H108: =SUMPRODUCT(--(($C$86:$O$86-$B108*($C$34:$O$34>=H$102))<$B$30)) -> 9 | I108: =SUMPRODUCT(--(($C$86:$O$86-$B108*($C$34:$O$34>=I$102))<$B$30)) -> 8 | J108: =SUMPRODUCT(--(($C$86:$O$86-$B108*($C$34:$O$34>=J$102))<$B$30)) -> 7 | ... O108: =SUMPRODUCT(--(($C$86:$O$86-$B108*($C$34:$O$34>=O$102))<$B$30)) -> 2
B109: =B98 -> 3500 | C109: =SUMPRODUCT(--(($C$86:$O$86-$B109*($C$34:$O$34>=C$102))<$B$30)) -> 13 | D109: =SUMPRODUCT(--(($C$86:$O$86-$B109*($C$34:$O$34>=D$102))<$B$30)) -> 12 | E109: =SUMPRODUCT(--(($C$86:$O$86-$B109*($C$34:$O$34>=E$102))<$B$30)) -> 11 | F109: =SUMPRODUCT(--(($C$86:$O$86-$B109*($C$34:$O$34>=F$102))<$B$30)) -> 10 | G109: =SUMPRODUCT(--(($C$86:$O$86-$B109*($C$34:$O$34>=G$102))<$B$30)) -> 9 | H109: =SUMPRODUCT(--(($C$86:$O$86-$B109*($C$34:$O$34>=H$102))<$B$30)) -> 9 | I109: =SUMPRODUCT(--(($C$86:$O$86-$B109*($C$34:$O$34>=I$102))<$B$30)) -> 8 | J109: =SUMPRODUCT(--(($C$86:$O$86-$B109*($C$34:$O$34>=J$102))<$B$30)) -> 7 | ... O109: =SUMPRODUCT(--(($C$86:$O$86-$B109*($C$34:$O$34>=O$102))<$B$30)) -> 2
B110: =B99 -> 7076 | C110: =SUMPRODUCT(--(($C$86:$O$86-$B110*($C$34:$O$34>=C$102))<$B$30)) -> 13 | D110: =SUMPRODUCT(--(($C$86:$O$86-$B110*($C$34:$O$34>=D$102))<$B$30)) -> 12 | E110: =SUMPRODUCT(--(($C$86:$O$86-$B110*($C$34:$O$34>=E$102))<$B$30)) -> 11 | F110: =SUMPRODUCT(--(($C$86:$O$86-$B110*($C$34:$O$34>=F$102))<$B$30)) -> 10 | G110: =SUMPRODUCT(--(($C$86:$O$86-$B110*($C$34:$O$34>=G$102))<$B$30)) -> 9 | H110: =SUMPRODUCT(--(($C$86:$O$86-$B110*($C$34:$O$34>=H$102))<$B$30)) -> 9 | I110: =SUMPRODUCT(--(($C$86:$O$86-$B110*($C$34:$O$34>=I$102))<$B$30)) -> 8 | J110: =SUMPRODUCT(--(($C$86:$O$86-$B110*($C$34:$O$34>=J$102))<$B$30)) -> 7 | ... O110: =SUMPRODUCT(--(($C$86:$O$86-$B110*($C$34:$O$34>=O$102))<$B$30)) -> 2
...

Sheet 2_Capital_Structure_Waterfall
A1: 2. CAPITAL STRUCTURE, RESTRUCTURING MECHANICS & DEBT SCHEDULES
A2: ₹ crore | Pre-restructuring stack → scenario haircuts / equity conversion → post-restructuring stack | Cash-pay vs PIK toggles | +200 bps default penalty trigger
A4: A. DEFAULT PENALTY TRIGGER LOGIC
A5: TWCF payment-default flag (closing cash < 0) | B5: ='1_TWCF_13_Week_Liquidity'!$B$79 -> 0
A6: Scenario contractual default (standstill / CIRP) | B6: ='0_Control_Panel'!$E$84 -> 0
A7: Manual override | B7: ='0_Control_Panel'!$B$19 -> 0
A8: PENALTY ACTIVE (1/0) = MAX(above) | B8: =MAX(B5:B7) -> 0
A9: Penalty applied (decimal) | B9: =B8*'0_Control_Panel'!$B$20/10000 -> 0
A12: B. DEBT STACK — PRE- TO POST-RESTRUCTURING (IBC s.53 classification)
A13: Tranche / creditor | B13: IBC s.53 class | C13: Security / status | D13: Face (₹ cr) | E13: Base rate | F13: Penalty | G13: All-in rate | H13: Mode 1=Cash 2=PIK | I13: Annual interest | J13: Cash interest | K13: PIK accrual | L13: Haircut % | M13: Equity conv % | N13: Converted to equity | O13: Written off | P13: Post-deal balance | Q13: Maturity ext (yrs) | R13: Treatment
A14: Statutory — Spectrum DPO (DoT) | B14: 53(1)(e)/(f) Govt dues | C14: Unsecured statutory | D14: ='0_Control_Panel'!$B$25 -> 130299 | E14: ='0_Control_Panel'!$E$73 -> 0.075 | F14: =$B$9*0 -> 0 | G14: =E14+F14 -> 0.075 | H14: ='0_Control_Panel'!$E$74 -> 2 | I14: =P14*G14 -> 7817.94 | J14: =IF(H14=1,I14,0) -> 0 | K14: =IF(H14=2,I14,0) -> 7817.94 | L14: =0 -> 0 | M14: ='0_Control_Panel'!$E$70 -> 0.2 | N14: =D14*M14 -> 26059.8 | O14: =D14*L14 -> 0 | P14: =D14-N14-O14 -> 104239.2 | Q14: =0 -> 0 | R14: Plan A: equity swap + 4-yr moratorium + rate reset
A15: Statutory — AGR dues (nominal, DoT) | B15: 53(1)(e)/(f) Govt dues | C15: Unsecured statutory | D15: ='0_Control_Panel'!$B$26 -> 64046 | E15: 0 | F15: =$B$9*0 -> 0 | G15: =E15+F15 -> 0 | H15: 1 | I15: =P15*G15 -> 0 | J15: =IF(H15=1,I15,0) -> 0 | K15: =IF(H15=2,I15,0) -> 0 | L15: =0 -> 0 | M15: ='0_Control_Panel'!$E$69 -> 0.25 | N15: =D15*M15 -> 16011.5 | O15: =D15*L15 -> 0 | P15: =D15-N15-O15 -> 48034.5 | Q15: =0 -> 0 | R15: Interest-free staggered FY27–FY41; Plan A partial swap
A16: Senior secured bank loans — SBI consortium (existing) | B16: 53(1)(b) Secured FC | C16: First charge, pari passu | D16: ='0_Control_Panel'!$B$28 -> 211 | E16: 0.105 | F16: =$B$9*1 -> 0 | G16: =E16+F16 -> 0.105 | H16: ='0_Control_Panel'!$B$21 -> 1 | I16: =P16*G16 -> 22.155 | J16: =IF(H16=1,I16,0) -> 22.155 | K16: =IF(H16=2,I16,0) -> 0 | L16: ='0_Control_Panel'!$E$75 -> 0 | M16: =0 -> 0 | N16: =D16*M16 -> 0 | O16: =D16*L16 -> 0 | P16: =D16-N16-O16 -> 211 | Q16: ='0_Control_Panel'!$E$80 -> 5 | R16: Plan B haircut 35–50%; +5-yr extension
A17: SBI-led capex facility (pro forma new money, drawn) | B17: 53(1)(b) Secured FC | C17: Pari passu first charge | D17: ='0_Control_Panel'!$B$58*'0_Control_Panel'!$E$83 -> 15000 | E17: 0.1025 | F17: =$B$9*1 -> 0 | G17: =E17+F17 -> 0.1025 | H17: ='0_Control_Panel'!$B$21 -> 1 | I17: =P17*G17 -> 1537.5 | J17: =IF(H17=1,I17,0) -> 1537.5 | K17: =IF(H17=2,I17,0) -> 0 | L17: =0 -> 0 | M17: =0 -> 0 | N17: =D17*M17 -> 0 | O17: =D17*L17 -> 0 | P17: =D17-N17-O17 -> 15000 | Q17: ='0_Control_Panel'!$E$80 -> 5 | R17: New money; drawn FY27; amortises from FY29
A18: Non-convertible debentures (secured) | B18: 53(1)(b) Secured FC | C18: Secured, debenture trustee | D18: ='0_Control_Panel'!$B$29 -> 3300 | E18: 0.1075 | F18: =$B$9*1 -> 0 | G18: =E18+F18 -> 0.1075 | H18: ='0_Control_Panel'!$B$22 -> 1 | I18: =P18*G18 -> 354.75 | J18: =IF(H18=1,I18,0) -> 354.75 | K18: =IF(H18=2,I18,0) -> 0 | L18: ='0_Control_Panel'!$E$76 -> 0 | M18: =0 -> 0 | N18: =D18*M18 -> 0 | O18: =D18*L18 -> 0 | P18: =D18-N18-O18 -> 3300 | Q18: ='0_Control_Panel'!$E$80 -> 5 | R18: Bullet FY29; Plan B 25% haircut
A19: Lease liabilities — Indus Towers & other towercos | B19: 53(1)(f) Operational | C19: Unsecured; Indus security pkg | D19: ='0_Control_Panel'!$B$52 -> 19500 | E19: 0.095 | F19: =$B$9*0 -> 0 | G19: =E19+F19 -> 0.095 | H19: 1 | I19: =P19*G19 -> 1852.5 | J19: =IF(H19=1,I19,0) -> 1852.5 | K19: =IF(H19=2,I19,0) -> 0 | L19: =0 -> 0 | M19: =0 -> 0 | N19: =D19*M19 -> 0 | O19: =D19*L19 -> 0 | P19: =D19-N19-O19 -> 19500 | Q19: =0 -> 0 | R19: Ind AS 116; reinstated (critical supplier)
A20: Trade payables — Indus Towers (MSA) | B20: 53(1)(f) Operational | C20: Unsecured | D20: ='0_Control_Panel'!$B$53 -> 2800 | E20: 0 | F20: =$B$9*0 -> 0 | G20: =E20+F20 -> 0 | H20: 1 | I20: =P20*G20 -> 0 | J20: =IF(H20=1,I20,0) -> 0 | K20: =IF(H20=2,I20,0) -> 0 | L20: =0 -> 0 | M20: =0 -> 0 | N20: =D20*M20 -> 0 | O20: =D20*L20 -> 0 | P20: =D20-N20-O20 -> 2800 | Q20: =0 -> 0 | R20: Paid in full — critical vendor
A21: Trade payables — Ericsson / Nokia / Samsung | B21: 53(1)(f) Operational | C21: Unsecured | D21: ='0_Control_Panel'!$B$54 -> 5500 | E21: 0 | F21: =$B$9*0 -> 0 | G21: =E21+F21 -> 0 | H21: 1 | I21: =P21*G21 -> 0 | J21: =IF(H21=1,I21,0) -> 0 | K21: =IF(H21=2,I21,0) -> 0 | L21: ='0_Control_Panel'!$E$77 -> 0 | M21: =0 -> 0 | N21: =D21*M21 -> 0 | O21: =D21*L21 -> 0 | P21: =D21-N21-O21 -> 5500 | Q21: =0 -> 0 | R21: Plan B 15% haircut / deferral
A22: Trade payables — other operational creditors | B22: 53(1)(f) Operational | C22: Unsecured | D22: ='0_Control_Panel'!$B$55 -> 3200 | E22: 0 | F22: =$B$9*0 -> 0 | G22: =E22+F22 -> 0 | H22: 1 | I22: =P22*G22 -> 0 | J22: =IF(H22=1,I22,0) -> 0 | K22: =IF(H22=2,I22,0) -> 0 | L22: ='0_Control_Panel'!$E$77 -> 0 | M22: =0 -> 0 | N22: =D22*M22 -> 0 | O22: =D22*L22 -> 0 | P22: =D22-N22-O22 -> 3200 | Q22: =0 -> 0 | R22: Plan B 15% haircut
A23: Other liabilities & provisions | B23: 53(1)(f) Remaining | C23: Unsecured | D23: ='0_Control_Panel'!$B$57 -> 22000 | E23: 0 | F23: =$B$9*0 -> 0 | G23: =E23+F23 -> 0 | H23: 1 | I23: =P23*G23 -> 0 | J23: =IF(H23=1,I23,0) -> 0 | K23: =IF(H23=2,I23,0) -> 0 | L23: =0 -> 0 | M23: =0 -> 0 | N23: =D23*M23 -> 0 | O23: =D23*L23 -> 0 | P23: =D23-N23-O23 -> 22000 | Q23: =0 -> 0 | R23: Reinstated
A24: TOTAL CLAIMS (AGR at nominal) | D24: =SUM(D14:D23) -> 265856 | I24: =SUM(I14:I23) -> 11584.845 | J24: =SUM(J14:J23) -> 3766.905 | K24: =SUM(K14:K23) -> 7817.94 | N24: =SUM(N14:N23) -> 42071.3 | O24: =SUM(O14:O23) -> 0 | P24: =SUM(P14:P23) -> 223784.7
A25: of which statutory Government dues | D25: =D14+D15 -> 194345 | N25: =N14+N15 -> 42071.3 | O25: =O14+O15 -> 0 | P25: =P14+P15 -> 152273.7
A26: of which funded financial debt (bank + SBI + NCD) | D26: =D16+D17+D18 -> 18511 | N26: =N16+N17+N18 -> 0 | O26: =O16+O17+O18 -> 0 | P26: =P16+P17+P18 -> 18511
A27: of which operational creditors (lease + trade + other) | D27: =D19+D20+D21+D22+D23 -> 53000 | N27: =N19+N20+N21+N22+N23 -> 0 | O27: =O19+O20+O21+O22+O23 -> 0 | P27: =P19+P20+P21+P22+P23 -> 53000
A28: Statutory dues as % of total claims | D28: =D25/D24 -> 0.73101604 | P28: =P25/P24 -> 0.68044732
A29: Haircut gain recognised (bank + NCD + vendors) — P&L exceptional | O29: =O16+O18+O21+O22 -> 0
A30: Plan B bank haircut quantum vs total claims (materiality test) | O30: =IFERROR(O16/D24,0) -> 0
A32: C. PRO FORMA OWNERSHIP & DILUTION | B32: Crore shares | C32: % pre | D32: % post
A33: Shares outstanding — pre-deal | B33: ='0_Control_Panel'!$B$40 -> 10834.304
A34: Government of India — existing | B34: =B33*'0_Control_Panel'!$B$37 -> 5307.7254 | C34: =B34/B33 -> 0.4899 | D34: =(B34+B36)/B38 -> 0.5840404
A35: Promoters (ABG / Vodafone) & public — existing | B35: =B33-B34 -> 5526.5784 | C35: =B35/B33 -> 0.5101 | D35: =B35/B38 -> 0.33923217
A36: New shares — statutory dues conversion (to Govt) | B36: =(N14+N15)/'0_Control_Panel'!$E$71 -> 4207.13
A37: New shares — new-money equity (promoters / QIP) | B37: ='0_Control_Panel'!$E$81/'0_Control_Panel'!$E$82 -> 1250 | D37: =B37/B38 -> 0.076727439
A38: Shares outstanding — post-deal (fully diluted) | B38: =B33+B36+B37 -> 16291.434
A39: Government economic stake — post | B39: =(B34+B36)/B38 -> 0.5840404
A40: Government voting-stake cap | B40: ='0_Control_Panel'!$E$88 -> 0.49
A41: Excess Govt shares to be issued as non-voting OCRPS (crore) | B41: =MAX(0,(B34+B36)-B40*B38) -> 1532.0529
A42: Dilution to existing non-Govt holders (%) | B42: =1-(B35/B38)/(B35/B33) -> 0.33496929
A44: D. ANNUAL DEBT SCHEDULES (feed 3_Restructuring_Projections)
C45: Pre-deal | D45: FY27E | E45: FY28E | F45: FY29E | G45: FY30E | H45: FY31E
A46: Year index | C46: 0 | D46: =C46+1 -> 1 | E46: =D46+1 -> 2 | F46: =E46+1 -> 3 | G46: =F46+1 -> 4 | H46: =G46+1 -> 5
A48: D1. Spectrum DPO — DoT (moratorium / Cash-vs-PIK logic)
A49: Contractual instalment (pre-deal schedule) | D49: ='0_Control_Panel'!$B$42 -> 7076 | E49: ='0_Control_Panel'!$B$43 -> 15000 | F49: ='0_Control_Panel'!$B$44 -> 27000 | G49: ='0_Control_Panel'!$B$45 -> 18000 | H49: ='0_Control_Panel'!$B$46 -> 18000
A50: Opening balance (post-conversion) | C50: =D14 -> 130299 | D50: =$P$14 -> 104239.2 | E50: =D54 -> 112057.14 | F50: =E54 -> 120461.43 | G50: =F54 -> 129496.03 | H50: =G54 -> 139208.23
A51: Interest expense (opening × post-deal rate) | D51: =D50*$G$14 -> 7817.94 | E51: =E50*$G$14 -> 8404.2855 | F51: =F50*$G$14 -> 9034.6069 | G51: =G50*$G$14 -> 9712.2024 | H51: =H50*$G$14 -> 10440.618
A52: Cash instalment paid | D52: =IF(D$46<='0_Control_Panel'!$E$72,IF($H$14=1,D51,0),D49*(1-'0_Control_Panel'!$E$70)) -> 0 | E52: =IF(E$46<='0_Control_Panel'!$E$72,IF($H$14=1,E51,0),E49*(1-'0_Control_Panel'!$E$70)) -> 0 | F52: =IF(F$46<='0_Control_Panel'!$E$72,IF($H$14=1,F51,0),F49*(1-'0_Control_Panel'!$E$70)) -> 0 | G52: =IF(G$46<='0_Control_Panel'!$E$72,IF($H$14=1,G51,0),G49*(1-'0_Control_Panel'!$E$70)) -> 0 | H52: =IF(H$46<='0_Control_Panel'!$E$72,IF($H$14=1,H51,0),H49*(1-'0_Control_Panel'!$E$70)) -> 14400
A53: of which interest capitalised (PIK) | D53: =MAX(0,D51-D52) -> 7817.94 | E53: =MAX(0,E51-E52) -> 8404.2855 | F53: =MAX(0,F51-F52) -> 9034.6069 | G53: =MAX(0,G51-G52) -> 9712.2024 | H53: =MAX(0,H51-H52) -> 0
A54: Closing balance | C54: =D14 -> 130299 | D54: =D50+D51-D52 -> 112057.14 | E54: =E50+E51-E52 -> 120461.43 | F54: =F50+F51-F52 -> 129496.03 | G54: =G50+G51-G52 -> 139208.23 | H54: =H50+H51-H52 -> 135248.85
A56: D2. AGR dues — book (carrying value accretes toward nominal)
A57: Opening carrying value (post-conversion) | C57: ='0_Control_Panel'!$B$27 -> 25759 | D57: =$C57*(1-$M$15) -> 19319.25 | E57: =D60 -> 20482.001 | F57: =E60 -> 21720.331 | G57: =F60 -> 23039.153 | H57: =G60 -> 24443.698
A58: Accretion (non-cash unwind of discount) | D58: =D57*$B$64 -> 1255.7513 | E58: =E57*$B$64 -> 1331.3301 | F58: =F57*$B$64 -> 1411.8215 | G58: =G57*$B$64 -> 1497.5449 | H58: =H57*$B$64 -> 1588.8404
A59: Cash instalment paid | D59: ='0_Control_Panel'!$B$47*(1-$M$15) -> 93 | E59: ='0_Control_Panel'!$B$47*(1-$M$15) -> 93 | F59: ='0_Control_Panel'!$B$47*(1-$M$15) -> 93 | G59: ='0_Control_Panel'!$B$47*(1-$M$15) -> 93 | H59: ='0_Control_Panel'!$B$47*(1-$M$15) -> 93
A60: Closing carrying value | C60: ='0_Control_Panel'!$B$27 -> 25759 | D60: =D57+D58-D59 -> 20482.001 | E60: =E57+E58-E59 -> 21720.331 | F60: =F57+F58-F59 -> 23039.153 | G60: =G57+G58-G59 -> 24443.698 | H60: =H57+H58-H59 -> 25939.538
A61: Book value derecognised on conversion (to equity) | D61: =$C57*$M$15 -> 6439.75 | E61: =0 -> 0 | F61: =0 -> 0 | G61: =0 -> 0 | H61: =0 -> 0
A62: Nominal claim outstanding (for IBC claims) | C62: ='0_Control_Panel'!$B$26 -> 64046 | D62: =$P$15-'0_Control_Panel'!$B$47*(1-$M$15) -> 47941.5 | E62: =D62-E59 -> 47848.5 | F62: =E62-F59 -> 47755.5 | G62: =F62-G59 -> 47662.5 | H62: =G62-H59 -> 47569.5
A64: AGR accretion rate (implied discount rate on back-ended schedule) | B64: 0.065
A66: D3. Senior secured bank loans — SBI consortium (existing)
A67: Opening balance (post-haircut) | C67: =D16 -> 211 | D67: =$P$16 -> 211 | E67: =D71 -> 175.83333 | F67: =E71 -> 140.66667 | G67: =F71 -> 105.5 | H67: =G71 -> 70.333333
A68: Interest (opening × all-in rate incl. penalty) | D68: =D67*$G$16 -> 22.155 | E68: =E67*$G$16 -> 18.4625 | F68: =F67*$G$16 -> 14.77 | G68: =G67*$G$16 -> 11.0775 | H68: =H67*$G$16 -> 7.385
A69: PIK accrual (if mode = 2) | D69: =IF($H$16=2,D68,0) -> 0 | E69: =IF($H$16=2,E68,0) -> 0 | F69: =IF($H$16=2,F68,0) -> 0 | G69: =IF($H$16=2,G68,0) -> 0 | H69: =IF($H$16=2,H68,0) -> 0
A70: Scheduled repayment (straight-line over 1 + extension yrs) | D70: =MIN(D67+D69,$P$16/(1+$Q$16)) -> 35.166667 | E70: =MIN(E67+E69,$P$16/(1+$Q$16)) -> 35.166667 | F70: =MIN(F67+F69,$P$16/(1+$Q$16)) -> 35.166667 | G70: =MIN(G67+G69,$P$16/(1+$Q$16)) -> 35.166667 | H70: =MIN(H67+H69,$P$16/(1+$Q$16)) -> 35.166667
A71: Closing balance | C71: =D16 -> 211 | D71: =D67+D69-D70 -> 175.83333 | E71: =E67+E69-E70 -> 140.66667 | F71: =F67+F69-F70 -> 105.5 | G71: =G67+G69-G70 -> 70.333333 | H71: =H67+H69-H70 -> 35.166667
A73: D4. SBI-led capex facility — new money (pro forma)
A74: Opening balance | C74: =0 -> 0 | D74: =0 -> 0 | E74: =D79 -> 15000 | F74: =E79 -> 15000 | G74: =F79 -> 13500 | H74: =G79 -> 12000
A75: Drawdown | D75: =$D$17 -> 15000 | E75: =0 -> 0 | F75: =0 -> 0 | G75: =0 -> 0 | H75: =0 -> 0
A76: Interest ((opening + draw) × all-in rate) | D76: =(D74+D75)*$G$17 -> 1537.5 | E76: =(E74+E75)*$G$17 -> 1537.5 | F76: =(F74+F75)*$G$17 -> 1537.5 | G76: =(G74+G75)*$G$17 -> 1383.75 | H76: =(H74+H75)*$G$17 -> 1230
A77: PIK accrual (if mode = 2) | D77: =IF($H$17=2,D76,0) -> 0 | E77: =IF($H$17=2,E76,0) -> 0 | F77: =IF($H$17=2,F76,0) -> 0 | G77: =IF($H$17=2,G76,0) -> 0 | H77: =IF($H$17=2,H76,0) -> 0
A78: Repayment (from FY29 over 5 + extension yrs) | D78: =IF(D$46>=3,MIN(D74+D77,$D$17/(5+$Q$17)),0) -> 0 | E78: =IF(E$46>=3,MIN(E74+E77,$D$17/(5+$Q$17)),0) -> 0 | F78: =IF(F$46>=3,MIN(F74+F77,$D$17/(5+$Q$17)),0) -> 1500 | G78: =IF(G$46>=3,MIN(G74+G77,$D$17/(5+$Q$17)),0) -> 1500 | H78: =IF(H$46>=3,MIN(H74+H77,$D$17/(5+$Q$17)),0) -> 1500
A79: Closing balance | C79: =0 -> 0 | D79: =D74+D75+D77-D78 -> 15000 | E79: =E74+E75+E77-E78 -> 15000 | F79: =F74+F75+F77-F78 -> 13500 | G79: =G74+G75+G77-G78 -> 12000 | H79: =H74+H75+H77-H78 -> 10500
A81: D5. Non-convertible debentures
A82: Opening balance (post-haircut) | C82: =D18 -> 3300 | D82: =$P$18 -> 3300 | E82: =D86 -> 3300 | F82: =E86 -> 3300 | G82: =F86 -> 3300 | H82: =G86 -> 3300
A83: Coupon (opening × all-in rate incl. penalty) | D83: =D82*$G$18 -> 354.75 | E83: =E82*$G$18 -> 354.75 | F83: =F82*$G$18 -> 354.75 | G83: =G82*$G$18 -> 354.75 | H83: =H82*$G$18 -> 354.75
A84: PIK accrual (if mode = 2) | D84: =IF($H$18=2,D83,0) -> 0 | E84: =IF($H$18=2,E83,0) -> 0 | F84: =IF($H$18=2,F83,0) -> 0 | G84: =IF($H$18=2,G83,0) -> 0 | H84: =IF($H$18=2,H83,0) -> 0
A85: Bullet repayment (FY29 + extension) | D85: =IF(D$46=3+$Q$18,D82+D84,0) -> 0 | E85: =IF(E$46=3+$Q$18,E82+E84,0) -> 0 | F85: =IF(F$46=3+$Q$18,F82+F84,0) -> 0 | G85: =IF(G$46=3+$Q$18,G82+G84,0) -> 0 | H85: =IF(H$46=3+$Q$18,H82+H84,0) -> 0
A86: Closing balance | C86: =D18 -> 3300 | D86: =D82+D84-D85 -> 3300 | E86: =E82+E84-E85 -> 3300 | F86: =F82+F84-F85 -> 3300 | G86: =G82+G84-G85 -> 3300 | H86: =H82+H84-H85 -> 3300
A88: Total statutory cash payments to DoT (spectrum + AGR) | D88: =D52+D59 -> 93 | E88: =E52+E59 -> 93 | F88: =F52+F59 -> 93 | G88: =G52+G59 -> 93 | H88: =H52+H59 -> 14493
A89: Pre-deal contractual DoT payments (for comparison) | D89: =D49+'0_Control_Panel'!$B$47 -> 7200 | E89: =E49+'0_Control_Panel'!$B$47 -> 15124 | F89: =F49+'0_Control_Panel'!$B$47 -> 27124 | G89: =G49+'0_Control_Panel'!$B$47 -> 18124 | H89: =H49+'0_Control_Panel'!$B$47 -> 18124
A90: DoT cash deferral vs contractual schedule (FY27–31) | D90: =D89-D88 -> 7107 | E90: =E89-E88 -> 15031 | F90: =F89-F88 -> 27031 | G90: =G89-G88 -> 18031 | H90: =H89-H88 -> 3631
A91: D6. DoT CASH DEFERRAL — NPV, CARRY-FORWARD & CLIFF TEST (v3: replaces the "cash relief" framing)
A92: Discount rate = post-deal spectrum all-in rate (G14) | B92: =$G$14 -> 0.075
A93: Discount factor (end-year) | D93: =1/(1+$B$92)^D$46 -> 0.93023256 | E93: =1/(1+$B$92)^E$46 -> 0.86533261 | F93: =1/(1+$B$92)^F$46 -> 0.80496057 | G93: =1/(1+$B$92)^G$46 -> 0.74880053 | H93: =1/(1+$B$92)^H$46 -> 0.69655863
A94: PV of DoT cash deferral by year (B94 = NPV, ₹ cr) | B94: =SUM(D94:H94) -> 57407.693 | D94: =D90*D93 -> 6611.1628 | E94: =E90*E93 -> 13006.814 | F94: =F90*F93 -> 21758.889 | G94: =G90*G93 -> 13501.622 | H94: =H90*H93 -> 2529.2044
A95: Nominal deferral FY27–31 (sum of row 90) | B95: =SUM(D90:H90) -> 70831
A96: NPV ÷ nominal (%) | B96: =IFERROR(B94/B95,0) -> 0.81048825
A97: MEMO — OBLIGATIONS CARRIED TO FY32+ (deferred, not forgiven)
A98: Spectrum DPO closing balance FY31 (H54) | B98: =H54 -> 135248.85
A99: AGR closing balance FY31 — nominal (H62) | B99: =H62 -> 47569.5
A100: AGR closing balance FY31 — carrying (H60) | B100: =H60 -> 25939.538
A101: TOTAL carried to FY32+ (DPO + AGR nominal) | B101: =B98+B99 -> 182818.35
A102: memo: DPO + AGR at carrying value | B102: =B98+B100 -> 161188.39
A104: CLIFF TEST — can FY31 earnings carry what falls due after the deferral?
A105: FY31 cash EBITDA (3_Proj H39) | B105: ='3_Restructuring_Projections'!$H$39 -> 23763.682
A106: FY31 closing DPO + AGR (nominal) ÷ FY31 cash EBITDA (x) | B106: =IFERROR(B101/B105,0) -> 7.6931829
A107: Horizon FY32–FY44 (years) — MODEL ASSUMPTION | B107: 13
A108: Implied annual instalment — straight-line (₹ cr) | B108: =B101/B107 -> 14062.95
A109: Implied annual instalment — level annuity (₹ cr) | B109: =-PMT(B92,B107,B101) -> 22498.394
A110: annuity instalment ÷ FY31 cash EBITDA (%) | B110: =IFERROR(B109/B105,0) -> 0.94675537
A111: FY31 cash EBITDA less capex (3_Proj H39 − H61) | B111: ='3_Restructuring_Projections'!$H$39-'3_Restructuring_Projections'!$H$61 -> 11763.682
A112: annuity instalment ÷ (cash EBITDA − capex) (%) | B112: =IF(B111>0,B109/B111,0) -> 1.9125299 | C112: =IF(B111>0,"","n/m: cash EBITDA ≤ capex")
A113: Flag thresholds: WATCH / CLIFF — MODEL ASSUMPTION | B113: 0.3 | C113: 0.5
...

Sheet 3_Restructuring_Projections
A1: 3. FIVE-YEAR INTEGRATED 3-STATEMENT PROJECTIONS (FY27E–FY31E) + GOING-CONCERN DCF
A2: ₹ crore | Opening column = Q1 FY27 annualised run-rate / pro forma opening balance sheet | Fiscal year ending 31-March | Liquidity facility auto-draws to hold minimum cash
A4: ₹ crore | B4: Driver | C4: Run-rate / Open | D4: FY27E | E4: FY28E | F4: FY29E | G4: FY30E | H4: FY31E
A5: Year index | C5: 0 | D5: =C5+1 -> 1 | E5: =D5+1 -> 2 | F5: =E5+1 -> 3 | G5: =F5+1 -> 4 | H5: =G5+1 -> 5
A6: OPERATING DRIVERS
A7: Monthly churn | B7: 0.0005 | C7: 0.038 | D7: =MAX($B$8,C7-$B$7*'0_Control_Panel'!$B$17) -> 0.0375 | E7: =MAX($B$8,D7-$B$7*'0_Control_Panel'!$B$17) -> 0.037 | F7: =MAX($B$8,E7-$B$7*'0_Control_Panel'!$B$17) -> 0.0365 | G7: =MAX($B$8,F7-$B$7*'0_Control_Panel'!$B$17) -> 0.036 | H7: =MAX($B$8,G7-$B$7*'0_Control_Panel'!$B$17) -> 0.0355 | I7: Driver col = annual reduction in monthly churn (pp) when switch on; floor below.
A8: Monthly churn floor | B8: 0.035
A9: Monthly gross-add rate (% of opening base) | B9: 0.0385 | D9: =$B$9 -> 0.0385 | E9: =$B$9 -> 0.0385 | F9: =$B$9 -> 0.0385 | G9: =$B$9 -> 0.0385 | H9: =$B$9 -> 0.0385
A10: Subscribers — opening (mn) | D10: =C12 -> 193.1 | E10: =D12 -> 195.4172 | F10: =E12 -> 198.93471 | G10: =F12 -> 203.70914 | H10: =G12 -> 209.82042
A11: Net adds (mn) | D11: =D10*(D9-D7)*12 -> 2.3172 | E11: =E10*(E9-E7)*12 -> 3.5175096 | F11: =F10*(F9-F7)*12 -> 4.774433 | G11: =G10*(G9-G7)*12 -> 6.1112743 | H11: =H10*(H9-H7)*12 -> 7.553535
A12: Subscribers — closing (mn) | C12: ='0_Control_Panel'!$B$35 -> 193.1 | D12: =D10+D11 -> 195.4172 | E12: =E10+E11 -> 198.93471 | F12: =F10+F11 -> 203.70914 | G12: =G10+G11 -> 209.82042 | H12: =H10+H11 -> 217.37395
A13: Average subscribers (mn) | D13: =AVERAGE(D10,D12) -> 194.2586 | E13: =AVERAGE(E10,E12) -> 197.17595 | F13: =AVERAGE(F10,F12) -> 201.32193 | G13: =AVERAGE(G10,G12) -> 206.76478 | H13: =AVERAGE(H10,H12) -> 213.59718
A14: ARPU growth (active case) | D14: ='0_Control_Panel'!$B$15 -> 0.07 | E14: ='0_Control_Panel'!$B$15 -> 0.07 | F14: ='0_Control_Panel'!$B$15 -> 0.07 | G14: ='0_Control_Panel'!$B$15 -> 0.07 | H14: ='0_Control_Panel'!$B$15 -> 0.07
A15: 5G ARPU premium | D15: ='0_Control_Panel'!$B$9*'0_Control_Panel'!$B$16 -> 0.005 | E15: ='0_Control_Panel'!$B$9*'0_Control_Panel'!$B$16 -> 0.005 | F15: ='0_Control_Panel'!$B$9*'0_Control_Panel'!$B$16 -> 0.005 | G15: ='0_Control_Panel'!$B$9*'0_Control_Panel'!$B$16 -> 0.005 | H15: ='0_Control_Panel'!$B$9*'0_Control_Panel'!$B$16 -> 0.005
A16: ARPU (₹/month) | C16: ='0_Control_Panel'!$B$36 -> 195 | D16: =C16*(1+D14+D15) -> 209.625 | E16: =D16*(1+E14+E15) -> 225.34688 | F16: =E16*(1+F14+F15) -> 242.24789 | G16: =F16*(1+G14+G15) -> 260.41648 | H16: =G16*(1+H14+H15) -> 279.94772
A17: Mobile service revenue | C17: ='0_Control_Panel'!$B$35*'0_Control_Panel'!$B$36*12/10 -> 45185.4 | D17: =D13*D16*12/10 -> 48865.751 | E17: =E13*E16*12/10 -> 53319.582 | F17: =F13*F16*12/10 -> 58523.774 | G17: =G13*G16*12/10 -> 64613.948 | H17: =H13*H16*12/10 -> 71755.253 | I17: mn subs × ₹/month × 12 ÷ 10 = ₹ crore
A18: Other revenue (enterprise, M2M, wholesale) — % of mobile | B18: =C18/C17 -> 0.034759015 | C18: ='0_Control_Panel'!$B$31*4-C17 -> 1570.6 | D18: =D17*$B$18 -> 1698.5254 | E18: =E17*$B$18 -> 1853.3362 | F18: =F17*$B$18 -> 2034.2288 | G18: =G17*$B$18 -> 2245.9172 | H18: =H17*$B$18 -> 2494.1419
A19: TOTAL REVENUE | C19: =C17+C18 -> 46756 | D19: =D17+D18 -> 50564.276 | E19: =E17+E18 -> 55172.918 | F19: =F17+F18 -> 60558.003 | G19: =G17+G18 -> 66859.865 | H19: =H17+H18 -> 74249.395 | I19: Run-rate = Q1 FY27 × 4 = ₹46,756 cr
A20: Revenue growth | D20: =D19/C19-1 -> 0.08145 | E20: =E19/D19-1 -> 0.091144235 | F20: =F19/E19-1 -> 0.097603766 | G20: =G19/F19-1 -> 0.10406324 | H20: =H19/G19-1 -> 0.11052266
A21: COST STRUCTURE (% of revenue) — driver column = annual rationalisation step if switch on
A22: Network opex ex-lease (power, fuel, O&M) | B22: 0.006 | C22: 0.215 | D22: =C22-$B$22*'0_Control_Panel'!$B$18 -> 0.209 | E22: =D22-$B$22*'0_Control_Panel'!$B$18 -> 0.203 | F22: =E22-$B$22*'0_Control_Panel'!$B$18 -> 0.197 | G22: =F22-$B$22*'0_Control_Panel'!$B$18 -> 0.191 | H22: =G22-$B$22*'0_Control_Panel'!$B$18 -> 0.185
A23: Licence fee & SUC | B23: 0 | C23: 0.09 | D23: =C23-$B$23*'0_Control_Panel'!$B$18 -> 0.09 | E23: =D23-$B$23*'0_Control_Panel'!$B$18 -> 0.09 | F23: =E23-$B$23*'0_Control_Panel'!$B$18 -> 0.09 | G23: =F23-$B$23*'0_Control_Panel'!$B$18 -> 0.09 | H23: =G23-$B$23*'0_Control_Panel'!$B$18 -> 0.09
A24: Employee | B24: 0.001 | C24: 0.046 | D24: =C24-$B$24*'0_Control_Panel'!$B$18 -> 0.045 | E24: =D24-$B$24*'0_Control_Panel'!$B$18 -> 0.044 | F24: =E24-$B$24*'0_Control_Panel'!$B$18 -> 0.043 | G24: =F24-$B$24*'0_Control_Panel'!$B$18 -> 0.042 | H24: =G24-$B$24*'0_Control_Panel'!$B$18 -> 0.041
A25: SG&A & customer acquisition | B25: 0.004 | C25: 0.118 | D25: =C25-$B$25*'0_Control_Panel'!$B$18 -> 0.114 | E25: =D25-$B$25*'0_Control_Panel'!$B$18 -> 0.11 | F25: =E25-$B$25*'0_Control_Panel'!$B$18 -> 0.106 | G25: =F25-$B$25*'0_Control_Panel'!$B$18 -> 0.102 | H25: =G25-$B$25*'0_Control_Panel'!$B$18 -> 0.098
A26: Interconnect, roaming & other | B26: 0.002 | C26: 0.1 | D26: =C26-$B$26*'0_Control_Panel'!$B$18 -> 0.098 | E26: =D26-$B$26*'0_Control_Panel'!$B$18 -> 0.096 | F26: =E26-$B$26*'0_Control_Panel'!$B$18 -> 0.094 | G26: =F26-$B$26*'0_Control_Panel'!$B$18 -> 0.092 | H26: =G26-$B$26*'0_Control_Panel'!$B$18 -> 0.09
A27: Total opex % (ex-lease) | C27: =SUM(C22:C26) -> 0.569 | D27: =SUM(D22:D26) -> 0.556 | E27: =SUM(E22:E26) -> 0.543 | F27: =SUM(F22:F26) -> 0.53 | G27: =SUM(G22:G26) -> 0.517 | H27: =SUM(H22:H26) -> 0.504
A28: INCOME STATEMENT
A29: Revenue | C29: =C19 -> 46756 | D29: =D19 -> 50564.276 | E29: =E19 -> 55172.918 | F29: =F19 -> 60558.003 | G29: =G19 -> 66859.865 | H29: =H19 -> 74249.395
A30: Network opex | C30: =-C19*C22 -> -10052.54 | D30: =-D19*D22 -> -10567.934 | E30: =-E19*E22 -> -11200.102 | F30: =-F19*F22 -> -11929.927 | G30: =-G19*G22 -> -12770.234 | H30: =-H19*H22 -> -13736.138
A31: Licence fee & SUC | C31: =-C19*C23 -> -4208.04 | D31: =-D19*D23 -> -4550.7849 | E31: =-E19*E23 -> -4965.5627 | F31: =-F19*F23 -> -5450.2203 | G31: =-G19*G23 -> -6017.3879 | H31: =-H19*H23 -> -6682.4456
A32: Employee costs | C32: =-C19*C24 -> -2150.776 | D32: =-D19*D24 -> -2275.3924 | E32: =-E19*E24 -> -2427.6084 | F32: =-F19*F24 -> -2603.9941 | G32: =-G19*G24 -> -2808.1143 | H32: =-H19*H24 -> -3044.2252
A33: SG&A | C33: =-C19*C25 -> -5517.208 | D33: =-D19*D25 -> -5764.3275 | E33: =-E19*E25 -> -6069.021 | F33: =-F19*F25 -> -6419.1483 | G33: =-G19*G25 -> -6819.7062 | H33: =-H19*H25 -> -7276.4407
A34: Interconnect & other | C34: =-C19*C26 -> -4675.6 | D34: =-D19*D26 -> -4955.2991 | E34: =-E19*E26 -> -5296.6002 | F34: =-F19*F26 -> -5692.4523 | G34: =-G19*G26 -> -6151.1076 | H34: =-H19*H26 -> -6682.4456
A35: EBITDA (Ind AS 116) | C35: =SUM(C29:C34) -> 20151.836 | D35: =SUM(D29:D34) -> 22450.539 | E35: =SUM(E29:E34) -> 25214.024 | F35: =SUM(F29:F34) -> 28462.261 | G35: =SUM(G29:G34) -> 32293.315 | H35: =SUM(H29:H34) -> 36827.7 | I35: Check: run-rate ≈ ₹5,034 cr × 4
A36: EBITDA margin | C36: =C35/C19 -> 0.431 | D36: =D35/D19 -> 0.444 | E36: =E35/E19 -> 0.457 | F36: =F35/F19 -> 0.47 | G36: =G35/G19 -> 0.483 | H36: =H35/H19 -> 0.496
A37: Lease-rental growth (sites; +5G densification if on) | B37: 0.03 | D37: =$B$37+'0_Control_Panel'!$B$9*0.02 -> 0.05 | E37: =$B$37+'0_Control_Panel'!$B$9*0.02 -> 0.05 | F37: =$B$37+'0_Control_Panel'!$B$9*0.02 -> 0.05 | G37: =$B$37+'0_Control_Panel'!$B$9*0.02 -> 0.05 | H37: =$B$37+'0_Control_Panel'!$B$9*0.02 -> 0.05
A38: Lease rentals paid (Indus Towers & others) | C38: =('0_Control_Panel'!$B$32-'0_Control_Panel'!$B$33)*4 -> 10236 | D38: =C38*(1+D37) -> 10747.8 | E38: =D38*(1+E37) -> 11285.19 | F38: =E38*(1+F37) -> 11849.45 | G38: =F38*(1+G37) -> 12441.922 | H38: =G38*(1+H37) -> 13064.018
A39: CASH EBITDA (EBITDA − lease rentals) | C39: =C35-C38 -> 9915.836 | D39: =D35-D38 -> 11702.739 | E39: =E35-E38 -> 13928.834 | F39: =F35-F38 -> 16612.812 | G39: =G35-G38 -> 19851.393 | H39: =H35-H38 -> 23763.682 | I39: Run-rate ≈ ₹2,475 cr × 4. Management targets ~3x in three years.
A40: Depreciation — PP&E | B40: 0.22 | D40: =-C67*$B$40 -> -8360 | E40: =-D67*$B$40 -> -9380.8 | F40: =-E67*$B$40 -> -10727.024 | G40: =-F67*$B$40 -> -11777.079 | H40: =-G67*$B$40 -> -11826.121
A41: Amortisation — spectrum & intangibles | B41: 0.09 | D41: =-C68*$B$41 -> -8550 | E41: =-D68*$B$41 -> -7780.5 | F41: =-E68*$B$41 -> -7080.255 | G41: =-F68*$B$41 -> -6443.032 | H41: =-G68*$B$41 -> -5863.1592
A42: Depreciation — right-of-use | B42: 0.3 | D42: =-C69*$B$42 -> -4500 | E42: =-D69*$B$42 -> -6111.09 | F42: =-E69*$B$42 -> -7386.9075 | G42: =-F69*$B$42 -> -8435.437 | H42: =-G69*$B$42 -> -9332.6377
A43: EBIT | D43: =D35+SUM(D40:D42) -> 1040.5386 | E43: =E35+SUM(E40:E42) -> 1941.6337 | F43: =F35+SUM(F40:F42) -> 3268.0749 | G43: =G35+SUM(G40:G42) -> 5637.7671 | H43: =H35+SUM(H40:H42) -> 9805.7818
A44: Interest — spectrum DPO | D44: =-'2_Capital_Structure_Waterfall'!D51 -> -7817.94 | E44: =-'2_Capital_Structure_Waterfall'!E51 -> -8404.2855 | F44: =-'2_Capital_Structure_Waterfall'!F51 -> -9034.6069 | G44: =-'2_Capital_Structure_Waterfall'!G51 -> -9712.2024 | H44: =-'2_Capital_Structure_Waterfall'!H51 -> -10440.618
A45: Accretion — AGR (non-cash) | D45: =-'2_Capital_Structure_Waterfall'!D58 -> -1255.7513 | E45: =-'2_Capital_Structure_Waterfall'!E58 -> -1331.3301 | F45: =-'2_Capital_Structure_Waterfall'!F58 -> -1411.8215 | G45: =-'2_Capital_Structure_Waterfall'!G58 -> -1497.5449 | H45: =-'2_Capital_Structure_Waterfall'!H58 -> -1588.8404
A46: Interest — lease liabilities | B46: 0.095 | D46: =-C77*$B$46 -> -1852.5 | E46: =-D77*$B$46 -> -1945.125 | F46: =-E77*$B$46 -> -2042.3812 | G46: =-F77*$B$46 -> -2144.5003 | H46: =-G77*$B$46 -> -2251.7253
A47: Interest — bank (existing) | D47: =-'2_Capital_Structure_Waterfall'!D68 -> -22.155 | E47: =-'2_Capital_Structure_Waterfall'!E68 -> -18.4625 | F47: =-'2_Capital_Structure_Waterfall'!F68 -> -14.77 | G47: =-'2_Capital_Structure_Waterfall'!G68 -> -11.0775 | H47: =-'2_Capital_Structure_Waterfall'!H68 -> -7.385
A48: Interest — SBI facility | D48: =-'2_Capital_Structure_Waterfall'!D76 -> -1537.5 | E48: =-'2_Capital_Structure_Waterfall'!E76 -> -1537.5 | F48: =-'2_Capital_Structure_Waterfall'!F76 -> -1537.5 | G48: =-'2_Capital_Structure_Waterfall'!G76 -> -1383.75 | H48: =-'2_Capital_Structure_Waterfall'!H76 -> -1230
A49: Interest — NCDs | D49: =-'2_Capital_Structure_Waterfall'!D83 -> -354.75 | E49: =-'2_Capital_Structure_Waterfall'!E83 -> -354.75 | F49: =-'2_Capital_Structure_Waterfall'!F83 -> -354.75 | G49: =-'2_Capital_Structure_Waterfall'!G83 -> -354.75 | H49: =-'2_Capital_Structure_Waterfall'!H83 -> -354.75
A50: Interest — liquidity facility (on opening) | B50: 0.11 | D50: =-C76*$B$50 -> 0 | E50: =-D76*$B$50 -> 0 | F50: =-E76*$B$50 -> 0 | G50: =-F76*$B$50 -> 0 | H50: =-G76*$B$50 -> 0
A51: Interest income on cash (on opening) | B51: 0.06 | D51: =C64*$B$51 -> 393.48 | E51: =D64*$B$51 -> 2061.5956 | F51: =E64*$B$51 -> 1956.0891 | G51: =F64*$B$51 -> 1854.2812 | H51: =G64*$B$51 -> 2076.5989
A52: Exceptional — gain on debt/payables haircut | D52: ='2_Capital_Structure_Waterfall'!$O$29 -> 0 | E52: =0 -> 0 | F52: =0 -> 0 | G52: =0 -> 0 | H52: =0 -> 0
A53: Exceptional — restructuring / CIRP costs | D53: =-'0_Control_Panel'!$E$85 -> -150 | E53: =0 -> 0 | F53: =0 -> 0 | G53: =0 -> 0 | H53: =0 -> 0
A54: Profit / (loss) before tax | D54: =D43+SUM(D44:D53) -> -11556.578 | E54: =E43+SUM(E44:E53) -> -9588.2237 | F54: =F43+SUM(F44:F53) -> -9171.6657 | G54: =G43+SUM(G44:G53) -> -7611.7769 | H54: =H43+SUM(H44:H53) -> -3990.9376
A55: Tax — NOL shield active (1 = no cash tax) | B55: 1
A56: Tax expense (25.17% if NOL exhausted) | B56: 0.2517 | D56: =IF($B$55=1,0,-MAX(0,D54)*$B$56) -> 0 | E56: =IF($B$55=1,0,-MAX(0,E54)*$B$56) -> 0 | F56: =IF($B$55=1,0,-MAX(0,F54)*$B$56) -> 0 | G56: =IF($B$55=1,0,-MAX(0,G54)*$B$56) -> 0 | H56: =IF($B$55=1,0,-MAX(0,H54)*$B$56) -> 0
A57: NET INCOME / (LOSS) | D57: =D54+D56 -> -11556.578 | E57: =E54+E56 -> -9588.2237 | F57: =F54+F56 -> -9171.6657 | G57: =G54+G56 -> -7611.7769 | H57: =H54+H56 -> -3990.9376
A58: CAPEX
A59: 4G coverage & capacity capex | C59: ='0_Control_Panel'!$B$34*4 -> 7720 | D59: =9000 -> 9000 | E59: =10000 -> 10000 | F59: =10000 -> 10000 | G59: =8000 -> 8000 | H59: =8000 -> 8000
A60: 5G rollout capex (× switch × intensity) | D60: =4000*'0_Control_Panel'!$B$9*'0_Control_Panel'!$B$10 -> 4000 | E60: =5500*'0_Control_Panel'!$B$9*'0_Control_Panel'!$B$10 -> 5500 | F60: =5500*'0_Control_Panel'!$B$9*'0_Control_Panel'!$B$10 -> 5500 | G60: =4000*'0_Control_Panel'!$B$9*'0_Control_Panel'!$B$10 -> 4000 | H60: =4000*'0_Control_Panel'!$B$9*'0_Control_Panel'!$B$10 -> 4000
A61: Total capex | C61: =C59 -> 7720 | D61: =D59+D60 -> 13000 | E61: =E59+E60 -> 15500 | F61: =F59+F60 -> 15500 | G61: =G59+G60 -> 12000 | H61: =H59+H60 -> 12000 | I61: FY27–29 base ≈ ₹47,000 cr vs ₹45,000 cr guidance
A62: Capex / revenue | D62: =D61/D19 -> 0.25709851 | E62: =E61/E19 -> 0.28093493 | F62: =F61/F19 -> 0.25595296 | G62: =G61/G19 -> 0.17947987 | H62: =H61/H19 -> 0.16161748
A63: BALANCE SHEET
A64: Cash & bank | C64: ='0_Control_Panel'!$B$30 -> 6558 | D64: =D102 -> 34359.927 | E64: =E102 -> 32601.485 | F64: =F102 -> 30904.686 | G64: =G102 -> 34609.981 | H64: =H102 -> 29115.598
A65: Trade receivables (days of revenue) | B65: =C65/C19*365 -> 18.735563 | C65: ='0_Control_Panel'!$B$59 -> 2400 | D65: =D19*$B$65/365 -> 2595.48 | E65: =E19*$B$65/365 -> 2832.043 | F65: =F19*$B$65/365 -> 3108.4611 | G65: =G19*$B$65/365 -> 3431.9376 | H65: =H19*$B$65/365 -> 3811.2445
A66: Other current assets (% revenue) | B66: =C66/C19 -> 0.31012063 | C66: ='0_Control_Panel'!$B$60 -> 14500 | D66: =D19*$B$66 -> 15681.025 | E66: =E19*$B$66 -> 17110.26 | F66: =F19*$B$66 -> 18780.286 | G66: =G19*$B$66 -> 20734.623 | H66: =H19*$B$66 -> 23026.269
A67: Net PP&E | C67: ='0_Control_Panel'!$B$61 -> 38000 | D67: =C67+D61+D40-'0_Control_Panel'!$E$89 -> 42640 | E67: =D67+E61+E40 -> 48759.2 | F67: =E67+F61+F40 -> 53532.176 | G67: =F67+G61+G40 -> 53755.097 | H67: =G67+H61+H40 -> 53928.976
A68: Spectrum & intangibles | C68: ='0_Control_Panel'!$B$62 -> 95000 | D68: =C68+D41 -> 86450 | E68: =D68+E41 -> 78669.5 | F68: =E68+F41 -> 71589.245 | G68: =F68+G41 -> 65146.213 | H68: =G68+H41 -> 59283.054
A69: Right-of-use assets | C69: ='0_Control_Panel'!$B$63 -> 15000 | D69: =C69+D42+D105 -> 20370.3 | E69: =D69+E42+E105 -> 24623.025 | F69: =E69+F42+F105 -> 28118.123 | G69: =F69+G42+G105 -> 31108.792 | H69: =G69+H42+H105 -> 33773.566
A70: TOTAL ASSETS | C70: =SUM(C64:C69) -> 171458 | D70: =SUM(D64:D69) -> 202096.73 | E70: =SUM(E64:E69) -> 204595.51 | F70: =SUM(F64:F69) -> 206032.98 | G70: =SUM(G64:G69) -> 208786.64 | H70: =SUM(H64:H69) -> 202938.71
A71: Spectrum DPO | C71: ='0_Control_Panel'!$B$25 -> 130299 | D71: ='2_Capital_Structure_Waterfall'!D54 -> 112057.14 | E71: ='2_Capital_Structure_Waterfall'!E54 -> 120461.43 | F71: ='2_Capital_Structure_Waterfall'!F54 -> 129496.03 | G71: ='2_Capital_Structure_Waterfall'!G54 -> 139208.23 | H71: ='2_Capital_Structure_Waterfall'!H54 -> 135248.85
A72: AGR DPO (carrying) | C72: ='0_Control_Panel'!$B$27 -> 25759 | D72: ='2_Capital_Structure_Waterfall'!D60 -> 20482.001 | E72: ='2_Capital_Structure_Waterfall'!E60 -> 21720.331 | F72: ='2_Capital_Structure_Waterfall'!F60 -> 23039.153 | G72: ='2_Capital_Structure_Waterfall'!G60 -> 24443.698 | H72: ='2_Capital_Structure_Waterfall'!H60 -> 25939.538
A73: Bank loans (existing) | C73: ='0_Control_Panel'!$B$28 -> 211 | D73: ='2_Capital_Structure_Waterfall'!D71 -> 175.83333 | E73: ='2_Capital_Structure_Waterfall'!E71 -> 140.66667 | F73: ='2_Capital_Structure_Waterfall'!F71 -> 105.5 | G73: ='2_Capital_Structure_Waterfall'!G71 -> 70.333333 | H73: ='2_Capital_Structure_Waterfall'!H71 -> 35.166667
A74: SBI-led facility | C74: =0 -> 0 | D74: ='2_Capital_Structure_Waterfall'!D79 -> 15000 | E74: ='2_Capital_Structure_Waterfall'!E79 -> 15000 | F74: ='2_Capital_Structure_Waterfall'!F79 -> 13500 | G74: ='2_Capital_Structure_Waterfall'!G79 -> 12000 | H74: ='2_Capital_Structure_Waterfall'!H79 -> 10500
A75: NCDs | C75: ='0_Control_Panel'!$B$29 -> 3300 | D75: ='2_Capital_Structure_Waterfall'!D86 -> 3300 | E75: ='2_Capital_Structure_Waterfall'!E86 -> 3300 | F75: ='2_Capital_Structure_Waterfall'!F86 -> 3300 | G75: ='2_Capital_Structure_Waterfall'!G86 -> 3300 | H75: ='2_Capital_Structure_Waterfall'!H86 -> 3300
A76: Liquidity facility (auto-draw) | C76: =0 -> 0 | D76: =C76+D101 -> 0 | E76: =D76+E101 -> 0 | F76: =E76+F101 -> 0 | G76: =F76+G101 -> 0 | H76: =G76+H101 -> 0
A77: Lease liabilities | C77: ='0_Control_Panel'!$B$52 -> 19500 | D77: =C77-D46+D105-D38 -> 20475 | E77: =D77-E46+E105-E38 -> 21498.75 | F77: =E77-F46+F105-F38 -> 22573.688 | G77: =F77-G46+G105-G38 -> 23702.372 | H77: =G77-H46+H105-H38 -> 24887.49
A78: Trade payables (% of opex + capex) | B78: =C78/(-SUM(C30:C34)+C61) -> 0.33504094 | C78: ='0_Control_Panel'!$B$56 -> 11500 | D78: =$B$78*(-SUM(D30:D34)+D61) -> 13774.785 | E78: =$B$78*(-SUM(E30:E34)+E61) -> 15230.591 | F78: =$B$78*(-SUM(F30:F34)+F61) -> 15946.522 | G78: =$B$78*(-SUM(G30:G34)+G61) -> 15601.701 | H78: =$B$78*(-SUM(H30:H34)+H61) -> 16558.291
A79: Other liabilities & provisions | C79: ='0_Control_Panel'!$B$57 -> 22000 | D79: =C79 -> 22000 | E79: =D79 -> 22000 | F79: =E79 -> 22000 | G79: =F79 -> 22000 | H79: =G79 -> 22000
A80: TOTAL LIABILITIES | C80: =SUM(C71:C79) -> 212569 | D80: =SUM(D71:D79) -> 207264.76 | E80: =SUM(E71:E79) -> 219351.76 | F80: =SUM(F71:F79) -> 229960.89 | G80: =SUM(G71:G79) -> 240326.34 | H80: =SUM(H71:H79) -> 238469.34
A81: Shareholders' equity / (deficit) | C81: =C70-C80 -> -41111 | D81: =C81+D57+D103+D104 -> -5168.0276 | E81: =D81+E57+E103+E104 -> -14756.251 | F81: =E81+F57+F103+F104 -> -23927.917 | G81: =F81+G57+G103+G104 -> -31539.694 | H81: =G81+H57+H103+H104 -> -35530.632
A82: TOTAL LIABILITIES + EQUITY | C82: =C80+C81 -> 171458 | D82: =D80+D81 -> 202096.73 | E82: =E80+E81 -> 204595.51 | F82: =F80+F81 -> 206032.98 | G82: =G80+G81 -> 208786.64 | H82: =H80+H81 -> 202938.71
A83: BALANCE CHECK (must be zero) | C83: =ROUND(C70-C82,2) -> 0 | D83: =ROUND(D70-D82,2) -> 0 | E83: =ROUND(E70-E82,2) -> 0 | F83: =ROUND(F70-F82,2) -> 0 | G83: =ROUND(G70-G82,2) -> 0 | H83: =ROUND(H70-H82,2) -> 0
A84: CASH FLOW STATEMENT
A85: Net income | D85: =D57 -> -11556.578 | E85: =E57 -> -9588.2237 | F85: =F57 -> -9171.6657 | G85: =G57 -> -7611.7769 | H85: =H57 -> -3990.9376
A86: + D&A | D86: =-SUM(D40:D42) -> 21410 | E86: =-SUM(E40:E42) -> 23272.39 | F86: =-SUM(F40:F42) -> 25194.186 | G86: =-SUM(G40:G42) -> 26655.548 | H86: =-SUM(H40:H42) -> 27021.918
A87: + Non-cash interest (spectrum, AGR accretion, lease, PIK) | D87: =-D44-D45-D46+'2_Capital_Structure_Waterfall'!D69+'2_Capital_Structure_Waterfall'!D77+'2_Capital_Structure_Waterfall'!D84 -> 10926.191 | E87: =-E44-E45-E46+'2_Capital_Structure_Waterfall'!E69+'2_Capital_Structure_Waterfall'!E77+'2_Capital_Structure_Waterfall'!E84 -> 11680.741 | F87: =-F44-F45-F46+'2_Capital_Structure_Waterfall'!F69+'2_Capital_Structure_Waterfall'!F77+'2_Capital_Structure_Waterfall'!F84 -> 12488.81 | G87: =-G44-G45-G46+'2_Capital_Structure_Waterfall'!G69+'2_Capital_Structure_Waterfall'!G77+'2_Capital_Structure_Waterfall'!G84 -> 13354.248 | H87: =-H44-H45-H46+'2_Capital_Structure_Waterfall'!H69+'2_Capital_Structure_Waterfall'!H77+'2_Capital_Structure_Waterfall'!H84 -> 14281.183
A88: − Non-cash haircut gain | D88: =-D52 -> 0 | E88: =-E52 -> 0 | F88: =-F52 -> 0 | G88: =-G52 -> 0 | H88: =-H52 -> 0
A89: ± Working capital (receivables, OCA, payables ex-haircut) | D89: =-(D65-C65)-(D66-C66)+(D78-C78)+IF(D$5=1,'2_Capital_Structure_Waterfall'!$O$21+'2_Capital_Structure_Waterfall'!$O$22,0) -> 898.28008 | E89: =-(E65-D65)-(E66-D66)+(E78-D78)+IF(E$5=1,'2_Capital_Structure_Waterfall'!$O$21+'2_Capital_Structure_Waterfall'!$O$22,0) -> -209.99254 | F89: =-(F65-E65)-(F66-E66)+(F78-E78)+IF(F$5=1,'2_Capital_Structure_Waterfall'!$O$21+'2_Capital_Structure_Waterfall'!$O$22,0) -> -1230.5127 | G89: =-(G65-F65)-(G66-F66)+(G78-F78)+IF(G$5=1,'2_Capital_Structure_Waterfall'!$O$21+'2_Capital_Structure_Waterfall'!$O$22,0) -> -2622.6352 | H89: =-(H65-G65)-(H66-G66)+(H78-G78)+IF(H$5=1,'2_Capital_Structure_Waterfall'!$O$21+'2_Capital_Structure_Waterfall'!$O$22,0) -> -1714.3622
A90: CASH FLOW FROM OPERATIONS | D90: =SUM(D85:D89) -> 21677.894 | E90: =SUM(E85:E89) -> 25154.914 | F90: =SUM(F85:F89) -> 27280.818 | G90: =SUM(G85:G89) -> 29775.383 | H90: =SUM(H85:H89) -> 35597.802
A91: Capex | D91: =-D61 -> -13000 | E91: =-E61 -> -15500 | F91: =-F61 -> -15500 | G91: =-G61 -> -12000 | H91: =-H61 -> -12000
A92: Spectrum DPO instalments (DoT) | D92: =-'2_Capital_Structure_Waterfall'!D52 -> 0 | E92: =-'2_Capital_Structure_Waterfall'!E52 -> 0 | F92: =-'2_Capital_Structure_Waterfall'!F52 -> 0 | G92: =-'2_Capital_Structure_Waterfall'!G52 -> 0 | H92: =-'2_Capital_Structure_Waterfall'!H52 -> -14400
A93: AGR instalments (DoT) | D93: =-'2_Capital_Structure_Waterfall'!D59 -> -93 | E93: =-'2_Capital_Structure_Waterfall'!E59 -> -93 | F93: =-'2_Capital_Structure_Waterfall'!F59 -> -93 | G93: =-'2_Capital_Structure_Waterfall'!G59 -> -93 | H93: =-'2_Capital_Structure_Waterfall'!H59 -> -93
A94: Lease rentals (principal + interest) | D94: =-D38 -> -10747.8 | E94: =-E38 -> -11285.19 | F94: =-F38 -> -11849.45 | G94: =-G38 -> -12441.922 | H94: =-H38 -> -13064.018
A95: SBI facility drawdown | D95: ='2_Capital_Structure_Waterfall'!D75 -> 15000 | E95: ='2_Capital_Structure_Waterfall'!E75 -> 0 | F95: ='2_Capital_Structure_Waterfall'!F75 -> 0 | G95: ='2_Capital_Structure_Waterfall'!G75 -> 0 | H95: ='2_Capital_Structure_Waterfall'!H75 -> 0
A96: Debt repayments (bank, SBI, NCD) | D96: =-'2_Capital_Structure_Waterfall'!D70-'2_Capital_Structure_Waterfall'!D78-'2_Capital_Structure_Waterfall'!D85 -> -35.166667 | E96: =-'2_Capital_Structure_Waterfall'!E70-'2_Capital_Structure_Waterfall'!E78-'2_Capital_Structure_Waterfall'!E85 -> -35.166667 | F96: =-'2_Capital_Structure_Waterfall'!F70-'2_Capital_Structure_Waterfall'!F78-'2_Capital_Structure_Waterfall'!F85 -> -1535.1667 | G96: =-'2_Capital_Structure_Waterfall'!G70-'2_Capital_Structure_Waterfall'!G78-'2_Capital_Structure_Waterfall'!G85 -> -1535.1667 | H96: =-'2_Capital_Structure_Waterfall'!H70-'2_Capital_Structure_Waterfall'!H78-'2_Capital_Structure_Waterfall'!H85 -> -1535.1667
A97: New-money equity + asset-sale proceeds (FY27) | D97: ='0_Control_Panel'!$E$81+'0_Control_Panel'!$E$89 -> 15000 | E97: =0 -> 0 | F97: =0 -> 0 | G97: =0 -> 0 | H97: =0 -> 0
A98: CASH FLOW FROM FINANCING (pre-liquidity facility) | D98: =SUM(D92:D97) -> 19124.033 | E98: =SUM(E92:E97) -> -11413.357 | F98: =SUM(F92:F97) -> -13477.616 | G98: =SUM(G92:G97) -> -14070.089 | H98: =SUM(H92:H97) -> -29092.185
A99: Cash before liquidity facility | D99: =C64+D90+D91+D98 -> 34359.927 | E99: =D64+E90+E91+E98 -> 32601.485 | F99: =E64+F90+F91+F98 -> 30904.686 | G99: =F64+G90+G91+G98 -> 34609.981 | H99: =G64+H90+H91+H98 -> 29115.598
A100: Minimum cash balance | B100: ='0_Control_Panel'!$B$49 -> 4000 | D100: =$B$100 -> 4000 | E100: =$B$100 -> 4000 | F100: =$B$100 -> 4000 | G100: =$B$100 -> 4000 | H100: =$B$100 -> 4000
A101: LIQUIDITY FACILITY DRAW REQUIRED | D101: =MAX(0,D100-D99) -> 0 | E101: =MAX(0,E100-E99) -> 0 | F101: =MAX(0,F100-F99) -> 0 | G101: =MAX(0,G100-G99) -> 0 | H101: =MAX(0,H100-H99) -> 0
...

Sheet 4_Liquidation_Waterfall
A1: 4. LIQUIDATION ANALYSIS — ASSET RECOVERY & IBC SECTION 53 DISTRIBUTION WATERFALL
A2: ₹ crore | Liquidation commencement assumed at end of 13-week window | Statutory hierarchy per Insolvency and Bankruptcy Code, 2016, s.53(1)(a)–(h)
A4: A. SWITCHES
A5: Recovery case (1 = Low, 2 = Mid, 3 = High) | B5: 2 | H5: Mid used for memo.
A6: Spectrum right-to-use included in liquidation estate (1/0) | B6: 1 | H6: Legally contested: DoT position is that spectrum is a sovereign resource; Aircel/RCom CIRPs show transfer is conditional on clearing DoT dues.
A7: Treat Govt dues as secured — Rainbow Papers (SC, 2022) sensitivity (1/0) | B7: 0 | H7: If 1, statutory dues rank pari passu with secured creditors in s.53(1)(b).
A8: Include pro forma SBI facility in secured claims (1/0) | B8: 0 | H8: v3 default 0 for the "today" comparison: the ₹15,000 cr pro forma SBI facility is not drawn today, and v2 counted it as a secured claim with no matching asset (understating the Govt recovery). Set 1 for the failure-after-drawdown case. Both Govt recoveries are shown live in block F below (rows 55-75).
A10: B. ASSET-BY-ASSET RECOVERY SCHEDULE
A11: Asset | B11: Book value | C11: Low % | D11: Mid % | E11: High % | F11: Selected % | G11: Proceeds | H11: Recovery rationale
A12: Spectrum right-to-use (all bands, incl. 5G 3.3 GHz / 26 GHz) | B12: ='0_Control_Panel'!$B$62*$B$6 -> 95000 | C12: 0.25 | D12: 0.35 | E12: 0.45 | F12: =CHOOSE($B$5,C12,D12,E12) -> 0.35 | G12: =B12*F12 -> 33250 | H12: Forced sale to Jio/Airtel only (two bidders); DoT may cancel licence/reclaim; buyer assumes DoT dues.
A13: Network PP&E (RAN, microwave, fibre, core) | B13: ='0_Control_Panel'!$B$61 -> 38000 | C13: 0.1 | D13: 0.15 | E13: 0.2 | F13: =CHOOSE($B$5,C13,D13,E13) -> 0.15 | G13: =B13*F13 -> 5700 | H13: Vendor-locked radio equipment; scrap/redeploy value; fibre sells better.
A14: Right-of-use assets (tower leases) | B14: ='0_Control_Panel'!$B$63 -> 15000 | C14: 0 | D14: 0 | E14: 0.02 | F14: =CHOOSE($B$5,C14,D14,E14) -> 0 | G14: =B14*F14 -> 0 | H14: Leases terminate on liquidation; Indus re-lets tenancy.
A15: Cash (min of 13-week TWCF, floored at nil) | B15: =MAX(0,'1_TWCF_13_Week_Liquidity'!$B$75) -> 3000.0279 | C15: 1 | D15: 1 | E15: 1 | F15: =CHOOSE($B$5,C15,D15,E15) -> 1 | G15: =B15*F15 -> 3000.0279 | H15: Encumbrance-free cash at liquidation commencement.
A16: Trade receivables | B16: ='0_Control_Panel'!$B$59 -> 2400 | C16: 0.5 | D16: 0.6 | E16: 0.7 | F16: =CHOOSE($B$5,C16,D16,E16) -> 0.6 | G16: =B16*F16 -> 1440 | H16: Enterprise receivables; prepaid has none.
A17: Other current assets (GST input credits, deposits, refunds) | B17: ='0_Control_Panel'!$B$60 -> 14500 | C17: 0.15 | D17: 0.25 | E17: 0.35 | F17: =CHOOSE($B$5,C17,D17,E17) -> 0.25 | G17: =B17*F17 -> 3625 | H17: GST ITC monetisable only partially; refunds slow.
A18: GROSS LIQUIDATION PROCEEDS | B18: =SUM(B12:B17) -> 167900.03 | F18: =G18/B18 -> 0.28001799 | G18: =SUM(G12:G17) -> 47015.028
A19: Low / High proceeds (memo) | C19: =SUMPRODUCT(B12:B17,C12:C17) -> 33925.028 | E19: =SUMPRODUCT(B12:B17,E12:E17) -> 60405.028
A21: C. IBC SECTION 53 DISTRIBUTION WATERFALL
A22: Priority tier | B22: Claim | C22: Available | D22: Recovered | E22: Recovery % | F22: Shortfall | H22: Composition / legal basis
A23: Inputs: workmen dues (24 months) | B23: 150
A24: Inputs: employee wages (12 months, non-workmen) | B24: 700
A25: Inputs: Govt dues falling in 2 yrs preceding (s.53(1)(e)) — calc | B25: ='0_Control_Panel'!$B$42+'0_Control_Panel'!$B$43+2*'0_Control_Panel'!$B$47+'1_TWCF_13_Week_Liquidity'!$B$9*'1_TWCF_13_Week_Liquidity'!$B$17 -> 23402.31
A26: Inputs: total statutory Govt claims (spectrum DPO + AGR nominal) | B26: ='0_Control_Panel'!$B$25+'0_Control_Panel'!$B$26 -> 194345
A27: Inputs: secured financial creditors (bank + NCD + SBI pro forma) | B27: ='0_Control_Panel'!$B$28+'0_Control_Panel'!$B$29+'0_Control_Panel'!$B$58*'0_Control_Panel'!$B$83*$B$8 -> 3511 | H27: SBI pro forma drawn at Plan A draw % (failure after drawdown).
A28: Inputs: operational creditors (lease + trade + other) | B28: ='0_Control_Panel'!$B$52+'0_Control_Panel'!$B$56+'0_Control_Panel'!$B$57 -> 53000
A30: s.53(1)(a) — CIRP & liquidation costs | B30: ='0_Control_Panel'!$D$85 -> 2500 | C30: =$G$18 -> 47015.028 | D30: =MIN(B30,C30) -> 2500 | E30: =IFERROR(D30/B30,0) -> 1 | F30: =B30-D30 -> 0 | H30: IRP/RP & liquidator fees, interim finance, asset preservation.
A31: s.53(1)(b) — Workmen (24m) + secured creditors relinquishing security | B31: =$B$23+$B$27+$B$7*$B$26 -> 3661 | C31: =C30-D30 -> 44515.028 | D31: =MIN(B31,C31) -> 3661 | E31: =IFERROR(D31/B31,0) -> 1 | F31: =B31-D31 -> 0 | H31: Bank, NCD, SBI facility pari passu with workmen; + Govt if Rainbow switch.
A32: s.53(1)(c) — Employee wages (12 months) | B32: =$B$24 -> 700 | C32: =C31-D31 -> 40854.028 | D32: =MIN(B32,C32) -> 700 | E32: =IFERROR(D32/B32,0) -> 1 | F32: =B32-D32 -> 0
A33: s.53(1)(d) — Unsecured financial creditors | B33: =0 -> 0 | C33: =C32-D32 -> 40154.028 | D33: =MIN(B33,C33) -> 0 | E33: =IFERROR(D33/B33,0) -> 0 | F33: =B33-D33 -> 0 | H33: None material.
A34: s.53(1)(e) — Govt dues (2 yrs preceding) + secured unpaid post-enforcement | B34: =$B$25*(1-$B$7) -> 23402.31 | C34: =C33-D33 -> 40154.028 | D34: =MIN(B34,C34) -> 23402.31 | E34: =IFERROR(D34/B34,0) -> 1 | F34: =B34-D34 -> 0 | H34: Spectrum FY27–28 instalments, AGR, current LF/SUC.
A35: s.53(1)(f) — Remaining debts & dues (balance Govt + operational creditors) | B35: =($B$26-$B$25)*(1-$B$7)+$B$28 -> 223942.69 | C35: =C34-D34 -> 16751.718 | D35: =MIN(B35,C35) -> 16751.718 | E35: =IFERROR(D35/B35,0) -> 0.074803592 | F35: =B35-D35 -> 207190.97 | H35: Indus Towers, Ericsson/Nokia/Samsung, lease claims, balance DoT dues.
A36: s.53(1)(g)–(h) — Preference & equity shareholders | B36: =0 -> 0 | C36: =C35-D35 -> 0 | D36: =C36 -> 0 | E36: =IFERROR(D36/B36,0) -> 0 | F36: =B36-D36 -> 0 | H36: Residual only.
A37: TOTAL | B37: =SUM(B30:B36) -> 254206 | D37: =SUM(D30:D36) -> 47015.028 | E37: =D37/B37 -> 0.18494854 | F37: =SUM(F30:F36) -> 207190.97
A39: D. RECOVERY BY CREDITOR CLASS — LIQUIDATION vs GOING CONCERN
A40: Creditor class | B40: Claim | C40: Liquidation ₹ | D40: Liquidation % | E40: Plan A (GC) % | F40: Plan B % | G40: Δ Plan A vs Liq (pp) | H40: Comment
A41: Secured financial creditors (SBI consortium, NCD holders) | B41: =$B$27 -> 3511 | C41: =B41*E31 -> 3511 | D41: =IFERROR(C41/B41,0) -> 1 | E41: =1 -> 1 | F41: =1-('0_Control_Panel'!$B$28*'0_Control_Panel'!$C$75+'0_Control_Panel'!$B$29*'0_Control_Panel'!$C$76)/('0_Control_Panel'!$B$28+'0_Control_Panel'!$B$29) -> 0.74098547 | G41: =(E41-D41)*100 -> 0 | H41: =IF($B$6=1,"Conditional: banks are NOT impaired only IF spectrum is in the estate (B6 = 1, recovered at "&TEXT($F$12,"0%")&" of book) — s.53 then ranks them 2nd and liquidation covers them. If spectrum is excluded and the ₹15,000 cr SBI facility is counted, secured lenders recover about "&TEXT('6_Reconciliations'!$C$94,"0%")&" (6_Reconciliations R6 snapshot).","Spectrum EXCLUDED (B6 = 0): secured lenders recover "&TEXT($D$41,"0%")&" live — banks ARE impaired in this case; see R6 for the SBI-facility variants.") -> Conditional: banks are NOT impaired only IF spectrum is in the estate (B6 = 1, recovered at 35% of book) — s.53 then ranks them 2nd and liquidation covers them. If spectrum is excluded and the ₹15,000 cr SBI facility is counted, secured lenders recover about 60% (6_Reconciliations R6 snapshot).
A42: Government of India — DoT statutory dues | B42: =$B$26 -> 194345 | C42: =IF($B$7=1,$B$26*E31,D34+(B42-$B$25)*E35) -> 36189.438 | D42: =IFERROR(C42/B42,0) -> 0.18621234 | E42: ='3_Restructuring_Projections'!$C$129 -> 0.51241554 | F42: ='3_Restructuring_Projections'!$C$129 -> 0.51241554 | G42: =(E42-D42)*100 -> 32.620319 | H42: The fulcrum creditor: GC value accrues overwhelmingly to the Govt.
A43: Indus Towers (lease + MSA payables) | B43: ='0_Control_Panel'!$B$52+'0_Control_Panel'!$B$53 -> 22300 | C43: =B43*E35 -> 1668.1201 | D43: =IFERROR(C43/B43,0) -> 0.074803592 | E43: =1 -> 1 | F43: =1 -> 1 | G43: =(E43-D43)*100 -> 92.519641 | H43: Critical supplier; paid in full in GC plans.
A44: Network vendors (Ericsson / Nokia / Samsung) | B44: ='0_Control_Panel'!$B$54 -> 5500 | C44: =B44*E35 -> 411.41976 | D44: =IFERROR(C44/B44,0) -> 0.074803592 | E44: =1 -> 1 | F44: =1-'0_Control_Panel'!$C$77 -> 0.85 | G44: =(E44-D44)*100 -> 92.519641
A45: Other operational creditors & provisions | B45: ='0_Control_Panel'!$B$55+'0_Control_Panel'!$B$57 -> 25200 | C45: =B45*E35 -> 1885.0505 | D45: =IFERROR(C45/B45,0) -> 0.074803592 | E45: =1 -> 1 | F45: =1-'0_Control_Panel'!$C$77*'0_Control_Panel'!$B$55/('0_Control_Panel'!$B$55+'0_Control_Panel'!$B$57) -> 0.98095238 | G45: =(E45-D45)*100 -> 92.519641
A47: E. BANK HAIRCUT SENSITIVITY — PLAN B vs LIQUIDATION (IBC s.30(2)(b) liquidation-value floor test)
A48: Bank / NCD haircut | B48: Recovery % | C48: Recovery ₹ (bank+NCD) | D48: Liquidation % | E48: Passes s.30(2)(b)? | H48: Interpretation
A49: 0.35 | B49: =1-A49 -> 0.65 | C49: =('0_Control_Panel'!$B$28+'0_Control_Panel'!$B$29)*B49 -> 2282.15 | D49: =E31 -> 1 | E49: =IF(B49>=D49,"YES","NO — dissenting FCs entitled to liquidation value") -> NO — dissenting FCs entitled to liquidation value | H49: A 35–50% bank haircut is economically irrational for lenders when s.53 liquidation recovery is ~100%.
A50: 0.4 | B50: =1-A50 -> 0.6 | C50: =('0_Control_Panel'!$B$28+'0_Control_Panel'!$B$29)*B50 -> 2106.6 | D50: =E31 -> 1 | E50: =IF(B50>=D50,"YES","NO — dissenting FCs entitled to liquidation value") -> NO — dissenting FCs entitled to liquidation value
A51: 0.45 | B51: =1-A51 -> 0.55 | C51: =('0_Control_Panel'!$B$28+'0_Control_Panel'!$B$29)*B51 -> 1931.05 | D51: =E31 -> 1 | E51: =IF(B51>=D51,"YES","NO — dissenting FCs entitled to liquidation value") -> NO — dissenting FCs entitled to liquidation value
A52: 0.5 | B52: =1-A52 -> 0.5 | C52: =('0_Control_Panel'!$B$28+'0_Control_Panel'!$B$29)*B52 -> 1755.5 | D52: =E31 -> 1 | E52: =IF(B52>=D52,"YES","NO — dissenting FCs entitled to liquidation value") -> NO — dissenting FCs entitled to liquidation value
A53: Legal note (v2): s.30(2)(b) binds a CIRP resolution plan. It does NOT bind an out-of-court ICA, so the Plan B test above shows the lenders' BATNA (100% in liquidation), not a statutory bar. Verify current RBI framework (2019 directions may have been superseded).
A55: F. GOVT LIQUIDATION RECOVERY — BOTH SBI-FACILITY TREATMENTS (live; v3). Same asset proceeds in B and C; D adds the matching cash.
A56: ₹ crore | B56: SBI EXCLUDED (today) | C56: SBI INCLUDED, no matching asset | D56: SBI INCLUDED + matching cash held
A57: Secured financial claims (bank + NCD [+ SBI facility]) | B57: ='0_Control_Panel'!$B$28+'0_Control_Panel'!$B$29 -> 3511 | C57: ='0_Control_Panel'!$B$28+'0_Control_Panel'!$B$29+'0_Control_Panel'!$B$58*'0_Control_Panel'!$B$83 -> 18511 | D57: ='0_Control_Panel'!$B$28+'0_Control_Panel'!$B$29+'0_Control_Panel'!$B$58*'0_Control_Panel'!$B$83 -> 18511
A58: Gross liquidation proceeds | B58: =$G$18 -> 47015.028 | C58: =$G$18 -> 47015.028 | D58: =$G$18+'0_Control_Panel'!$B$58*'0_Control_Panel'!$B$83 -> 62015.028
A59: s.53(1)(a) costs paid | B59: =MIN($B$30,B58) -> 2500 | C59: =MIN($B$30,C58) -> 2500 | D59: =MIN($B$30,D58) -> 2500
A60: Available for s.53(1)(b) | B60: =B58-B59 -> 44515.028 | C60: =C58-C59 -> 44515.028 | D60: =D58-D59 -> 59515.028
A61: s.53(1)(b) claim (workmen + secured [+ Govt if Rainbow, B7]) | B61: =$B$23+B57+$B$7*$B$26 -> 3661 | C61: =$B$23+C57+$B$7*$B$26 -> 18661 | D61: =$B$23+D57+$B$7*$B$26 -> 18661
A62: s.53(1)(b) paid | B62: =MIN(B61,B60) -> 3661 | C62: =MIN(C61,C60) -> 18661 | D62: =MIN(D61,D60) -> 18661
A63: Secured recovery (%) | B63: =IFERROR(B62/B61,0) -> 1 | C63: =IFERROR(C62/C61,0) -> 1 | D63: =IFERROR(D62/D61,0) -> 1
A64: Available after (b) | B64: =B60-B62 -> 40854.028 | C64: =C60-C62 -> 25854.028 | D64: =D60-D62 -> 40854.028
A65: s.53(1)(c) wages paid | B65: =MIN($B$24,B64) -> 700 | C65: =MIN($B$24,C64) -> 700 | D65: =MIN($B$24,D64) -> 700
A66: Available for (d)-(e) | B66: =B64-B65-MIN($B$33,B64-B65) -> 40154.028 | C66: =C64-C65-MIN($B$33,C64-C65) -> 25154.028 | D66: =D64-D65-MIN($B$33,D64-D65) -> 40154.028
A67: s.53(1)(e) Govt dues (2 yrs) paid | B67: =MIN($B$25*(1-$B$7),B66) -> 23402.31 | C67: =MIN($B$25*(1-$B$7),C66) -> 23402.31 | D67: =MIN($B$25*(1-$B$7),D66) -> 23402.31
A68: Available for (f) | B68: =B66-B67 -> 16751.718 | C68: =C66-C67 -> 1751.7177 | D68: =D66-D67 -> 16751.718
A69: s.53(1)(f) claim | B69: =($B$26-$B$25)*(1-$B$7)+$B$28 -> 223942.69 | C69: =($B$26-$B$25)*(1-$B$7)+$B$28 -> 223942.69 | D69: =($B$26-$B$25)*(1-$B$7)+$B$28 -> 223942.69
A70: s.53(1)(f) paid | B70: =MIN(B69,B68) -> 16751.718 | C70: =MIN(C69,C68) -> 1751.7177 | D70: =MIN(D69,D68) -> 16751.718
A71: Tier (f) recovery (%) | B71: =IFERROR(B70/B69,0) -> 0.074803592 | C71: =IFERROR(C70/C69,0) -> 0.0078221696 | D71: =IFERROR(D70/D69,0) -> 0.074803592
A72: GOVT LIQUIDATION RECOVERY (₹ cr) | B72: =IF($B$7=1,$B$26*B63,B67+($B$26-$B$25)*B71) -> 36189.438 | C72: =IF($B$7=1,$B$26*C63,C67+($B$26-$B$25)*C71) -> 24739.453 | D72: =IF($B$7=1,$B$26*D63,D67+($B$26-$B$25)*D71) -> 36189.438
A73: GOVT LIQUIDATION RECOVERY (%) | B73: =B72/$B$26 -> 0.18621234 | C73: =C72/$B$26 -> 0.12729658 | D73: =D72/$B$26 -> 0.18621234
A74: Check: active column (B8) ties to D42 (must be 0) | B74: =ROUND(IF($B$8=1,C73,B73)-$D$42,6) -> 0
A75: With the facility counted but no asset behind it (col C) secured claims rise by the drawn amount with no matching proceeds, which lowers the Govt recovery; column D (matching cash held) returns it to column B because assets and claims rise together. Cash raised and then spent on capex would sit between B and C.

Sheet 5_Logic_Map
A1: MODEL LOGIC MAP — KEY CELLS, FORMULAS & FLOW (v3)
A2: Read with the Control Panel and 6_Reconciliations R7 (change log). Formulas shown as written in the workbook.
A4: Sheet | B4: Key cell | C4: Logic
A5: Control Panel | B5: 0_Control_Panel!$B$5 | C5: Master scenario switch (1 = Plan A, 2 = Plan B, 3 = Plan C, 4 = Plan D). Matrix column E = CHOOSE($B$5, B, C, D, F) — Plan D sits in column F.
A6: Control Panel | B6: 0_Control_Panel!$E$71 | C6: Conversion price = MAX(CHOOSE(scenario), par ₹10) — par floor under Companies Act s.53.
A7: Control Panel | B7: 0_Control_Panel!$B$15 | C7: Active ARPU growth = CHOOSE(ARPU case, Low, Base, High).
A8: TWCF | B8: 1_TWCF_13_Week_Liquidity!$B$11 | C8: Collection efficiency = 98.5% × (1 − scenario receipts stress).
A9: TWCF | B9: 1_TWCF_13_Week_Liquidity!C45 | C9: Indus rent = −IF(first week of month, quarterly rentals × Indus share / 3, 0).
A10: TWCF | B10: 1_TWCF_13_Week_Liquidity!C58 | C10: Spectrum instalment = −IF(week = due week, amount × (1 − relief_flag × (moratorium>0)), 0).
A11: TWCF | B11: 1_TWCF_13_Week_Liquidity!C71 | C11: Alert = IF(close<0,"DEFAULT",IF(close<threshold,"BREACH","OK")); red conditional format.
A12: Capital Structure | B12: 2_Capital_Structure_Waterfall!$B$8 | C12: Penalty active = MAX(TWCF payment default, scenario default, manual override); +bps feeds bank/SBI/NCD all-in rate.
A13: Capital Structure | B13: 2_Capital_Structure_Waterfall!P14 | C13: Post-deal balance = Face − Converted (Face × conv%) − Written off (Face × haircut%).
A14: Capital Structure | B14: 2_Capital_Structure_Waterfall!D52 | C14: Spectrum cash = IF(yr ≤ moratorium, IF(Cash mode, interest, 0 [PIK]), contractual instalment × (1 − conv%)).
A15: Capital Structure | B15: 2_Capital_Structure_Waterfall!$B$39 | C15: Govt stake = (existing Govt shares + conversion shares) / post-deal shares; excess over 49% → OCRPS.
... A44: Reconciliations | B44: 6_Reconciliations!$B$2 | C44: Snapshot date for the static tables R2-R6.

Sheet 6_Reconciliations
A1: 6. RECONCILIATIONS, SNAPSHOTS & CHANGE LOG (live formulas in black; static run snapshots in blue — regenerate by toggling the switches named in each block)
A2: Snapshot date for static tables R2–R6 (v3 build): | B2: 46301
A3: R1. CLAIMS — why Control Panel B65 and the liquidation waterfall B37 differ and both are right (v3: ≈ ₹2.51 trn vs ≈ ₹2.54 trn; the v1/v2 memo figures ₹2.48 trn / ₹2.66 trn pre-date the Q1 FY27 DPO update and counted the ₹15k cr SBI facility)
A4: Total claims — nominal, AGR at face (v3 ≈ ₹2.51 trn; memo: "₹2.48 trn") | B4: ='0_Control_Panel'!B65 -> 250856 | J4: Control Panel B65
A5: + SBI-led facility assumed drawn before failure (only if 4_Liq B8 = 1; v3 default 0) | B5: ='4_Liquidation_Waterfall'!B27-'0_Control_Panel'!B28-'0_Control_Panel'!B29 -> 0 | J5: 4_Liq B27 less existing bank + NCD. Nil at the v3 default (4_Liq B8 = 0); a Plan-A construct when B8 = 1 — in a pure Plan B/C world this line is nil.
A6: + s.53(1)(a) CIRP & liquidation costs | B6: ='4_Liquidation_Waterfall'!B30 -> 2500 | J6: Priority cost, not a pre-existing claim
A7: + s.53(1)(c) employee wages (12 months) | B7: ='4_Liquidation_Waterfall'!B24 -> 700 | J7: May already sit inside "other liabilities" ₹22,000 cr — possible overlap
A8: + s.53(1)(b) workmen dues (24 months) | B8: ='4_Liquidation_Waterfall'!B23 -> 150 | J8: As above
A9: → Claims in the waterfall (v3 ≈ ₹2.54 trn; memo: "₹2.66 trn admitted claims", which included the SBI facility) | B9: =SUM(B4:B8) -> 254206
A10: Waterfall total (4_Liquidation_Waterfall B37) | B10: ='4_Liquidation_Waterfall'!B37 -> 254206
A11: Check (must be 0) | B11: =ROUND(B9-B10,2) -> 0
A12: Govt statutory dues as % of Control Panel B65 / of the waterfall total (B9) | B12: =('0_Control_Panel'!B25+'0_Control_Panel'!B26)/B4 -> 0.77472733 | C12: =('0_Control_Panel'!B25+'0_Control_Panel'!B26)/B9 -> 0.76451775 | J12: ="Both bases show the same thing: ~"&TEXT(C12,"0%")&"–"&TEXT(B12,"0%")&" of the stack is Govt dues; lenders are ~"&TEXT(C13,"0.0%")&"–"&TEXT(B13,"0.0%")&" ("&TEXT(('0_Control_Panel'!B28+'0_Control_Panel'!B29+'0_Control_Panel'!B58*'0_Control_Panel'!B83)/B9,"0.0%")&" if the new ₹15k cr facility is counted)." -> Both bases show the same thing: ~76%–77% of the stack is Govt dues; lenders are ~1.4%–1.4% (7.3% if the new ₹15k cr facility is counted).
A13: Bank + NCD (funded debt) as % of B65 / of the waterfall total (B9) | B13: =('0_Control_Panel'!B28+'0_Control_Panel'!B29)/B4 -> 0.013996077 | C13: =('0_Control_Panel'!B28+'0_Control_Panel'!B29)/B9 -> 0.013811633
A14: Secured financial creditors as counted in the waterfall (SBI facility only if 4_Liq B8 = 1), as % of the waterfall total (B9) | B14: ='4_Liquidation_Waterfall'!B27/B9 -> 0.013811633
A16: R2. EV RANGE — one construction for the exec summary AND the football field (v1 mixed three methods)
A17: Snapshot date: see B2 (06-Oct-2026, v3). Static snapshot of model runs (Plan A / Base ARPU / 5G on / levers on unless stated). Blue = pasted run output; regenerate by toggling the switches named in each block.
A18: Case (Plan A structure) | B18: EV — exit multiple | C18: EV — Gordon cross-check | D18: TV % of EV (exit) | E18: FY29 cash EBITDA | F18: Govt rec. — Strict | G18: Govt rec. — Middle | H18: Govt rec. — Conservative | I18: EV ÷ liquidation (exit)
A19: High ARPU 11% (mgmt plan) | B19: 149596.25 | C19: 113475.13 | D19: 0.88424428 | E19: 19909.682 | F19: 0.78542413 | G19: 0.72625101 | H19: 0.49213127 | I19: =B19/'4_Liquidation_Waterfall'!$G$18 -> 3.1818816 | J19: v1 football field plotted ±10% bands around the exit-multiple EV for four cases (e.g. High 135–165k around 149.6k) and Gordon↔exit only for Base. v2 plots Gordon↔exit for every case.
A20: Base ARPU 7% | B20: 108038.4 | C20: 65514.731 | D20: 0.9342138 | E20: 16612.812 | F20: 0.57158866 | G20: 0.51241554 | H20: 0.2782958 | I20: =B20/'4_Liquidation_Waterfall'!$G$18 -> 2.2979545
A21: Base, 5G capex phased (switch off) | B21: 126397.16 | C21: 108231.62 | D21: 0.81025513 | E21: 16881.804 | F21: 0.66605344 | G21: 0.60688032 | H21: 0.37276058 | I21: =B21/'4_Liquidation_Waterfall'!$G$18 -> 2.6884416
A22: Low ARPU 4% | B22: 80335.492 | C22: 33344.895 | D22: 0.99943275 | E22: 14295.806 | F22: 0.42904367 | G22: 0.36987055 | H22: 0.13575082 | I22: =B22/'4_Liquidation_Waterfall'!$G$18 -> 1.7087194 | J22: Gordon in the Low case (₹33.3 k) is BELOW liquidation mid (₹47.0k): the crossover is earlier than the v1 memo said, though Gordon applies a 4% perpetuity to FY31 FCF that still carries ₹12k growth-level capex (punitive).
A23: Downside: Low ARPU, no churn/opex levers (STRESS) | B23: 45361.068 | C23: -7355.5585 | D23: 1.1923328 | E23: 11493.75 | F23: 0.24908317 | G23: 0.18991005 | H23: 0 | I23: =B23/'4_Liquidation_Waterfall'!$G$18 -> 0.96482061
A24: Liquidation proceeds — low / mid / high (live) | B24: ='4_Liquidation_Waterfall'!C19 -> 33925.028 | C24: ='4_Liquidation_Waterfall'!G18 -> 47015.028 | D24: ='4_Liquidation_Waterfall'!E19 -> 60405.028
A25: Range used in corrected exec summary — exit-multiple EV, four standard cases (min / max) | B25: =MIN(B19:B22) -> 80335.492 | C25: =MAX(B19:B22) -> 149596.25
A26: Gordon cross-check, four standard cases (min / max) | B26: =MIN(C19:C22) -> 33344.895 | C26: =MAX(C19:C22) -> 113475.13
A27: Full span incl. downside, both methods (min / max) | B27: =MIN(B19:C23) -> -7355.5585 | C27: =MAX(B19:C23) -> 149596.25
A28: Live check — active-case EV (C121) vs snapshot Base row; valid only at Plan A / Base ARPU / 5G on / levers on | B28: =IF(AND('0_Control_Panel'!B11=2,'0_Control_Panel'!B9=1,'0_Control_Panel'!B17=1,'0_Control_Panel'!B18=1),IF(ABS('3_Restructuring_Projections'!C121-B20)<1,"OK","STALE"),"n/a (switches differ)") -> OK
A30: R3. LIQUIDITY — why DSCR is negative and obligations are 6.0x yet "no liquidity facility" is needed (ACTIVE plan, live)
A31: ₹ crore | B31: FY27E | C31: FY28E | D31: FY29E | E31: FY30E | F31: FY31E
A32: Cash EBITDA | B32: ='3_Restructuring_Projections'!D39 -> 11702.739 | C32: ='3_Restructuring_Projections'!E39 -> 13928.834 | D32: ='3_Restructuring_Projections'!F39 -> 16612.812 | E32: ='3_Restructuring_Projections'!G39 -> 19851.393 | F32: ='3_Restructuring_Projections'!H39 -> 23763.682
A33: Less: capex | B33: =-'3_Restructuring_Projections'!D61 -> -13000 | C33: =-'3_Restructuring_Projections'!E61 -> -15500 | D33: =-'3_Restructuring_Projections'!F61 -> -15500 | E33: =-'3_Restructuring_Projections'!G61 -> -12000 | F33: =-'3_Restructuring_Projections'!H61 -> -12000
A34: Cash EBITDA − capex (DSCR numerator) | B34: =B32+B33 -> -1297.2614 | C34: =C32+C33 -> -1571.1663 | D34: =D32+D33 -> 1112.8119 | E34: =E32+E33 -> 7851.3929 | F34: =F32+F33 -> 11763.682
A35: DoT cash paid (spectrum + AGR) | B35: ='3_Restructuring_Projections'!D92+'3_Restructuring_Projections'!D93 -> -93 | C35: ='3_Restructuring_Projections'!E92+'3_Restructuring_Projections'!E93 -> -93 | D35: ='3_Restructuring_Projections'!F92+'3_Restructuring_Projections'!F93 -> -93 | E35: ='3_Restructuring_Projections'!G92+'3_Restructuring_Projections'!G93 -> -93 | F35: ='3_Restructuring_Projections'!H92+'3_Restructuring_Projections'!H93 -> -14493
A36: New money in (equity + asset sale + SBI draw) | B36: ='3_Restructuring_Projections'!D97+'3_Restructuring_Projections'!D95 -> 30000 | C36: ='3_Restructuring_Projections'!E97+'3_Restructuring_Projections'!E95 -> 0 | D36: ='3_Restructuring_Projections'!F97+'3_Restructuring_Projections'!F95 -> 0 | E36: ='3_Restructuring_Projections'!G97+'3_Restructuring_Projections'!G95 -> 0 | F36: ='3_Restructuring_Projections'!H97+'3_Restructuring_Projections'!H95 -> 0
A37: Liquidity-facility draw required | B37: ='3_Restructuring_Projections'!D101 -> 0 | C37: ='3_Restructuring_Projections'!E101 -> 0 | D37: ='3_Restructuring_Projections'!F101 -> 0 | E37: ='3_Restructuring_Projections'!G101 -> 0 | F37: ='3_Restructuring_Projections'!H101 -> 0
A38: Closing cash | B38: ='3_Restructuring_Projections'!D102 -> 34359.927 | C38: ='3_Restructuring_Projections'!E102 -> 32601.485 | D38: ='3_Restructuring_Projections'!F102 -> 30904.686 | E38: ='3_Restructuring_Projections'!G102 -> 34609.981 | F38: ='3_Restructuring_Projections'!H102 -> 29115.598
A39: Headroom over ₹4,000 cr floor | B39: =B38-'3_Restructuring_Projections'!$B$100 -> 30359.927 | C39: =C38-'3_Restructuring_Projections'!$B$100 -> 28601.485 | D39: =D38-'3_Restructuring_Projections'!$B$100 -> 26904.686 | E39: =E38-'3_Restructuring_Projections'!$B$100 -> 30609.981 | F39: =F38-'3_Restructuring_Projections'!$B$100 -> 25115.598
A40: DSCR (x) | B40: ='3_Restructuring_Projections'!D110 -> -0.6351118 | C40: ='3_Restructuring_Projections'!E110 -> -0.77060293 | D40: ='3_Restructuring_Projections'!F110 -> 0.31478167 | E40: ='3_Restructuring_Projections'!G110 -> 2.3244487 | F40: ='3_Restructuring_Projections'!H110 -> 0.66762092
A41: Total obligations ÷ cash EBITDA — AGR at carrying value (as reported, x) | B41: ='3_Restructuring_Projections'!D109 -> 9.9681836 | C41: ='3_Restructuring_Projections'!E109 -> 9.1910738 | D41: ='3_Restructuring_Projections'!F109 -> 8.3391059 | E41: ='3_Restructuring_Projections'!G109 -> 7.2746676 | F41: ='3_Restructuring_Projections'!H109 -> 6.1399559
A42: Total obligations ÷ cash EBITDA — AGR at NOMINAL (x) | B42: =IFERROR(('3_Restructuring_Projections'!D107+'3_Restructuring_Projections'!D71+'2_Capital_Structure_Waterfall'!D62)/'3_Restructuring_Projections'!D39,0) -> 12.3146 | C42: =IFERROR(('3_Restructuring_Projections'!E107+'3_Restructuring_Projections'!E71+'2_Capital_Structure_Waterfall'!E62)/'3_Restructuring_Projections'!E39,0) -> 11.066907 | D42: =IFERROR(('3_Restructuring_Projections'!F107+'3_Restructuring_Projections'!F71+'2_Capital_Structure_Waterfall'!F62)/'3_Restructuring_Projections'!F39,0) -> 9.8268942 | E42: =IFERROR(('3_Restructuring_Projections'!G107+'3_Restructuring_Projections'!G71+'2_Capital_Structure_Waterfall'!G62)/'3_Restructuring_Projections'!G39,0) -> 8.4442985 | F42: =IFERROR(('3_Restructuring_Projections'!H107+'3_Restructuring_Projections'!H71+'2_Capital_Structure_Waterfall'!H62)/'3_Restructuring_Projections'!H39,0) -> 7.0501668
A44: Plan A funding gap with NO new money (liquidity facility needed, FY27–31) — static snapshot (06-Oct-2026, v3), by ARPU case
A45: Case | B45: Gap, no new money | C45: New money in Plan A | D45: Facility draw WITH new money
A46: High ARPU 11% (mgmt plan) | B46: 0 | C46: ='0_Control_Panel'!$B$81+'0_Control_Panel'!$B$58*'0_Control_Panel'!$B$83 -> 30000 | D46: 0
A47: Base ARPU 7% | B47: 410.09191 | C47: ='0_Control_Panel'!$B$81+'0_Control_Panel'!$B$58*'0_Control_Panel'!$B$83 -> 30000 | D47: 0
A48: Base, 5G capex phased (switch off) | B48: 0 | C48: ='0_Control_Panel'!$B$81+'0_Control_Panel'!$B$58*'0_Control_Panel'!$B$83 -> 30000 | D48: 0
A49: Low ARPU 4% | B49: 11777.692 | C49: ='0_Control_Panel'!$B$81+'0_Control_Panel'!$B$58*'0_Control_Panel'!$B$83 -> 30000 | D49: 0
A50: Downside: Low ARPU, no churn/opex levers (STRESS) | B50: 26759.219 | C50: ='0_Control_Panel'!$B$81+'0_Control_Panel'!$B$58*'0_Control_Panel'!$B$83 -> 30000 | D50: 669.64496
A52: Reading: in the Base case Plan A needs only ~₹0.4k cr of new money; the ₹30k cr package is insurance sized to the Low/Downside cases. DSCR < 1.0x in FY27-28 because capex exceeds cash EBITDA, funded from pre-raised cash — hence both statements are true.
A54: R4. PLAN A / B / C / D COMPARISON — static snapshot (set 0_Control_Panel!B5 = 1..4 to reproduce)
A55: Snapshot date: see B2 (06-Oct-2026, v3). Static snapshot of model runs (Plan A / Base ARPU / 5G on / levers on unless stated). Blue = pasted run output.
A56: Output | B56: Plan A | C56: Plan B | D56: Plan C | E56: Plan D | F56: Live (active) | G56: Snapshot tie-out
A57: 13-week minimum closing cash (₹ cr) | B57: 3000.0279 | C57: 3274.6809 | D57: 2311.7544 | E57: 2690.0655 | F57: ='0_Control_Panel'!B92 -> 3000.0279 | G57: =IF(ABS(INDEX(B57:E57,'0_Control_Panel'!$B$5)-F57)<0.5,"OK","differs") -> OK | J57: Plan C is shown after the v2 s.14 fix (moratorium 2 yrs, PIK). Its "liquidity need" is not decision-relevant — the plan ends in liquidation.
A58: Weeks below ₹40 bn floor (of 13) | B58: 5 | C58: 3 | D58: 7 | E58: 6 | F58: ='0_Control_Panel'!B93 -> 5 | G58: =IF(ABS(INDEX(B58:E58,'0_Control_Panel'!$B$5)-F58)<0.5,"OK","differs") -> OK
A59: Default penalty (+200 bps) triggered | B59: 0 | C59: 1 | D59: 1 | E59: 0 | F59: ='0_Control_Panel'!B96 -> 0 | G59: =IF(ABS(INDEX(B59:E59,'0_Control_Panel'!$B$5)-F59)<0.5,"OK","differs") -> OK
A60: Statutory dues converted to equity (₹ cr) | B60: 42071.3 | C60: 0 | D60: 0 | E60: 0 | F60: ='0_Control_Panel'!B97 -> 42071.3 | G60: =IF(ABS(INDEX(B60:E60,'0_Control_Panel'!$B$5)-F60)<0.5,"OK","differs") -> OK
A61: DoT cash deferral FY27–31 vs contract (₹ cr) | B61: 70831 | C61: 0 | D61: 22076 | E61: 7076 | F61: ='0_Control_Panel'!B98 -> 70831 | G61: =IF(ABS(INDEX(B61:E61,'0_Control_Panel'!$B$5)-F61)<0.5,"OK","differs") -> OK
A62: Cumulative liquidity facility needed FY27–31 (₹ cr) | B62: 0 | C62: 71499.233 | D62: 63695.508 | E62: 31404.554 | F62: ='0_Control_Panel'!B102 -> 0 | G62: =IF(ABS(INDEX(B62:E62,'0_Control_Panel'!$B$5)-F62)<0.5,"OK","differs") -> OK
A63: Minimum DSCR FY27–31 (x) | B63: -0.77060293 | C63: -0.15313717 | D63: -2.8841969 | E63: -0.99420588 | F63: ='0_Control_Panel'!B103 -> -0.77060293 | G63: =IF(ABS(INDEX(B63:E63,'0_Control_Panel'!$B$5)-F63)<0.5,"OK","differs") -> OK
A64: Government economic stake post-deal | B64: 0.5840404 | C64: 0.45818251 | D64: 0.4899 | E64: 0.40186533 | F64: ='0_Control_Panel'!B99 -> 0.5840404 | G64: =IF(ABS(INDEX(B64:E64,'0_Control_Panel'!$B$5)-F64)<0.0005,"OK","differs") -> OK
A65: Going-concern EV — exit multiple (₹ cr) | B65: 108038.4 | C65: 109263.33 | D65: 108038.4 | E65: 108038.4 | F65: ='0_Control_Panel'!B104 -> 108038.4 | G65: =IF(ABS(INDEX(B65:E65,'0_Control_Panel'!$B$5)-F65)<0.5,"OK","differs") -> OK
A66: Liquidation proceeds, mid (₹ cr) | B66: 47015.028 | C66: 47289.681 | D66: 46326.754 | E66: 46705.066 | F66: ='0_Control_Panel'!B105 -> 47015.028 | G66: =IF(ABS(INDEX(B66:E66,'0_Control_Panel'!$B$5)-F66)<0.5,"OK","differs") -> OK
A67: Govt recovery GC — Strict | B67: 0.57158866 | C67: 0.58257085 | D67: 0.57158866 | E67: 0.57158866 | F67: ='0_Control_Panel'!B112 -> 0.57158866 | G67: =IF(ABS(INDEX(B67:E67,'0_Control_Panel'!$B$5)-F67)<0.0005,"OK","differs") -> OK | J67: GC recovery % is identical across A/B/C/D except for haircuts because unlevered EV does not depend on structure: plans differ in FEASIBILITY (funding, consents, timing) and in who holds the surplus, not in EV.
A68: Govt recovery GC — Middle | B68: 0.51241554 | C68: 0.53011259 | D68: 0.51241554 | E68: 0.51241554 | F68: ='0_Control_Panel'!B113 -> 0.51241554 | G68: =IF(ABS(INDEX(B68:E68,'0_Control_Panel'!$B$5)-F68)<0.0005,"OK","differs") -> OK
A69: Govt recovery GC — Conservative | B69: 0.2782958 | C69: 0.29599285 | D69: 0.2782958 | E69: 0.2782958 | F69: ='0_Control_Panel'!B114 -> 0.2782958 | G69: =IF(ABS(INDEX(B69:E69,'0_Control_Panel'!$B$5)-F69)<0.0005,"OK","differs") -> OK
A70: Govt recovery in liquidation | B70: 0.18621234 | C70: 0.1872911 | D70: 0.183509 | E70: 0.1849949 | F70: ='0_Control_Panel'!B108 -> 0.18621234 | G70: =IF(ABS(INDEX(B70:E70,'0_Control_Panel'!$B$5)-F70)<0.0005,"OK","differs") -> OK
A71: FY31 closing cash (₹ cr) | B71: 29115.598 | C71: 4000 | D71: 4000 | E71: 4000
A72: FY31 total obligations ÷ cash EBITDA (AGR carrying, x) | B72: 6.1399559 | C72: 8.8875142 | D72: 9.4709238 | E72: 7.6559179
A73: Balance check (all four plans, all years) — verified when run | B73: 0 | C73: 0 | D73: 0 | E73: 0 | F73: ='0_Control_Panel'!B110 -> 0
A75: R5. PLAN D — what a strategic investor must write (static snapshot, 06-Oct-2026 v3; Plan D inputs in 0_Control_Panel column F)
A76: Strategic equity assumed in the Plan D column (₹ cr) — illustrative | B76: ='0_Control_Panel'!F81 -> 30000
A77: Liquidity still needed FY27–31 at that cheque, with 12-month DoT standstill (₹ cr) | B77: 31404.554 | J77: Plan D is credible only with a six-figure-crore cheque; no buyer is identified in the files. Treat it as a complement to Plan A (a strategic can be the source of the ₹15k cr new equity), not a rival.
A78: Break-even cheque: equity such that liquidity need = 0 (₹ cr; bisection) | B78: 53902.56
A79: Break-even cheque ÷ reference market cap (0_Control_Panel B39) | B79: =B78/'0_Control_Panel'!B39 -> 0.39360564
A80: Govt economic stake post-deal at break-even cheque | B80: 0.35153417
A81: Liquidity needed at ₹30,000 cr cheque if NO DoT standstill (₹ cr) | B81: 41200.48
A82: Liquidity needed at ₹30,000 cr cheque if ₹10,000 cr non-spectrum asset sold at book, zero EBITDA lost (₹ cr) | B82: 17926.858
A83: Compare: Plan A new money (equity + SBI draw, ₹ cr) with the DoT cash deferral (row 61) | B83: ='0_Control_Panel'!B81+'0_Control_Panel'!B58*'0_Control_Panel'!B83 -> 30000
A85: R6. LIQUIDATION SWITCHES — the "banks are not impaired" and "Plan B fails s.30(2)(b)" claims depend on the spectrum-in-estate, SBI-facility and Rainbow switches (static snapshot, 06-Oct-2026 v3; 4_Liq B8 default is now 0)
A86: Case | B86: Gross proceeds (₹ cr) | C86: Secured FC recovery | D86: Govt recovery | E86: Tier (f) recovery | F86: Plan B 35% haircut (65%) passes s.30(2)(b)?
A87: Mid recovery, spectrum in estate, SBI facility EXCLUDED (memo base; v3 default B8 = 0) | B87: 47015.028 | C87: 1 | D87: 0.18621234 | E87: 0.074803592 | F87: =IF(0.65>=C87,"YES","NO") -> NO
A88: Low recovery (SBI excluded) | B88: 33925.028 | C88: 1 | D88: 0.13479852 | E88: 0.016351137 | F88: =IF(0.65>=C88,"YES","NO") -> NO | J88: v1 said "with spectrum excluded, liquidation value roughly halves". Run result (v3): ₹47,015 → ₹13,765 cr (−71%). Secured lenders recover 60% if the ₹15,000 cr SBI facility is counted (row 94) and 100% if not (row 90) — a 35% haircut (65% recovery) clears the liquidation floor only in the SBI-included case.
A89: High recovery (SBI excluded) | B89: 60405.028 | C89: 1 | D89: 0.23880448 | E89: 0.13459568 | F89: =IF(0.65>=C89,"YES","NO") -> NO
A90: Spectrum EXCLUDED from estate (mid; SBI excluded) | B90: 13765.028 | C90: 1 | D90: 0.035524598 | E90: 0 | F90: =IF(0.65>=C90,"YES","NO") -> NO
A91: Spectrum excluded + low recovery (SBI excluded) | B91: 10175.028 | C91: 1 | D91: 0.017052293 | E91: 0 | F91: =IF(0.65>=C91,"YES","NO") -> NO
A92: Govt dues secured — Rainbow Papers (mid; SBI excluded) | B92: 47015.028 | C92: 0.22481656 | D92: 0.22481656 | E92: 0 | F92: =IF(0.65>=C92,"YES","NO") -> YES | J92: Under Rainbow Papers lenders recover ~22%, so EVERY 35–50% haircut would pass the s.30(2)(b) test — Plan B's rejection rests on the base-case switches, not on law.
A93: Spectrum in estate, SBI facility INCLUDED as secured claim, no matching asset (mid; the v2 default) | B93: 47015.028 | C93: 1 | D93: 0.12729658 | E93: 0.0078221696 | F93: =IF(0.65>=C93,"YES","NO") -> NO
A94: Spectrum EXCLUDED + SBI facility INCLUDED (mid; v2 basis — the v2 "63%" case; 60% in v3) | B94: 13765.028 | C94: 0.6036669 | D94: 0 | E94: 0 | F94: =IF(0.65>=C94,"YES","NO") -> YES
A96: R7. CHANGE LOG — v2 → v3 is the block that starts at row 125 (this release); the v1 → v2 log below (rows 97-123) is retained for history. Values in the v1 → v2 block are as at 4-Oct-2026 and are NOT updated.
A97: Output | B97: v1 | C97: v2 | D97: Δ | J97: Why it moved
A98: Govt recovery GC — Plan A (headline, Middle treatment) | B98: 0.30346696 | C98: 0.52028357 | D98: =C98-B98 -> 0.21681661 | J98: Bridge no longer deducts lease liabilities (already in cash-EBITDA FCF) or the ₹22,000 cr plug; adds SBI facility, new money and new-equity netting; keeps trade payables.
A99: Strict treatment | C99: 0.58036528 | J99: New: only funded debt deducted.
A100: Conservative treatment | C100: 0.28256898 | J100: New: v1-style deductions + trapped cash; lease double-count retained deliberately as a stress.
A101: Govt recovery GC — Plan B | B101: 0.30986662 | C101: 0.53825236 | D101: =C101-B101 -> 0.22838574 | J101: Same bridge change (Middle).
A102: Bridge deductions C125 (₹ cr) | B102: -56511 | C102: -45011 | D102: =C102-B102 -> 11500 | J102: Middle: SBI facility −15,000, new-equity −15,000, bank −211, NCD −3,300, trade −11,500.
A103: Bridge cash C126 (₹ cr) | B103: 6558 | C103: 36558 | D103: =C103-B103 -> 30000 | J103: Adds ₹30,000 cr new-money cash (SBI draw + equity) at close.
A104: Value available C127 (₹ cr) | B104: 58085.397 | C104: 99585.397 | D104: =C104-B104 -> 41500 | J104: Result of the two lines above.
A105: Govt recovery range (new) | J105: 28.3% (Conservative) – 58.0% (Strict); Middle 52.0%.
A106: Plan C: liquidity need FY27–31 (₹ cr) | B106: 94951.84 | C106: 63695.508 | D106: =C106-B106 -> -31256.331 | J106: s.14 moratorium now applied for the 24-month CIRP: DPO instalments no longer forced into cash; interest accrues.
A107: Plan C: minimum DSCR (x) | B107: -0.16508536 | C107: -2.8841969 | D107: =C107-B107 -> -2.7191116 | J107: Same cause; DSCR denominator ≈ 0 during stay, so ratio is not meaningful.
A108: Plan C: DoT cash relief FY27–31 (₹ cr) | B108: 0 | C108: 22076 | D108: =C108-B108 -> 22076 | J108: Same cause.
...
